package com.appsflyer;

import android.content.Context;
import java.lang.ref.WeakReference;
import java.util.Map;
import java.util.concurrent.ScheduledExecutorService;
import java.util.concurrent.atomic.AtomicInteger;

abstract class AppsFlyerLib$AttributionIdFetcher
  implements Runnable
{
  private static AtomicInteger d = new AtomicInteger(0);
  protected WeakReference<Context> a = null;
  private String b;
  private ScheduledExecutorService c;
  
  public AppsFlyerLib$AttributionIdFetcher(Context paramContext, String paramString, ScheduledExecutorService paramScheduledExecutorService)
  {
    a = new WeakReference(paramContext);
    b = paramString;
    c = paramScheduledExecutorService;
  }
  
  public abstract String a();
  
  protected abstract void a(String paramString, int paramInt);
  
  protected abstract void a(Map<String, String> paramMap);
  
  /* Error */
  public void run()
  {
    // Byte code:
    //   0: aconst_null
    //   1: astore 7
    //   3: aload_0
    //   4: getfield 38	com/appsflyer/AppsFlyerLib$AttributionIdFetcher:b	Ljava/lang/String;
    //   7: ifnull +13 -> 20
    //   10: aload_0
    //   11: getfield 38	com/appsflyer/AppsFlyerLib$AttributionIdFetcher:b	Ljava/lang/String;
    //   14: invokevirtual 54	java/lang/String:length	()I
    //   17: ifne +4 -> 21
    //   20: return
    //   21: getstatic 25	com/appsflyer/AppsFlyerLib$AttributionIdFetcher:d	Ljava/util/concurrent/atomic/AtomicInteger;
    //   24: invokevirtual 57	java/util/concurrent/atomic/AtomicInteger:incrementAndGet	()I
    //   27: pop
    //   28: aload_0
    //   29: getfield 31	com/appsflyer/AppsFlyerLib$AttributionIdFetcher:a	Ljava/lang/ref/WeakReference;
    //   32: invokevirtual 61	java/lang/ref/WeakReference:get	()Ljava/lang/Object;
    //   35: checkcast 63	android/content/Context
    //   38: astore 9
    //   40: aload 9
    //   42: ifnonnull +22 -> 64
    //   45: getstatic 25	com/appsflyer/AppsFlyerLib$AttributionIdFetcher:d	Ljava/util/concurrent/atomic/AtomicInteger;
    //   48: invokevirtual 66	java/util/concurrent/atomic/AtomicInteger:decrementAndGet	()I
    //   51: pop
    //   52: iconst_0
    //   53: ifeq -33 -> 20
    //   56: new 68	java/lang/NullPointerException
    //   59: dup
    //   60: invokespecial 69	java/lang/NullPointerException:<init>	()V
    //   63: athrow
    //   64: invokestatic 75	java/lang/System:currentTimeMillis	()J
    //   67: lstore_2
    //   68: aload 9
    //   70: aload 9
    //   72: invokestatic 81	com/appsflyer/AppsFlyerLib:g	(Landroid/content/Context;)Ljava/lang/String;
    //   75: invokestatic 84	com/appsflyer/AppsFlyerLib:b	(Landroid/content/Context;Ljava/lang/String;)Ljava/lang/String;
    //   78: astore 5
    //   80: ldc 86
    //   82: astore 4
    //   84: aload 5
    //   86: ifnull +25 -> 111
    //   89: new 88	java/lang/StringBuilder
    //   92: dup
    //   93: invokespecial 89	java/lang/StringBuilder:<init>	()V
    //   96: ldc 91
    //   98: invokevirtual 95	java/lang/StringBuilder:append	(Ljava/lang/String;)Ljava/lang/StringBuilder;
    //   101: aload 5
    //   103: invokevirtual 95	java/lang/StringBuilder:append	(Ljava/lang/String;)Ljava/lang/StringBuilder;
    //   106: invokevirtual 98	java/lang/StringBuilder:toString	()Ljava/lang/String;
    //   109: astore 4
    //   111: new 88	java/lang/StringBuilder
    //   114: dup
    //   115: invokespecial 89	java/lang/StringBuilder:<init>	()V
    //   118: aload_0
    //   119: invokevirtual 100	com/appsflyer/AppsFlyerLib$AttributionIdFetcher:a	()Ljava/lang/String;
    //   122: invokevirtual 95	java/lang/StringBuilder:append	(Ljava/lang/String;)Ljava/lang/StringBuilder;
    //   125: aload 9
    //   127: invokevirtual 103	android/content/Context:getPackageName	()Ljava/lang/String;
    //   130: invokevirtual 95	java/lang/StringBuilder:append	(Ljava/lang/String;)Ljava/lang/StringBuilder;
    //   133: aload 4
    //   135: invokevirtual 95	java/lang/StringBuilder:append	(Ljava/lang/String;)Ljava/lang/StringBuilder;
    //   138: ldc 105
    //   140: invokevirtual 95	java/lang/StringBuilder:append	(Ljava/lang/String;)Ljava/lang/StringBuilder;
    //   143: aload_0
    //   144: getfield 38	com/appsflyer/AppsFlyerLib$AttributionIdFetcher:b	Ljava/lang/String;
    //   147: invokevirtual 95	java/lang/StringBuilder:append	(Ljava/lang/String;)Ljava/lang/StringBuilder;
    //   150: ldc 107
    //   152: invokevirtual 95	java/lang/StringBuilder:append	(Ljava/lang/String;)Ljava/lang/StringBuilder;
    //   155: aload 9
    //   157: invokestatic 109	com/appsflyer/AppsFlyerLib:d	(Landroid/content/Context;)Ljava/lang/String;
    //   160: invokevirtual 95	java/lang/StringBuilder:append	(Ljava/lang/String;)Ljava/lang/StringBuilder;
    //   163: astore 5
    //   165: aload 9
    //   167: invokestatic 113	com/appsflyer/AppsFlyerLib:e	(Landroid/content/Context;)Z
    //   170: ifeq +29 -> 199
    //   173: new 88	java/lang/StringBuilder
    //   176: dup
    //   177: invokespecial 89	java/lang/StringBuilder:<init>	()V
    //   180: ldc 115
    //   182: invokevirtual 95	java/lang/StringBuilder:append	(Ljava/lang/String;)Ljava/lang/StringBuilder;
    //   185: aload 5
    //   187: invokevirtual 98	java/lang/StringBuilder:toString	()Ljava/lang/String;
    //   190: invokevirtual 95	java/lang/StringBuilder:append	(Ljava/lang/String;)Ljava/lang/StringBuilder;
    //   193: invokevirtual 98	java/lang/StringBuilder:toString	()Ljava/lang/String;
    //   196: invokestatic 120	com/appsflyer/LogMessages:b	(Ljava/lang/String;)V
    //   199: new 122	java/net/URL
    //   202: dup
    //   203: aload 5
    //   205: invokevirtual 98	java/lang/StringBuilder:toString	()Ljava/lang/String;
    //   208: invokespecial 124	java/net/URL:<init>	(Ljava/lang/String;)V
    //   211: invokevirtual 128	java/net/URL:openConnection	()Ljava/net/URLConnection;
    //   214: checkcast 130	java/net/HttpURLConnection
    //   217: astore 6
    //   219: aload 6
    //   221: astore 4
    //   223: aload 6
    //   225: ldc -124
    //   227: invokevirtual 135	java/net/HttpURLConnection:setRequestMethod	(Ljava/lang/String;)V
    //   230: aload 6
    //   232: astore 4
    //   234: aload 6
    //   236: sipush 10000
    //   239: invokevirtual 138	java/net/HttpURLConnection:setConnectTimeout	(I)V
    //   242: aload 6
    //   244: astore 4
    //   246: aload 6
    //   248: ldc -116
    //   250: ldc -114
    //   252: invokevirtual 146	java/net/HttpURLConnection:setRequestProperty	(Ljava/lang/String;Ljava/lang/String;)V
    //   255: aload 6
    //   257: astore 4
    //   259: aload 6
    //   261: invokevirtual 149	java/net/HttpURLConnection:connect	()V
    //   264: aload 6
    //   266: astore 4
    //   268: aload 6
    //   270: invokevirtual 152	java/net/HttpURLConnection:getResponseCode	()I
    //   273: sipush 200
    //   276: if_icmpne +503 -> 779
    //   279: aload 6
    //   281: astore 4
    //   283: aload 9
    //   285: ldc -102
    //   287: invokestatic 75	java/lang/System:currentTimeMillis	()J
    //   290: lload_2
    //   291: lsub
    //   292: ldc2_w 155
    //   295: ldiv
    //   296: invokestatic 159	com/appsflyer/AppsFlyerLib:a	(Landroid/content/Context;Ljava/lang/String;J)V
    //   299: aload 6
    //   301: astore 4
    //   303: new 88	java/lang/StringBuilder
    //   306: dup
    //   307: invokespecial 89	java/lang/StringBuilder:<init>	()V
    //   310: astore 10
    //   312: new 161	java/io/InputStreamReader
    //   315: dup
    //   316: aload 6
    //   318: invokevirtual 165	java/net/HttpURLConnection:getInputStream	()Ljava/io/InputStream;
    //   321: invokespecial 168	java/io/InputStreamReader:<init>	(Ljava/io/InputStream;)V
    //   324: astore 8
    //   326: new 170	java/io/BufferedReader
    //   329: dup
    //   330: aload 8
    //   332: invokespecial 173	java/io/BufferedReader:<init>	(Ljava/io/Reader;)V
    //   335: astore 5
    //   337: aload 5
    //   339: invokevirtual 176	java/io/BufferedReader:readLine	()Ljava/lang/String;
    //   342: astore 4
    //   344: aload 4
    //   346: ifnull +142 -> 488
    //   349: aload 10
    //   351: aload 4
    //   353: invokevirtual 95	java/lang/StringBuilder:append	(Ljava/lang/String;)Ljava/lang/StringBuilder;
    //   356: bipush 10
    //   358: invokevirtual 179	java/lang/StringBuilder:append	(C)Ljava/lang/StringBuilder;
    //   361: pop
    //   362: goto -25 -> 337
    //   365: astore 4
    //   367: aload 5
    //   369: astore 7
    //   371: aload 4
    //   373: astore 5
    //   375: aload 7
    //   377: ifnull +12 -> 389
    //   380: aload 6
    //   382: astore 4
    //   384: aload 7
    //   386: invokevirtual 181	java/io/BufferedReader:close	()V
    //   389: aload 8
    //   391: ifnull +12 -> 403
    //   394: aload 6
    //   396: astore 4
    //   398: aload 8
    //   400: invokevirtual 182	java/io/InputStreamReader:close	()V
    //   403: aload 6
    //   405: astore 4
    //   407: aload 5
    //   409: athrow
    //   410: astore 4
    //   412: aload 6
    //   414: astore 5
    //   416: aload 4
    //   418: astore 6
    //   420: aload 5
    //   422: astore 4
    //   424: invokestatic 185	com/appsflyer/AppsFlyerLib:b	()Lcom/appsflyer/AppsFlyerConversionListener;
    //   427: ifnull +17 -> 444
    //   430: aload 5
    //   432: astore 4
    //   434: aload_0
    //   435: aload 6
    //   437: invokevirtual 188	java/lang/Throwable:getMessage	()Ljava/lang/String;
    //   440: iconst_0
    //   441: invokevirtual 190	com/appsflyer/AppsFlyerLib$AttributionIdFetcher:a	(Ljava/lang/String;I)V
    //   444: aload 5
    //   446: astore 4
    //   448: ldc -64
    //   450: aload 6
    //   452: invokevirtual 188	java/lang/Throwable:getMessage	()Ljava/lang/String;
    //   455: aload 6
    //   457: invokestatic 197	android/util/Log:e	(Ljava/lang/String;Ljava/lang/String;Ljava/lang/Throwable;)I
    //   460: pop
    //   461: getstatic 25	com/appsflyer/AppsFlyerLib$AttributionIdFetcher:d	Ljava/util/concurrent/atomic/AtomicInteger;
    //   464: invokevirtual 66	java/util/concurrent/atomic/AtomicInteger:decrementAndGet	()I
    //   467: pop
    //   468: aload 5
    //   470: ifnull +8 -> 478
    //   473: aload 5
    //   475: invokevirtual 200	java/net/HttpURLConnection:disconnect	()V
    //   478: aload_0
    //   479: getfield 40	com/appsflyer/AppsFlyerLib$AttributionIdFetcher:c	Ljava/util/concurrent/ScheduledExecutorService;
    //   482: invokeinterface 205 1 0
    //   487: return
    //   488: aload 5
    //   490: ifnull +12 -> 502
    //   493: aload 6
    //   495: astore 4
    //   497: aload 5
    //   499: invokevirtual 181	java/io/BufferedReader:close	()V
    //   502: aload 8
    //   504: ifnull +12 -> 516
    //   507: aload 6
    //   509: astore 4
    //   511: aload 8
    //   513: invokevirtual 182	java/io/InputStreamReader:close	()V
    //   516: aload 6
    //   518: astore 4
    //   520: aload 9
    //   522: invokestatic 113	com/appsflyer/AppsFlyerLib:e	(Landroid/content/Context;)Z
    //   525: ifeq +33 -> 558
    //   528: aload 6
    //   530: astore 4
    //   532: new 88	java/lang/StringBuilder
    //   535: dup
    //   536: invokespecial 89	java/lang/StringBuilder:<init>	()V
    //   539: ldc -49
    //   541: invokevirtual 95	java/lang/StringBuilder:append	(Ljava/lang/String;)Ljava/lang/StringBuilder;
    //   544: aload 10
    //   546: invokevirtual 98	java/lang/StringBuilder:toString	()Ljava/lang/String;
    //   549: invokevirtual 95	java/lang/StringBuilder:append	(Ljava/lang/String;)Ljava/lang/StringBuilder;
    //   552: invokevirtual 98	java/lang/StringBuilder:toString	()Ljava/lang/String;
    //   555: invokestatic 120	com/appsflyer/LogMessages:b	(Ljava/lang/String;)V
    //   558: aload 6
    //   560: astore 4
    //   562: aload 10
    //   564: invokevirtual 208	java/lang/StringBuilder:length	()I
    //   567: ifle +187 -> 754
    //   570: aload 9
    //   572: ifnull +182 -> 754
    //   575: aload 6
    //   577: astore 4
    //   579: aload 10
    //   581: invokevirtual 98	java/lang/StringBuilder:toString	()Ljava/lang/String;
    //   584: invokestatic 211	com/appsflyer/AppsFlyerLib:d	(Ljava/lang/String;)Ljava/util/Map;
    //   587: astore 5
    //   589: aload 6
    //   591: astore 4
    //   593: aload 5
    //   595: ldc -43
    //   597: invokeinterface 218 2 0
    //   602: checkcast 50	java/lang/String
    //   605: astore 7
    //   607: aload 7
    //   609: ifnull +31 -> 640
    //   612: aload 6
    //   614: astore 4
    //   616: ldc -36
    //   618: aload 7
    //   620: invokevirtual 224	java/lang/String:equals	(Ljava/lang/Object;)Z
    //   623: ifeq +17 -> 640
    //   626: aload 6
    //   628: astore 4
    //   630: aload 9
    //   632: ldc -30
    //   634: invokestatic 75	java/lang/System:currentTimeMillis	()J
    //   637: invokestatic 159	com/appsflyer/AppsFlyerLib:a	(Landroid/content/Context;Ljava/lang/String;J)V
    //   640: aload 6
    //   642: astore 4
    //   644: aload 9
    //   646: ldc -28
    //   648: aload 10
    //   650: invokevirtual 98	java/lang/StringBuilder:toString	()Ljava/lang/String;
    //   653: invokestatic 231	com/appsflyer/AppsFlyerLib:a	(Landroid/content/Context;Ljava/lang/String;Ljava/lang/String;)V
    //   656: aload 6
    //   658: astore 4
    //   660: aload 9
    //   662: invokestatic 113	com/appsflyer/AppsFlyerLib:e	(Landroid/content/Context;)Z
    //   665: ifeq +38 -> 703
    //   668: aload 6
    //   670: astore 4
    //   672: ldc -64
    //   674: new 88	java/lang/StringBuilder
    //   677: dup
    //   678: invokespecial 89	java/lang/StringBuilder:<init>	()V
    //   681: ldc -23
    //   683: invokevirtual 95	java/lang/StringBuilder:append	(Ljava/lang/String;)Ljava/lang/StringBuilder;
    //   686: aload 7
    //   688: invokevirtual 95	java/lang/StringBuilder:append	(Ljava/lang/String;)Ljava/lang/StringBuilder;
    //   691: ldc -21
    //   693: invokevirtual 95	java/lang/StringBuilder:append	(Ljava/lang/String;)Ljava/lang/StringBuilder;
    //   696: invokevirtual 98	java/lang/StringBuilder:toString	()Ljava/lang/String;
    //   699: invokestatic 238	android/util/Log:d	(Ljava/lang/String;Ljava/lang/String;)I
    //   702: pop
    //   703: aload 6
    //   705: astore 4
    //   707: invokestatic 185	com/appsflyer/AppsFlyerLib:b	()Lcom/appsflyer/AppsFlyerConversionListener;
    //   710: ifnull +44 -> 754
    //   713: aload 6
    //   715: astore 4
    //   717: getstatic 25	com/appsflyer/AppsFlyerLib$AttributionIdFetcher:d	Ljava/util/concurrent/atomic/AtomicInteger;
    //   720: invokevirtual 241	java/util/concurrent/atomic/AtomicInteger:intValue	()I
    //   723: istore_1
    //   724: iload_1
    //   725: iconst_1
    //   726: if_icmpgt +28 -> 754
    //   729: aload 6
    //   731: astore 4
    //   733: aload 9
    //   735: invokestatic 244	com/appsflyer/AppsFlyerLib:b	(Landroid/content/Context;)Ljava/util/Map;
    //   738: astore 7
    //   740: aload 7
    //   742: astore 5
    //   744: aload 6
    //   746: astore 4
    //   748: aload_0
    //   749: aload 5
    //   751: invokevirtual 246	com/appsflyer/AppsFlyerLib$AttributionIdFetcher:a	(Ljava/util/Map;)V
    //   754: getstatic 25	com/appsflyer/AppsFlyerLib$AttributionIdFetcher:d	Ljava/util/concurrent/atomic/AtomicInteger;
    //   757: invokevirtual 66	java/util/concurrent/atomic/AtomicInteger:decrementAndGet	()I
    //   760: pop
    //   761: aload 6
    //   763: ifnull -285 -> 478
    //   766: aload 6
    //   768: invokevirtual 200	java/net/HttpURLConnection:disconnect	()V
    //   771: goto -293 -> 478
    //   774: astore 4
    //   776: goto -32 -> 744
    //   779: aload 6
    //   781: astore 4
    //   783: invokestatic 185	com/appsflyer/AppsFlyerLib:b	()Lcom/appsflyer/AppsFlyerConversionListener;
    //   786: ifnull +39 -> 825
    //   789: aload 6
    //   791: astore 4
    //   793: aload_0
    //   794: new 88	java/lang/StringBuilder
    //   797: dup
    //   798: invokespecial 89	java/lang/StringBuilder:<init>	()V
    //   801: ldc -8
    //   803: invokevirtual 95	java/lang/StringBuilder:append	(Ljava/lang/String;)Ljava/lang/StringBuilder;
    //   806: aload 6
    //   808: invokevirtual 152	java/net/HttpURLConnection:getResponseCode	()I
    //   811: invokevirtual 251	java/lang/StringBuilder:append	(I)Ljava/lang/StringBuilder;
    //   814: invokevirtual 98	java/lang/StringBuilder:toString	()Ljava/lang/String;
    //   817: aload 6
    //   819: invokevirtual 152	java/net/HttpURLConnection:getResponseCode	()I
    //   822: invokevirtual 190	com/appsflyer/AppsFlyerLib$AttributionIdFetcher:a	(Ljava/lang/String;I)V
    //   825: aload 6
    //   827: astore 4
    //   829: aload 9
    //   831: invokestatic 113	com/appsflyer/AppsFlyerLib:e	(Landroid/content/Context;)Z
    //   834: ifeq -80 -> 754
    //   837: aload 6
    //   839: astore 4
    //   841: new 88	java/lang/StringBuilder
    //   844: dup
    //   845: invokespecial 89	java/lang/StringBuilder:<init>	()V
    //   848: ldc -3
    //   850: invokevirtual 95	java/lang/StringBuilder:append	(Ljava/lang/String;)Ljava/lang/StringBuilder;
    //   853: aload 6
    //   855: invokevirtual 152	java/net/HttpURLConnection:getResponseCode	()I
    //   858: invokevirtual 251	java/lang/StringBuilder:append	(I)Ljava/lang/StringBuilder;
    //   861: ldc -1
    //   863: invokevirtual 95	java/lang/StringBuilder:append	(Ljava/lang/String;)Ljava/lang/StringBuilder;
    //   866: aload 5
    //   868: invokevirtual 258	java/lang/StringBuilder:append	(Ljava/lang/Object;)Ljava/lang/StringBuilder;
    //   871: invokevirtual 98	java/lang/StringBuilder:toString	()Ljava/lang/String;
    //   874: invokestatic 120	com/appsflyer/LogMessages:b	(Ljava/lang/String;)V
    //   877: goto -123 -> 754
    //   880: astore 6
    //   882: aload 4
    //   884: astore 5
    //   886: aload 6
    //   888: astore 4
    //   890: getstatic 25	com/appsflyer/AppsFlyerLib$AttributionIdFetcher:d	Ljava/util/concurrent/atomic/AtomicInteger;
    //   893: invokevirtual 66	java/util/concurrent/atomic/AtomicInteger:decrementAndGet	()I
    //   896: pop
    //   897: aload 5
    //   899: ifnull +8 -> 907
    //   902: aload 5
    //   904: invokevirtual 200	java/net/HttpURLConnection:disconnect	()V
    //   907: aload 4
    //   909: athrow
    //   910: astore 4
    //   912: aconst_null
    //   913: astore 5
    //   915: goto -25 -> 890
    //   918: astore 6
    //   920: aconst_null
    //   921: astore 5
    //   923: goto -503 -> 420
    //   926: astore 5
    //   928: aconst_null
    //   929: astore 8
    //   931: goto -556 -> 375
    //   934: astore 5
    //   936: goto -561 -> 375
    // Local variable table:
    //   start	length	slot	name	signature
    //   0	939	0	this	AttributionIdFetcher
    //   723	4	1	i	int
    //   67	224	2	l	long
    //   82	270	4	localObject1	Object
    //   365	7	4	localObject2	Object
    //   382	24	4	localObject3	Object
    //   410	7	4	localThrowable1	Throwable
    //   422	325	4	localObject4	Object
    //   774	1	4	localAttributionIDNotReady	AttributionIDNotReady
    //   781	127	4	localObject5	Object
    //   910	1	4	localObject6	Object
    //   78	844	5	localObject7	Object
    //   926	1	5	localObject8	Object
    //   934	1	5	localObject9	Object
    //   217	637	6	localObject10	Object
    //   880	7	6	localObject11	Object
    //   918	1	6	localThrowable2	Throwable
    //   1	740	7	localObject12	Object
    //   324	606	8	localInputStreamReader	java.io.InputStreamReader
    //   38	792	9	localContext	Context
    //   310	339	10	localStringBuilder	StringBuilder
    // Exception table:
    //   from	to	target	type
    //   337	344	365	finally
    //   349	362	365	finally
    //   223	230	410	java/lang/Throwable
    //   234	242	410	java/lang/Throwable
    //   246	255	410	java/lang/Throwable
    //   259	264	410	java/lang/Throwable
    //   268	279	410	java/lang/Throwable
    //   283	299	410	java/lang/Throwable
    //   303	312	410	java/lang/Throwable
    //   384	389	410	java/lang/Throwable
    //   398	403	410	java/lang/Throwable
    //   407	410	410	java/lang/Throwable
    //   497	502	410	java/lang/Throwable
    //   511	516	410	java/lang/Throwable
    //   520	528	410	java/lang/Throwable
    //   532	558	410	java/lang/Throwable
    //   562	570	410	java/lang/Throwable
    //   579	589	410	java/lang/Throwable
    //   593	607	410	java/lang/Throwable
    //   616	626	410	java/lang/Throwable
    //   630	640	410	java/lang/Throwable
    //   644	656	410	java/lang/Throwable
    //   660	668	410	java/lang/Throwable
    //   672	703	410	java/lang/Throwable
    //   707	713	410	java/lang/Throwable
    //   717	724	410	java/lang/Throwable
    //   733	740	410	java/lang/Throwable
    //   748	754	410	java/lang/Throwable
    //   783	789	410	java/lang/Throwable
    //   793	825	410	java/lang/Throwable
    //   829	837	410	java/lang/Throwable
    //   841	877	410	java/lang/Throwable
    //   733	740	774	com/appsflyer/AttributionIDNotReady
    //   223	230	880	finally
    //   234	242	880	finally
    //   246	255	880	finally
    //   259	264	880	finally
    //   268	279	880	finally
    //   283	299	880	finally
    //   303	312	880	finally
    //   384	389	880	finally
    //   398	403	880	finally
    //   407	410	880	finally
    //   424	430	880	finally
    //   434	444	880	finally
    //   448	461	880	finally
    //   497	502	880	finally
    //   511	516	880	finally
    //   520	528	880	finally
    //   532	558	880	finally
    //   562	570	880	finally
    //   579	589	880	finally
    //   593	607	880	finally
    //   616	626	880	finally
    //   630	640	880	finally
    //   644	656	880	finally
    //   660	668	880	finally
    //   672	703	880	finally
    //   707	713	880	finally
    //   717	724	880	finally
    //   733	740	880	finally
    //   748	754	880	finally
    //   783	789	880	finally
    //   793	825	880	finally
    //   829	837	880	finally
    //   841	877	880	finally
    //   28	40	910	finally
    //   64	80	910	finally
    //   89	111	910	finally
    //   111	199	910	finally
    //   199	219	910	finally
    //   28	40	918	java/lang/Throwable
    //   64	80	918	java/lang/Throwable
    //   89	111	918	java/lang/Throwable
    //   111	199	918	java/lang/Throwable
    //   199	219	918	java/lang/Throwable
    //   312	326	926	finally
    //   326	337	934	finally
  }
}

/* Location:
 * Qualified Name:     com.appsflyer.AppsFlyerLib.AttributionIdFetcher
 * Java Class Version: 6 (50.0)
 * JD-Core Version:    0.7.1
 */