package com.estrongs.android.ftp;

class c
  extends Thread
{
  c(a parama) {}
  
  /* Error */
  public void run()
  {
    // Byte code:
    //   0: aload_0
    //   1: getfield 10	com/estrongs/android/ftp/c:a	Lcom/estrongs/android/ftp/a;
    //   4: iconst_1
    //   5: putfield 23	com/estrongs/android/ftp/a:e	Z
    //   8: getstatic 26	com/estrongs/android/ftp/a:d	Z
    //   11: ifne +41 -> 52
    //   14: aload_0
    //   15: getfield 10	com/estrongs/android/ftp/c:a	Lcom/estrongs/android/ftp/a;
    //   18: invokestatic 29	com/estrongs/android/ftp/a:e	(Lcom/estrongs/android/ftp/a;)Ljava/net/ServerSocket;
    //   21: invokevirtual 35	java/net/ServerSocket:accept	()Ljava/net/Socket;
    //   24: astore_2
    //   25: getstatic 38	com/estrongs/android/ftp/a:i	Z
    //   28: istore_1
    //   29: iload_1
    //   30: ifeq +14 -> 44
    //   33: aload_2
    //   34: invokevirtual 43	java/net/Socket:close	()V
    //   37: goto -29 -> 8
    //   40: astore_2
    //   41: goto -33 -> 8
    //   44: getstatic 26	com/estrongs/android/ftp/a:d	Z
    //   47: istore_1
    //   48: iload_1
    //   49: ifeq +36 -> 85
    //   52: aload_0
    //   53: getfield 10	com/estrongs/android/ftp/c:a	Lcom/estrongs/android/ftp/a;
    //   56: invokestatic 29	com/estrongs/android/ftp/a:e	(Lcom/estrongs/android/ftp/a;)Ljava/net/ServerSocket;
    //   59: ifnull +13 -> 72
    //   62: aload_0
    //   63: getfield 10	com/estrongs/android/ftp/c:a	Lcom/estrongs/android/ftp/a;
    //   66: invokestatic 29	com/estrongs/android/ftp/a:e	(Lcom/estrongs/android/ftp/a;)Ljava/net/ServerSocket;
    //   69: invokevirtual 44	java/net/ServerSocket:close	()V
    //   72: aload_0
    //   73: getfield 10	com/estrongs/android/ftp/c:a	Lcom/estrongs/android/ftp/a;
    //   76: iconst_0
    //   77: putfield 23	com/estrongs/android/ftp/a:e	Z
    //   80: iconst_0
    //   81: putstatic 26	com/estrongs/android/ftp/a:d	Z
    //   84: return
    //   85: new 46	com/estrongs/android/ftp/h
    //   88: dup
    //   89: aload_2
    //   90: aload_0
    //   91: getfield 10	com/estrongs/android/ftp/c:a	Lcom/estrongs/android/ftp/a;
    //   94: invokespecial 49	com/estrongs/android/ftp/h:<init>	(Ljava/net/Socket;Lcom/estrongs/android/ftp/a;)V
    //   97: astore_2
    //   98: aload_2
    //   99: getstatic 53	com/estrongs/android/ftp/a:f	Ljava/lang/String;
    //   102: invokevirtual 56	com/estrongs/android/ftp/h:a	(Ljava/lang/String;)V
    //   105: aload_2
    //   106: invokevirtual 59	com/estrongs/android/ftp/h:start	()V
    //   109: goto -101 -> 8
    //   112: astore_2
    //   113: aload_2
    //   114: invokevirtual 62	java/lang/Exception:printStackTrace	()V
    //   117: aload_0
    //   118: getfield 10	com/estrongs/android/ftp/c:a	Lcom/estrongs/android/ftp/a;
    //   121: invokestatic 29	com/estrongs/android/ftp/a:e	(Lcom/estrongs/android/ftp/a;)Ljava/net/ServerSocket;
    //   124: ifnull +13 -> 137
    //   127: aload_0
    //   128: getfield 10	com/estrongs/android/ftp/c:a	Lcom/estrongs/android/ftp/a;
    //   131: invokestatic 29	com/estrongs/android/ftp/a:e	(Lcom/estrongs/android/ftp/a;)Ljava/net/ServerSocket;
    //   134: invokevirtual 44	java/net/ServerSocket:close	()V
    //   137: aload_0
    //   138: getfield 10	com/estrongs/android/ftp/c:a	Lcom/estrongs/android/ftp/a;
    //   141: iconst_0
    //   142: putfield 23	com/estrongs/android/ftp/a:e	Z
    //   145: iconst_0
    //   146: putstatic 26	com/estrongs/android/ftp/a:d	Z
    //   149: return
    //   150: astore_2
    //   151: aload_0
    //   152: getfield 10	com/estrongs/android/ftp/c:a	Lcom/estrongs/android/ftp/a;
    //   155: invokestatic 29	com/estrongs/android/ftp/a:e	(Lcom/estrongs/android/ftp/a;)Ljava/net/ServerSocket;
    //   158: ifnull +13 -> 171
    //   161: aload_0
    //   162: getfield 10	com/estrongs/android/ftp/c:a	Lcom/estrongs/android/ftp/a;
    //   165: invokestatic 29	com/estrongs/android/ftp/a:e	(Lcom/estrongs/android/ftp/a;)Ljava/net/ServerSocket;
    //   168: invokevirtual 44	java/net/ServerSocket:close	()V
    //   171: aload_0
    //   172: getfield 10	com/estrongs/android/ftp/c:a	Lcom/estrongs/android/ftp/a;
    //   175: iconst_0
    //   176: putfield 23	com/estrongs/android/ftp/a:e	Z
    //   179: iconst_0
    //   180: putstatic 26	com/estrongs/android/ftp/a:d	Z
    //   183: aload_2
    //   184: athrow
    //   185: astore_3
    //   186: goto -15 -> 171
    //   189: astore_2
    //   190: goto -53 -> 137
    //   193: astore_2
    //   194: goto -122 -> 72
    // Local variable table:
    //   start	length	slot	name	signature
    //   0	197	0	this	c
    //   28	21	1	bool	boolean
    //   24	10	2	localSocket	java.net.Socket
    //   40	50	2	localException1	Exception
    //   97	9	2	localh	h
    //   112	2	2	localException2	Exception
    //   150	34	2	localObject	Object
    //   189	1	2	localException3	Exception
    //   193	1	2	localException4	Exception
    //   185	1	3	localException5	Exception
    // Exception table:
    //   from	to	target	type
    //   33	37	40	java/lang/Exception
    //   0	8	112	java/lang/Exception
    //   8	29	112	java/lang/Exception
    //   44	48	112	java/lang/Exception
    //   85	109	112	java/lang/Exception
    //   0	8	150	finally
    //   8	29	150	finally
    //   33	37	150	finally
    //   44	48	150	finally
    //   85	109	150	finally
    //   113	117	150	finally
    //   151	171	185	java/lang/Exception
    //   117	137	189	java/lang/Exception
    //   52	72	193	java/lang/Exception
  }
}

/* Location:
 * Qualified Name:     com.estrongs.android.ftp.c
 * Java Class Version: 6 (50.0)
 * JD-Core Version:    0.7.1
 */