package com.estrongs.android.ftp;

import java.net.InetAddress;
import java.net.ServerSocket;
import java.util.concurrent.locks.Lock;
import java.util.concurrent.locks.ReentrantLock;

public class i
  extends Thread
{
  public ServerSocket a = null;
  public InetAddress b = null;
  public int c;
  public int d = 0;
  public Object e = null;
  public boolean f = false;
  public Lock g = new ReentrantLock();
  
  public i(h paramh) {}
  
  public void a()
  {
    try
    {
      if (a != null) {
        a.close();
      }
      g.unlock();
      return;
    }
    catch (Exception localException) {}
  }
  
  /* Error */
  public void run()
  {
    // Byte code:
    //   0: iconst_0
    //   1: istore_1
    //   2: aconst_null
    //   3: astore 5
    //   5: aload_0
    //   6: getfield 23	com/estrongs/android/ftp/i:h	Lcom/estrongs/android/ftp/h;
    //   9: invokestatic 60	com/estrongs/android/ftp/h:a	(Lcom/estrongs/android/ftp/h;)Ljava/lang/Integer;
    //   12: astore_3
    //   13: aload_3
    //   14: monitorenter
    //   15: aload_0
    //   16: getfield 23	com/estrongs/android/ftp/i:h	Lcom/estrongs/android/ftp/h;
    //   19: invokestatic 60	com/estrongs/android/ftp/h:a	(Lcom/estrongs/android/ftp/h;)Ljava/lang/Integer;
    //   22: invokevirtual 66	java/lang/Integer:intValue	()I
    //   25: ifne +27 -> 52
    //   28: aload_0
    //   29: getfield 23	com/estrongs/android/ftp/i:h	Lcom/estrongs/android/ftp/h;
    //   32: aload_0
    //   33: invokevirtual 71	java/lang/Object:hashCode	()I
    //   36: invokestatic 75	java/lang/Integer:valueOf	(I)Ljava/lang/Integer;
    //   39: invokestatic 78	com/estrongs/android/ftp/h:a	(Lcom/estrongs/android/ftp/h;Ljava/lang/Integer;)Ljava/lang/Integer;
    //   42: pop
    //   43: aload_0
    //   44: getfield 23	com/estrongs/android/ftp/i:h	Lcom/estrongs/android/ftp/h;
    //   47: aload_0
    //   48: invokestatic 81	com/estrongs/android/ftp/h:a	(Lcom/estrongs/android/ftp/h;Lcom/estrongs/android/ftp/i;)Lcom/estrongs/android/ftp/i;
    //   51: pop
    //   52: aload_3
    //   53: monitorexit
    //   54: aload_0
    //   55: getfield 28	com/estrongs/android/ftp/i:a	Ljava/net/ServerSocket;
    //   58: ifnull +1749 -> 1807
    //   61: aload_0
    //   62: getfield 28	com/estrongs/android/ftp/i:a	Ljava/net/ServerSocket;
    //   65: invokevirtual 85	java/net/ServerSocket:accept	()Ljava/net/Socket;
    //   68: astore_3
    //   69: aload_0
    //   70: getfield 28	com/estrongs/android/ftp/i:a	Ljava/net/ServerSocket;
    //   73: invokevirtual 49	java/net/ServerSocket:close	()V
    //   76: aload_0
    //   77: getfield 41	com/estrongs/android/ftp/i:g	Ljava/util/concurrent/locks/Lock;
    //   80: invokeinterface 88 1 0
    //   85: aload_0
    //   86: getfield 41	com/estrongs/android/ftp/i:g	Ljava/util/concurrent/locks/Lock;
    //   89: invokeinterface 54 1 0
    //   94: aload_0
    //   95: getfield 36	com/estrongs/android/ftp/i:f	Z
    //   98: ifne +10 -> 108
    //   101: aload_0
    //   102: getfield 32	com/estrongs/android/ftp/i:d	I
    //   105: ifne +127 -> 232
    //   108: aload_0
    //   109: getfield 23	com/estrongs/android/ftp/i:h	Lcom/estrongs/android/ftp/h;
    //   112: invokestatic 60	com/estrongs/android/ftp/h:a	(Lcom/estrongs/android/ftp/h;)Ljava/lang/Integer;
    //   115: astore_3
    //   116: aload_3
    //   117: monitorenter
    //   118: aload_0
    //   119: getfield 23	com/estrongs/android/ftp/i:h	Lcom/estrongs/android/ftp/h;
    //   122: invokestatic 60	com/estrongs/android/ftp/h:a	(Lcom/estrongs/android/ftp/h;)Ljava/lang/Integer;
    //   125: invokevirtual 66	java/lang/Integer:intValue	()I
    //   128: aload_0
    //   129: invokevirtual 71	java/lang/Object:hashCode	()I
    //   132: if_icmpne +24 -> 156
    //   135: aload_0
    //   136: getfield 23	com/estrongs/android/ftp/i:h	Lcom/estrongs/android/ftp/h;
    //   139: iconst_0
    //   140: invokestatic 75	java/lang/Integer:valueOf	(I)Ljava/lang/Integer;
    //   143: invokestatic 78	com/estrongs/android/ftp/h:a	(Lcom/estrongs/android/ftp/h;Ljava/lang/Integer;)Ljava/lang/Integer;
    //   146: pop
    //   147: aload_0
    //   148: getfield 23	com/estrongs/android/ftp/i:h	Lcom/estrongs/android/ftp/h;
    //   151: aconst_null
    //   152: invokestatic 81	com/estrongs/android/ftp/h:a	(Lcom/estrongs/android/ftp/h;Lcom/estrongs/android/ftp/i;)Lcom/estrongs/android/ftp/i;
    //   155: pop
    //   156: aload_3
    //   157: monitorexit
    //   158: aload_0
    //   159: getfield 36	com/estrongs/android/ftp/i:f	Z
    //   162: ifeq +12 -> 174
    //   165: aload_0
    //   166: getfield 23	com/estrongs/android/ftp/i:h	Lcom/estrongs/android/ftp/h;
    //   169: ldc 90
    //   171: invokestatic 93	com/estrongs/android/ftp/h:a	(Lcom/estrongs/android/ftp/h;Ljava/lang/String;)V
    //   174: return
    //   175: astore 4
    //   177: aload_3
    //   178: monitorexit
    //   179: aload 4
    //   181: athrow
    //   182: astore_3
    //   183: aload_3
    //   184: invokevirtual 96	java/lang/Exception:printStackTrace	()V
    //   187: aload_0
    //   188: getfield 28	com/estrongs/android/ftp/i:a	Ljava/net/ServerSocket;
    //   191: invokevirtual 49	java/net/ServerSocket:close	()V
    //   194: aconst_null
    //   195: astore_3
    //   196: goto -120 -> 76
    //   199: astore_3
    //   200: aconst_null
    //   201: astore_3
    //   202: goto -126 -> 76
    //   205: astore_3
    //   206: aload_0
    //   207: getfield 28	com/estrongs/android/ftp/i:a	Ljava/net/ServerSocket;
    //   210: invokevirtual 49	java/net/ServerSocket:close	()V
    //   213: aload_3
    //   214: athrow
    //   215: astore 4
    //   217: aload 4
    //   219: invokevirtual 96	java/lang/Exception:printStackTrace	()V
    //   222: goto -128 -> 94
    //   225: astore 4
    //   227: aload_3
    //   228: monitorexit
    //   229: aload 4
    //   231: athrow
    //   232: aload_3
    //   233: astore 4
    //   235: aload_3
    //   236: ifnonnull +40 -> 276
    //   239: aload_3
    //   240: astore 4
    //   242: aload_0
    //   243: getfield 30	com/estrongs/android/ftp/i:b	Ljava/net/InetAddress;
    //   246: ifnull +30 -> 276
    //   249: aload_3
    //   250: astore 4
    //   252: aload_0
    //   253: getfield 98	com/estrongs/android/ftp/i:c	I
    //   256: ifeq +20 -> 276
    //   259: new 100	java/net/Socket
    //   262: dup
    //   263: aload_0
    //   264: getfield 30	com/estrongs/android/ftp/i:b	Ljava/net/InetAddress;
    //   267: aload_0
    //   268: getfield 98	com/estrongs/android/ftp/i:c	I
    //   271: invokespecial 103	java/net/Socket:<init>	(Ljava/net/InetAddress;I)V
    //   274: astore 4
    //   276: aload 4
    //   278: astore_3
    //   279: aload_3
    //   280: ifnonnull +81 -> 361
    //   283: aload_0
    //   284: getfield 23	com/estrongs/android/ftp/i:h	Lcom/estrongs/android/ftp/h;
    //   287: invokestatic 60	com/estrongs/android/ftp/h:a	(Lcom/estrongs/android/ftp/h;)Ljava/lang/Integer;
    //   290: astore_3
    //   291: aload_3
    //   292: monitorenter
    //   293: aload_0
    //   294: getfield 23	com/estrongs/android/ftp/i:h	Lcom/estrongs/android/ftp/h;
    //   297: invokestatic 60	com/estrongs/android/ftp/h:a	(Lcom/estrongs/android/ftp/h;)Ljava/lang/Integer;
    //   300: invokevirtual 66	java/lang/Integer:intValue	()I
    //   303: aload_0
    //   304: invokevirtual 71	java/lang/Object:hashCode	()I
    //   307: if_icmpne +24 -> 331
    //   310: aload_0
    //   311: getfield 23	com/estrongs/android/ftp/i:h	Lcom/estrongs/android/ftp/h;
    //   314: iconst_0
    //   315: invokestatic 75	java/lang/Integer:valueOf	(I)Ljava/lang/Integer;
    //   318: invokestatic 78	com/estrongs/android/ftp/h:a	(Lcom/estrongs/android/ftp/h;Ljava/lang/Integer;)Ljava/lang/Integer;
    //   321: pop
    //   322: aload_0
    //   323: getfield 23	com/estrongs/android/ftp/i:h	Lcom/estrongs/android/ftp/h;
    //   326: aconst_null
    //   327: invokestatic 81	com/estrongs/android/ftp/h:a	(Lcom/estrongs/android/ftp/h;Lcom/estrongs/android/ftp/i;)Lcom/estrongs/android/ftp/i;
    //   330: pop
    //   331: aload_3
    //   332: monitorexit
    //   333: aload_0
    //   334: getfield 23	com/estrongs/android/ftp/i:h	Lcom/estrongs/android/ftp/h;
    //   337: ldc 105
    //   339: invokestatic 93	com/estrongs/android/ftp/h:a	(Lcom/estrongs/android/ftp/h;Ljava/lang/String;)V
    //   342: return
    //   343: astore_3
    //   344: aload_3
    //   345: invokevirtual 96	java/lang/Exception:printStackTrace	()V
    //   348: aload 5
    //   350: astore_3
    //   351: goto -72 -> 279
    //   354: astore 4
    //   356: aload_3
    //   357: monitorexit
    //   358: aload 4
    //   360: athrow
    //   361: aload_0
    //   362: getfield 32	com/estrongs/android/ftp/i:d	I
    //   365: iconst_1
    //   366: if_icmpeq +27 -> 393
    //   369: aload_0
    //   370: getfield 32	com/estrongs/android/ftp/i:d	I
    //   373: iconst_2
    //   374: if_icmpeq +19 -> 393
    //   377: aload_0
    //   378: getfield 32	com/estrongs/android/ftp/i:d	I
    //   381: iconst_3
    //   382: if_icmpeq +11 -> 393
    //   385: aload_0
    //   386: getfield 32	com/estrongs/android/ftp/i:d	I
    //   389: iconst_4
    //   390: if_icmpne +555 -> 945
    //   393: aload_0
    //   394: getfield 34	com/estrongs/android/ftp/i:e	Ljava/lang/Object;
    //   397: checkcast 107	java/lang/String
    //   400: astore 4
    //   402: aload 4
    //   404: ifnonnull +94 -> 498
    //   407: aload_0
    //   408: getfield 23	com/estrongs/android/ftp/i:h	Lcom/estrongs/android/ftp/h;
    //   411: ldc 109
    //   413: invokestatic 93	com/estrongs/android/ftp/h:a	(Lcom/estrongs/android/ftp/h;Ljava/lang/String;)V
    //   416: aload_3
    //   417: ifnull +7 -> 424
    //   420: aload_3
    //   421: invokevirtual 110	java/net/Socket:close	()V
    //   424: aload_0
    //   425: getfield 23	com/estrongs/android/ftp/i:h	Lcom/estrongs/android/ftp/h;
    //   428: invokestatic 60	com/estrongs/android/ftp/h:a	(Lcom/estrongs/android/ftp/h;)Ljava/lang/Integer;
    //   431: astore_3
    //   432: aload_3
    //   433: monitorenter
    //   434: aload_0
    //   435: getfield 23	com/estrongs/android/ftp/i:h	Lcom/estrongs/android/ftp/h;
    //   438: invokestatic 60	com/estrongs/android/ftp/h:a	(Lcom/estrongs/android/ftp/h;)Ljava/lang/Integer;
    //   441: invokevirtual 66	java/lang/Integer:intValue	()I
    //   444: aload_0
    //   445: invokevirtual 71	java/lang/Object:hashCode	()I
    //   448: if_icmpne +24 -> 472
    //   451: aload_0
    //   452: getfield 23	com/estrongs/android/ftp/i:h	Lcom/estrongs/android/ftp/h;
    //   455: iconst_0
    //   456: invokestatic 75	java/lang/Integer:valueOf	(I)Ljava/lang/Integer;
    //   459: invokestatic 78	com/estrongs/android/ftp/h:a	(Lcom/estrongs/android/ftp/h;Ljava/lang/Integer;)Ljava/lang/Integer;
    //   462: pop
    //   463: aload_0
    //   464: getfield 23	com/estrongs/android/ftp/i:h	Lcom/estrongs/android/ftp/h;
    //   467: aconst_null
    //   468: invokestatic 81	com/estrongs/android/ftp/h:a	(Lcom/estrongs/android/ftp/h;Lcom/estrongs/android/ftp/i;)Lcom/estrongs/android/ftp/i;
    //   471: pop
    //   472: aload_3
    //   473: monitorexit
    //   474: aload_0
    //   475: getfield 36	com/estrongs/android/ftp/i:f	Z
    //   478: ifeq -304 -> 174
    //   481: aload_0
    //   482: getfield 23	com/estrongs/android/ftp/i:h	Lcom/estrongs/android/ftp/h;
    //   485: ldc 90
    //   487: invokestatic 93	com/estrongs/android/ftp/h:a	(Lcom/estrongs/android/ftp/h;Ljava/lang/String;)V
    //   490: return
    //   491: astore 4
    //   493: aload_3
    //   494: monitorexit
    //   495: aload 4
    //   497: athrow
    //   498: new 112	java/io/File
    //   501: dup
    //   502: aload 4
    //   504: invokespecial 115	java/io/File:<init>	(Ljava/lang/String;)V
    //   507: astore 5
    //   509: getstatic 121	java/lang/System:out	Ljava/io/PrintStream;
    //   512: new 123	java/lang/StringBuilder
    //   515: dup
    //   516: invokespecial 124	java/lang/StringBuilder:<init>	()V
    //   519: ldc 126
    //   521: invokevirtual 130	java/lang/StringBuilder:append	(Ljava/lang/String;)Ljava/lang/StringBuilder;
    //   524: aload 4
    //   526: invokevirtual 130	java/lang/StringBuilder:append	(Ljava/lang/String;)Ljava/lang/StringBuilder;
    //   529: invokevirtual 134	java/lang/StringBuilder:toString	()Ljava/lang/String;
    //   532: invokevirtual 139	java/io/PrintStream:println	(Ljava/lang/String;)V
    //   535: aload_0
    //   536: getfield 32	com/estrongs/android/ftp/i:d	I
    //   539: iconst_4
    //   540: if_icmpeq +102 -> 642
    //   543: aload 5
    //   545: invokevirtual 143	java/io/File:exists	()Z
    //   548: ifne +94 -> 642
    //   551: aload_0
    //   552: getfield 23	com/estrongs/android/ftp/i:h	Lcom/estrongs/android/ftp/h;
    //   555: ldc 109
    //   557: invokestatic 93	com/estrongs/android/ftp/h:a	(Lcom/estrongs/android/ftp/h;Ljava/lang/String;)V
    //   560: aload_3
    //   561: ifnull +7 -> 568
    //   564: aload_3
    //   565: invokevirtual 110	java/net/Socket:close	()V
    //   568: aload_0
    //   569: getfield 23	com/estrongs/android/ftp/i:h	Lcom/estrongs/android/ftp/h;
    //   572: invokestatic 60	com/estrongs/android/ftp/h:a	(Lcom/estrongs/android/ftp/h;)Ljava/lang/Integer;
    //   575: astore_3
    //   576: aload_3
    //   577: monitorenter
    //   578: aload_0
    //   579: getfield 23	com/estrongs/android/ftp/i:h	Lcom/estrongs/android/ftp/h;
    //   582: invokestatic 60	com/estrongs/android/ftp/h:a	(Lcom/estrongs/android/ftp/h;)Ljava/lang/Integer;
    //   585: invokevirtual 66	java/lang/Integer:intValue	()I
    //   588: aload_0
    //   589: invokevirtual 71	java/lang/Object:hashCode	()I
    //   592: if_icmpne +24 -> 616
    //   595: aload_0
    //   596: getfield 23	com/estrongs/android/ftp/i:h	Lcom/estrongs/android/ftp/h;
    //   599: iconst_0
    //   600: invokestatic 75	java/lang/Integer:valueOf	(I)Ljava/lang/Integer;
    //   603: invokestatic 78	com/estrongs/android/ftp/h:a	(Lcom/estrongs/android/ftp/h;Ljava/lang/Integer;)Ljava/lang/Integer;
    //   606: pop
    //   607: aload_0
    //   608: getfield 23	com/estrongs/android/ftp/i:h	Lcom/estrongs/android/ftp/h;
    //   611: aconst_null
    //   612: invokestatic 81	com/estrongs/android/ftp/h:a	(Lcom/estrongs/android/ftp/h;Lcom/estrongs/android/ftp/i;)Lcom/estrongs/android/ftp/i;
    //   615: pop
    //   616: aload_3
    //   617: monitorexit
    //   618: aload_0
    //   619: getfield 36	com/estrongs/android/ftp/i:f	Z
    //   622: ifeq -448 -> 174
    //   625: aload_0
    //   626: getfield 23	com/estrongs/android/ftp/i:h	Lcom/estrongs/android/ftp/h;
    //   629: ldc 90
    //   631: invokestatic 93	com/estrongs/android/ftp/h:a	(Lcom/estrongs/android/ftp/h;Ljava/lang/String;)V
    //   634: return
    //   635: astore 4
    //   637: aload_3
    //   638: monitorexit
    //   639: aload 4
    //   641: athrow
    //   642: aload_0
    //   643: getfield 23	com/estrongs/android/ftp/i:h	Lcom/estrongs/android/ftp/h;
    //   646: ldc -111
    //   648: invokestatic 93	com/estrongs/android/ftp/h:a	(Lcom/estrongs/android/ftp/h;Ljava/lang/String;)V
    //   651: new 123	java/lang/StringBuilder
    //   654: dup
    //   655: invokespecial 124	java/lang/StringBuilder:<init>	()V
    //   658: astore 4
    //   660: aload 5
    //   662: invokevirtual 148	java/io/File:isDirectory	()Z
    //   665: ifne +138 -> 803
    //   668: aload_0
    //   669: getfield 23	com/estrongs/android/ftp/i:h	Lcom/estrongs/android/ftp/h;
    //   672: aload_0
    //   673: getfield 32	com/estrongs/android/ftp/i:d	I
    //   676: aload 5
    //   678: invokevirtual 151	com/estrongs/android/ftp/h:a	(ILjava/io/File;)Ljava/lang/String;
    //   681: astore 5
    //   683: aload 5
    //   685: ifnull +11 -> 696
    //   688: aload 4
    //   690: aload 5
    //   692: invokevirtual 130	java/lang/StringBuilder:append	(Ljava/lang/String;)Ljava/lang/StringBuilder;
    //   695: pop
    //   696: aload_0
    //   697: getfield 23	com/estrongs/android/ftp/i:h	Lcom/estrongs/android/ftp/h;
    //   700: new 153	java/io/BufferedOutputStream
    //   703: dup
    //   704: aload_3
    //   705: invokevirtual 157	java/net/Socket:getOutputStream	()Ljava/io/OutputStream;
    //   708: invokespecial 160	java/io/BufferedOutputStream:<init>	(Ljava/io/OutputStream;)V
    //   711: aload 4
    //   713: invokevirtual 134	java/lang/StringBuilder:toString	()Ljava/lang/String;
    //   716: invokestatic 163	com/estrongs/android/ftp/h:a	(Lcom/estrongs/android/ftp/h;Ljava/io/BufferedOutputStream;Ljava/lang/String;)V
    //   719: aload_0
    //   720: getfield 23	com/estrongs/android/ftp/i:h	Lcom/estrongs/android/ftp/h;
    //   723: ldc -91
    //   725: invokestatic 93	com/estrongs/android/ftp/h:a	(Lcom/estrongs/android/ftp/h;Ljava/lang/String;)V
    //   728: aload_3
    //   729: ifnull +7 -> 736
    //   732: aload_3
    //   733: invokevirtual 110	java/net/Socket:close	()V
    //   736: aload_0
    //   737: getfield 23	com/estrongs/android/ftp/i:h	Lcom/estrongs/android/ftp/h;
    //   740: invokestatic 60	com/estrongs/android/ftp/h:a	(Lcom/estrongs/android/ftp/h;)Ljava/lang/Integer;
    //   743: astore_3
    //   744: aload_3
    //   745: monitorenter
    //   746: aload_0
    //   747: getfield 23	com/estrongs/android/ftp/i:h	Lcom/estrongs/android/ftp/h;
    //   750: invokestatic 60	com/estrongs/android/ftp/h:a	(Lcom/estrongs/android/ftp/h;)Ljava/lang/Integer;
    //   753: invokevirtual 66	java/lang/Integer:intValue	()I
    //   756: aload_0
    //   757: invokevirtual 71	java/lang/Object:hashCode	()I
    //   760: if_icmpne +24 -> 784
    //   763: aload_0
    //   764: getfield 23	com/estrongs/android/ftp/i:h	Lcom/estrongs/android/ftp/h;
    //   767: iconst_0
    //   768: invokestatic 75	java/lang/Integer:valueOf	(I)Ljava/lang/Integer;
    //   771: invokestatic 78	com/estrongs/android/ftp/h:a	(Lcom/estrongs/android/ftp/h;Ljava/lang/Integer;)Ljava/lang/Integer;
    //   774: pop
    //   775: aload_0
    //   776: getfield 23	com/estrongs/android/ftp/i:h	Lcom/estrongs/android/ftp/h;
    //   779: aconst_null
    //   780: invokestatic 81	com/estrongs/android/ftp/h:a	(Lcom/estrongs/android/ftp/h;Lcom/estrongs/android/ftp/i;)Lcom/estrongs/android/ftp/i;
    //   783: pop
    //   784: aload_3
    //   785: monitorexit
    //   786: aload_0
    //   787: getfield 36	com/estrongs/android/ftp/i:f	Z
    //   790: ifeq -616 -> 174
    //   793: aload_0
    //   794: getfield 23	com/estrongs/android/ftp/i:h	Lcom/estrongs/android/ftp/h;
    //   797: ldc 90
    //   799: invokestatic 93	com/estrongs/android/ftp/h:a	(Lcom/estrongs/android/ftp/h;Ljava/lang/String;)V
    //   802: return
    //   803: aload 5
    //   805: invokevirtual 169	java/io/File:listFiles	()[Ljava/io/File;
    //   808: astore 5
    //   810: iload_1
    //   811: aload 5
    //   813: arraylength
    //   814: if_icmpge -118 -> 696
    //   817: aload_0
    //   818: getfield 36	com/estrongs/android/ftp/i:f	Z
    //   821: istore_2
    //   822: iload_2
    //   823: ifeq +85 -> 908
    //   826: aload_3
    //   827: ifnull +7 -> 834
    //   830: aload_3
    //   831: invokevirtual 110	java/net/Socket:close	()V
    //   834: aload_0
    //   835: getfield 23	com/estrongs/android/ftp/i:h	Lcom/estrongs/android/ftp/h;
    //   838: invokestatic 60	com/estrongs/android/ftp/h:a	(Lcom/estrongs/android/ftp/h;)Ljava/lang/Integer;
    //   841: astore_3
    //   842: aload_3
    //   843: monitorenter
    //   844: aload_0
    //   845: getfield 23	com/estrongs/android/ftp/i:h	Lcom/estrongs/android/ftp/h;
    //   848: invokestatic 60	com/estrongs/android/ftp/h:a	(Lcom/estrongs/android/ftp/h;)Ljava/lang/Integer;
    //   851: invokevirtual 66	java/lang/Integer:intValue	()I
    //   854: aload_0
    //   855: invokevirtual 71	java/lang/Object:hashCode	()I
    //   858: if_icmpne +24 -> 882
    //   861: aload_0
    //   862: getfield 23	com/estrongs/android/ftp/i:h	Lcom/estrongs/android/ftp/h;
    //   865: iconst_0
    //   866: invokestatic 75	java/lang/Integer:valueOf	(I)Ljava/lang/Integer;
    //   869: invokestatic 78	com/estrongs/android/ftp/h:a	(Lcom/estrongs/android/ftp/h;Ljava/lang/Integer;)Ljava/lang/Integer;
    //   872: pop
    //   873: aload_0
    //   874: getfield 23	com/estrongs/android/ftp/i:h	Lcom/estrongs/android/ftp/h;
    //   877: aconst_null
    //   878: invokestatic 81	com/estrongs/android/ftp/h:a	(Lcom/estrongs/android/ftp/h;Lcom/estrongs/android/ftp/i;)Lcom/estrongs/android/ftp/i;
    //   881: pop
    //   882: aload_3
    //   883: monitorexit
    //   884: aload_0
    //   885: getfield 36	com/estrongs/android/ftp/i:f	Z
    //   888: ifeq -714 -> 174
    //   891: aload_0
    //   892: getfield 23	com/estrongs/android/ftp/i:h	Lcom/estrongs/android/ftp/h;
    //   895: ldc 90
    //   897: invokestatic 93	com/estrongs/android/ftp/h:a	(Lcom/estrongs/android/ftp/h;Ljava/lang/String;)V
    //   900: return
    //   901: astore 4
    //   903: aload_3
    //   904: monitorexit
    //   905: aload 4
    //   907: athrow
    //   908: aload_0
    //   909: getfield 23	com/estrongs/android/ftp/i:h	Lcom/estrongs/android/ftp/h;
    //   912: aload_0
    //   913: getfield 32	com/estrongs/android/ftp/i:d	I
    //   916: aload 5
    //   918: iload_1
    //   919: aaload
    //   920: invokevirtual 151	com/estrongs/android/ftp/h:a	(ILjava/io/File;)Ljava/lang/String;
    //   923: astore 6
    //   925: aload 6
    //   927: ifnull +11 -> 938
    //   930: aload 4
    //   932: aload 6
    //   934: invokevirtual 130	java/lang/StringBuilder:append	(Ljava/lang/String;)Ljava/lang/StringBuilder;
    //   937: pop
    //   938: iload_1
    //   939: iconst_1
    //   940: iadd
    //   941: istore_1
    //   942: goto -132 -> 810
    //   945: aload_0
    //   946: getfield 32	com/estrongs/android/ftp/i:d	I
    //   949: iconst_5
    //   950: if_icmpne +375 -> 1325
    //   953: aload_0
    //   954: getfield 34	com/estrongs/android/ftp/i:e	Ljava/lang/Object;
    //   957: checkcast 171	com/estrongs/android/ftp/j
    //   960: astore 4
    //   962: aload 4
    //   964: getfield 174	com/estrongs/android/ftp/j:b	Ljava/lang/String;
    //   967: astore 5
    //   969: new 112	java/io/File
    //   972: dup
    //   973: aload 5
    //   975: invokespecial 115	java/io/File:<init>	(Ljava/lang/String;)V
    //   978: astore 6
    //   980: aload 6
    //   982: invokevirtual 143	java/io/File:exists	()Z
    //   985: ifeq +23 -> 1008
    //   988: aload 6
    //   990: invokevirtual 148	java/io/File:isDirectory	()Z
    //   993: ifne +15 -> 1008
    //   996: aload_0
    //   997: getfield 23	com/estrongs/android/ftp/i:h	Lcom/estrongs/android/ftp/h;
    //   1000: aload 5
    //   1002: invokestatic 177	com/estrongs/android/ftp/h:b	(Lcom/estrongs/android/ftp/h;Ljava/lang/String;)Z
    //   1005: ifne +94 -> 1099
    //   1008: aload_0
    //   1009: getfield 23	com/estrongs/android/ftp/i:h	Lcom/estrongs/android/ftp/h;
    //   1012: ldc -77
    //   1014: invokestatic 93	com/estrongs/android/ftp/h:a	(Lcom/estrongs/android/ftp/h;Ljava/lang/String;)V
    //   1017: aload_3
    //   1018: ifnull +7 -> 1025
    //   1021: aload_3
    //   1022: invokevirtual 110	java/net/Socket:close	()V
    //   1025: aload_0
    //   1026: getfield 23	com/estrongs/android/ftp/i:h	Lcom/estrongs/android/ftp/h;
    //   1029: invokestatic 60	com/estrongs/android/ftp/h:a	(Lcom/estrongs/android/ftp/h;)Ljava/lang/Integer;
    //   1032: astore_3
    //   1033: aload_3
    //   1034: monitorenter
    //   1035: aload_0
    //   1036: getfield 23	com/estrongs/android/ftp/i:h	Lcom/estrongs/android/ftp/h;
    //   1039: invokestatic 60	com/estrongs/android/ftp/h:a	(Lcom/estrongs/android/ftp/h;)Ljava/lang/Integer;
    //   1042: invokevirtual 66	java/lang/Integer:intValue	()I
    //   1045: aload_0
    //   1046: invokevirtual 71	java/lang/Object:hashCode	()I
    //   1049: if_icmpne +24 -> 1073
    //   1052: aload_0
    //   1053: getfield 23	com/estrongs/android/ftp/i:h	Lcom/estrongs/android/ftp/h;
    //   1056: iconst_0
    //   1057: invokestatic 75	java/lang/Integer:valueOf	(I)Ljava/lang/Integer;
    //   1060: invokestatic 78	com/estrongs/android/ftp/h:a	(Lcom/estrongs/android/ftp/h;Ljava/lang/Integer;)Ljava/lang/Integer;
    //   1063: pop
    //   1064: aload_0
    //   1065: getfield 23	com/estrongs/android/ftp/i:h	Lcom/estrongs/android/ftp/h;
    //   1068: aconst_null
    //   1069: invokestatic 81	com/estrongs/android/ftp/h:a	(Lcom/estrongs/android/ftp/h;Lcom/estrongs/android/ftp/i;)Lcom/estrongs/android/ftp/i;
    //   1072: pop
    //   1073: aload_3
    //   1074: monitorexit
    //   1075: aload_0
    //   1076: getfield 36	com/estrongs/android/ftp/i:f	Z
    //   1079: ifeq -905 -> 174
    //   1082: aload_0
    //   1083: getfield 23	com/estrongs/android/ftp/i:h	Lcom/estrongs/android/ftp/h;
    //   1086: ldc 90
    //   1088: invokestatic 93	com/estrongs/android/ftp/h:a	(Lcom/estrongs/android/ftp/h;Ljava/lang/String;)V
    //   1091: return
    //   1092: astore 4
    //   1094: aload_3
    //   1095: monitorexit
    //   1096: aload 4
    //   1098: athrow
    //   1099: aload_0
    //   1100: getfield 23	com/estrongs/android/ftp/i:h	Lcom/estrongs/android/ftp/h;
    //   1103: ldc -75
    //   1105: invokestatic 93	com/estrongs/android/ftp/h:a	(Lcom/estrongs/android/ftp/h;Ljava/lang/String;)V
    //   1108: aload_0
    //   1109: getfield 23	com/estrongs/android/ftp/i:h	Lcom/estrongs/android/ftp/h;
    //   1112: aload_0
    //   1113: aload 6
    //   1115: aload_3
    //   1116: iconst_0
    //   1117: aload 4
    //   1119: getfield 184	com/estrongs/android/ftp/j:a	J
    //   1122: invokestatic 187	com/estrongs/android/ftp/h:a	(Lcom/estrongs/android/ftp/h;Lcom/estrongs/android/ftp/i;Ljava/io/File;Ljava/net/Socket;ZJ)V
    //   1125: aload_0
    //   1126: getfield 36	com/estrongs/android/ftp/i:f	Z
    //   1129: istore_2
    //   1130: iload_2
    //   1131: ifeq +85 -> 1216
    //   1134: aload_3
    //   1135: ifnull +7 -> 1142
    //   1138: aload_3
    //   1139: invokevirtual 110	java/net/Socket:close	()V
    //   1142: aload_0
    //   1143: getfield 23	com/estrongs/android/ftp/i:h	Lcom/estrongs/android/ftp/h;
    //   1146: invokestatic 60	com/estrongs/android/ftp/h:a	(Lcom/estrongs/android/ftp/h;)Ljava/lang/Integer;
    //   1149: astore_3
    //   1150: aload_3
    //   1151: monitorenter
    //   1152: aload_0
    //   1153: getfield 23	com/estrongs/android/ftp/i:h	Lcom/estrongs/android/ftp/h;
    //   1156: invokestatic 60	com/estrongs/android/ftp/h:a	(Lcom/estrongs/android/ftp/h;)Ljava/lang/Integer;
    //   1159: invokevirtual 66	java/lang/Integer:intValue	()I
    //   1162: aload_0
    //   1163: invokevirtual 71	java/lang/Object:hashCode	()I
    //   1166: if_icmpne +24 -> 1190
    //   1169: aload_0
    //   1170: getfield 23	com/estrongs/android/ftp/i:h	Lcom/estrongs/android/ftp/h;
    //   1173: iconst_0
    //   1174: invokestatic 75	java/lang/Integer:valueOf	(I)Ljava/lang/Integer;
    //   1177: invokestatic 78	com/estrongs/android/ftp/h:a	(Lcom/estrongs/android/ftp/h;Ljava/lang/Integer;)Ljava/lang/Integer;
    //   1180: pop
    //   1181: aload_0
    //   1182: getfield 23	com/estrongs/android/ftp/i:h	Lcom/estrongs/android/ftp/h;
    //   1185: aconst_null
    //   1186: invokestatic 81	com/estrongs/android/ftp/h:a	(Lcom/estrongs/android/ftp/h;Lcom/estrongs/android/ftp/i;)Lcom/estrongs/android/ftp/i;
    //   1189: pop
    //   1190: aload_3
    //   1191: monitorexit
    //   1192: aload_0
    //   1193: getfield 36	com/estrongs/android/ftp/i:f	Z
    //   1196: ifeq -1022 -> 174
    //   1199: aload_0
    //   1200: getfield 23	com/estrongs/android/ftp/i:h	Lcom/estrongs/android/ftp/h;
    //   1203: ldc 90
    //   1205: invokestatic 93	com/estrongs/android/ftp/h:a	(Lcom/estrongs/android/ftp/h;Ljava/lang/String;)V
    //   1208: return
    //   1209: astore 4
    //   1211: aload_3
    //   1212: monitorexit
    //   1213: aload 4
    //   1215: athrow
    //   1216: aload_0
    //   1217: getfield 23	com/estrongs/android/ftp/i:h	Lcom/estrongs/android/ftp/h;
    //   1220: ldc -91
    //   1222: invokestatic 93	com/estrongs/android/ftp/h:a	(Lcom/estrongs/android/ftp/h;Ljava/lang/String;)V
    //   1225: goto -497 -> 728
    //   1228: astore 4
    //   1230: iconst_1
    //   1231: istore_1
    //   1232: aload 4
    //   1234: invokevirtual 96	java/lang/Exception:printStackTrace	()V
    //   1237: iload_1
    //   1238: ifeq +12 -> 1250
    //   1241: aload_0
    //   1242: getfield 23	com/estrongs/android/ftp/i:h	Lcom/estrongs/android/ftp/h;
    //   1245: ldc -67
    //   1247: invokestatic 93	com/estrongs/android/ftp/h:a	(Lcom/estrongs/android/ftp/h;Ljava/lang/String;)V
    //   1250: aload_3
    //   1251: ifnull +7 -> 1258
    //   1254: aload_3
    //   1255: invokevirtual 110	java/net/Socket:close	()V
    //   1258: aload_0
    //   1259: getfield 23	com/estrongs/android/ftp/i:h	Lcom/estrongs/android/ftp/h;
    //   1262: invokestatic 60	com/estrongs/android/ftp/h:a	(Lcom/estrongs/android/ftp/h;)Ljava/lang/Integer;
    //   1265: astore_3
    //   1266: aload_3
    //   1267: monitorenter
    //   1268: aload_0
    //   1269: getfield 23	com/estrongs/android/ftp/i:h	Lcom/estrongs/android/ftp/h;
    //   1272: invokestatic 60	com/estrongs/android/ftp/h:a	(Lcom/estrongs/android/ftp/h;)Ljava/lang/Integer;
    //   1275: invokevirtual 66	java/lang/Integer:intValue	()I
    //   1278: aload_0
    //   1279: invokevirtual 71	java/lang/Object:hashCode	()I
    //   1282: if_icmpne +24 -> 1306
    //   1285: aload_0
    //   1286: getfield 23	com/estrongs/android/ftp/i:h	Lcom/estrongs/android/ftp/h;
    //   1289: iconst_0
    //   1290: invokestatic 75	java/lang/Integer:valueOf	(I)Ljava/lang/Integer;
    //   1293: invokestatic 78	com/estrongs/android/ftp/h:a	(Lcom/estrongs/android/ftp/h;Ljava/lang/Integer;)Ljava/lang/Integer;
    //   1296: pop
    //   1297: aload_0
    //   1298: getfield 23	com/estrongs/android/ftp/i:h	Lcom/estrongs/android/ftp/h;
    //   1301: aconst_null
    //   1302: invokestatic 81	com/estrongs/android/ftp/h:a	(Lcom/estrongs/android/ftp/h;Lcom/estrongs/android/ftp/i;)Lcom/estrongs/android/ftp/i;
    //   1305: pop
    //   1306: aload_3
    //   1307: monitorexit
    //   1308: aload_0
    //   1309: getfield 36	com/estrongs/android/ftp/i:f	Z
    //   1312: ifeq -1138 -> 174
    //   1315: aload_0
    //   1316: getfield 23	com/estrongs/android/ftp/i:h	Lcom/estrongs/android/ftp/h;
    //   1319: ldc 90
    //   1321: invokestatic 93	com/estrongs/android/ftp/h:a	(Lcom/estrongs/android/ftp/h;Ljava/lang/String;)V
    //   1324: return
    //   1325: aload_0
    //   1326: getfield 32	com/estrongs/android/ftp/i:d	I
    //   1329: bipush 6
    //   1331: if_icmpeq +12 -> 1343
    //   1334: aload_0
    //   1335: getfield 32	com/estrongs/android/ftp/i:d	I
    //   1338: bipush 7
    //   1340: if_icmpne -612 -> 728
    //   1343: aload_0
    //   1344: getfield 34	com/estrongs/android/ftp/i:e	Ljava/lang/Object;
    //   1347: checkcast 171	com/estrongs/android/ftp/j
    //   1350: astore 4
    //   1352: aload 4
    //   1354: getfield 174	com/estrongs/android/ftp/j:b	Ljava/lang/String;
    //   1357: astore 5
    //   1359: new 112	java/io/File
    //   1362: dup
    //   1363: aload 5
    //   1365: invokespecial 115	java/io/File:<init>	(Ljava/lang/String;)V
    //   1368: astore 6
    //   1370: aload 6
    //   1372: invokevirtual 148	java/io/File:isDirectory	()Z
    //   1375: ifne +15 -> 1390
    //   1378: aload_0
    //   1379: getfield 23	com/estrongs/android/ftp/i:h	Lcom/estrongs/android/ftp/h;
    //   1382: aload 5
    //   1384: invokestatic 177	com/estrongs/android/ftp/h:b	(Lcom/estrongs/android/ftp/h;Ljava/lang/String;)Z
    //   1387: ifne +94 -> 1481
    //   1390: aload_0
    //   1391: getfield 23	com/estrongs/android/ftp/i:h	Lcom/estrongs/android/ftp/h;
    //   1394: ldc -65
    //   1396: invokestatic 93	com/estrongs/android/ftp/h:a	(Lcom/estrongs/android/ftp/h;Ljava/lang/String;)V
    //   1399: aload_3
    //   1400: ifnull +7 -> 1407
    //   1403: aload_3
    //   1404: invokevirtual 110	java/net/Socket:close	()V
    //   1407: aload_0
    //   1408: getfield 23	com/estrongs/android/ftp/i:h	Lcom/estrongs/android/ftp/h;
    //   1411: invokestatic 60	com/estrongs/android/ftp/h:a	(Lcom/estrongs/android/ftp/h;)Ljava/lang/Integer;
    //   1414: astore_3
    //   1415: aload_3
    //   1416: monitorenter
    //   1417: aload_0
    //   1418: getfield 23	com/estrongs/android/ftp/i:h	Lcom/estrongs/android/ftp/h;
    //   1421: invokestatic 60	com/estrongs/android/ftp/h:a	(Lcom/estrongs/android/ftp/h;)Ljava/lang/Integer;
    //   1424: invokevirtual 66	java/lang/Integer:intValue	()I
    //   1427: aload_0
    //   1428: invokevirtual 71	java/lang/Object:hashCode	()I
    //   1431: if_icmpne +24 -> 1455
    //   1434: aload_0
    //   1435: getfield 23	com/estrongs/android/ftp/i:h	Lcom/estrongs/android/ftp/h;
    //   1438: iconst_0
    //   1439: invokestatic 75	java/lang/Integer:valueOf	(I)Ljava/lang/Integer;
    //   1442: invokestatic 78	com/estrongs/android/ftp/h:a	(Lcom/estrongs/android/ftp/h;Ljava/lang/Integer;)Ljava/lang/Integer;
    //   1445: pop
    //   1446: aload_0
    //   1447: getfield 23	com/estrongs/android/ftp/i:h	Lcom/estrongs/android/ftp/h;
    //   1450: aconst_null
    //   1451: invokestatic 81	com/estrongs/android/ftp/h:a	(Lcom/estrongs/android/ftp/h;Lcom/estrongs/android/ftp/i;)Lcom/estrongs/android/ftp/i;
    //   1454: pop
    //   1455: aload_3
    //   1456: monitorexit
    //   1457: aload_0
    //   1458: getfield 36	com/estrongs/android/ftp/i:f	Z
    //   1461: ifeq -1287 -> 174
    //   1464: aload_0
    //   1465: getfield 23	com/estrongs/android/ftp/i:h	Lcom/estrongs/android/ftp/h;
    //   1468: ldc 90
    //   1470: invokestatic 93	com/estrongs/android/ftp/h:a	(Lcom/estrongs/android/ftp/h;Ljava/lang/String;)V
    //   1473: return
    //   1474: astore 4
    //   1476: aload_3
    //   1477: monitorexit
    //   1478: aload 4
    //   1480: athrow
    //   1481: aload 6
    //   1483: invokevirtual 143	java/io/File:exists	()Z
    //   1486: ifeq +35 -> 1521
    //   1489: aload_0
    //   1490: getfield 32	com/estrongs/android/ftp/i:d	I
    //   1493: bipush 6
    //   1495: if_icmpne +26 -> 1521
    //   1498: aload 4
    //   1500: getfield 184	com/estrongs/android/ftp/j:a	J
    //   1503: lconst_0
    //   1504: lcmp
    //   1505: ifne +16 -> 1521
    //   1508: invokestatic 196	com/estrongs/fs/d:a	()Lcom/estrongs/fs/d;
    //   1511: aload 6
    //   1513: invokevirtual 199	java/io/File:getAbsolutePath	()Ljava/lang/String;
    //   1516: aconst_null
    //   1517: invokevirtual 202	com/estrongs/fs/d:a	(Ljava/lang/String;Lcom/estrongs/a/b/s;)Z
    //   1520: pop
    //   1521: aload_0
    //   1522: getfield 23	com/estrongs/android/ftp/i:h	Lcom/estrongs/android/ftp/h;
    //   1525: ldc -75
    //   1527: invokestatic 93	com/estrongs/android/ftp/h:a	(Lcom/estrongs/android/ftp/h;Ljava/lang/String;)V
    //   1530: aload_0
    //   1531: getfield 36	com/estrongs/android/ftp/i:f	Z
    //   1534: istore_2
    //   1535: iload_2
    //   1536: ifeq +85 -> 1621
    //   1539: aload_3
    //   1540: ifnull +7 -> 1547
    //   1543: aload_3
    //   1544: invokevirtual 110	java/net/Socket:close	()V
    //   1547: aload_0
    //   1548: getfield 23	com/estrongs/android/ftp/i:h	Lcom/estrongs/android/ftp/h;
    //   1551: invokestatic 60	com/estrongs/android/ftp/h:a	(Lcom/estrongs/android/ftp/h;)Ljava/lang/Integer;
    //   1554: astore_3
    //   1555: aload_3
    //   1556: monitorenter
    //   1557: aload_0
    //   1558: getfield 23	com/estrongs/android/ftp/i:h	Lcom/estrongs/android/ftp/h;
    //   1561: invokestatic 60	com/estrongs/android/ftp/h:a	(Lcom/estrongs/android/ftp/h;)Ljava/lang/Integer;
    //   1564: invokevirtual 66	java/lang/Integer:intValue	()I
    //   1567: aload_0
    //   1568: invokevirtual 71	java/lang/Object:hashCode	()I
    //   1571: if_icmpne +24 -> 1595
    //   1574: aload_0
    //   1575: getfield 23	com/estrongs/android/ftp/i:h	Lcom/estrongs/android/ftp/h;
    //   1578: iconst_0
    //   1579: invokestatic 75	java/lang/Integer:valueOf	(I)Ljava/lang/Integer;
    //   1582: invokestatic 78	com/estrongs/android/ftp/h:a	(Lcom/estrongs/android/ftp/h;Ljava/lang/Integer;)Ljava/lang/Integer;
    //   1585: pop
    //   1586: aload_0
    //   1587: getfield 23	com/estrongs/android/ftp/i:h	Lcom/estrongs/android/ftp/h;
    //   1590: aconst_null
    //   1591: invokestatic 81	com/estrongs/android/ftp/h:a	(Lcom/estrongs/android/ftp/h;Lcom/estrongs/android/ftp/i;)Lcom/estrongs/android/ftp/i;
    //   1594: pop
    //   1595: aload_3
    //   1596: monitorexit
    //   1597: aload_0
    //   1598: getfield 36	com/estrongs/android/ftp/i:f	Z
    //   1601: ifeq -1427 -> 174
    //   1604: aload_0
    //   1605: getfield 23	com/estrongs/android/ftp/i:h	Lcom/estrongs/android/ftp/h;
    //   1608: ldc 90
    //   1610: invokestatic 93	com/estrongs/android/ftp/h:a	(Lcom/estrongs/android/ftp/h;Ljava/lang/String;)V
    //   1613: return
    //   1614: astore 4
    //   1616: aload_3
    //   1617: monitorexit
    //   1618: aload 4
    //   1620: athrow
    //   1621: aload_0
    //   1622: getfield 23	com/estrongs/android/ftp/i:h	Lcom/estrongs/android/ftp/h;
    //   1625: aload_0
    //   1626: aload 6
    //   1628: aload_3
    //   1629: iconst_1
    //   1630: aload 4
    //   1632: getfield 184	com/estrongs/android/ftp/j:a	J
    //   1635: invokestatic 187	com/estrongs/android/ftp/h:a	(Lcom/estrongs/android/ftp/h;Lcom/estrongs/android/ftp/i;Ljava/io/File;Ljava/net/Socket;ZJ)V
    //   1638: aload_0
    //   1639: getfield 23	com/estrongs/android/ftp/i:h	Lcom/estrongs/android/ftp/h;
    //   1642: ldc -91
    //   1644: invokestatic 93	com/estrongs/android/ftp/h:a	(Lcom/estrongs/android/ftp/h;Ljava/lang/String;)V
    //   1647: goto -919 -> 728
    //   1650: astore 4
    //   1652: aload_3
    //   1653: ifnull +7 -> 1660
    //   1656: aload_3
    //   1657: invokevirtual 110	java/net/Socket:close	()V
    //   1660: aload_0
    //   1661: getfield 23	com/estrongs/android/ftp/i:h	Lcom/estrongs/android/ftp/h;
    //   1664: invokestatic 60	com/estrongs/android/ftp/h:a	(Lcom/estrongs/android/ftp/h;)Ljava/lang/Integer;
    //   1667: astore_3
    //   1668: aload_3
    //   1669: monitorenter
    //   1670: aload_0
    //   1671: getfield 23	com/estrongs/android/ftp/i:h	Lcom/estrongs/android/ftp/h;
    //   1674: invokestatic 60	com/estrongs/android/ftp/h:a	(Lcom/estrongs/android/ftp/h;)Ljava/lang/Integer;
    //   1677: invokevirtual 66	java/lang/Integer:intValue	()I
    //   1680: aload_0
    //   1681: invokevirtual 71	java/lang/Object:hashCode	()I
    //   1684: if_icmpne +24 -> 1708
    //   1687: aload_0
    //   1688: getfield 23	com/estrongs/android/ftp/i:h	Lcom/estrongs/android/ftp/h;
    //   1691: iconst_0
    //   1692: invokestatic 75	java/lang/Integer:valueOf	(I)Ljava/lang/Integer;
    //   1695: invokestatic 78	com/estrongs/android/ftp/h:a	(Lcom/estrongs/android/ftp/h;Ljava/lang/Integer;)Ljava/lang/Integer;
    //   1698: pop
    //   1699: aload_0
    //   1700: getfield 23	com/estrongs/android/ftp/i:h	Lcom/estrongs/android/ftp/h;
    //   1703: aconst_null
    //   1704: invokestatic 81	com/estrongs/android/ftp/h:a	(Lcom/estrongs/android/ftp/h;Lcom/estrongs/android/ftp/i;)Lcom/estrongs/android/ftp/i;
    //   1707: pop
    //   1708: aload_3
    //   1709: monitorexit
    //   1710: aload_0
    //   1711: getfield 36	com/estrongs/android/ftp/i:f	Z
    //   1714: ifeq +12 -> 1726
    //   1717: aload_0
    //   1718: getfield 23	com/estrongs/android/ftp/i:h	Lcom/estrongs/android/ftp/h;
    //   1721: ldc 90
    //   1723: invokestatic 93	com/estrongs/android/ftp/h:a	(Lcom/estrongs/android/ftp/h;Ljava/lang/String;)V
    //   1726: aload 4
    //   1728: athrow
    //   1729: astore 4
    //   1731: aload_3
    //   1732: monitorexit
    //   1733: aload 4
    //   1735: athrow
    //   1736: astore 4
    //   1738: aload_3
    //   1739: monitorexit
    //   1740: aload 4
    //   1742: athrow
    //   1743: astore 4
    //   1745: aload_3
    //   1746: monitorexit
    //   1747: aload 4
    //   1749: athrow
    //   1750: astore_3
    //   1751: goto -1327 -> 424
    //   1754: astore_3
    //   1755: goto -1187 -> 568
    //   1758: astore_3
    //   1759: goto -925 -> 834
    //   1762: astore_3
    //   1763: goto -738 -> 1025
    //   1766: astore_3
    //   1767: goto -625 -> 1142
    //   1770: astore_3
    //   1771: goto -364 -> 1407
    //   1774: astore_3
    //   1775: goto -228 -> 1547
    //   1778: astore_3
    //   1779: goto -1043 -> 736
    //   1782: astore_3
    //   1783: goto -525 -> 1258
    //   1786: astore_3
    //   1787: goto -127 -> 1660
    //   1790: astore 4
    //   1792: iconst_0
    //   1793: istore_1
    //   1794: goto -562 -> 1232
    //   1797: astore 4
    //   1799: goto -1586 -> 213
    //   1802: astore 4
    //   1804: goto -1728 -> 76
    //   1807: aconst_null
    //   1808: astore_3
    //   1809: goto -1740 -> 69
    // Local variable table:
    //   start	length	slot	name	signature
    //   0	1812	0	this	i
    //   1	1793	1	i	int
    //   821	715	2	bool	boolean
    //   12	166	3	localObject1	Object
    //   182	2	3	localException1	Exception
    //   195	1	3	localObject2	Object
    //   199	1	3	localException2	Exception
    //   201	1	3	localObject3	Object
    //   205	45	3	localObject4	Object
    //   278	54	3	localObject5	Object
    //   343	2	3	localException3	Exception
    //   1750	1	3	localException4	Exception
    //   1754	1	3	localException5	Exception
    //   1758	1	3	localException6	Exception
    //   1762	1	3	localException7	Exception
    //   1766	1	3	localException8	Exception
    //   1770	1	3	localException9	Exception
    //   1774	1	3	localException10	Exception
    //   1778	1	3	localException11	Exception
    //   1782	1	3	localException12	Exception
    //   1786	1	3	localException13	Exception
    //   1808	1	3	localObject7	Object
    //   175	5	4	localObject8	Object
    //   215	3	4	localException14	Exception
    //   225	5	4	localObject9	Object
    //   233	44	4	localObject10	Object
    //   354	5	4	localObject11	Object
    //   400	3	4	str1	String
    //   491	34	4	str2	String
    //   635	5	4	localObject12	Object
    //   658	54	4	localStringBuilder	StringBuilder
    //   901	30	4	localObject13	Object
    //   960	3	4	localj1	j
    //   1092	26	4	localObject14	Object
    //   1209	5	4	localObject15	Object
    //   1228	5	4	localException15	Exception
    //   1350	3	4	localj2	j
    //   1474	25	4	localObject16	Object
    //   1614	17	4	localObject17	Object
    //   1650	77	4	localObject18	Object
    //   1729	5	4	localObject19	Object
    //   1736	5	4	localObject20	Object
    //   1743	5	4	localObject21	Object
    //   1790	1	4	localException16	Exception
    //   1797	1	4	localException17	Exception
    //   1802	1	4	localException18	Exception
    //   3	1380	5	localObject22	Object
    //   923	704	6	localObject23	Object
    // Exception table:
    //   from	to	target	type
    //   15	52	175	finally
    //   52	54	175	finally
    //   177	179	175	finally
    //   54	69	182	java/lang/Exception
    //   187	194	199	java/lang/Exception
    //   54	69	205	finally
    //   183	187	205	finally
    //   76	94	215	java/lang/Exception
    //   118	156	225	finally
    //   156	158	225	finally
    //   227	229	225	finally
    //   242	249	343	java/lang/Exception
    //   252	276	343	java/lang/Exception
    //   293	331	354	finally
    //   331	333	354	finally
    //   356	358	354	finally
    //   434	472	491	finally
    //   472	474	491	finally
    //   493	495	491	finally
    //   578	616	635	finally
    //   616	618	635	finally
    //   637	639	635	finally
    //   844	882	901	finally
    //   882	884	901	finally
    //   903	905	901	finally
    //   1035	1073	1092	finally
    //   1073	1075	1092	finally
    //   1094	1096	1092	finally
    //   1152	1190	1209	finally
    //   1190	1192	1209	finally
    //   1211	1213	1209	finally
    //   651	683	1228	java/lang/Exception
    //   688	696	1228	java/lang/Exception
    //   696	728	1228	java/lang/Exception
    //   803	810	1228	java/lang/Exception
    //   810	822	1228	java/lang/Exception
    //   908	925	1228	java/lang/Exception
    //   930	938	1228	java/lang/Exception
    //   1108	1130	1228	java/lang/Exception
    //   1216	1225	1228	java/lang/Exception
    //   1530	1535	1228	java/lang/Exception
    //   1621	1647	1228	java/lang/Exception
    //   1417	1455	1474	finally
    //   1455	1457	1474	finally
    //   1476	1478	1474	finally
    //   1557	1595	1614	finally
    //   1595	1597	1614	finally
    //   1616	1618	1614	finally
    //   361	393	1650	finally
    //   393	402	1650	finally
    //   407	416	1650	finally
    //   498	560	1650	finally
    //   642	651	1650	finally
    //   651	683	1650	finally
    //   688	696	1650	finally
    //   696	728	1650	finally
    //   803	810	1650	finally
    //   810	822	1650	finally
    //   908	925	1650	finally
    //   930	938	1650	finally
    //   945	1008	1650	finally
    //   1008	1017	1650	finally
    //   1099	1108	1650	finally
    //   1108	1130	1650	finally
    //   1216	1225	1650	finally
    //   1232	1237	1650	finally
    //   1241	1250	1650	finally
    //   1325	1343	1650	finally
    //   1343	1390	1650	finally
    //   1390	1399	1650	finally
    //   1481	1521	1650	finally
    //   1521	1530	1650	finally
    //   1530	1535	1650	finally
    //   1621	1647	1650	finally
    //   746	784	1729	finally
    //   784	786	1729	finally
    //   1731	1733	1729	finally
    //   1268	1306	1736	finally
    //   1306	1308	1736	finally
    //   1738	1740	1736	finally
    //   1670	1708	1743	finally
    //   1708	1710	1743	finally
    //   1745	1747	1743	finally
    //   420	424	1750	java/lang/Exception
    //   564	568	1754	java/lang/Exception
    //   830	834	1758	java/lang/Exception
    //   1021	1025	1762	java/lang/Exception
    //   1138	1142	1766	java/lang/Exception
    //   1403	1407	1770	java/lang/Exception
    //   1543	1547	1774	java/lang/Exception
    //   732	736	1778	java/lang/Exception
    //   1254	1258	1782	java/lang/Exception
    //   1656	1660	1786	java/lang/Exception
    //   361	393	1790	java/lang/Exception
    //   393	402	1790	java/lang/Exception
    //   407	416	1790	java/lang/Exception
    //   498	560	1790	java/lang/Exception
    //   642	651	1790	java/lang/Exception
    //   945	1008	1790	java/lang/Exception
    //   1008	1017	1790	java/lang/Exception
    //   1099	1108	1790	java/lang/Exception
    //   1325	1343	1790	java/lang/Exception
    //   1343	1390	1790	java/lang/Exception
    //   1390	1399	1790	java/lang/Exception
    //   1481	1521	1790	java/lang/Exception
    //   1521	1530	1790	java/lang/Exception
    //   206	213	1797	java/lang/Exception
    //   69	76	1802	java/lang/Exception
  }
}

/* Location:
 * Qualified Name:     com.estrongs.android.ftp.i
 * Java Class Version: 6 (50.0)
 * JD-Core Version:    0.7.1
 */