package com.estrongs.android.pop.app.ad;

class c
  extends Thread
{
  c(a parama, String paramString) {}
  
  /* Error */
  public void run()
  {
    // Byte code:
    //   0: ldc2_w 22
    //   3: invokestatic 27	com/estrongs/android/pop/app/ad/c:sleep	(J)V
    //   6: new 29	com/duapps/ad/f
    //   9: dup
    //   10: invokestatic 34	com/estrongs/android/pop/FexApplication:a	()Lcom/estrongs/android/pop/FexApplication;
    //   13: sipush 10336
    //   16: iconst_1
    //   17: invokespecial 37	com/duapps/ad/f:<init>	(Landroid/content/Context;II)V
    //   20: invokevirtual 39	com/duapps/ad/f:a	()V
    //   23: invokestatic 34	com/estrongs/android/pop/FexApplication:a	()Lcom/estrongs/android/pop/FexApplication;
    //   26: invokestatic 44	com/estrongs/android/j/c:a	(Landroid/content/Context;)Lcom/estrongs/android/j/c;
    //   29: astore_1
    //   30: new 46	org/json/JSONObject
    //   33: dup
    //   34: invokespecial 47	org/json/JSONObject:<init>	()V
    //   37: astore_2
    //   38: aload_2
    //   39: ldc 49
    //   41: aload_0
    //   42: getfield 14	com/estrongs/android/pop/app/ad/c:a	Ljava/lang/String;
    //   45: invokevirtual 53	org/json/JSONObject:put	(Ljava/lang/String;Ljava/lang/Object;)Lorg/json/JSONObject;
    //   48: pop
    //   49: aload_1
    //   50: ldc 55
    //   52: aload_2
    //   53: invokevirtual 58	com/estrongs/android/j/c:b	(Ljava/lang/String;Lorg/json/JSONObject;)V
    //   56: return
    //   57: astore_1
    //   58: invokestatic 34	com/estrongs/android/pop/FexApplication:a	()Lcom/estrongs/android/pop/FexApplication;
    //   61: invokestatic 44	com/estrongs/android/j/c:a	(Landroid/content/Context;)Lcom/estrongs/android/j/c;
    //   64: astore_2
    //   65: new 46	org/json/JSONObject
    //   68: dup
    //   69: invokespecial 47	org/json/JSONObject:<init>	()V
    //   72: astore_3
    //   73: aload_3
    //   74: ldc 60
    //   76: ldc 62
    //   78: invokevirtual 53	org/json/JSONObject:put	(Ljava/lang/String;Ljava/lang/Object;)Lorg/json/JSONObject;
    //   81: pop
    //   82: aload_3
    //   83: ldc 64
    //   85: aload_1
    //   86: invokevirtual 68	java/lang/Exception:getMessage	()Ljava/lang/String;
    //   89: invokevirtual 53	org/json/JSONObject:put	(Ljava/lang/String;Ljava/lang/Object;)Lorg/json/JSONObject;
    //   92: pop
    //   93: aload_2
    //   94: ldc 55
    //   96: aload_3
    //   97: invokevirtual 58	com/estrongs/android/j/c:b	(Ljava/lang/String;Lorg/json/JSONObject;)V
    //   100: return
    //   101: astore_1
    //   102: return
    //   103: astore_1
    //   104: goto -98 -> 6
    //   107: astore_1
    //   108: return
    // Local variable table:
    //   start	length	slot	name	signature
    //   0	109	0	this	c
    //   29	21	1	localc	com.estrongs.android.j.c
    //   57	29	1	localException1	Exception
    //   101	1	1	localException2	Exception
    //   103	1	1	localException3	Exception
    //   107	1	1	localException4	Exception
    //   37	57	2	localObject	Object
    //   72	25	3	localJSONObject	org.json.JSONObject
    // Exception table:
    //   from	to	target	type
    //   6	23	57	java/lang/Exception
    //   58	100	101	java/lang/Exception
    //   0	6	103	java/lang/Exception
    //   23	56	107	java/lang/Exception
  }
}

/* Location:
 * Qualified Name:     com.estrongs.android.pop.app.ad.c
 * Java Class Version: 6 (50.0)
 * JD-Core Version:    0.7.1
 */