package com.estrongs.android.pop.app;

class bk
  implements Runnable
{
  bk(bi parambi) {}
  
  /* Error */
  public void run()
  {
    // Byte code:
    //   0: aload_0
    //   1: getfield 12	com/estrongs/android/pop/app/bk:a	Lcom/estrongs/android/pop/app/bi;
    //   4: invokestatic 25	com/estrongs/android/pop/app/bi:c	(Lcom/estrongs/android/pop/app/bi;)Ljava/lang/Object;
    //   7: astore_1
    //   8: aload_1
    //   9: monitorenter
    //   10: aload_0
    //   11: getfield 12	com/estrongs/android/pop/app/bk:a	Lcom/estrongs/android/pop/app/bi;
    //   14: invokestatic 29	com/estrongs/android/pop/app/bi:d	(Lcom/estrongs/android/pop/app/bi;)Lcom/estrongs/android/pop/zeroconf/w;
    //   17: astore_2
    //   18: aload_2
    //   19: ifnull +6 -> 25
    //   22: aload_1
    //   23: monitorexit
    //   24: return
    //   25: aload_0
    //   26: getfield 12	com/estrongs/android/pop/app/bk:a	Lcom/estrongs/android/pop/app/bi;
    //   29: new 31	com/estrongs/android/pop/zeroconf/w
    //   32: dup
    //   33: invokestatic 36	com/estrongs/android/pop/FexApplication:a	()Lcom/estrongs/android/pop/FexApplication;
    //   36: iconst_2
    //   37: invokespecial 39	com/estrongs/android/pop/zeroconf/w:<init>	(Landroid/content/Context;I)V
    //   40: invokestatic 42	com/estrongs/android/pop/app/bi:a	(Lcom/estrongs/android/pop/app/bi;Lcom/estrongs/android/pop/zeroconf/w;)Lcom/estrongs/android/pop/zeroconf/w;
    //   43: pop
    //   44: aload_0
    //   45: getfield 12	com/estrongs/android/pop/app/bk:a	Lcom/estrongs/android/pop/app/bi;
    //   48: invokestatic 29	com/estrongs/android/pop/app/bi:d	(Lcom/estrongs/android/pop/app/bi;)Lcom/estrongs/android/pop/zeroconf/w;
    //   51: getstatic 46	com/estrongs/android/pop/zeroconf/w:b	Ljava/lang/String;
    //   54: getstatic 47	com/estrongs/android/pop/app/bi:b	Ljava/lang/String;
    //   57: getstatic 50	com/estrongs/android/pop/app/bi:a	I
    //   60: invokevirtual 53	com/estrongs/android/pop/zeroconf/w:a	(Ljava/lang/String;Ljava/lang/String;I)Z
    //   63: pop
    //   64: aload_0
    //   65: getfield 12	com/estrongs/android/pop/app/bk:a	Lcom/estrongs/android/pop/app/bi;
    //   68: invokestatic 29	com/estrongs/android/pop/app/bi:d	(Lcom/estrongs/android/pop/app/bi;)Lcom/estrongs/android/pop/zeroconf/w;
    //   71: aload_0
    //   72: getfield 12	com/estrongs/android/pop/app/bk:a	Lcom/estrongs/android/pop/app/bi;
    //   75: invokevirtual 56	com/estrongs/android/pop/zeroconf/w:a	(Lcom/estrongs/android/pop/zeroconf/v;)V
    //   78: aload_1
    //   79: monitorexit
    //   80: return
    //   81: astore_2
    //   82: aload_1
    //   83: monitorexit
    //   84: aload_2
    //   85: athrow
    //   86: astore_2
    //   87: aload_0
    //   88: getfield 12	com/estrongs/android/pop/app/bk:a	Lcom/estrongs/android/pop/app/bi;
    //   91: aconst_null
    //   92: invokestatic 42	com/estrongs/android/pop/app/bi:a	(Lcom/estrongs/android/pop/app/bi;Lcom/estrongs/android/pop/zeroconf/w;)Lcom/estrongs/android/pop/zeroconf/w;
    //   95: pop
    //   96: aload_2
    //   97: invokevirtual 59	java/lang/Exception:printStackTrace	()V
    //   100: goto -22 -> 78
    // Local variable table:
    //   start	length	slot	name	signature
    //   0	103	0	this	bk
    //   17	2	2	localw	com.estrongs.android.pop.zeroconf.w
    //   81	4	2	localObject2	Object
    //   86	11	2	localException	Exception
    // Exception table:
    //   from	to	target	type
    //   10	18	81	finally
    //   22	24	81	finally
    //   25	78	81	finally
    //   78	80	81	finally
    //   82	84	81	finally
    //   87	100	81	finally
    //   10	18	86	java/lang/Exception
    //   25	78	86	java/lang/Exception
  }
}

/* Location:
 * Qualified Name:     com.estrongs.android.pop.app.bk
 * Java Class Version: 6 (50.0)
 * JD-Core Version:    0.7.1
 */