package com.estrongs.android.pop.app;

import android.os.Handler;

class le
  extends Handler
{
  le(RecommItemImageViewer paramRecommItemImageViewer) {}
  
  /* Error */
  public void handleMessage(android.os.Message paramMessage)
  {
    // Byte code:
    //   0: aload_0
    //   1: monitorenter
    //   2: aload_1
    //   3: getfield 22	android/os/Message:arg1	I
    //   6: istore_2
    //   7: iload_2
    //   8: tableswitch	default:+20->28, 123468:+23->31
    //   28: aload_0
    //   29: monitorexit
    //   30: return
    //   31: aload_0
    //   32: getfield 10	com/estrongs/android/pop/app/le:a	Lcom/estrongs/android/pop/app/RecommItemImageViewer;
    //   35: aload_1
    //   36: getfield 26	android/os/Message:obj	Ljava/lang/Object;
    //   39: invokevirtual 31	com/estrongs/android/pop/app/RecommItemImageViewer:a	(Ljava/lang/Object;)V
    //   42: goto -14 -> 28
    //   45: astore_1
    //   46: aload_0
    //   47: monitorexit
    //   48: aload_1
    //   49: athrow
    // Local variable table:
    //   start	length	slot	name	signature
    //   0	50	0	this	le
    //   0	50	1	paramMessage	android.os.Message
    //   6	2	2	i	int
    // Exception table:
    //   from	to	target	type
    //   2	7	45	finally
    //   31	42	45	finally
  }
}

/* Location:
 * Qualified Name:     com.estrongs.android.pop.app.le
 * Java Class Version: 6 (50.0)
 * JD-Core Version:    0.7.1
 */