package com.estrongs.fs.impl.local;

final class n
  implements Runnable
{
  /* Error */
  public void run()
  {
    // Byte code:
    //   0: new 18	java/io/BufferedWriter
    //   3: dup
    //   4: new 20	java/io/OutputStreamWriter
    //   7: dup
    //   8: aload_0
    //   9: getfield 22	com/estrongs/fs/impl/local/n:a	Ljava/lang/Process;
    //   12: invokevirtual 28	java/lang/Process:getOutputStream	()Ljava/io/OutputStream;
    //   15: invokespecial 32	java/io/OutputStreamWriter:<init>	(Ljava/io/OutputStream;)V
    //   18: invokespecial 35	java/io/BufferedWriter:<init>	(Ljava/io/Writer;)V
    //   21: astore_1
    //   22: aload_1
    //   23: aload_0
    //   24: getfield 37	com/estrongs/fs/impl/local/n:b	Ljava/lang/String;
    //   27: invokevirtual 41	java/io/BufferedWriter:write	(Ljava/lang/String;)V
    //   30: aload_1
    //   31: invokevirtual 44	java/io/BufferedWriter:close	()V
    //   34: new 46	java/io/BufferedReader
    //   37: dup
    //   38: new 48	java/io/InputStreamReader
    //   41: dup
    //   42: aload_0
    //   43: getfield 22	com/estrongs/fs/impl/local/n:a	Ljava/lang/Process;
    //   46: invokevirtual 52	java/lang/Process:getErrorStream	()Ljava/io/InputStream;
    //   49: invokespecial 55	java/io/InputStreamReader:<init>	(Ljava/io/InputStream;)V
    //   52: invokespecial 58	java/io/BufferedReader:<init>	(Ljava/io/Reader;)V
    //   55: astore_1
    //   56: aload_1
    //   57: invokevirtual 62	java/io/BufferedReader:readLine	()Ljava/lang/String;
    //   60: astore_2
    //   61: aload_2
    //   62: ifnull +17 -> 79
    //   65: aload_0
    //   66: getfield 64	com/estrongs/fs/impl/local/n:c	Ljava/lang/StringBuilder;
    //   69: aload_2
    //   70: invokevirtual 70	java/lang/StringBuilder:append	(Ljava/lang/String;)Ljava/lang/StringBuilder;
    //   73: ldc 72
    //   75: invokevirtual 70	java/lang/StringBuilder:append	(Ljava/lang/String;)Ljava/lang/StringBuilder;
    //   78: pop
    //   79: aload_1
    //   80: invokevirtual 73	java/io/BufferedReader:close	()V
    //   83: return
    //   84: astore_2
    //   85: aload_2
    //   86: invokevirtual 76	java/io/IOException:printStackTrace	()V
    //   89: aload_1
    //   90: invokevirtual 44	java/io/BufferedWriter:close	()V
    //   93: goto -59 -> 34
    //   96: astore_1
    //   97: goto -63 -> 34
    //   100: astore_2
    //   101: aload_1
    //   102: invokevirtual 44	java/io/BufferedWriter:close	()V
    //   105: aload_2
    //   106: athrow
    //   107: astore_2
    //   108: aload_2
    //   109: invokevirtual 76	java/io/IOException:printStackTrace	()V
    //   112: aload_1
    //   113: invokevirtual 73	java/io/BufferedReader:close	()V
    //   116: return
    //   117: astore_1
    //   118: return
    //   119: astore_2
    //   120: aload_1
    //   121: invokevirtual 73	java/io/BufferedReader:close	()V
    //   124: aload_2
    //   125: athrow
    //   126: astore_1
    //   127: goto -93 -> 34
    //   130: astore_1
    //   131: goto -26 -> 105
    //   134: astore_1
    //   135: return
    //   136: astore_1
    //   137: goto -13 -> 124
    // Local variable table:
    //   start	length	slot	name	signature
    //   0	140	0	this	n
    //   21	69	1	localObject1	Object
    //   96	17	1	localIOException1	java.io.IOException
    //   117	4	1	localIOException2	java.io.IOException
    //   126	1	1	localIOException3	java.io.IOException
    //   130	1	1	localIOException4	java.io.IOException
    //   134	1	1	localIOException5	java.io.IOException
    //   136	1	1	localIOException6	java.io.IOException
    //   60	10	2	str	String
    //   84	2	2	localIOException7	java.io.IOException
    //   100	6	2	localObject2	Object
    //   107	2	2	localIOException8	java.io.IOException
    //   119	6	2	localObject3	Object
    // Exception table:
    //   from	to	target	type
    //   22	30	84	java/io/IOException
    //   89	93	96	java/io/IOException
    //   22	30	100	finally
    //   85	89	100	finally
    //   56	61	107	java/io/IOException
    //   65	79	107	java/io/IOException
    //   112	116	117	java/io/IOException
    //   56	61	119	finally
    //   65	79	119	finally
    //   108	112	119	finally
    //   30	34	126	java/io/IOException
    //   101	105	130	java/io/IOException
    //   79	83	134	java/io/IOException
    //   120	124	136	java/io/IOException
  }
}

/* Location:
 * Qualified Name:     com.estrongs.fs.impl.local.n
 * Java Class Version: 6 (50.0)
 * JD-Core Version:    0.7.1
 */