package com.estrongs.android.ui.c.b;

import android.view.View.OnClickListener;
import com.estrongs.android.pop.app.shortcut.ShortcutFormat;

class c
  implements View.OnClickListener
{
  c(b paramb, String paramString, ShortcutFormat paramShortcutFormat) {}
  
  /* Error */
  public void onClick(android.view.View paramView)
  {
    // Byte code:
    //   0: aload_0
    //   1: getfield 18	com/estrongs/android/ui/c/b/c:a	Ljava/lang/String;
    //   4: astore_1
    //   5: aload_1
    //   6: ifnull +6 -> 12
    //   9: invokestatic 32	com/estrongs/android/pop/utils/cv:a	()V
    //   12: aload_0
    //   13: getfield 20	com/estrongs/android/ui/c/b/c:b	Lcom/estrongs/android/pop/app/shortcut/ShortcutFormat;
    //   16: getfield 37	com/estrongs/android/pop/app/shortcut/ShortcutFormat:targetLocation	Ljava/lang/String;
    //   19: astore_1
    //   20: aload_1
    //   21: invokestatic 43	com/estrongs/android/util/am:t	(Ljava/lang/String;)Z
    //   24: ifeq +68 -> 92
    //   27: aload_0
    //   28: getfield 16	com/estrongs/android/ui/c/b/c:c	Lcom/estrongs/android/ui/c/b/b;
    //   31: getfield 48	com/estrongs/android/ui/c/b/b:a	Lcom/estrongs/android/pop/view/FileExplorerActivity;
    //   34: aload_1
    //   35: invokevirtual 53	com/estrongs/android/pop/view/FileExplorerActivity:b	(Ljava/lang/String;)Lcom/estrongs/android/view/aw;
    //   38: astore_1
    //   39: aload_1
    //   40: ifnull +40 -> 80
    //   43: aload_1
    //   44: instanceof 55
    //   47: ifeq +33 -> 80
    //   50: aload_0
    //   51: getfield 18	com/estrongs/android/ui/c/b/c:a	Ljava/lang/String;
    //   54: invokestatic 59	com/estrongs/android/pop/utils/cu:a	(Ljava/lang/String;)Z
    //   57: ifeq +23 -> 80
    //   60: aload_1
    //   61: checkcast 55	com/estrongs/android/view/WebViewWrapper
    //   64: invokestatic 64	com/estrongs/android/pop/FexApplication:a	()Lcom/estrongs/android/pop/FexApplication;
    //   67: invokestatic 69	com/estrongs/android/pop/ad:a	(Landroid/content/Context;)Lcom/estrongs/android/pop/ad;
    //   70: invokevirtual 73	com/estrongs/android/pop/ad:aL	()Ljava/lang/String;
    //   73: aload_0
    //   74: getfield 18	com/estrongs/android/ui/c/b/c:a	Ljava/lang/String;
    //   77: invokevirtual 76	com/estrongs/android/view/WebViewWrapper:a	(Ljava/lang/String;Ljava/lang/String;)V
    //   80: aload_0
    //   81: getfield 16	com/estrongs/android/ui/c/b/c:c	Lcom/estrongs/android/ui/c/b/b;
    //   84: aload_0
    //   85: getfield 20	com/estrongs/android/ui/c/b/c:b	Lcom/estrongs/android/pop/app/shortcut/ShortcutFormat;
    //   88: invokestatic 79	com/estrongs/android/ui/c/b/b:a	(Lcom/estrongs/android/ui/c/b/b;Lcom/estrongs/android/pop/app/shortcut/ShortcutFormat;)V
    //   91: return
    //   92: aload_1
    //   93: invokestatic 82	com/estrongs/android/util/am:bb	(Ljava/lang/String;)Z
    //   96: ifeq +118 -> 214
    //   99: aload_1
    //   100: invokestatic 86	com/estrongs/android/util/am:C	(Ljava/lang/String;)Ljava/lang/String;
    //   103: astore_1
    //   104: aload_0
    //   105: getfield 16	com/estrongs/android/ui/c/b/c:c	Lcom/estrongs/android/ui/c/b/b;
    //   108: getfield 48	com/estrongs/android/ui/c/b/b:a	Lcom/estrongs/android/pop/view/FileExplorerActivity;
    //   111: invokestatic 91	com/estrongs/fs/d:a	(Landroid/content/Context;)Lcom/estrongs/fs/d;
    //   114: aload_1
    //   115: invokevirtual 94	com/estrongs/fs/d:h	(Ljava/lang/String;)Z
    //   118: ifeq +67 -> 185
    //   121: invokestatic 99	com/estrongs/android/ui/d/e:c	()I
    //   124: bipush 12
    //   126: if_icmpge +27 -> 153
    //   129: aload_0
    //   130: getfield 16	com/estrongs/android/ui/c/b/c:c	Lcom/estrongs/android/ui/c/b/b;
    //   133: getfield 48	com/estrongs/android/ui/c/b/b:a	Lcom/estrongs/android/pop/view/FileExplorerActivity;
    //   136: aload_1
    //   137: invokevirtual 102	com/estrongs/android/pop/view/FileExplorerActivity:e	(Ljava/lang/String;)Lcom/estrongs/android/view/aw;
    //   140: pop
    //   141: aload_0
    //   142: getfield 16	com/estrongs/android/ui/c/b/c:c	Lcom/estrongs/android/ui/c/b/b;
    //   145: aload_0
    //   146: getfield 20	com/estrongs/android/ui/c/b/c:b	Lcom/estrongs/android/pop/app/shortcut/ShortcutFormat;
    //   149: invokestatic 79	com/estrongs/android/ui/c/b/b:a	(Lcom/estrongs/android/ui/c/b/b;Lcom/estrongs/android/pop/app/shortcut/ShortcutFormat;)V
    //   152: return
    //   153: aload_0
    //   154: getfield 16	com/estrongs/android/ui/c/b/c:c	Lcom/estrongs/android/ui/c/b/b;
    //   157: getfield 48	com/estrongs/android/ui/c/b/b:a	Lcom/estrongs/android/pop/view/FileExplorerActivity;
    //   160: ldc 103
    //   162: invokevirtual 106	com/estrongs/android/pop/view/FileExplorerActivity:a	(I)V
    //   165: goto -24 -> 141
    //   168: astore_1
    //   169: aload_1
    //   170: invokevirtual 109	java/lang/Exception:printStackTrace	()V
    //   173: aload_0
    //   174: getfield 16	com/estrongs/android/ui/c/b/c:c	Lcom/estrongs/android/ui/c/b/b;
    //   177: aload_0
    //   178: getfield 20	com/estrongs/android/ui/c/b/c:b	Lcom/estrongs/android/pop/app/shortcut/ShortcutFormat;
    //   181: invokestatic 79	com/estrongs/android/ui/c/b/b:a	(Lcom/estrongs/android/ui/c/b/b;Lcom/estrongs/android/pop/app/shortcut/ShortcutFormat;)V
    //   184: return
    //   185: aload_0
    //   186: getfield 16	com/estrongs/android/ui/c/b/c:c	Lcom/estrongs/android/ui/c/b/b;
    //   189: getfield 48	com/estrongs/android/ui/c/b/b:a	Lcom/estrongs/android/pop/view/FileExplorerActivity;
    //   192: aconst_null
    //   193: aload_1
    //   194: invokevirtual 110	com/estrongs/android/pop/view/FileExplorerActivity:a	(Ljava/lang/String;Ljava/lang/String;)V
    //   197: goto -56 -> 141
    //   200: astore_1
    //   201: aload_0
    //   202: getfield 16	com/estrongs/android/ui/c/b/c:c	Lcom/estrongs/android/ui/c/b/b;
    //   205: aload_0
    //   206: getfield 20	com/estrongs/android/ui/c/b/c:b	Lcom/estrongs/android/pop/app/shortcut/ShortcutFormat;
    //   209: invokestatic 79	com/estrongs/android/ui/c/b/b:a	(Lcom/estrongs/android/ui/c/b/b;Lcom/estrongs/android/pop/app/shortcut/ShortcutFormat;)V
    //   212: aload_1
    //   213: athrow
    //   214: aload_1
    //   215: invokestatic 113	com/estrongs/android/util/am:bQ	(Ljava/lang/String;)Z
    //   218: ifeq +18 -> 236
    //   221: aload_0
    //   222: getfield 16	com/estrongs/android/ui/c/b/c:c	Lcom/estrongs/android/ui/c/b/b;
    //   225: getfield 48	com/estrongs/android/ui/c/b/b:a	Lcom/estrongs/android/pop/view/FileExplorerActivity;
    //   228: aload_1
    //   229: invokevirtual 116	com/estrongs/android/pop/view/FileExplorerActivity:d	(Ljava/lang/String;)Lcom/estrongs/android/view/aw;
    //   232: pop
    //   233: goto -92 -> 141
    //   236: aload_0
    //   237: getfield 16	com/estrongs/android/ui/c/b/c:c	Lcom/estrongs/android/ui/c/b/b;
    //   240: getfield 48	com/estrongs/android/ui/c/b/b:a	Lcom/estrongs/android/pop/view/FileExplorerActivity;
    //   243: invokestatic 91	com/estrongs/fs/d:a	(Landroid/content/Context;)Lcom/estrongs/fs/d;
    //   246: aload_1
    //   247: invokevirtual 118	com/estrongs/fs/d:b	(Ljava/lang/String;)Z
    //   250: ifeq +101 -> 351
    //   253: aload_0
    //   254: getfield 16	com/estrongs/android/ui/c/b/c:c	Lcom/estrongs/android/ui/c/b/b;
    //   257: getfield 48	com/estrongs/android/ui/c/b/b:a	Lcom/estrongs/android/pop/view/FileExplorerActivity;
    //   260: invokestatic 91	com/estrongs/fs/d:a	(Landroid/content/Context;)Lcom/estrongs/fs/d;
    //   263: aload_1
    //   264: invokevirtual 94	com/estrongs/fs/d:h	(Ljava/lang/String;)Z
    //   267: ifne +31 -> 298
    //   270: aload_1
    //   271: invokestatic 121	com/estrongs/android/util/am:S	(Ljava/lang/String;)Z
    //   274: ifne +24 -> 298
    //   277: aload_1
    //   278: invokestatic 124	com/estrongs/android/util/am:T	(Ljava/lang/String;)Z
    //   281: ifne +17 -> 298
    //   284: aload_1
    //   285: invokestatic 127	com/estrongs/android/util/am:U	(Ljava/lang/String;)Z
    //   288: ifne +10 -> 298
    //   291: aload_1
    //   292: invokestatic 130	com/estrongs/android/util/am:W	(Ljava/lang/String;)Z
    //   295: ifeq +41 -> 336
    //   298: invokestatic 99	com/estrongs/android/ui/d/e:c	()I
    //   301: bipush 12
    //   303: if_icmpge +18 -> 321
    //   306: aload_0
    //   307: getfield 16	com/estrongs/android/ui/c/b/c:c	Lcom/estrongs/android/ui/c/b/b;
    //   310: getfield 48	com/estrongs/android/ui/c/b/b:a	Lcom/estrongs/android/pop/view/FileExplorerActivity;
    //   313: aload_1
    //   314: invokevirtual 102	com/estrongs/android/pop/view/FileExplorerActivity:e	(Ljava/lang/String;)Lcom/estrongs/android/view/aw;
    //   317: pop
    //   318: goto -177 -> 141
    //   321: aload_0
    //   322: getfield 16	com/estrongs/android/ui/c/b/c:c	Lcom/estrongs/android/ui/c/b/b;
    //   325: getfield 48	com/estrongs/android/ui/c/b/b:a	Lcom/estrongs/android/pop/view/FileExplorerActivity;
    //   328: ldc 103
    //   330: invokevirtual 106	com/estrongs/android/pop/view/FileExplorerActivity:a	(I)V
    //   333: goto -192 -> 141
    //   336: aload_0
    //   337: getfield 16	com/estrongs/android/ui/c/b/c:c	Lcom/estrongs/android/ui/c/b/b;
    //   340: getfield 48	com/estrongs/android/ui/c/b/b:a	Lcom/estrongs/android/pop/view/FileExplorerActivity;
    //   343: aconst_null
    //   344: aload_1
    //   345: invokevirtual 110	com/estrongs/android/pop/view/FileExplorerActivity:a	(Ljava/lang/String;Ljava/lang/String;)V
    //   348: goto -207 -> 141
    //   351: aload_0
    //   352: getfield 16	com/estrongs/android/ui/c/b/c:c	Lcom/estrongs/android/ui/c/b/b;
    //   355: getfield 48	com/estrongs/android/ui/c/b/b:a	Lcom/estrongs/android/pop/view/FileExplorerActivity;
    //   358: ldc -125
    //   360: invokevirtual 106	com/estrongs/android/pop/view/FileExplorerActivity:a	(I)V
    //   363: goto -222 -> 141
    //   366: astore_1
    //   367: goto -355 -> 12
    // Local variable table:
    //   start	length	slot	name	signature
    //   0	370	0	this	c
    //   0	370	1	paramView	android.view.View
    // Exception table:
    //   from	to	target	type
    //   0	5	168	java/lang/Exception
    //   12	39	168	java/lang/Exception
    //   43	80	168	java/lang/Exception
    //   92	141	168	java/lang/Exception
    //   153	165	168	java/lang/Exception
    //   185	197	168	java/lang/Exception
    //   214	233	168	java/lang/Exception
    //   236	298	168	java/lang/Exception
    //   298	318	168	java/lang/Exception
    //   321	333	168	java/lang/Exception
    //   336	348	168	java/lang/Exception
    //   351	363	168	java/lang/Exception
    //   0	5	200	finally
    //   9	12	200	finally
    //   12	39	200	finally
    //   43	80	200	finally
    //   92	141	200	finally
    //   153	165	200	finally
    //   169	173	200	finally
    //   185	197	200	finally
    //   214	233	200	finally
    //   236	298	200	finally
    //   298	318	200	finally
    //   321	333	200	finally
    //   336	348	200	finally
    //   351	363	200	finally
    //   9	12	366	java/lang/Exception
  }
}

/* Location:
 * Qualified Name:     com.estrongs.android.ui.c.b.c
 * Java Class Version: 6 (50.0)
 * JD-Core Version:    0.7.1
 */