package com.estrongs.android.appinfo;

class c
  extends Thread
{
  c(AppFolderInfoManager paramAppFolderInfoManager, String paramString) {}
  
  /* Error */
  public void run()
  {
    // Byte code:
    //   0: invokestatic 26	com/estrongs/android/pop/FexApplication:a	()Lcom/estrongs/android/pop/FexApplication;
    //   3: invokevirtual 30	com/estrongs/android/pop/FexApplication:getPackageManager	()Landroid/content/pm/PackageManager;
    //   6: astore_1
    //   7: aload_1
    //   8: aload_0
    //   9: getfield 14	com/estrongs/android/appinfo/c:a	Ljava/lang/String;
    //   12: iconst_0
    //   13: invokevirtual 36	android/content/pm/PackageManager:getApplicationInfo	(Ljava/lang/String;I)Landroid/content/pm/ApplicationInfo;
    //   16: astore_2
    //   17: aload_2
    //   18: ifnull +93 -> 111
    //   21: aload_1
    //   22: aload_1
    //   23: aload_2
    //   24: getfield 41	android/content/pm/ApplicationInfo:packageName	Ljava/lang/String;
    //   27: iconst_0
    //   28: invokevirtual 36	android/content/pm/PackageManager:getApplicationInfo	(Ljava/lang/String;I)Landroid/content/pm/ApplicationInfo;
    //   31: invokevirtual 45	android/content/pm/PackageManager:getApplicationLabel	(Landroid/content/pm/ApplicationInfo;)Ljava/lang/CharSequence;
    //   34: invokevirtual 51	java/lang/Object:toString	()Ljava/lang/String;
    //   37: astore_3
    //   38: aload_0
    //   39: getfield 14	com/estrongs/android/appinfo/c:a	Ljava/lang/String;
    //   42: astore 4
    //   44: aload_0
    //   45: getfield 12	com/estrongs/android/appinfo/c:b	Lcom/estrongs/android/appinfo/AppFolderInfoManager;
    //   48: getfield 57	com/estrongs/android/appinfo/AppFolderInfoManager:t	Ljava/lang/Object;
    //   51: astore_2
    //   52: aload_2
    //   53: monitorenter
    //   54: aload_0
    //   55: getfield 12	com/estrongs/android/appinfo/c:b	Lcom/estrongs/android/appinfo/AppFolderInfoManager;
    //   58: getfield 61	com/estrongs/android/appinfo/AppFolderInfoManager:s	Landroid/database/sqlite/SQLiteDatabase;
    //   61: ifnonnull +10 -> 71
    //   64: aload_0
    //   65: getfield 12	com/estrongs/android/appinfo/c:b	Lcom/estrongs/android/appinfo/AppFolderInfoManager;
    //   68: invokestatic 64	com/estrongs/android/appinfo/AppFolderInfoManager:b	(Lcom/estrongs/android/appinfo/AppFolderInfoManager;)V
    //   71: aload_0
    //   72: getfield 12	com/estrongs/android/appinfo/c:b	Lcom/estrongs/android/appinfo/AppFolderInfoManager;
    //   75: getfield 61	com/estrongs/android/appinfo/AppFolderInfoManager:s	Landroid/database/sqlite/SQLiteDatabase;
    //   78: ifnonnull +6 -> 84
    //   81: aload_2
    //   82: monitorexit
    //   83: return
    //   84: aload_0
    //   85: getfield 12	com/estrongs/android/appinfo/c:b	Lcom/estrongs/android/appinfo/AppFolderInfoManager;
    //   88: getfield 61	com/estrongs/android/appinfo/AppFolderInfoManager:s	Landroid/database/sqlite/SQLiteDatabase;
    //   91: ldc 66
    //   93: iconst_2
    //   94: anewarray 47	java/lang/Object
    //   97: dup
    //   98: iconst_0
    //   99: aload 4
    //   101: aastore
    //   102: dup
    //   103: iconst_1
    //   104: aload_3
    //   105: aastore
    //   106: invokevirtual 72	android/database/sqlite/SQLiteDatabase:execSQL	(Ljava/lang/String;[Ljava/lang/Object;)V
    //   109: aload_2
    //   110: monitorexit
    //   111: aload_1
    //   112: aload_0
    //   113: getfield 14	com/estrongs/android/appinfo/c:a	Ljava/lang/String;
    //   116: iconst_0
    //   117: invokevirtual 76	android/content/pm/PackageManager:getPackageInfo	(Ljava/lang/String;I)Landroid/content/pm/PackageInfo;
    //   120: astore_2
    //   121: aload_2
    //   122: ifnull +20 -> 142
    //   125: aload_0
    //   126: getfield 12	com/estrongs/android/appinfo/c:b	Lcom/estrongs/android/appinfo/AppFolderInfoManager;
    //   129: aload_1
    //   130: aload_2
    //   131: invokestatic 79	com/estrongs/android/appinfo/AppFolderInfoManager:a	(Lcom/estrongs/android/appinfo/AppFolderInfoManager;Landroid/content/pm/PackageManager;Landroid/content/pm/PackageInfo;)V
    //   134: return
    //   135: astore_1
    //   136: return
    //   137: astore_1
    //   138: aload_2
    //   139: monitorexit
    //   140: aload_1
    //   141: athrow
    //   142: return
    // Local variable table:
    //   start	length	slot	name	signature
    //   0	143	0	this	c
    //   6	124	1	localPackageManager	android.content.pm.PackageManager
    //   135	1	1	localException	Exception
    //   137	4	1	localObject1	Object
    //   37	68	3	str1	String
    //   42	58	4	str2	String
    // Exception table:
    //   from	to	target	type
    //   0	17	135	java/lang/Exception
    //   21	54	135	java/lang/Exception
    //   111	121	135	java/lang/Exception
    //   125	134	135	java/lang/Exception
    //   140	142	135	java/lang/Exception
    //   54	71	137	finally
    //   71	83	137	finally
    //   84	111	137	finally
    //   138	140	137	finally
  }
}

/* Location:
 * Qualified Name:     com.estrongs.android.appinfo.c
 * Java Class Version: 6 (50.0)
 * JD-Core Version:    0.7.1
 */