package com.estrongs.android.a;

class x
  implements Runnable
{
  x(v paramv) {}
  
  /* Error */
  public void run()
  {
    // Byte code:
    //   0: aload_0
    //   1: getfield 12	com/estrongs/android/a/x:a	Lcom/estrongs/android/a/v;
    //   4: invokestatic 27	com/estrongs/android/a/v:f	(Lcom/estrongs/android/a/v;)Ljava/util/concurrent/CyclicBarrier;
    //   7: invokevirtual 33	java/util/concurrent/CyclicBarrier:await	()I
    //   10: pop
    //   11: aload_0
    //   12: getfield 12	com/estrongs/android/a/x:a	Lcom/estrongs/android/a/v;
    //   15: invokestatic 37	com/estrongs/android/a/v:g	(Lcom/estrongs/android/a/v;)Z
    //   18: ifeq +15 -> 33
    //   21: aload_0
    //   22: getfield 12	com/estrongs/android/a/x:a	Lcom/estrongs/android/a/v;
    //   25: invokestatic 40	com/estrongs/android/a/v:h	(Lcom/estrongs/android/a/v;)Z
    //   28: istore_1
    //   29: iload_1
    //   30: ifeq +28 -> 58
    //   33: invokestatic 44	com/estrongs/android/a/v:c	()Ljava/lang/String;
    //   36: ldc 46
    //   38: invokestatic 52	com/estrongs/android/util/l:b	(Ljava/lang/String;Ljava/lang/String;)V
    //   41: return
    //   42: astore_2
    //   43: aload_2
    //   44: invokevirtual 55	java/lang/InterruptedException:printStackTrace	()V
    //   47: goto -36 -> 11
    //   50: astore_2
    //   51: aload_2
    //   52: invokevirtual 56	java/util/concurrent/BrokenBarrierException:printStackTrace	()V
    //   55: goto -44 -> 11
    //   58: aload_0
    //   59: getfield 12	com/estrongs/android/a/x:a	Lcom/estrongs/android/a/v;
    //   62: invokestatic 60	com/estrongs/android/a/v:i	(Lcom/estrongs/android/a/v;)Ljava/util/concurrent/BlockingQueue;
    //   65: invokeinterface 66 1 0
    //   70: checkcast 68	com/estrongs/android/a/am
    //   73: astore_2
    //   74: aload_2
    //   75: invokevirtual 71	com/estrongs/android/a/am:f	()Z
    //   78: ifeq +39 -> 117
    //   81: aload_0
    //   82: getfield 12	com/estrongs/android/a/x:a	Lcom/estrongs/android/a/v;
    //   85: iconst_1
    //   86: invokestatic 74	com/estrongs/android/a/v:b	(Lcom/estrongs/android/a/v;Z)Z
    //   89: pop
    //   90: aload_0
    //   91: getfield 12	com/estrongs/android/a/x:a	Lcom/estrongs/android/a/v;
    //   94: invokestatic 78	com/estrongs/android/a/v:j	(Lcom/estrongs/android/a/v;)Ljava/util/concurrent/atomic/AtomicInteger;
    //   97: invokevirtual 83	java/util/concurrent/atomic/AtomicInteger:decrementAndGet	()I
    //   100: pop
    //   101: goto -90 -> 11
    //   104: astore_2
    //   105: aload_0
    //   106: getfield 12	com/estrongs/android/a/x:a	Lcom/estrongs/android/a/v;
    //   109: iconst_0
    //   110: invokestatic 85	com/estrongs/android/a/v:c	(Lcom/estrongs/android/a/v;Z)Z
    //   113: pop
    //   114: goto -103 -> 11
    //   117: aload_0
    //   118: getfield 12	com/estrongs/android/a/x:a	Lcom/estrongs/android/a/v;
    //   121: aload_2
    //   122: invokestatic 88	com/estrongs/android/a/v:a	(Lcom/estrongs/android/a/v;Lcom/estrongs/android/a/am;)V
    //   125: goto -35 -> 90
    // Local variable table:
    //   start	length	slot	name	signature
    //   0	128	0	this	x
    //   28	2	1	bool	boolean
    //   42	2	2	localInterruptedException1	InterruptedException
    //   50	2	2	localBrokenBarrierException	java.util.concurrent.BrokenBarrierException
    //   73	2	2	localam	am
    //   104	18	2	localInterruptedException2	InterruptedException
    // Exception table:
    //   from	to	target	type
    //   0	11	42	java/lang/InterruptedException
    //   0	11	50	java/util/concurrent/BrokenBarrierException
    //   21	29	104	java/lang/InterruptedException
    //   58	90	104	java/lang/InterruptedException
    //   90	101	104	java/lang/InterruptedException
    //   117	125	104	java/lang/InterruptedException
  }
}

/* Location:
 * Qualified Name:     com.estrongs.android.a.x
 * Java Class Version: 6 (50.0)
 * JD-Core Version:    0.7.1
 */