package com.estrongs.fs.b;

class ax
  extends Thread
{
  String a;
  int b;
  
  ax(au paramau, String paramString, int paramInt)
  {
    super("Find Thread:" + paramString);
    a = paramString;
    b = paramInt;
  }
  
  /* Error */
  public void run()
  {
    // Byte code:
    //   0: new 44	java/net/Socket
    //   3: dup
    //   4: invokespecial 45	java/net/Socket:<init>	()V
    //   7: astore 6
    //   9: aload 6
    //   11: new 47	java/net/InetSocketAddress
    //   14: dup
    //   15: aload_0
    //   16: getfield 34	com/estrongs/fs/b/ax:a	Ljava/lang/String;
    //   19: invokestatic 53	java/net/InetAddress:getByName	(Ljava/lang/String;)Ljava/net/InetAddress;
    //   22: getstatic 57	com/estrongs/a/b/d:a	I
    //   25: invokespecial 60	java/net/InetSocketAddress:<init>	(Ljava/net/InetAddress;I)V
    //   28: sipush 2000
    //   31: invokevirtual 64	java/net/Socket:connect	(Ljava/net/SocketAddress;I)V
    //   34: aload 6
    //   36: invokevirtual 68	java/net/Socket:isConnected	()Z
    //   39: ifne +107 -> 146
    //   42: new 40	java/lang/Exception
    //   45: dup
    //   46: ldc 70
    //   48: invokespecial 71	java/lang/Exception:<init>	(Ljava/lang/String;)V
    //   51: athrow
    //   52: astore_2
    //   53: aconst_null
    //   54: astore_3
    //   55: aconst_null
    //   56: astore_2
    //   57: aload_2
    //   58: ifnull +7 -> 65
    //   61: aload_2
    //   62: invokevirtual 76	java/io/DataInputStream:close	()V
    //   65: aload_3
    //   66: ifnull +7 -> 73
    //   69: aload_3
    //   70: invokevirtual 79	java/io/DataOutputStream:close	()V
    //   73: aload 6
    //   75: invokevirtual 80	java/net/Socket:close	()V
    //   78: invokestatic 85	com/estrongs/fs/b/au:a	()[[Ljava/lang/String;
    //   81: astore_2
    //   82: aload_2
    //   83: monitorenter
    //   84: iconst_0
    //   85: ifeq +517 -> 602
    //   88: invokestatic 85	com/estrongs/fs/b/au:a	()[[Ljava/lang/String;
    //   91: aload_0
    //   92: getfield 36	com/estrongs/fs/b/ax:b	I
    //   95: invokestatic 88	com/estrongs/fs/b/au:b	()I
    //   98: idiv
    //   99: aaload
    //   100: aload_0
    //   101: getfield 36	com/estrongs/fs/b/ax:b	I
    //   104: invokestatic 88	com/estrongs/fs/b/au:b	()I
    //   107: irem
    //   108: new 16	java/lang/StringBuilder
    //   111: dup
    //   112: invokespecial 19	java/lang/StringBuilder:<init>	()V
    //   115: aload_0
    //   116: getfield 34	com/estrongs/fs/b/ax:a	Ljava/lang/String;
    //   119: invokevirtual 25	java/lang/StringBuilder:append	(Ljava/lang/String;)Ljava/lang/StringBuilder;
    //   122: ldc 90
    //   124: invokevirtual 25	java/lang/StringBuilder:append	(Ljava/lang/String;)Ljava/lang/StringBuilder;
    //   127: aconst_null
    //   128: invokevirtual 25	java/lang/StringBuilder:append	(Ljava/lang/String;)Ljava/lang/StringBuilder;
    //   131: invokevirtual 29	java/lang/StringBuilder:toString	()Ljava/lang/String;
    //   134: aastore
    //   135: aload_0
    //   136: getfield 14	com/estrongs/fs/b/ax:c	Lcom/estrongs/fs/b/au;
    //   139: invokestatic 93	com/estrongs/fs/b/au:b	(Lcom/estrongs/fs/b/au;)J
    //   142: pop2
    //   143: aload_2
    //   144: monitorexit
    //   145: return
    //   146: aload 6
    //   148: sipush 10000
    //   151: invokevirtual 97	java/net/Socket:setSoTimeout	(I)V
    //   154: new 73	java/io/DataInputStream
    //   157: dup
    //   158: aload 6
    //   160: invokevirtual 101	java/net/Socket:getInputStream	()Ljava/io/InputStream;
    //   163: invokespecial 104	java/io/DataInputStream:<init>	(Ljava/io/InputStream;)V
    //   166: astore_2
    //   167: new 78	java/io/DataOutputStream
    //   170: dup
    //   171: aload 6
    //   173: invokevirtual 108	java/net/Socket:getOutputStream	()Ljava/io/OutputStream;
    //   176: invokespecial 111	java/io/DataOutputStream:<init>	(Ljava/io/OutputStream;)V
    //   179: astore_3
    //   180: aload_3
    //   181: new 16	java/lang/StringBuilder
    //   184: dup
    //   185: invokespecial 19	java/lang/StringBuilder:<init>	()V
    //   188: ldc 113
    //   190: invokevirtual 25	java/lang/StringBuilder:append	(Ljava/lang/String;)Ljava/lang/StringBuilder;
    //   193: getstatic 115	com/estrongs/a/b/d:b	Ljava/lang/String;
    //   196: invokevirtual 120	java/lang/String:length	()I
    //   199: ldc 122
    //   201: invokevirtual 120	java/lang/String:length	()I
    //   204: iadd
    //   205: invokevirtual 125	java/lang/StringBuilder:append	(I)Ljava/lang/StringBuilder;
    //   208: ldc 122
    //   210: invokevirtual 25	java/lang/StringBuilder:append	(Ljava/lang/String;)Ljava/lang/StringBuilder;
    //   213: ldc 122
    //   215: invokevirtual 25	java/lang/StringBuilder:append	(Ljava/lang/String;)Ljava/lang/StringBuilder;
    //   218: invokevirtual 29	java/lang/StringBuilder:toString	()Ljava/lang/String;
    //   221: ldc 127
    //   223: invokevirtual 131	java/lang/String:getBytes	(Ljava/lang/String;)[B
    //   226: invokevirtual 135	java/io/DataOutputStream:write	([B)V
    //   229: aload_3
    //   230: getstatic 115	com/estrongs/a/b/d:b	Ljava/lang/String;
    //   233: invokevirtual 138	java/lang/String:getBytes	()[B
    //   236: invokevirtual 135	java/io/DataOutputStream:write	([B)V
    //   239: aload_3
    //   240: ldc 122
    //   242: invokevirtual 138	java/lang/String:getBytes	()[B
    //   245: invokevirtual 135	java/io/DataOutputStream:write	([B)V
    //   248: aload_2
    //   249: invokevirtual 141	java/io/DataInputStream:readLine	()Ljava/lang/String;
    //   252: ldc -113
    //   254: invokevirtual 147	java/lang/String:indexOf	(Ljava/lang/String;)I
    //   257: iconst_m1
    //   258: if_icmpne +499 -> 757
    //   261: new 40	java/lang/Exception
    //   264: dup
    //   265: invokespecial 148	java/lang/Exception:<init>	()V
    //   268: athrow
    //   269: aload_2
    //   270: invokevirtual 141	java/io/DataInputStream:readLine	()Ljava/lang/String;
    //   273: astore 4
    //   275: aload 4
    //   277: invokevirtual 120	java/lang/String:length	()I
    //   280: ifne +115 -> 395
    //   283: iload_1
    //   284: ifne +126 -> 410
    //   287: new 40	java/lang/Exception
    //   290: dup
    //   291: invokespecial 148	java/lang/Exception:<init>	()V
    //   294: athrow
    //   295: astore 5
    //   297: aload_2
    //   298: astore 4
    //   300: aload 5
    //   302: astore_2
    //   303: aload 4
    //   305: ifnull +8 -> 313
    //   308: aload 4
    //   310: invokevirtual 76	java/io/DataInputStream:close	()V
    //   313: aload_3
    //   314: ifnull +7 -> 321
    //   317: aload_3
    //   318: invokevirtual 79	java/io/DataOutputStream:close	()V
    //   321: aload 6
    //   323: invokevirtual 80	java/net/Socket:close	()V
    //   326: invokestatic 85	com/estrongs/fs/b/au:a	()[[Ljava/lang/String;
    //   329: astore_3
    //   330: aload_3
    //   331: monitorenter
    //   332: iconst_0
    //   333: ifeq +342 -> 675
    //   336: invokestatic 85	com/estrongs/fs/b/au:a	()[[Ljava/lang/String;
    //   339: aload_0
    //   340: getfield 36	com/estrongs/fs/b/ax:b	I
    //   343: invokestatic 88	com/estrongs/fs/b/au:b	()I
    //   346: idiv
    //   347: aaload
    //   348: aload_0
    //   349: getfield 36	com/estrongs/fs/b/ax:b	I
    //   352: invokestatic 88	com/estrongs/fs/b/au:b	()I
    //   355: irem
    //   356: new 16	java/lang/StringBuilder
    //   359: dup
    //   360: invokespecial 19	java/lang/StringBuilder:<init>	()V
    //   363: aload_0
    //   364: getfield 34	com/estrongs/fs/b/ax:a	Ljava/lang/String;
    //   367: invokevirtual 25	java/lang/StringBuilder:append	(Ljava/lang/String;)Ljava/lang/StringBuilder;
    //   370: ldc 90
    //   372: invokevirtual 25	java/lang/StringBuilder:append	(Ljava/lang/String;)Ljava/lang/StringBuilder;
    //   375: aconst_null
    //   376: invokevirtual 25	java/lang/StringBuilder:append	(Ljava/lang/String;)Ljava/lang/StringBuilder;
    //   379: invokevirtual 29	java/lang/StringBuilder:toString	()Ljava/lang/String;
    //   382: aastore
    //   383: aload_0
    //   384: getfield 14	com/estrongs/fs/b/ax:c	Lcom/estrongs/fs/b/au;
    //   387: invokestatic 93	com/estrongs/fs/b/au:b	(Lcom/estrongs/fs/b/au;)J
    //   390: pop2
    //   391: aload_3
    //   392: monitorexit
    //   393: aload_2
    //   394: athrow
    //   395: aload 4
    //   397: ldc -106
    //   399: invokevirtual 154	java/lang/String:equals	(Ljava/lang/Object;)Z
    //   402: ifeq -133 -> 269
    //   405: iconst_1
    //   406: istore_1
    //   407: goto -138 -> 269
    //   410: aload_2
    //   411: invokevirtual 141	java/io/DataInputStream:readLine	()Ljava/lang/String;
    //   414: astore 4
    //   416: aload_2
    //   417: ifnull +7 -> 424
    //   420: aload_2
    //   421: invokevirtual 76	java/io/DataInputStream:close	()V
    //   424: aload_3
    //   425: ifnull +7 -> 432
    //   428: aload_3
    //   429: invokevirtual 79	java/io/DataOutputStream:close	()V
    //   432: aload 6
    //   434: invokevirtual 80	java/net/Socket:close	()V
    //   437: invokestatic 85	com/estrongs/fs/b/au:a	()[[Ljava/lang/String;
    //   440: astore_2
    //   441: aload_2
    //   442: monitorenter
    //   443: aload 4
    //   445: ifnull +91 -> 536
    //   448: invokestatic 85	com/estrongs/fs/b/au:a	()[[Ljava/lang/String;
    //   451: aload_0
    //   452: getfield 36	com/estrongs/fs/b/ax:b	I
    //   455: invokestatic 88	com/estrongs/fs/b/au:b	()I
    //   458: idiv
    //   459: aaload
    //   460: aload_0
    //   461: getfield 36	com/estrongs/fs/b/ax:b	I
    //   464: invokestatic 88	com/estrongs/fs/b/au:b	()I
    //   467: irem
    //   468: new 16	java/lang/StringBuilder
    //   471: dup
    //   472: invokespecial 19	java/lang/StringBuilder:<init>	()V
    //   475: aload_0
    //   476: getfield 34	com/estrongs/fs/b/ax:a	Ljava/lang/String;
    //   479: invokevirtual 25	java/lang/StringBuilder:append	(Ljava/lang/String;)Ljava/lang/StringBuilder;
    //   482: ldc 90
    //   484: invokevirtual 25	java/lang/StringBuilder:append	(Ljava/lang/String;)Ljava/lang/StringBuilder;
    //   487: aload 4
    //   489: invokevirtual 25	java/lang/StringBuilder:append	(Ljava/lang/String;)Ljava/lang/StringBuilder;
    //   492: invokevirtual 29	java/lang/StringBuilder:toString	()Ljava/lang/String;
    //   495: aastore
    //   496: aload_0
    //   497: getfield 14	com/estrongs/fs/b/ax:c	Lcom/estrongs/fs/b/au;
    //   500: invokestatic 93	com/estrongs/fs/b/au:b	(Lcom/estrongs/fs/b/au;)J
    //   503: pop2
    //   504: aload_2
    //   505: monitorexit
    //   506: return
    //   507: astore_3
    //   508: aload_2
    //   509: monitorexit
    //   510: aload_3
    //   511: athrow
    //   512: astore_2
    //   513: aload_2
    //   514: invokevirtual 157	java/io/IOException:printStackTrace	()V
    //   517: goto -93 -> 424
    //   520: astore_2
    //   521: aload_2
    //   522: invokevirtual 157	java/io/IOException:printStackTrace	()V
    //   525: goto -93 -> 432
    //   528: astore_2
    //   529: aload_2
    //   530: invokevirtual 158	java/lang/Exception:printStackTrace	()V
    //   533: goto -96 -> 437
    //   536: aload_0
    //   537: getfield 14	com/estrongs/fs/b/ax:c	Lcom/estrongs/fs/b/au;
    //   540: invokestatic 161	com/estrongs/fs/b/au:a	(Lcom/estrongs/fs/b/au;)Ljava/util/ArrayList;
    //   543: aload_0
    //   544: getfield 34	com/estrongs/fs/b/ax:a	Ljava/lang/String;
    //   547: invokevirtual 166	java/util/ArrayList:contains	(Ljava/lang/Object;)Z
    //   550: ifne -54 -> 496
    //   553: invokestatic 85	com/estrongs/fs/b/au:a	()[[Ljava/lang/String;
    //   556: aload_0
    //   557: getfield 36	com/estrongs/fs/b/ax:b	I
    //   560: invokestatic 88	com/estrongs/fs/b/au:b	()I
    //   563: idiv
    //   564: aaload
    //   565: aload_0
    //   566: getfield 36	com/estrongs/fs/b/ax:b	I
    //   569: invokestatic 88	com/estrongs/fs/b/au:b	()I
    //   572: irem
    //   573: aconst_null
    //   574: aastore
    //   575: goto -79 -> 496
    //   578: astore_2
    //   579: aload_2
    //   580: invokevirtual 157	java/io/IOException:printStackTrace	()V
    //   583: goto -518 -> 65
    //   586: astore_2
    //   587: aload_2
    //   588: invokevirtual 157	java/io/IOException:printStackTrace	()V
    //   591: goto -518 -> 73
    //   594: astore_2
    //   595: aload_2
    //   596: invokevirtual 158	java/lang/Exception:printStackTrace	()V
    //   599: goto -521 -> 78
    //   602: aload_0
    //   603: getfield 14	com/estrongs/fs/b/ax:c	Lcom/estrongs/fs/b/au;
    //   606: invokestatic 161	com/estrongs/fs/b/au:a	(Lcom/estrongs/fs/b/au;)Ljava/util/ArrayList;
    //   609: aload_0
    //   610: getfield 34	com/estrongs/fs/b/ax:a	Ljava/lang/String;
    //   613: invokevirtual 166	java/util/ArrayList:contains	(Ljava/lang/Object;)Z
    //   616: ifne -481 -> 135
    //   619: invokestatic 85	com/estrongs/fs/b/au:a	()[[Ljava/lang/String;
    //   622: aload_0
    //   623: getfield 36	com/estrongs/fs/b/ax:b	I
    //   626: invokestatic 88	com/estrongs/fs/b/au:b	()I
    //   629: idiv
    //   630: aaload
    //   631: aload_0
    //   632: getfield 36	com/estrongs/fs/b/ax:b	I
    //   635: invokestatic 88	com/estrongs/fs/b/au:b	()I
    //   638: irem
    //   639: aconst_null
    //   640: aastore
    //   641: goto -506 -> 135
    //   644: astore_3
    //   645: aload_2
    //   646: monitorexit
    //   647: aload_3
    //   648: athrow
    //   649: astore 4
    //   651: aload 4
    //   653: invokevirtual 157	java/io/IOException:printStackTrace	()V
    //   656: goto -343 -> 313
    //   659: astore_3
    //   660: aload_3
    //   661: invokevirtual 157	java/io/IOException:printStackTrace	()V
    //   664: goto -343 -> 321
    //   667: astore_3
    //   668: aload_3
    //   669: invokevirtual 158	java/lang/Exception:printStackTrace	()V
    //   672: goto -346 -> 326
    //   675: aload_0
    //   676: getfield 14	com/estrongs/fs/b/ax:c	Lcom/estrongs/fs/b/au;
    //   679: invokestatic 161	com/estrongs/fs/b/au:a	(Lcom/estrongs/fs/b/au;)Ljava/util/ArrayList;
    //   682: aload_0
    //   683: getfield 34	com/estrongs/fs/b/ax:a	Ljava/lang/String;
    //   686: invokevirtual 166	java/util/ArrayList:contains	(Ljava/lang/Object;)Z
    //   689: ifne -306 -> 383
    //   692: invokestatic 85	com/estrongs/fs/b/au:a	()[[Ljava/lang/String;
    //   695: aload_0
    //   696: getfield 36	com/estrongs/fs/b/ax:b	I
    //   699: invokestatic 88	com/estrongs/fs/b/au:b	()I
    //   702: idiv
    //   703: aaload
    //   704: aload_0
    //   705: getfield 36	com/estrongs/fs/b/ax:b	I
    //   708: invokestatic 88	com/estrongs/fs/b/au:b	()I
    //   711: irem
    //   712: aconst_null
    //   713: aastore
    //   714: goto -331 -> 383
    //   717: astore_2
    //   718: aload_3
    //   719: monitorexit
    //   720: aload_2
    //   721: athrow
    //   722: astore_2
    //   723: aconst_null
    //   724: astore_3
    //   725: aconst_null
    //   726: astore 4
    //   728: goto -425 -> 303
    //   731: astore_3
    //   732: aload_2
    //   733: astore 4
    //   735: aconst_null
    //   736: astore 5
    //   738: aload_3
    //   739: astore_2
    //   740: aload 5
    //   742: astore_3
    //   743: goto -440 -> 303
    //   746: astore_3
    //   747: aconst_null
    //   748: astore_3
    //   749: goto -692 -> 57
    //   752: astore 4
    //   754: goto -697 -> 57
    //   757: iconst_0
    //   758: istore_1
    //   759: goto -490 -> 269
    // Local variable table:
    //   start	length	slot	name	signature
    //   0	762	0	this	ax
    //   283	476	1	i	int
    //   52	1	2	localException1	Exception
    //   56	453	2	localObject1	Object
    //   512	2	2	localIOException1	java.io.IOException
    //   520	2	2	localIOException2	java.io.IOException
    //   528	2	2	localException2	Exception
    //   578	2	2	localIOException3	java.io.IOException
    //   586	2	2	localIOException4	java.io.IOException
    //   594	52	2	localException3	Exception
    //   717	4	2	localObject2	Object
    //   722	11	2	localObject3	Object
    //   739	1	2	localObject4	Object
    //   54	375	3	localObject5	Object
    //   507	4	3	localObject6	Object
    //   644	4	3	localObject7	Object
    //   659	2	3	localIOException5	java.io.IOException
    //   667	52	3	localException4	Exception
    //   724	1	3	localObject8	Object
    //   731	8	3	localObject9	Object
    //   742	1	3	localObject10	Object
    //   746	1	3	localException5	Exception
    //   748	1	3	localObject11	Object
    //   273	215	4	localObject12	Object
    //   649	3	4	localIOException6	java.io.IOException
    //   726	8	4	localObject13	Object
    //   752	1	4	localException6	Exception
    //   295	6	5	localObject14	Object
    //   736	5	5	localObject15	Object
    //   7	426	6	localSocket	java.net.Socket
    // Exception table:
    //   from	to	target	type
    //   9	52	52	java/lang/Exception
    //   146	167	52	java/lang/Exception
    //   180	269	295	finally
    //   269	283	295	finally
    //   287	295	295	finally
    //   395	405	295	finally
    //   410	416	295	finally
    //   448	496	507	finally
    //   496	506	507	finally
    //   508	510	507	finally
    //   536	575	507	finally
    //   420	424	512	java/io/IOException
    //   428	432	520	java/io/IOException
    //   432	437	528	java/lang/Exception
    //   61	65	578	java/io/IOException
    //   69	73	586	java/io/IOException
    //   73	78	594	java/lang/Exception
    //   88	135	644	finally
    //   135	145	644	finally
    //   602	641	644	finally
    //   645	647	644	finally
    //   308	313	649	java/io/IOException
    //   317	321	659	java/io/IOException
    //   321	326	667	java/lang/Exception
    //   336	383	717	finally
    //   383	393	717	finally
    //   675	714	717	finally
    //   718	720	717	finally
    //   9	52	722	finally
    //   146	167	722	finally
    //   167	180	731	finally
    //   167	180	746	java/lang/Exception
    //   180	269	752	java/lang/Exception
    //   269	283	752	java/lang/Exception
    //   287	295	752	java/lang/Exception
    //   395	405	752	java/lang/Exception
    //   410	416	752	java/lang/Exception
  }
}

/* Location:
 * Qualified Name:     com.estrongs.fs.b.ax
 * Java Class Version: 6 (50.0)
 * JD-Core Version:    0.7.1
 */