package com.estrongs.fs.b;

import android.app.Activity;
import android.content.Intent;
import com.estrongs.a.a;
import com.estrongs.a.a.m;
import com.estrongs.a.q;
import com.estrongs.android.pop.app.ShowDialogActivity;
import com.estrongs.android.util.ap;
import com.estrongs.android.util.bg;
import com.estrongs.fs.d;
import com.estrongs.fs.h;
import com.estrongs.fs.w;
import java.net.InetAddress;
import java.net.UnknownHostException;
import java.util.List;

public class bo
  extends a
{
  Activity a;
  d b;
  Long c = Long.valueOf(0L);
  private List<h> d;
  private String e;
  private InetAddress f = null;
  private com.estrongs.a.a.p g = new bq(this);
  
  bo(Activity paramActivity, List<h> paramList, String paramString)
  {
    a = paramActivity;
    b = d.a(paramActivity);
    d = paramList;
    e = paramString;
    int i = e.indexOf(':');
    e = e.substring(0, i);
    canRestart = false;
    canPause = false;
    task_type = 21;
    paramString = new StringBuilder();
    int j = paramList.size();
    i = 0;
    if (i < j)
    {
      paramActivity = ((h)paramList.get(i)).getName();
      if (paramActivity != null) {
        break label316;
      }
      paramActivity = ap.d(((h)paramList.get(i)).getAbsolutePath());
    }
    label316:
    for (;;)
    {
      if (((h)paramList.get(i)).getExtra("displayname") != null) {
        paramActivity = (String)((h)paramList.get(i)).getExtra("displayname");
      }
      for (;;)
      {
        paramString.append(paramActivity);
        if (i + 1 != j)
        {
          paramString.append(" , ");
          if (i >= 4)
          {
            paramString.append("...");
            processData.j = paramString.toString();
            e();
            setDescription(a.getString(2131232481) + e);
          }
        }
        try
        {
          f = InetAddress.getByName(e);
          return;
        }
        catch (UnknownHostException paramActivity)
        {
          paramActivity.printStackTrace();
          return;
        }
        i += 1;
        break;
      }
    }
  }
  
  public static bo a(Activity paramActivity, List<h> paramList, String paramString, boolean paramBoolean)
  {
    paramList = new bo(paramActivity, paramList, paramString);
    paramList.addTaskStatusChangeListener(new bp());
    if (paramBoolean)
    {
      paramString = new Intent(paramActivity, ShowDialogActivity.class);
      paramString.setFlags(268435456);
      paramString.putExtra("task_title", paramActivity.getString(2131232197));
      paramString.putExtra("task_id", paramList.getTaskId());
      paramString.putExtra("creatreNotification", true);
      paramActivity.startActivity(paramString);
      paramList.execute();
      return paramList;
    }
    paramList.addTaskStatusChangeListener(g);
    paramList.execute();
    return paramList;
  }
  
  private void e()
  {
    h localh = (h)d.get(0);
    String str = "";
    int j = d.size();
    int i = 0;
    if ((i >= 3) || (i == j))
    {
      if (!str.endsWith(",")) {
        break label367;
      }
      str = str.substring(0, str.length() - 1);
    }
    label367:
    for (;;)
    {
      recordSummary("title", str);
      recordSummary("items_ori_count", Integer.valueOf(j));
      recordSummary("task_id", Long.valueOf(getTaskId()));
      recordSummary("task_type", Integer.valueOf(task_type));
      recordSummary("restartable", Boolean.valueOf(false));
      recordSummary("items_selected_count", Integer.valueOf(d.size()));
      recordSummary("source", ((h)d.get(0)).getAbsolutePath());
      recordSummary("target", e);
      if (localh.getFileType().a()) {
        recordSummary("file_type", localh.getFileType().c());
      }
      for (;;)
      {
        if (startTime == -1L) {
          startTime = System.currentTimeMillis();
        }
        recordSummary("start_time", Long.valueOf(startTime));
        return;
        if (((h)d.get(i)).getExtra("displayname") != null) {}
        for (str = str + ((h)d.get(i)).getExtra("displayname") + ",";; str = str + ((h)d.get(i)).getName() + ",")
        {
          i += 1;
          break;
        }
        recordSummary("file_type", Integer.valueOf(bg.b(localh.getName())));
      }
    }
  }
  
  protected String a(com.estrongs.a.p paramp)
  {
    if ((paramp != null) && (b != null)) {
      return b).a;
    }
    return null;
  }
  
  public InetAddress a()
  {
    return f;
  }
  
  protected Object b(com.estrongs.a.p paramp)
  {
    if ((paramp != null) && (b != null)) {
      return b).b;
    }
    return Integer.valueOf(-1);
  }
  
  protected String b()
  {
    return getDescription() + " successfully.";
  }
  
  protected String c()
  {
    return getDescription() + " cancelled.";
  }
  
  public List<h> d()
  {
    return d;
  }
  
  public void handleMessage(int paramInt, Object... paramVarArgs)
  {
    switch (paramInt)
    {
    default: 
      super.handleMessage(paramInt, paramVarArgs);
    }
    do
    {
      return;
      processData.g = ((Long)paramVarArgs[0]).longValue();
      processData.h = ((Long)paramVarArgs[1]).longValue();
      return;
      processData.f = ((Long)paramVarArgs[0]).longValue();
      processData.a = ((String)paramVarArgs[1]);
      processData.e = ((Long)paramVarArgs[2]).longValue();
    } while (!hasProgressListener());
    long l = System.currentTimeMillis();
    processData.b = ((int)((float)processData.f / ((Long.valueOf(l).longValue() - c.longValue()) / 1000.0D)));
    onProgress(processData);
  }
  
  /* Error */
  public boolean task()
  {
    // Byte code:
    //   0: aload_0
    //   1: getfield 122	com/estrongs/fs/b/bo:processData	Lcom/estrongs/a/a/m;
    //   4: lconst_0
    //   5: putfield 335	com/estrongs/a/a/m:c	J
    //   8: aload_0
    //   9: getfield 122	com/estrongs/fs/b/bo:processData	Lcom/estrongs/a/a/m;
    //   12: lconst_0
    //   13: putfield 337	com/estrongs/a/a/m:d	J
    //   16: aload_0
    //   17: getfield 122	com/estrongs/fs/b/bo:processData	Lcom/estrongs/a/a/m;
    //   20: new 79	java/lang/StringBuilder
    //   23: dup
    //   24: invokespecial 80	java/lang/StringBuilder:<init>	()V
    //   27: aload_0
    //   28: getfield 45	com/estrongs/fs/b/bo:a	Landroid/app/Activity;
    //   31: ldc_w 338
    //   34: invokevirtual 139	android/app/Activity:getString	(I)Ljava/lang/String;
    //   37: invokevirtual 114	java/lang/StringBuilder:append	(Ljava/lang/String;)Ljava/lang/StringBuilder;
    //   40: aload_0
    //   41: getfield 56	com/estrongs/fs/b/bo:e	Ljava/lang/String;
    //   44: invokevirtual 114	java/lang/StringBuilder:append	(Ljava/lang/String;)Ljava/lang/StringBuilder;
    //   47: invokevirtual 125	java/lang/StringBuilder:toString	()Ljava/lang/String;
    //   50: putfield 315	com/estrongs/a/a/m:a	Ljava/lang/String;
    //   53: aload_0
    //   54: aload_0
    //   55: getfield 122	com/estrongs/fs/b/bo:processData	Lcom/estrongs/a/a/m;
    //   58: invokevirtual 328	com/estrongs/fs/b/bo:onProgress	(Lcom/estrongs/a/a/m;)V
    //   61: invokestatic 342	com/estrongs/a/a:getCurrentTask	()Lcom/estrongs/a/a;
    //   64: astore 22
    //   66: new 344	com/estrongs/a/b/c
    //   69: dup
    //   70: aload_0
    //   71: getfield 54	com/estrongs/fs/b/bo:d	Ljava/util/List;
    //   74: invokespecial 347	com/estrongs/a/b/c:<init>	(Ljava/util/List;)V
    //   77: astore 17
    //   79: lconst_0
    //   80: lstore 10
    //   82: aload 22
    //   84: ifnull +13 -> 97
    //   87: aload 22
    //   89: invokevirtual 350	com/estrongs/a/a:taskStopped	()Z
    //   92: ifeq +5 -> 97
    //   95: iconst_0
    //   96: ireturn
    //   97: aload 17
    //   99: invokevirtual 353	com/estrongs/a/b/c:a	()Lcom/estrongs/fs/h;
    //   102: astore 18
    //   104: aload 18
    //   106: ifnull +53 -> 159
    //   109: aload 18
    //   111: invokeinterface 248 1 0
    //   116: getstatic 356	com/estrongs/fs/w:b	Lcom/estrongs/fs/w;
    //   119: if_acmpne +1827 -> 1946
    //   122: aload_0
    //   123: getfield 122	com/estrongs/fs/b/bo:processData	Lcom/estrongs/a/a/m;
    //   126: astore 19
    //   128: aload 19
    //   130: aload 19
    //   132: getfield 335	com/estrongs/a/a/m:c	J
    //   135: lconst_1
    //   136: ladd
    //   137: putfield 335	com/estrongs/a/a/m:c	J
    //   140: aload 18
    //   142: invokeinterface 358 1 0
    //   147: lload 10
    //   149: ladd
    //   150: lstore 6
    //   152: lload 6
    //   154: lstore 10
    //   156: goto -74 -> 82
    //   159: aload_0
    //   160: getfield 122	com/estrongs/fs/b/bo:processData	Lcom/estrongs/a/a/m;
    //   163: lload 10
    //   165: putfield 317	com/estrongs/a/a/m:e	J
    //   168: aload_0
    //   169: getfield 54	com/estrongs/fs/b/bo:d	Ljava/util/List;
    //   172: iconst_0
    //   173: invokeinterface 90 2 0
    //   178: checkcast 92	com/estrongs/fs/h
    //   181: ldc 106
    //   183: invokeinterface 110 2 0
    //   188: ifnull +242 -> 430
    //   191: aload_0
    //   192: getfield 122	com/estrongs/fs/b/bo:processData	Lcom/estrongs/a/a/m;
    //   195: aload_0
    //   196: getfield 54	com/estrongs/fs/b/bo:d	Ljava/util/List;
    //   199: iconst_0
    //   200: invokeinterface 90 2 0
    //   205: checkcast 92	com/estrongs/fs/h
    //   208: ldc 106
    //   210: invokeinterface 110 2 0
    //   215: checkcast 58	java/lang/String
    //   218: putfield 130	com/estrongs/a/a/m:j	Ljava/lang/String;
    //   221: aload_0
    //   222: getfield 54	com/estrongs/fs/b/bo:d	Ljava/util/List;
    //   225: invokeinterface 86 1 0
    //   230: iconst_1
    //   231: if_icmple +41 -> 272
    //   234: new 79	java/lang/StringBuilder
    //   237: dup
    //   238: invokespecial 80	java/lang/StringBuilder:<init>	()V
    //   241: astore 17
    //   243: aload_0
    //   244: getfield 122	com/estrongs/fs/b/bo:processData	Lcom/estrongs/a/a/m;
    //   247: astore 18
    //   249: aload 18
    //   251: aload 17
    //   253: aload 18
    //   255: getfield 130	com/estrongs/a/a/m:j	Ljava/lang/String;
    //   258: invokevirtual 114	java/lang/StringBuilder:append	(Ljava/lang/String;)Ljava/lang/StringBuilder;
    //   261: ldc 118
    //   263: invokevirtual 114	java/lang/StringBuilder:append	(Ljava/lang/String;)Ljava/lang/StringBuilder;
    //   266: invokevirtual 125	java/lang/StringBuilder:toString	()Ljava/lang/String;
    //   269: putfield 130	com/estrongs/a/a/m:j	Ljava/lang/String;
    //   272: aload_0
    //   273: aload_0
    //   274: getfield 122	com/estrongs/fs/b/bo:processData	Lcom/estrongs/a/a/m;
    //   277: invokevirtual 328	com/estrongs/fs/b/bo:onProgress	(Lcom/estrongs/a/a/m;)V
    //   280: aload_0
    //   281: ldc_w 359
    //   284: lload 10
    //   286: invokestatic 34	java/lang/Long:valueOf	(J)Ljava/lang/Long;
    //   289: invokevirtual 223	com/estrongs/fs/b/bo:recordSummary	(Ljava/lang/String;Ljava/lang/Object;)V
    //   292: aload_0
    //   293: getfield 54	com/estrongs/fs/b/bo:d	Ljava/util/List;
    //   296: iconst_0
    //   297: invokeinterface 90 2 0
    //   302: checkcast 92	com/estrongs/fs/h
    //   305: astore 17
    //   307: aload 17
    //   309: invokeinterface 99 1 0
    //   314: invokevirtual 217	java/lang/String:length	()I
    //   317: pop
    //   318: aload 17
    //   320: invokeinterface 96 1 0
    //   325: invokevirtual 217	java/lang/String:length	()I
    //   328: pop
    //   329: aload_0
    //   330: getfield 56	com/estrongs/fs/b/bo:e	Ljava/lang/String;
    //   333: invokestatic 149	java/net/InetAddress:getByName	(Ljava/lang/String;)Ljava/net/InetAddress;
    //   336: astore 18
    //   338: new 361	java/net/Socket
    //   341: dup
    //   342: invokespecial 362	java/net/Socket:<init>	()V
    //   345: astore 20
    //   347: aload 20
    //   349: new 364	java/net/InetSocketAddress
    //   352: dup
    //   353: aload 18
    //   355: getstatic 368	com/estrongs/a/b/d:a	I
    //   358: invokespecial 371	java/net/InetSocketAddress:<init>	(Ljava/net/InetAddress;I)V
    //   361: sipush 10000
    //   364: invokevirtual 375	java/net/Socket:connect	(Ljava/net/SocketAddress;I)V
    //   367: aload 20
    //   369: invokevirtual 378	java/net/Socket:isConnected	()Z
    //   372: ifne +86 -> 458
    //   375: new 331	java/lang/Exception
    //   378: dup
    //   379: ldc_w 380
    //   382: invokespecial 382	java/lang/Exception:<init>	(Ljava/lang/String;)V
    //   385: athrow
    //   386: astore 17
    //   388: aload 20
    //   390: astore 18
    //   392: aload 17
    //   394: invokevirtual 383	java/lang/Exception:printStackTrace	()V
    //   397: aload_0
    //   398: sipush 10000
    //   401: new 286	com/estrongs/a/q
    //   404: dup
    //   405: aload_0
    //   406: getfield 45	com/estrongs/fs/b/bo:a	Landroid/app/Activity;
    //   409: ldc_w 384
    //   412: invokevirtual 139	android/app/Activity:getString	(I)Ljava/lang/String;
    //   415: aload 17
    //   417: invokespecial 387	com/estrongs/a/q:<init>	(Ljava/lang/String;Ljava/lang/Exception;)V
    //   420: invokevirtual 391	com/estrongs/fs/b/bo:setTaskResult	(ILjava/lang/Object;)V
    //   423: aload 18
    //   425: invokevirtual 394	java/net/Socket:close	()V
    //   428: iconst_0
    //   429: ireturn
    //   430: aload_0
    //   431: getfield 122	com/estrongs/fs/b/bo:processData	Lcom/estrongs/a/a/m;
    //   434: aload_0
    //   435: getfield 54	com/estrongs/fs/b/bo:d	Ljava/util/List;
    //   438: iconst_0
    //   439: invokeinterface 90 2 0
    //   444: checkcast 92	com/estrongs/fs/h
    //   447: invokeinterface 96 1 0
    //   452: putfield 130	com/estrongs/a/a/m:j	Ljava/lang/String;
    //   455: goto -234 -> 221
    //   458: new 396	java/io/DataInputStream
    //   461: dup
    //   462: aload 20
    //   464: invokevirtual 400	java/net/Socket:getInputStream	()Ljava/io/InputStream;
    //   467: invokespecial 403	java/io/DataInputStream:<init>	(Ljava/io/InputStream;)V
    //   470: astore 24
    //   472: new 405	java/io/DataOutputStream
    //   475: dup
    //   476: aload 20
    //   478: invokevirtual 409	java/net/Socket:getOutputStream	()Ljava/io/OutputStream;
    //   481: invokespecial 412	java/io/DataOutputStream:<init>	(Ljava/io/OutputStream;)V
    //   484: astore 23
    //   486: aconst_null
    //   487: astore 18
    //   489: aload 17
    //   491: ldc 106
    //   493: invokeinterface 110 2 0
    //   498: ifnull +211 -> 709
    //   501: aload 17
    //   503: ldc 106
    //   505: invokeinterface 110 2 0
    //   510: checkcast 58	java/lang/String
    //   513: astore 19
    //   515: aload_0
    //   516: getfield 54	com/estrongs/fs/b/bo:d	Ljava/util/List;
    //   519: invokeinterface 86 1 0
    //   524: iconst_1
    //   525: if_icmple +196 -> 721
    //   528: ldc_w 414
    //   531: astore 17
    //   533: aload 23
    //   535: new 79	java/lang/StringBuilder
    //   538: dup
    //   539: invokespecial 80	java/lang/StringBuilder:<init>	()V
    //   542: ldc_w 416
    //   545: invokevirtual 114	java/lang/StringBuilder:append	(Ljava/lang/String;)Ljava/lang/StringBuilder;
    //   548: aload 19
    //   550: invokevirtual 114	java/lang/StringBuilder:append	(Ljava/lang/String;)Ljava/lang/StringBuilder;
    //   553: ldc_w 418
    //   556: invokevirtual 114	java/lang/StringBuilder:append	(Ljava/lang/String;)Ljava/lang/StringBuilder;
    //   559: ldc_w 420
    //   562: invokevirtual 114	java/lang/StringBuilder:append	(Ljava/lang/String;)Ljava/lang/StringBuilder;
    //   565: aload 17
    //   567: invokevirtual 114	java/lang/StringBuilder:append	(Ljava/lang/String;)Ljava/lang/StringBuilder;
    //   570: ldc_w 422
    //   573: invokevirtual 114	java/lang/StringBuilder:append	(Ljava/lang/String;)Ljava/lang/StringBuilder;
    //   576: aload_0
    //   577: getfield 54	com/estrongs/fs/b/bo:d	Ljava/util/List;
    //   580: invokeinterface 86 1 0
    //   585: invokevirtual 425	java/lang/StringBuilder:append	(I)Ljava/lang/StringBuilder;
    //   588: ldc_w 427
    //   591: invokevirtual 114	java/lang/StringBuilder:append	(Ljava/lang/String;)Ljava/lang/StringBuilder;
    //   594: ldc_w 429
    //   597: invokevirtual 114	java/lang/StringBuilder:append	(Ljava/lang/String;)Ljava/lang/StringBuilder;
    //   600: aload_0
    //   601: getfield 122	com/estrongs/fs/b/bo:processData	Lcom/estrongs/a/a/m;
    //   604: getfield 335	com/estrongs/a/a/m:c	J
    //   607: invokevirtual 432	java/lang/StringBuilder:append	(J)Ljava/lang/StringBuilder;
    //   610: ldc_w 427
    //   613: invokevirtual 114	java/lang/StringBuilder:append	(Ljava/lang/String;)Ljava/lang/StringBuilder;
    //   616: ldc_w 434
    //   619: invokevirtual 114	java/lang/StringBuilder:append	(Ljava/lang/String;)Ljava/lang/StringBuilder;
    //   622: lload 10
    //   624: invokevirtual 432	java/lang/StringBuilder:append	(J)Ljava/lang/StringBuilder;
    //   627: ldc_w 427
    //   630: invokevirtual 114	java/lang/StringBuilder:append	(Ljava/lang/String;)Ljava/lang/StringBuilder;
    //   633: ldc_w 436
    //   636: invokevirtual 114	java/lang/StringBuilder:append	(Ljava/lang/String;)Ljava/lang/StringBuilder;
    //   639: ldc_w 438
    //   642: invokevirtual 114	java/lang/StringBuilder:append	(Ljava/lang/String;)Ljava/lang/StringBuilder;
    //   645: ldc_w 427
    //   648: invokevirtual 114	java/lang/StringBuilder:append	(Ljava/lang/String;)Ljava/lang/StringBuilder;
    //   651: invokevirtual 125	java/lang/StringBuilder:toString	()Ljava/lang/String;
    //   654: ldc_w 440
    //   657: invokevirtual 444	java/lang/String:getBytes	(Ljava/lang/String;)[B
    //   660: invokevirtual 448	java/io/DataOutputStream:write	([B)V
    //   663: aload 18
    //   665: ifnull +10 -> 675
    //   668: aload 23
    //   670: aload 18
    //   672: invokevirtual 448	java/io/DataOutputStream:write	([B)V
    //   675: aload 24
    //   677: invokevirtual 451	java/io/DataInputStream:available	()I
    //   680: ifne +394 -> 1074
    //   683: ldc2_w 452
    //   686: invokestatic 459	java/lang/Thread:sleep	(J)V
    //   689: aload 22
    //   691: ifnull -16 -> 675
    //   694: aload 22
    //   696: invokevirtual 350	com/estrongs/a/a:taskStopped	()Z
    //   699: ifeq -24 -> 675
    //   702: aload 20
    //   704: invokevirtual 394	java/net/Socket:close	()V
    //   707: iconst_0
    //   708: ireturn
    //   709: aload 17
    //   711: invokeinterface 96 1 0
    //   716: astore 19
    //   718: goto -203 -> 515
    //   721: aload 17
    //   723: invokestatic 462	com/estrongs/android/util/bg:b	(Lcom/estrongs/fs/h;)Z
    //   726: istore 16
    //   728: iload 16
    //   730: ifeq +323 -> 1053
    //   733: new 464	android/graphics/BitmapFactory$Options
    //   736: dup
    //   737: invokespecial 465	android/graphics/BitmapFactory$Options:<init>	()V
    //   740: astore 18
    //   742: aload 18
    //   744: iconst_1
    //   745: putfield 468	android/graphics/BitmapFactory$Options:inJustDecodeBounds	Z
    //   748: aload 17
    //   750: invokeinterface 99 1 0
    //   755: aload 18
    //   757: invokestatic 474	android/graphics/BitmapFactory:decodeFile	(Ljava/lang/String;Landroid/graphics/BitmapFactory$Options;)Landroid/graphics/Bitmap;
    //   760: pop
    //   761: aload 18
    //   763: getfield 477	android/graphics/BitmapFactory$Options:outWidth	I
    //   766: istore_1
    //   767: aload 18
    //   769: getfield 480	android/graphics/BitmapFactory$Options:outHeight	I
    //   772: istore_2
    //   773: aload 18
    //   775: bipush 64
    //   777: putfield 477	android/graphics/BitmapFactory$Options:outWidth	I
    //   780: aload 18
    //   782: iload_2
    //   783: iload_1
    //   784: imul
    //   785: iload_1
    //   786: idiv
    //   787: putfield 480	android/graphics/BitmapFactory$Options:outHeight	I
    //   790: aload 18
    //   792: iconst_0
    //   793: putfield 468	android/graphics/BitmapFactory$Options:inJustDecodeBounds	Z
    //   796: getstatic 485	com/estrongs/android/pop/z:x	Z
    //   799: ifne +220 -> 1019
    //   802: iconst_1
    //   803: istore 16
    //   805: aload 18
    //   807: iload 16
    //   809: putfield 488	android/graphics/BitmapFactory$Options:inPurgeable	Z
    //   812: aload 18
    //   814: iconst_1
    //   815: putfield 491	android/graphics/BitmapFactory$Options:inInputShareable	Z
    //   818: aload 18
    //   820: iload_1
    //   821: bipush 64
    //   823: idiv
    //   824: putfield 494	android/graphics/BitmapFactory$Options:inSampleSize	I
    //   827: aload 17
    //   829: invokeinterface 99 1 0
    //   834: aload 18
    //   836: invokestatic 474	android/graphics/BitmapFactory:decodeFile	(Ljava/lang/String;Landroid/graphics/BitmapFactory$Options;)Landroid/graphics/Bitmap;
    //   839: astore 17
    //   841: new 79	java/lang/StringBuilder
    //   844: dup
    //   845: invokespecial 80	java/lang/StringBuilder:<init>	()V
    //   848: ldc_w 496
    //   851: invokevirtual 114	java/lang/StringBuilder:append	(Ljava/lang/String;)Ljava/lang/StringBuilder;
    //   854: aload 17
    //   856: invokevirtual 501	android/graphics/Bitmap:getWidth	()I
    //   859: invokevirtual 425	java/lang/StringBuilder:append	(I)Ljava/lang/StringBuilder;
    //   862: ldc_w 427
    //   865: invokevirtual 114	java/lang/StringBuilder:append	(Ljava/lang/String;)Ljava/lang/StringBuilder;
    //   868: ldc_w 503
    //   871: invokevirtual 114	java/lang/StringBuilder:append	(Ljava/lang/String;)Ljava/lang/StringBuilder;
    //   874: aload 17
    //   876: invokevirtual 506	android/graphics/Bitmap:getHeight	()I
    //   879: invokevirtual 425	java/lang/StringBuilder:append	(I)Ljava/lang/StringBuilder;
    //   882: ldc_w 427
    //   885: invokevirtual 114	java/lang/StringBuilder:append	(Ljava/lang/String;)Ljava/lang/StringBuilder;
    //   888: invokevirtual 125	java/lang/StringBuilder:toString	()Ljava/lang/String;
    //   891: astore 21
    //   893: aload 17
    //   895: invokevirtual 501	android/graphics/Bitmap:getWidth	()I
    //   898: aload 17
    //   900: invokevirtual 506	android/graphics/Bitmap:getHeight	()I
    //   903: imul
    //   904: newarray <illegal type>
    //   906: astore 18
    //   908: aload 17
    //   910: aload 18
    //   912: iconst_0
    //   913: aload 17
    //   915: invokevirtual 501	android/graphics/Bitmap:getWidth	()I
    //   918: iconst_0
    //   919: iconst_0
    //   920: aload 17
    //   922: invokevirtual 501	android/graphics/Bitmap:getWidth	()I
    //   925: aload 17
    //   927: invokevirtual 506	android/graphics/Bitmap:getHeight	()I
    //   930: invokevirtual 510	android/graphics/Bitmap:getPixels	([IIIIIII)V
    //   933: aload 18
    //   935: arraylength
    //   936: iconst_4
    //   937: imul
    //   938: newarray <illegal type>
    //   940: astore 17
    //   942: iconst_0
    //   943: istore_1
    //   944: iload_1
    //   945: aload 18
    //   947: arraylength
    //   948: if_icmpge +77 -> 1025
    //   951: aload 17
    //   953: iload_1
    //   954: iconst_4
    //   955: imul
    //   956: aload 18
    //   958: iload_1
    //   959: iaload
    //   960: bipush 24
    //   962: ishr
    //   963: i2b
    //   964: bastore
    //   965: aload 17
    //   967: iload_1
    //   968: iconst_4
    //   969: imul
    //   970: iconst_1
    //   971: iadd
    //   972: aload 18
    //   974: iload_1
    //   975: iaload
    //   976: bipush 16
    //   978: ishr
    //   979: i2b
    //   980: bastore
    //   981: aload 17
    //   983: iload_1
    //   984: iconst_4
    //   985: imul
    //   986: iconst_2
    //   987: iadd
    //   988: aload 18
    //   990: iload_1
    //   991: iaload
    //   992: bipush 8
    //   994: ishr
    //   995: i2b
    //   996: bastore
    //   997: aload 17
    //   999: iload_1
    //   1000: iconst_4
    //   1001: imul
    //   1002: iconst_3
    //   1003: iadd
    //   1004: aload 18
    //   1006: iload_1
    //   1007: iaload
    //   1008: iconst_0
    //   1009: ishr
    //   1010: i2b
    //   1011: bastore
    //   1012: iload_1
    //   1013: iconst_1
    //   1014: iadd
    //   1015: istore_1
    //   1016: goto -72 -> 944
    //   1019: iconst_0
    //   1020: istore 16
    //   1022: goto -217 -> 805
    //   1025: aload 17
    //   1027: astore 18
    //   1029: aload 21
    //   1031: astore 17
    //   1033: goto -500 -> 533
    //   1036: astore 17
    //   1038: aconst_null
    //   1039: astore 17
    //   1041: aload 17
    //   1043: astore 18
    //   1045: ldc_w 512
    //   1048: astore 17
    //   1050: goto -517 -> 533
    //   1053: aload 17
    //   1055: invokeinterface 248 1 0
    //   1060: invokevirtual 253	com/estrongs/fs/w:a	()Z
    //   1063: ifeq +875 -> 1938
    //   1066: ldc_w 514
    //   1069: astore 17
    //   1071: goto -538 -> 533
    //   1074: new 516	java/util/Properties
    //   1077: dup
    //   1078: invokespecial 517	java/util/Properties:<init>	()V
    //   1081: astore 19
    //   1083: ldc -48
    //   1085: astore 17
    //   1087: aload 24
    //   1089: invokevirtual 520	java/io/DataInputStream:readLine	()Ljava/lang/String;
    //   1092: astore 21
    //   1094: aload 21
    //   1096: invokevirtual 217	java/lang/String:length	()I
    //   1099: ifne +76 -> 1175
    //   1102: aload 19
    //   1104: ldc_w 522
    //   1107: invokevirtual 525	java/util/Properties:getProperty	(Ljava/lang/String;)Ljava/lang/String;
    //   1110: invokestatic 528	java/lang/Integer:parseInt	(Ljava/lang/String;)I
    //   1113: newarray <illegal type>
    //   1115: astore 17
    //   1117: aload 24
    //   1119: aload 17
    //   1121: invokevirtual 532	java/io/DataInputStream:read	([B)I
    //   1124: pop
    //   1125: new 58	java/lang/String
    //   1128: dup
    //   1129: aload 17
    //   1131: invokespecial 534	java/lang/String:<init>	([B)V
    //   1134: ldc_w 536
    //   1137: invokevirtual 540	java/lang/String:equals	(Ljava/lang/Object;)Z
    //   1140: ifne +116 -> 1256
    //   1143: aload_0
    //   1144: sipush 10000
    //   1147: new 286	com/estrongs/a/q
    //   1150: dup
    //   1151: aload_0
    //   1152: getfield 45	com/estrongs/fs/b/bo:a	Landroid/app/Activity;
    //   1155: ldc_w 541
    //   1158: invokevirtual 139	android/app/Activity:getString	(I)Ljava/lang/String;
    //   1161: aconst_null
    //   1162: invokespecial 387	com/estrongs/a/q:<init>	(Ljava/lang/String;Ljava/lang/Exception;)V
    //   1165: invokevirtual 391	com/estrongs/fs/b/bo:setTaskResult	(ILjava/lang/Object;)V
    //   1168: aload 20
    //   1170: invokevirtual 394	java/net/Socket:close	()V
    //   1173: iconst_0
    //   1174: ireturn
    //   1175: new 79	java/lang/StringBuilder
    //   1178: dup
    //   1179: invokespecial 80	java/lang/StringBuilder:<init>	()V
    //   1182: aload 17
    //   1184: invokevirtual 114	java/lang/StringBuilder:append	(Ljava/lang/String;)Ljava/lang/StringBuilder;
    //   1187: aload 21
    //   1189: invokevirtual 114	java/lang/StringBuilder:append	(Ljava/lang/String;)Ljava/lang/StringBuilder;
    //   1192: ldc_w 543
    //   1195: invokevirtual 114	java/lang/StringBuilder:append	(Ljava/lang/String;)Ljava/lang/StringBuilder;
    //   1198: invokevirtual 125	java/lang/StringBuilder:toString	()Ljava/lang/String;
    //   1201: astore 18
    //   1203: aload 21
    //   1205: bipush 58
    //   1207: invokevirtual 62	java/lang/String:indexOf	(I)I
    //   1210: istore_1
    //   1211: aload 18
    //   1213: astore 17
    //   1215: iload_1
    //   1216: iflt -129 -> 1087
    //   1219: aload 19
    //   1221: aload 21
    //   1223: iconst_0
    //   1224: iload_1
    //   1225: invokevirtual 66	java/lang/String:substring	(II)Ljava/lang/String;
    //   1228: invokevirtual 546	java/lang/String:trim	()Ljava/lang/String;
    //   1231: invokevirtual 549	java/lang/String:toLowerCase	()Ljava/lang/String;
    //   1234: aload 21
    //   1236: iload_1
    //   1237: iconst_1
    //   1238: iadd
    //   1239: invokevirtual 551	java/lang/String:substring	(I)Ljava/lang/String;
    //   1242: invokevirtual 546	java/lang/String:trim	()Ljava/lang/String;
    //   1245: invokevirtual 555	java/util/Properties:put	(Ljava/lang/Object;Ljava/lang/Object;)Ljava/lang/Object;
    //   1248: pop
    //   1249: aload 18
    //   1251: astore 17
    //   1253: goto -166 -> 1087
    //   1256: aload_0
    //   1257: invokestatic 268	java/lang/System:currentTimeMillis	()J
    //   1260: invokestatic 34	java/lang/Long:valueOf	(J)Ljava/lang/Long;
    //   1263: putfield 36	com/estrongs/fs/b/bo:c	Ljava/lang/Long;
    //   1266: iconst_0
    //   1267: istore_1
    //   1268: iconst_0
    //   1269: istore_3
    //   1270: lconst_0
    //   1271: lstore 6
    //   1273: iload_3
    //   1274: aload_0
    //   1275: getfield 54	com/estrongs/fs/b/bo:d	Ljava/util/List;
    //   1278: invokeinterface 86 1 0
    //   1283: if_icmpge +649 -> 1932
    //   1286: aload_0
    //   1287: getfield 54	com/estrongs/fs/b/bo:d	Ljava/util/List;
    //   1290: iload_3
    //   1291: invokeinterface 90 2 0
    //   1296: checkcast 92	com/estrongs/fs/h
    //   1299: astore 21
    //   1301: new 344	com/estrongs/a/b/c
    //   1304: dup
    //   1305: aload 21
    //   1307: invokespecial 558	com/estrongs/a/b/c:<init>	(Lcom/estrongs/fs/h;)V
    //   1310: astore 24
    //   1312: aload 21
    //   1314: invokeinterface 99 1 0
    //   1319: invokevirtual 217	java/lang/String:length	()I
    //   1322: istore 4
    //   1324: aload 21
    //   1326: invokeinterface 96 1 0
    //   1331: invokevirtual 217	java/lang/String:length	()I
    //   1334: istore 5
    //   1336: iload_1
    //   1337: istore_2
    //   1338: aload 24
    //   1340: invokevirtual 353	com/estrongs/a/b/c:a	()Lcom/estrongs/fs/h;
    //   1343: astore 25
    //   1345: aload 25
    //   1347: ifnonnull +70 -> 1417
    //   1350: iload_2
    //   1351: istore_1
    //   1352: iload_1
    //   1353: ifeq +531 -> 1884
    //   1356: iload_1
    //   1357: ifne +19 -> 1376
    //   1360: aload 23
    //   1362: ldc_w 560
    //   1365: invokevirtual 563	java/lang/String:getBytes	()[B
    //   1368: invokevirtual 448	java/io/DataOutputStream:write	([B)V
    //   1371: aload 23
    //   1373: invokevirtual 566	java/io/DataOutputStream:flush	()V
    //   1376: aload 20
    //   1378: invokevirtual 394	java/net/Socket:close	()V
    //   1381: iload_1
    //   1382: iconst_1
    //   1383: if_icmpne +28 -> 1411
    //   1386: aload_0
    //   1387: sipush 10000
    //   1390: new 286	com/estrongs/a/q
    //   1393: dup
    //   1394: aload_0
    //   1395: getfield 45	com/estrongs/fs/b/bo:a	Landroid/app/Activity;
    //   1398: ldc_w 567
    //   1401: invokevirtual 139	android/app/Activity:getString	(I)Ljava/lang/String;
    //   1404: aconst_null
    //   1405: invokespecial 387	com/estrongs/a/q:<init>	(Ljava/lang/String;Ljava/lang/Exception;)V
    //   1408: invokevirtual 391	com/estrongs/fs/b/bo:setTaskResult	(ILjava/lang/Object;)V
    //   1411: iload_1
    //   1412: ifne +486 -> 1898
    //   1415: iconst_1
    //   1416: ireturn
    //   1417: aload 25
    //   1419: invokeinterface 358 1 0
    //   1424: lstore 14
    //   1426: aload 21
    //   1428: ldc 106
    //   1430: invokeinterface 110 2 0
    //   1435: ifnull +106 -> 1541
    //   1438: aload 25
    //   1440: invokeinterface 99 1 0
    //   1445: aload 21
    //   1447: invokeinterface 99 1 0
    //   1452: invokevirtual 540	java/lang/String:equals	(Ljava/lang/Object;)Z
    //   1455: ifeq +86 -> 1541
    //   1458: aload 25
    //   1460: invokeinterface 248 1 0
    //   1465: getstatic 356	com/estrongs/fs/w:b	Lcom/estrongs/fs/w;
    //   1468: if_acmpne +73 -> 1541
    //   1471: aload 21
    //   1473: ldc 106
    //   1475: invokeinterface 110 2 0
    //   1480: checkcast 58	java/lang/String
    //   1483: checkcast 58	java/lang/String
    //   1486: astore 18
    //   1488: aload 23
    //   1490: aload 18
    //   1492: invokevirtual 563	java/lang/String:getBytes	()[B
    //   1495: invokevirtual 448	java/io/DataOutputStream:write	([B)V
    //   1498: aload 23
    //   1500: ldc_w 427
    //   1503: invokevirtual 563	java/lang/String:getBytes	()[B
    //   1506: invokevirtual 448	java/io/DataOutputStream:write	([B)V
    //   1509: aload 25
    //   1511: invokeinterface 248 1 0
    //   1516: getstatic 569	com/estrongs/fs/w:a	Lcom/estrongs/fs/w;
    //   1519: if_acmpne +52 -> 1571
    //   1522: aload 23
    //   1524: ldc_w 571
    //   1527: invokevirtual 563	java/lang/String:getBytes	()[B
    //   1530: invokevirtual 448	java/io/DataOutputStream:write	([B)V
    //   1533: aload 23
    //   1535: invokevirtual 566	java/io/DataOutputStream:flush	()V
    //   1538: goto -200 -> 1338
    //   1541: aload 25
    //   1543: invokeinterface 99 1 0
    //   1548: astore 18
    //   1550: aload 23
    //   1552: aload 18
    //   1554: iload 4
    //   1556: iload 5
    //   1558: isub
    //   1559: invokevirtual 551	java/lang/String:substring	(I)Ljava/lang/String;
    //   1562: invokevirtual 563	java/lang/String:getBytes	()[B
    //   1565: invokevirtual 448	java/io/DataOutputStream:write	([B)V
    //   1568: goto -70 -> 1498
    //   1571: aload 23
    //   1573: ldc_w 573
    //   1576: invokevirtual 563	java/lang/String:getBytes	()[B
    //   1579: invokevirtual 448	java/io/DataOutputStream:write	([B)V
    //   1582: aload 23
    //   1584: new 79	java/lang/StringBuilder
    //   1587: dup
    //   1588: invokespecial 80	java/lang/StringBuilder:<init>	()V
    //   1591: ldc -48
    //   1593: invokevirtual 114	java/lang/StringBuilder:append	(Ljava/lang/String;)Ljava/lang/StringBuilder;
    //   1596: lload 14
    //   1598: invokevirtual 432	java/lang/StringBuilder:append	(J)Ljava/lang/StringBuilder;
    //   1601: ldc_w 427
    //   1604: invokevirtual 114	java/lang/StringBuilder:append	(Ljava/lang/String;)Ljava/lang/StringBuilder;
    //   1607: invokevirtual 125	java/lang/StringBuilder:toString	()Ljava/lang/String;
    //   1610: invokevirtual 563	java/lang/String:getBytes	()[B
    //   1613: invokevirtual 448	java/io/DataOutputStream:write	([B)V
    //   1616: aload 23
    //   1618: invokevirtual 566	java/io/DataOutputStream:flush	()V
    //   1621: lconst_0
    //   1622: lstore 12
    //   1624: sipush 16384
    //   1627: newarray <illegal type>
    //   1629: astore 26
    //   1631: aconst_null
    //   1632: astore 17
    //   1634: aload 22
    //   1636: ifnull +57 -> 1693
    //   1639: aload 22
    //   1641: invokevirtual 350	com/estrongs/a/a:taskStopped	()Z
    //   1644: ifeq +49 -> 1693
    //   1647: iconst_2
    //   1648: istore_1
    //   1649: lload 6
    //   1651: lstore 8
    //   1653: aload_0
    //   1654: getfield 122	com/estrongs/fs/b/bo:processData	Lcom/estrongs/a/a/m;
    //   1657: astore 18
    //   1659: aload 18
    //   1661: aload 18
    //   1663: getfield 337	com/estrongs/a/a/m:d	J
    //   1666: lconst_1
    //   1667: ladd
    //   1668: putfield 337	com/estrongs/a/a/m:d	J
    //   1671: aload 17
    //   1673: invokevirtual 576	java/io/InputStream:close	()V
    //   1676: iload_1
    //   1677: istore_2
    //   1678: lload 8
    //   1680: lstore 6
    //   1682: iload_1
    //   1683: ifeq -345 -> 1338
    //   1686: lload 8
    //   1688: lstore 6
    //   1690: goto -338 -> 1352
    //   1693: lload 12
    //   1695: lload 14
    //   1697: lcmp
    //   1698: iflt +44 -> 1742
    //   1701: aload 23
    //   1703: ldc_w 578
    //   1706: invokevirtual 563	java/lang/String:getBytes	()[B
    //   1709: invokevirtual 448	java/io/DataOutputStream:write	([B)V
    //   1712: aload 23
    //   1714: invokevirtual 566	java/io/DataOutputStream:flush	()V
    //   1717: iload_2
    //   1718: istore_1
    //   1719: lload 6
    //   1721: lstore 8
    //   1723: goto -70 -> 1653
    //   1726: astore 18
    //   1728: aload 18
    //   1730: invokevirtual 383	java/lang/Exception:printStackTrace	()V
    //   1733: iconst_1
    //   1734: istore_1
    //   1735: lload 6
    //   1737: lstore 8
    //   1739: goto -86 -> 1653
    //   1742: aload 17
    //   1744: ifnonnull +191 -> 1935
    //   1747: aload_0
    //   1748: getfield 52	com/estrongs/fs/b/bo:b	Lcom/estrongs/fs/d;
    //   1751: aload 25
    //   1753: invokeinterface 99 1 0
    //   1758: invokevirtual 581	com/estrongs/fs/d:e	(Ljava/lang/String;)Ljava/io/InputStream;
    //   1761: astore 19
    //   1763: aload 19
    //   1765: astore 17
    //   1767: lload 6
    //   1769: lstore 8
    //   1771: aload 17
    //   1773: aload 26
    //   1775: invokevirtual 582	java/io/InputStream:read	([B)I
    //   1778: istore_1
    //   1779: lload 6
    //   1781: lstore 8
    //   1783: aload 23
    //   1785: aload 26
    //   1787: iconst_0
    //   1788: iload_1
    //   1789: invokevirtual 585	java/io/DataOutputStream:write	([BII)V
    //   1792: lload 6
    //   1794: lstore 8
    //   1796: aload 23
    //   1798: invokevirtual 566	java/io/DataOutputStream:flush	()V
    //   1801: lload 12
    //   1803: iload_1
    //   1804: i2l
    //   1805: ladd
    //   1806: lstore 12
    //   1808: lload 6
    //   1810: iload_1
    //   1811: i2l
    //   1812: ladd
    //   1813: lstore 6
    //   1815: lload 6
    //   1817: lstore 8
    //   1819: aload 22
    //   1821: bipush 9
    //   1823: iconst_2
    //   1824: anewarray 587	java/lang/Object
    //   1827: dup
    //   1828: iconst_0
    //   1829: lload 14
    //   1831: invokestatic 34	java/lang/Long:valueOf	(J)Ljava/lang/Long;
    //   1834: aastore
    //   1835: dup
    //   1836: iconst_1
    //   1837: lload 12
    //   1839: invokestatic 34	java/lang/Long:valueOf	(J)Ljava/lang/Long;
    //   1842: aastore
    //   1843: invokevirtual 590	com/estrongs/a/a:sendMessage	(I[Ljava/lang/Object;)V
    //   1846: lload 6
    //   1848: lstore 8
    //   1850: aload 22
    //   1852: iconst_2
    //   1853: iconst_3
    //   1854: anewarray 587	java/lang/Object
    //   1857: dup
    //   1858: iconst_0
    //   1859: lload 6
    //   1861: invokestatic 34	java/lang/Long:valueOf	(J)Ljava/lang/Long;
    //   1864: aastore
    //   1865: dup
    //   1866: iconst_1
    //   1867: aload 18
    //   1869: aastore
    //   1870: dup
    //   1871: iconst_2
    //   1872: lload 10
    //   1874: invokestatic 34	java/lang/Long:valueOf	(J)Ljava/lang/Long;
    //   1877: aastore
    //   1878: invokevirtual 590	com/estrongs/a/a:sendMessage	(I[Ljava/lang/Object;)V
    //   1881: goto -247 -> 1634
    //   1884: iload_3
    //   1885: iconst_1
    //   1886: iadd
    //   1887: istore_3
    //   1888: goto -615 -> 1273
    //   1891: astore 17
    //   1893: iconst_1
    //   1894: istore_1
    //   1895: goto -514 -> 1381
    //   1898: iconst_0
    //   1899: ireturn
    //   1900: astore 17
    //   1902: goto -1474 -> 428
    //   1905: astore 17
    //   1907: goto -231 -> 1676
    //   1910: astore 18
    //   1912: lload 8
    //   1914: lstore 6
    //   1916: goto -188 -> 1728
    //   1919: astore 17
    //   1921: aconst_null
    //   1922: astore 18
    //   1924: goto -1532 -> 392
    //   1927: astore 18
    //   1929: goto -888 -> 1041
    //   1932: goto -576 -> 1356
    //   1935: goto -168 -> 1767
    //   1938: ldc_w 512
    //   1941: astore 17
    //   1943: goto -1410 -> 533
    //   1946: lload 10
    //   1948: lstore 6
    //   1950: goto -1798 -> 152
    //   1953: astore 17
    //   1955: iconst_1
    //   1956: istore_1
    //   1957: goto -605 -> 1352
    // Local variable table:
    //   start	length	slot	name	signature
    //   0	1960	0	this	bo
    //   766	1191	1	i	int
    //   772	946	2	j	int
    //   1269	619	3	k	int
    //   1322	237	4	m	int
    //   1334	225	5	n	int
    //   150	1799	6	l1	long
    //   1651	262	8	l2	long
    //   80	1867	10	l3	long
    //   1622	216	12	l4	long
    //   1424	406	14	l5	long
    //   726	295	16	bool	boolean
    //   77	242	17	localObject1	Object
    //   386	116	17	localException1	Exception
    //   531	501	17	localObject2	Object
    //   1036	1	17	localException2	Exception
    //   1039	733	17	localObject3	Object
    //   1891	1	17	localException3	Exception
    //   1900	1	17	localException4	Exception
    //   1905	1	17	localException5	Exception
    //   1919	1	17	localException6	Exception
    //   1941	1	17	str	String
    //   1953	1	17	localIOException	java.io.IOException
    //   102	1560	18	localObject4	Object
    //   1726	142	18	localException7	Exception
    //   1910	1	18	localException8	Exception
    //   1922	1	18	localObject5	Object
    //   1927	1	18	localException9	Exception
    //   126	1638	19	localObject6	Object
    //   345	1032	20	localSocket	java.net.Socket
    //   891	581	21	localObject7	Object
    //   64	1787	22	locala	a
    //   484	1313	23	localDataOutputStream	java.io.DataOutputStream
    //   470	869	24	localObject8	Object
    //   1343	409	25	localh	h
    //   1629	157	26	arrayOfByte	byte[]
    // Exception table:
    //   from	to	target	type
    //   347	386	386	java/lang/Exception
    //   458	486	386	java/lang/Exception
    //   489	515	386	java/lang/Exception
    //   515	528	386	java/lang/Exception
    //   533	663	386	java/lang/Exception
    //   668	675	386	java/lang/Exception
    //   675	689	386	java/lang/Exception
    //   694	707	386	java/lang/Exception
    //   709	718	386	java/lang/Exception
    //   721	728	386	java/lang/Exception
    //   1053	1066	386	java/lang/Exception
    //   1074	1083	386	java/lang/Exception
    //   1087	1173	386	java/lang/Exception
    //   1175	1211	386	java/lang/Exception
    //   1219	1249	386	java/lang/Exception
    //   733	802	1036	java/lang/Exception
    //   805	942	1036	java/lang/Exception
    //   1701	1717	1726	java/lang/Exception
    //   1747	1763	1726	java/lang/Exception
    //   1360	1376	1891	java/lang/Exception
    //   1376	1381	1891	java/lang/Exception
    //   423	428	1900	java/lang/Exception
    //   1671	1676	1905	java/lang/Exception
    //   1771	1779	1910	java/lang/Exception
    //   1783	1792	1910	java/lang/Exception
    //   1796	1801	1910	java/lang/Exception
    //   1819	1846	1910	java/lang/Exception
    //   1850	1881	1910	java/lang/Exception
    //   292	347	1919	java/lang/Exception
    //   944	951	1927	java/lang/Exception
    //   1338	1345	1953	java/io/IOException
    //   1417	1498	1953	java/io/IOException
    //   1498	1538	1953	java/io/IOException
    //   1541	1568	1953	java/io/IOException
    //   1571	1621	1953	java/io/IOException
  }
}

/* Location:
 * Qualified Name:     com.estrongs.fs.b.bo
 * Java Class Version: 6 (50.0)
 * JD-Core Version:    0.7.1
 */