package com.estrongs.android.scanner;

class ag
  implements Runnable
{
  ag(af paramaf) {}
  
  /* Error */
  public void run()
  {
    // Byte code:
    //   0: aload_0
    //   1: getfield 12	com/estrongs/android/scanner/ag:a	Lcom/estrongs/android/scanner/af;
    //   4: new 23	com/estrongs/android/scanner/ah
    //   7: dup
    //   8: aload_0
    //   9: invokespecial 26	com/estrongs/android/scanner/ah:<init>	(Lcom/estrongs/android/scanner/ag;)V
    //   12: invokestatic 31	com/estrongs/android/scanner/af:a	(Lcom/estrongs/android/scanner/af;Ljava/lang/ThreadLocal;)Ljava/lang/ThreadLocal;
    //   15: pop
    //   16: aload_0
    //   17: getfield 12	com/estrongs/android/scanner/ag:a	Lcom/estrongs/android/scanner/af;
    //   20: invokestatic 34	com/estrongs/android/scanner/af:a	(Lcom/estrongs/android/scanner/af;)Ljava/util/concurrent/CyclicBarrier;
    //   23: invokevirtual 40	java/util/concurrent/CyclicBarrier:await	()I
    //   26: pop
    //   27: aload_0
    //   28: getfield 12	com/estrongs/android/scanner/ag:a	Lcom/estrongs/android/scanner/af;
    //   31: invokestatic 44	com/estrongs/android/scanner/af:b	(Lcom/estrongs/android/scanner/af;)Z
    //   34: ifeq +15 -> 49
    //   37: aload_0
    //   38: getfield 12	com/estrongs/android/scanner/ag:a	Lcom/estrongs/android/scanner/af;
    //   41: invokestatic 47	com/estrongs/android/scanner/af:c	(Lcom/estrongs/android/scanner/af;)Z
    //   44: istore_1
    //   45: iload_1
    //   46: ifeq +28 -> 74
    //   49: invokestatic 50	com/estrongs/android/scanner/af:b	()Ljava/lang/String;
    //   52: ldc 52
    //   54: invokestatic 57	com/estrongs/android/util/l:b	(Ljava/lang/String;Ljava/lang/String;)V
    //   57: return
    //   58: astore_2
    //   59: aload_2
    //   60: invokevirtual 60	java/lang/InterruptedException:printStackTrace	()V
    //   63: goto -36 -> 27
    //   66: astore_2
    //   67: aload_2
    //   68: invokevirtual 61	java/util/concurrent/BrokenBarrierException:printStackTrace	()V
    //   71: goto -44 -> 27
    //   74: aload_0
    //   75: getfield 12	com/estrongs/android/scanner/ag:a	Lcom/estrongs/android/scanner/af;
    //   78: invokestatic 65	com/estrongs/android/scanner/af:d	(Lcom/estrongs/android/scanner/af;)Ljava/util/concurrent/BlockingQueue;
    //   81: invokeinterface 71 1 0
    //   86: checkcast 73	com/estrongs/android/scanner/ak
    //   89: astore_2
    //   90: aload_0
    //   91: getfield 12	com/estrongs/android/scanner/ag:a	Lcom/estrongs/android/scanner/af;
    //   94: aload_2
    //   95: invokestatic 76	com/estrongs/android/scanner/af:a	(Lcom/estrongs/android/scanner/af;Lcom/estrongs/android/scanner/ak;)V
    //   98: aload_0
    //   99: getfield 12	com/estrongs/android/scanner/ag:a	Lcom/estrongs/android/scanner/af;
    //   102: invokestatic 80	com/estrongs/android/scanner/af:e	(Lcom/estrongs/android/scanner/af;)Ljava/util/concurrent/atomic/AtomicInteger;
    //   105: invokevirtual 85	java/util/concurrent/atomic/AtomicInteger:decrementAndGet	()I
    //   108: pop
    //   109: goto -82 -> 27
    //   112: astore_2
    //   113: aload_0
    //   114: getfield 12	com/estrongs/android/scanner/ag:a	Lcom/estrongs/android/scanner/af;
    //   117: iconst_0
    //   118: invokestatic 88	com/estrongs/android/scanner/af:a	(Lcom/estrongs/android/scanner/af;Z)Z
    //   121: pop
    //   122: goto -95 -> 27
    // Local variable table:
    //   start	length	slot	name	signature
    //   0	125	0	this	ag
    //   44	2	1	bool	boolean
    //   58	2	2	localInterruptedException1	InterruptedException
    //   66	2	2	localBrokenBarrierException	java.util.concurrent.BrokenBarrierException
    //   89	6	2	localak	ak
    //   112	1	2	localInterruptedException2	InterruptedException
    // Exception table:
    //   from	to	target	type
    //   16	27	58	java/lang/InterruptedException
    //   16	27	66	java/util/concurrent/BrokenBarrierException
    //   37	45	112	java/lang/InterruptedException
    //   74	109	112	java/lang/InterruptedException
  }
}

/* Location:
 * Qualified Name:     com.estrongs.android.scanner.ag
 * Java Class Version: 6 (50.0)
 * JD-Core Version:    0.7.1
 */