package com.estrongs.android.scanner;

class z
  implements Runnable
{
  z(y paramy) {}
  
  /* Error */
  public void run()
  {
    // Byte code:
    //   0: aload_0
    //   1: getfield 12	com/estrongs/android/scanner/z:a	Lcom/estrongs/android/scanner/y;
    //   4: invokestatic 26	com/estrongs/android/scanner/y:a	(Lcom/estrongs/android/scanner/y;)Ljava/util/concurrent/CyclicBarrier;
    //   7: invokevirtual 32	java/util/concurrent/CyclicBarrier:await	()I
    //   10: pop
    //   11: aload_0
    //   12: getfield 12	com/estrongs/android/scanner/z:a	Lcom/estrongs/android/scanner/y;
    //   15: invokestatic 36	com/estrongs/android/scanner/y:b	(Lcom/estrongs/android/scanner/y;)Z
    //   18: ifeq +15 -> 33
    //   21: aload_0
    //   22: getfield 12	com/estrongs/android/scanner/z:a	Lcom/estrongs/android/scanner/y;
    //   25: invokestatic 39	com/estrongs/android/scanner/y:c	(Lcom/estrongs/android/scanner/y;)Z
    //   28: istore_1
    //   29: iload_1
    //   30: ifeq +28 -> 58
    //   33: invokestatic 42	com/estrongs/android/scanner/y:b	()Ljava/lang/String;
    //   36: ldc 44
    //   38: invokestatic 49	com/estrongs/android/util/l:b	(Ljava/lang/String;Ljava/lang/String;)V
    //   41: return
    //   42: astore_2
    //   43: aload_2
    //   44: invokevirtual 52	java/lang/InterruptedException:printStackTrace	()V
    //   47: goto -36 -> 11
    //   50: astore_2
    //   51: aload_2
    //   52: invokevirtual 53	java/util/concurrent/BrokenBarrierException:printStackTrace	()V
    //   55: goto -44 -> 11
    //   58: aload_0
    //   59: getfield 12	com/estrongs/android/scanner/z:a	Lcom/estrongs/android/scanner/y;
    //   62: invokestatic 57	com/estrongs/android/scanner/y:d	(Lcom/estrongs/android/scanner/y;)Ljava/util/concurrent/BlockingQueue;
    //   65: invokeinterface 63 1 0
    //   70: checkcast 65	com/estrongs/android/scanner/a/f
    //   73: astore_2
    //   74: aload_2
    //   75: invokevirtual 69	com/estrongs/android/scanner/a/f:e	()Z
    //   78: ifeq +43 -> 121
    //   81: aload_0
    //   82: getfield 12	com/estrongs/android/scanner/z:a	Lcom/estrongs/android/scanner/y;
    //   85: iconst_1
    //   86: invokestatic 72	com/estrongs/android/scanner/y:a	(Lcom/estrongs/android/scanner/y;Z)Z
    //   89: pop
    //   90: aload_0
    //   91: getfield 12	com/estrongs/android/scanner/z:a	Lcom/estrongs/android/scanner/y;
    //   94: invokestatic 75	com/estrongs/android/scanner/y:e	(Lcom/estrongs/android/scanner/y;)Ljava/util/concurrent/atomic/AtomicInteger;
    //   97: invokevirtual 80	java/util/concurrent/atomic/AtomicInteger:decrementAndGet	()I
    //   100: pop
    //   101: goto -90 -> 11
    //   104: astore_2
    //   105: aload_0
    //   106: getfield 12	com/estrongs/android/scanner/z:a	Lcom/estrongs/android/scanner/y;
    //   109: iconst_0
    //   110: invokestatic 82	com/estrongs/android/scanner/y:b	(Lcom/estrongs/android/scanner/y;Z)Z
    //   113: pop
    //   114: aload_2
    //   115: invokevirtual 52	java/lang/InterruptedException:printStackTrace	()V
    //   118: goto -107 -> 11
    //   121: aload_0
    //   122: getfield 12	com/estrongs/android/scanner/z:a	Lcom/estrongs/android/scanner/y;
    //   125: aload_2
    //   126: invokestatic 85	com/estrongs/android/scanner/y:a	(Lcom/estrongs/android/scanner/y;Lcom/estrongs/android/scanner/a/f;)V
    //   129: goto -39 -> 90
    // Local variable table:
    //   start	length	slot	name	signature
    //   0	132	0	this	z
    //   28	2	1	bool	boolean
    //   42	2	2	localInterruptedException1	InterruptedException
    //   50	2	2	localBrokenBarrierException	java.util.concurrent.BrokenBarrierException
    //   73	2	2	localf	com.estrongs.android.scanner.a.f
    //   104	22	2	localInterruptedException2	InterruptedException
    // Exception table:
    //   from	to	target	type
    //   0	11	42	java/lang/InterruptedException
    //   0	11	50	java/util/concurrent/BrokenBarrierException
    //   21	29	104	java/lang/InterruptedException
    //   58	90	104	java/lang/InterruptedException
    //   90	101	104	java/lang/InterruptedException
    //   121	129	104	java/lang/InterruptedException
  }
}

/* Location:
 * Qualified Name:     com.estrongs.android.scanner.z
 * Java Class Version: 6 (50.0)
 * JD-Core Version:    0.7.1
 */