package com.estrongs.android.pop.app.b;

class s
  extends Thread
{
  s(k paramk, boolean paramBoolean) {}
  
  /* Error */
  public void run()
  {
    // Byte code:
    //   0: ldc 21
    //   2: monitorenter
    //   3: aload_0
    //   4: getfield 14	com/estrongs/android/pop/app/b/s:a	Z
    //   7: ifeq +39 -> 46
    //   10: aload_0
    //   11: getfield 12	com/estrongs/android/pop/app/b/s:b	Lcom/estrongs/android/pop/app/b/k;
    //   14: invokestatic 25	com/estrongs/android/pop/app/b/k:k	(Lcom/estrongs/android/pop/app/b/k;)V
    //   17: new 27	android/os/Message
    //   20: dup
    //   21: invokespecial 28	android/os/Message:<init>	()V
    //   24: astore_1
    //   25: aload_1
    //   26: iconst_1
    //   27: putfield 32	android/os/Message:what	I
    //   30: aload_0
    //   31: getfield 12	com/estrongs/android/pop/app/b/s:b	Lcom/estrongs/android/pop/app/b/k;
    //   34: invokestatic 35	com/estrongs/android/pop/app/b/k:a	(Lcom/estrongs/android/pop/app/b/k;)Landroid/os/Handler;
    //   37: aload_1
    //   38: invokevirtual 41	android/os/Handler:sendMessage	(Landroid/os/Message;)Z
    //   41: pop
    //   42: ldc 21
    //   44: monitorexit
    //   45: return
    //   46: aload_0
    //   47: getfield 12	com/estrongs/android/pop/app/b/s:b	Lcom/estrongs/android/pop/app/b/k;
    //   50: invokestatic 44	com/estrongs/android/pop/app/b/k:l	(Lcom/estrongs/android/pop/app/b/k;)V
    //   53: goto -36 -> 17
    //   56: astore_1
    //   57: ldc 21
    //   59: monitorexit
    //   60: aload_1
    //   61: athrow
    // Local variable table:
    //   start	length	slot	name	signature
    //   0	62	0	this	s
    //   24	14	1	localMessage	android.os.Message
    //   56	5	1	localObject	Object
    // Exception table:
    //   from	to	target	type
    //   3	17	56	finally
    //   17	45	56	finally
    //   46	53	56	finally
    //   57	60	56	finally
  }
}

/* Location:
 * Qualified Name:     com.estrongs.android.pop.app.b.s
 * Java Class Version: 6 (50.0)
 * JD-Core Version:    0.7.1
 */