package com.estrongs.android.widget;

class k
  extends Thread
{
  k(f paramf, String paramString) {}
  
  /* Error */
  public void run()
  {
    // Byte code:
    //   0: aconst_null
    //   1: astore_3
    //   2: aload_0
    //   3: getfield 12	com/estrongs/android/widget/k:b	Lcom/estrongs/android/widget/f;
    //   6: aload_0
    //   7: getfield 14	com/estrongs/android/widget/k:a	Ljava/lang/String;
    //   10: putfield 25	com/estrongs/android/widget/f:b	Ljava/lang/String;
    //   13: aload_0
    //   14: getfield 12	com/estrongs/android/widget/k:b	Lcom/estrongs/android/widget/f;
    //   17: invokestatic 28	com/estrongs/android/widget/f:b	(Lcom/estrongs/android/widget/f;)Lcom/estrongs/android/view/fv;
    //   20: invokevirtual 34	com/estrongs/android/view/fv:c	()Ljava/lang/String;
    //   23: astore_2
    //   24: aload_2
    //   25: astore_1
    //   26: aload_2
    //   27: aload_0
    //   28: getfield 12	com/estrongs/android/widget/k:b	Lcom/estrongs/android/widget/f;
    //   31: getfield 25	com/estrongs/android/widget/f:b	Ljava/lang/String;
    //   34: iconst_1
    //   35: aload_0
    //   36: getfield 12	com/estrongs/android/widget/k:b	Lcom/estrongs/android/widget/f;
    //   39: invokestatic 28	com/estrongs/android/widget/f:b	(Lcom/estrongs/android/widget/f;)Lcom/estrongs/android/view/fv;
    //   42: invokevirtual 38	com/estrongs/android/view/fv:ag	()Lcom/estrongs/fs/d;
    //   45: invokestatic 43	com/estrongs/fs/util/j:a	(Ljava/lang/String;Ljava/lang/String;ZLcom/estrongs/fs/d;)Z
    //   48: ifne +18 -> 66
    //   51: aload_2
    //   52: astore_1
    //   53: aload_0
    //   54: getfield 12	com/estrongs/android/widget/k:b	Lcom/estrongs/android/widget/f;
    //   57: invokestatic 47	com/estrongs/android/widget/f:d	(Lcom/estrongs/android/widget/f;)Landroid/app/Activity;
    //   60: ldc 48
    //   62: invokevirtual 54	android/app/Activity:getString	(I)Ljava/lang/String;
    //   65: astore_3
    //   66: aload_3
    //   67: ifnull +48 -> 115
    //   70: aload_0
    //   71: getfield 12	com/estrongs/android/widget/k:b	Lcom/estrongs/android/widget/f;
    //   74: invokestatic 47	com/estrongs/android/widget/f:d	(Lcom/estrongs/android/widget/f;)Landroid/app/Activity;
    //   77: aload_3
    //   78: iconst_0
    //   79: invokestatic 59	com/estrongs/android/ui/view/ak:a	(Landroid/content/Context;Ljava/lang/CharSequence;I)V
    //   82: invokestatic 64	com/estrongs/android/pop/ac:a	()I
    //   85: bipush 18
    //   87: if_icmplt +28 -> 115
    //   90: aload_2
    //   91: invokestatic 70	com/estrongs/android/util/ap:bJ	(Ljava/lang/String;)Z
    //   94: ifeq +21 -> 115
    //   97: aload_0
    //   98: getfield 12	com/estrongs/android/widget/k:b	Lcom/estrongs/android/widget/f;
    //   101: invokestatic 47	com/estrongs/android/widget/f:d	(Lcom/estrongs/android/widget/f;)Landroid/app/Activity;
    //   104: new 72	com/estrongs/android/widget/l
    //   107: dup
    //   108: aload_0
    //   109: invokespecial 75	com/estrongs/android/widget/l:<init>	(Lcom/estrongs/android/widget/k;)V
    //   112: invokevirtual 79	android/app/Activity:runOnUiThread	(Ljava/lang/Runnable;)V
    //   115: return
    //   116: astore_3
    //   117: aconst_null
    //   118: astore_2
    //   119: aload_2
    //   120: astore_1
    //   121: aload_3
    //   122: instanceof 81
    //   125: ifeq +95 -> 220
    //   128: aload_2
    //   129: astore_1
    //   130: new 83	java/lang/StringBuilder
    //   133: dup
    //   134: invokespecial 84	java/lang/StringBuilder:<init>	()V
    //   137: aload_0
    //   138: getfield 12	com/estrongs/android/widget/k:b	Lcom/estrongs/android/widget/f;
    //   141: invokestatic 47	com/estrongs/android/widget/f:d	(Lcom/estrongs/android/widget/f;)Landroid/app/Activity;
    //   144: ldc 48
    //   146: invokevirtual 54	android/app/Activity:getString	(I)Ljava/lang/String;
    //   149: invokevirtual 88	java/lang/StringBuilder:append	(Ljava/lang/String;)Ljava/lang/StringBuilder;
    //   152: ldc 90
    //   154: invokevirtual 88	java/lang/StringBuilder:append	(Ljava/lang/String;)Ljava/lang/StringBuilder;
    //   157: aload_3
    //   158: invokevirtual 93	com/estrongs/fs/FileSystemException:getMessage	()Ljava/lang/String;
    //   161: invokevirtual 88	java/lang/StringBuilder:append	(Ljava/lang/String;)Ljava/lang/StringBuilder;
    //   164: invokevirtual 96	java/lang/StringBuilder:toString	()Ljava/lang/String;
    //   167: astore_3
    //   168: aload_3
    //   169: astore_1
    //   170: aload_1
    //   171: ifnull -56 -> 115
    //   174: aload_0
    //   175: getfield 12	com/estrongs/android/widget/k:b	Lcom/estrongs/android/widget/f;
    //   178: invokestatic 47	com/estrongs/android/widget/f:d	(Lcom/estrongs/android/widget/f;)Landroid/app/Activity;
    //   181: aload_1
    //   182: iconst_0
    //   183: invokestatic 59	com/estrongs/android/ui/view/ak:a	(Landroid/content/Context;Ljava/lang/CharSequence;I)V
    //   186: invokestatic 64	com/estrongs/android/pop/ac:a	()I
    //   189: bipush 18
    //   191: if_icmplt -76 -> 115
    //   194: aload_2
    //   195: invokestatic 70	com/estrongs/android/util/ap:bJ	(Ljava/lang/String;)Z
    //   198: ifeq -83 -> 115
    //   201: aload_0
    //   202: getfield 12	com/estrongs/android/widget/k:b	Lcom/estrongs/android/widget/f;
    //   205: invokestatic 47	com/estrongs/android/widget/f:d	(Lcom/estrongs/android/widget/f;)Landroid/app/Activity;
    //   208: new 72	com/estrongs/android/widget/l
    //   211: dup
    //   212: aload_0
    //   213: invokespecial 75	com/estrongs/android/widget/l:<init>	(Lcom/estrongs/android/widget/k;)V
    //   216: invokevirtual 79	android/app/Activity:runOnUiThread	(Ljava/lang/Runnable;)V
    //   219: return
    //   220: aload_2
    //   221: astore_1
    //   222: new 83	java/lang/StringBuilder
    //   225: dup
    //   226: invokespecial 84	java/lang/StringBuilder:<init>	()V
    //   229: aload_0
    //   230: getfield 12	com/estrongs/android/widget/k:b	Lcom/estrongs/android/widget/f;
    //   233: invokestatic 47	com/estrongs/android/widget/f:d	(Lcom/estrongs/android/widget/f;)Landroid/app/Activity;
    //   236: ldc 48
    //   238: invokevirtual 54	android/app/Activity:getString	(I)Ljava/lang/String;
    //   241: invokevirtual 88	java/lang/StringBuilder:append	(Ljava/lang/String;)Ljava/lang/StringBuilder;
    //   244: ldc 90
    //   246: invokevirtual 88	java/lang/StringBuilder:append	(Ljava/lang/String;)Ljava/lang/StringBuilder;
    //   249: aload_3
    //   250: invokevirtual 93	com/estrongs/fs/FileSystemException:getMessage	()Ljava/lang/String;
    //   253: invokevirtual 88	java/lang/StringBuilder:append	(Ljava/lang/String;)Ljava/lang/StringBuilder;
    //   256: invokevirtual 96	java/lang/StringBuilder:toString	()Ljava/lang/String;
    //   259: astore_3
    //   260: aload_3
    //   261: astore_1
    //   262: goto -92 -> 170
    //   265: astore_2
    //   266: aconst_null
    //   267: astore_1
    //   268: iconst_0
    //   269: ifeq +48 -> 317
    //   272: aload_0
    //   273: getfield 12	com/estrongs/android/widget/k:b	Lcom/estrongs/android/widget/f;
    //   276: invokestatic 47	com/estrongs/android/widget/f:d	(Lcom/estrongs/android/widget/f;)Landroid/app/Activity;
    //   279: aconst_null
    //   280: iconst_0
    //   281: invokestatic 59	com/estrongs/android/ui/view/ak:a	(Landroid/content/Context;Ljava/lang/CharSequence;I)V
    //   284: invokestatic 64	com/estrongs/android/pop/ac:a	()I
    //   287: bipush 18
    //   289: if_icmplt +28 -> 317
    //   292: aload_1
    //   293: invokestatic 70	com/estrongs/android/util/ap:bJ	(Ljava/lang/String;)Z
    //   296: ifeq +21 -> 317
    //   299: aload_0
    //   300: getfield 12	com/estrongs/android/widget/k:b	Lcom/estrongs/android/widget/f;
    //   303: invokestatic 47	com/estrongs/android/widget/f:d	(Lcom/estrongs/android/widget/f;)Landroid/app/Activity;
    //   306: new 72	com/estrongs/android/widget/l
    //   309: dup
    //   310: aload_0
    //   311: invokespecial 75	com/estrongs/android/widget/l:<init>	(Lcom/estrongs/android/widget/k;)V
    //   314: invokevirtual 79	android/app/Activity:runOnUiThread	(Ljava/lang/Runnable;)V
    //   317: aload_2
    //   318: athrow
    //   319: astore_2
    //   320: goto -52 -> 268
    //   323: astore_3
    //   324: goto -205 -> 119
    // Local variable table:
    //   start	length	slot	name	signature
    //   0	327	0	this	k
    //   25	268	1	str1	String
    //   23	198	2	str2	String
    //   265	53	2	localObject1	Object
    //   319	1	2	localObject2	Object
    //   1	77	3	str3	String
    //   116	42	3	localFileSystemException1	com.estrongs.fs.FileSystemException
    //   167	94	3	str4	String
    //   323	1	3	localFileSystemException2	com.estrongs.fs.FileSystemException
    // Exception table:
    //   from	to	target	type
    //   2	24	116	com/estrongs/fs/FileSystemException
    //   2	24	265	finally
    //   26	51	319	finally
    //   53	66	319	finally
    //   121	128	319	finally
    //   130	168	319	finally
    //   222	260	319	finally
    //   26	51	323	com/estrongs/fs/FileSystemException
    //   53	66	323	com/estrongs/fs/FileSystemException
  }
}

/* Location:
 * Qualified Name:     com.estrongs.android.widget.k
 * Java Class Version: 6 (50.0)
 * JD-Core Version:    0.7.1
 */