package com.estrongs.android.pop.app.editor;

class ac
  extends Thread
{
  private StringBuilder b = null;
  private int c = 0;
  private boolean d = false;
  
  public ac(PopNoteEditor paramPopNoteEditor, int paramInt, boolean paramBoolean)
  {
    try
    {
      PopNoteEditor.u(paramPopNoteEditor).delete(0, PopNoteEditor.u(paramPopNoteEditor).length());
      b = new StringBuilder();
      PopNoteEditor.d(paramPopNoteEditor, 0);
      c = paramInt;
      d = paramBoolean;
      return;
    }
    catch (Exception localException)
    {
      for (;;) {}
    }
  }
  
  /* Error */
  public void run()
  {
    // Byte code:
    //   0: aload_0
    //   1: getfield 18	com/estrongs/android/pop/app/editor/ac:a	Lcom/estrongs/android/pop/app/editor/PopNoteEditor;
    //   4: invokestatic 55	com/estrongs/android/pop/app/editor/PopNoteEditor:t	(Lcom/estrongs/android/pop/app/editor/PopNoteEditor;)Ljava/lang/Object;
    //   7: astore 12
    //   9: aload 12
    //   11: monitorenter
    //   12: aload_0
    //   13: getfield 18	com/estrongs/android/pop/app/editor/ac:a	Lcom/estrongs/android/pop/app/editor/PopNoteEditor;
    //   16: invokestatic 59	com/estrongs/android/pop/app/editor/PopNoteEditor:o	(Lcom/estrongs/android/pop/app/editor/PopNoteEditor;)V
    //   19: aload_0
    //   20: getfield 27	com/estrongs/android/pop/app/editor/ac:d	Z
    //   23: ifeq +21 -> 44
    //   26: aload_0
    //   27: getfield 18	com/estrongs/android/pop/app/editor/ac:a	Lcom/estrongs/android/pop/app/editor/PopNoteEditor;
    //   30: aload_0
    //   31: getfield 18	com/estrongs/android/pop/app/editor/ac:a	Lcom/estrongs/android/pop/app/editor/PopNoteEditor;
    //   34: invokestatic 63	com/estrongs/android/pop/app/editor/PopNoteEditor:p	(Lcom/estrongs/android/pop/app/editor/PopNoteEditor;)Lcom/estrongs/android/pop/app/editor/c;
    //   37: invokevirtual 69	com/estrongs/android/pop/app/editor/c:g	()Ljava/lang/String;
    //   40: invokestatic 72	com/estrongs/android/pop/app/editor/PopNoteEditor:a	(Lcom/estrongs/android/pop/app/editor/PopNoteEditor;Ljava/lang/String;)Ljava/lang/String;
    //   43: pop
    //   44: aload_0
    //   45: getfield 18	com/estrongs/android/pop/app/editor/ac:a	Lcom/estrongs/android/pop/app/editor/PopNoteEditor;
    //   48: invokestatic 76	com/estrongs/android/pop/app/editor/PopNoteEditor:y	(Lcom/estrongs/android/pop/app/editor/PopNoteEditor;)Lcom/estrongs/android/pop/app/editor/b;
    //   51: astore 13
    //   53: aload 13
    //   55: ifnull +13 -> 68
    //   58: aload_0
    //   59: getfield 18	com/estrongs/android/pop/app/editor/ac:a	Lcom/estrongs/android/pop/app/editor/PopNoteEditor;
    //   62: invokestatic 76	com/estrongs/android/pop/app/editor/PopNoteEditor:y	(Lcom/estrongs/android/pop/app/editor/PopNoteEditor;)Lcom/estrongs/android/pop/app/editor/b;
    //   65: invokevirtual 81	com/estrongs/android/pop/app/editor/b:close	()V
    //   68: aload_0
    //   69: getfield 18	com/estrongs/android/pop/app/editor/ac:a	Lcom/estrongs/android/pop/app/editor/PopNoteEditor;
    //   72: aconst_null
    //   73: invokestatic 83	com/estrongs/android/pop/app/editor/PopNoteEditor:c	(Lcom/estrongs/android/pop/app/editor/PopNoteEditor;Ljava/lang/String;)Ljava/lang/String;
    //   76: pop
    //   77: aload_0
    //   78: getfield 18	com/estrongs/android/pop/app/editor/ac:a	Lcom/estrongs/android/pop/app/editor/PopNoteEditor;
    //   81: new 78	com/estrongs/android/pop/app/editor/b
    //   84: dup
    //   85: aload_0
    //   86: getfield 18	com/estrongs/android/pop/app/editor/ac:a	Lcom/estrongs/android/pop/app/editor/PopNoteEditor;
    //   89: invokestatic 87	com/estrongs/android/pop/app/editor/PopNoteEditor:i	(Lcom/estrongs/android/pop/app/editor/PopNoteEditor;)Landroid/content/Context;
    //   92: aload_0
    //   93: getfield 18	com/estrongs/android/pop/app/editor/ac:a	Lcom/estrongs/android/pop/app/editor/PopNoteEditor;
    //   96: invokestatic 91	com/estrongs/android/pop/app/editor/PopNoteEditor:v	(Lcom/estrongs/android/pop/app/editor/PopNoteEditor;)Ljava/io/File;
    //   99: aload_0
    //   100: getfield 18	com/estrongs/android/pop/app/editor/ac:a	Lcom/estrongs/android/pop/app/editor/PopNoteEditor;
    //   103: invokestatic 95	com/estrongs/android/pop/app/editor/PopNoteEditor:m	(Lcom/estrongs/android/pop/app/editor/PopNoteEditor;)Ljava/lang/String;
    //   106: invokespecial 98	com/estrongs/android/pop/app/editor/b:<init>	(Landroid/content/Context;Ljava/io/File;Ljava/lang/String;)V
    //   109: invokestatic 101	com/estrongs/android/pop/app/editor/PopNoteEditor:a	(Lcom/estrongs/android/pop/app/editor/PopNoteEditor;Lcom/estrongs/android/pop/app/editor/b;)Lcom/estrongs/android/pop/app/editor/b;
    //   112: pop
    //   113: sipush 4096
    //   116: newarray <illegal type>
    //   118: astore 13
    //   120: dconst_0
    //   121: dstore_3
    //   122: aload_0
    //   123: getfield 25	com/estrongs/android/pop/app/editor/ac:c	I
    //   126: i2l
    //   127: aload_0
    //   128: getfield 18	com/estrongs/android/pop/app/editor/ac:a	Lcom/estrongs/android/pop/app/editor/PopNoteEditor;
    //   131: invokestatic 105	com/estrongs/android/pop/app/editor/PopNoteEditor:E	(Lcom/estrongs/android/pop/app/editor/PopNoteEditor;)J
    //   134: lmul
    //   135: ldc2_w 106
    //   138: ldiv
    //   139: ldc2_w 108
    //   142: lsub
    //   143: lstore 8
    //   145: aload_0
    //   146: getfield 18	com/estrongs/android/pop/app/editor/ac:a	Lcom/estrongs/android/pop/app/editor/PopNoteEditor;
    //   149: invokestatic 113	com/estrongs/android/pop/app/editor/PopNoteEditor:x	(Lcom/estrongs/android/pop/app/editor/PopNoteEditor;)Lcom/estrongs/android/pop/app/editor/af;
    //   152: lload 8
    //   154: invokevirtual 118	com/estrongs/android/pop/app/editor/af:a	(J)Lcom/estrongs/android/pop/app/editor/ag;
    //   157: astore 14
    //   159: dload_3
    //   160: dstore_1
    //   161: aload 14
    //   163: ifnull +33 -> 196
    //   166: aload_0
    //   167: getfield 18	com/estrongs/android/pop/app/editor/ac:a	Lcom/estrongs/android/pop/app/editor/PopNoteEditor;
    //   170: invokestatic 76	com/estrongs/android/pop/app/editor/PopNoteEditor:y	(Lcom/estrongs/android/pop/app/editor/PopNoteEditor;)Lcom/estrongs/android/pop/app/editor/b;
    //   173: aload 14
    //   175: getfield 123	com/estrongs/android/pop/app/editor/ag:b	J
    //   178: invokevirtual 126	com/estrongs/android/pop/app/editor/b:a	(J)V
    //   181: aload_0
    //   182: getfield 18	com/estrongs/android/pop/app/editor/ac:a	Lcom/estrongs/android/pop/app/editor/PopNoteEditor;
    //   185: aload 14
    //   187: getfield 128	com/estrongs/android/pop/app/editor/ag:a	I
    //   190: invokestatic 47	com/estrongs/android/pop/app/editor/PopNoteEditor:d	(Lcom/estrongs/android/pop/app/editor/PopNoteEditor;I)I
    //   193: pop
    //   194: dload_3
    //   195: dstore_1
    //   196: aload_0
    //   197: getfield 18	com/estrongs/android/pop/app/editor/ac:a	Lcom/estrongs/android/pop/app/editor/PopNoteEditor;
    //   200: invokestatic 76	com/estrongs/android/pop/app/editor/PopNoteEditor:y	(Lcom/estrongs/android/pop/app/editor/PopNoteEditor;)Lcom/estrongs/android/pop/app/editor/b;
    //   203: aload 13
    //   205: invokevirtual 132	com/estrongs/android/pop/app/editor/b:read	([C)I
    //   208: istore 5
    //   210: iload 5
    //   212: ifge +280 -> 492
    //   215: goto +437 -> 652
    //   218: aload_0
    //   219: getfield 18	com/estrongs/android/pop/app/editor/ac:a	Lcom/estrongs/android/pop/app/editor/PopNoteEditor;
    //   222: invokestatic 33	com/estrongs/android/pop/app/editor/PopNoteEditor:u	(Lcom/estrongs/android/pop/app/editor/PopNoteEditor;)Ljava/lang/StringBuilder;
    //   225: aload_0
    //   226: getfield 23	com/estrongs/android/pop/app/editor/ac:b	Ljava/lang/StringBuilder;
    //   229: invokevirtual 135	java/lang/StringBuilder:toString	()Ljava/lang/String;
    //   232: invokevirtual 139	java/lang/StringBuilder:append	(Ljava/lang/String;)Ljava/lang/StringBuilder;
    //   235: pop
    //   236: aload_0
    //   237: getfield 18	com/estrongs/android/pop/app/editor/ac:a	Lcom/estrongs/android/pop/app/editor/PopNoteEditor;
    //   240: invokestatic 143	com/estrongs/android/pop/app/editor/PopNoteEditor:w	(Lcom/estrongs/android/pop/app/editor/PopNoteEditor;)I
    //   243: istore 6
    //   245: iconst_0
    //   246: istore 5
    //   248: iload 5
    //   250: iconst_3
    //   251: iload 6
    //   253: isub
    //   254: if_icmpge +22 -> 276
    //   257: aload_0
    //   258: getfield 18	com/estrongs/android/pop/app/editor/ac:a	Lcom/estrongs/android/pop/app/editor/PopNoteEditor;
    //   261: invokestatic 76	com/estrongs/android/pop/app/editor/PopNoteEditor:y	(Lcom/estrongs/android/pop/app/editor/PopNoteEditor;)Lcom/estrongs/android/pop/app/editor/b;
    //   264: aload 13
    //   266: invokevirtual 132	com/estrongs/android/pop/app/editor/b:read	([C)I
    //   269: istore 7
    //   271: iload 7
    //   273: ifge +346 -> 619
    //   276: dload_1
    //   277: aload_0
    //   278: getfield 25	com/estrongs/android/pop/app/editor/ac:c	I
    //   281: i2d
    //   282: dsub
    //   283: aload_0
    //   284: getfield 18	com/estrongs/android/pop/app/editor/ac:a	Lcom/estrongs/android/pop/app/editor/PopNoteEditor;
    //   287: invokestatic 105	com/estrongs/android/pop/app/editor/PopNoteEditor:E	(Lcom/estrongs/android/pop/app/editor/PopNoteEditor;)J
    //   290: l2d
    //   291: dmul
    //   292: ldc2_w 144
    //   295: ddiv
    //   296: d2i
    //   297: istore 5
    //   299: new 147	com/estrongs/android/pop/app/editor/ae
    //   302: dup
    //   303: aload_0
    //   304: getfield 18	com/estrongs/android/pop/app/editor/ac:a	Lcom/estrongs/android/pop/app/editor/PopNoteEditor;
    //   307: aload_0
    //   308: getfield 18	com/estrongs/android/pop/app/editor/ac:a	Lcom/estrongs/android/pop/app/editor/PopNoteEditor;
    //   311: invokestatic 33	com/estrongs/android/pop/app/editor/PopNoteEditor:u	(Lcom/estrongs/android/pop/app/editor/PopNoteEditor;)Ljava/lang/StringBuilder;
    //   314: invokevirtual 135	java/lang/StringBuilder:toString	()Ljava/lang/String;
    //   317: iconst_0
    //   318: aload_0
    //   319: getfield 18	com/estrongs/android/pop/app/editor/ac:a	Lcom/estrongs/android/pop/app/editor/PopNoteEditor;
    //   322: aload_0
    //   323: getfield 18	com/estrongs/android/pop/app/editor/ac:a	Lcom/estrongs/android/pop/app/editor/PopNoteEditor;
    //   326: invokestatic 150	com/estrongs/android/pop/app/editor/PopNoteEditor:a	(Lcom/estrongs/android/pop/app/editor/PopNoteEditor;)Lcom/estrongs/android/pop/app/editor/ReaderTextView;
    //   329: aload_0
    //   330: getfield 18	com/estrongs/android/pop/app/editor/ac:a	Lcom/estrongs/android/pop/app/editor/PopNoteEditor;
    //   333: invokestatic 153	com/estrongs/android/pop/app/editor/PopNoteEditor:b	(Lcom/estrongs/android/pop/app/editor/PopNoteEditor;)Lcom/estrongs/android/pop/app/editor/ObservableScrollView;
    //   336: invokevirtual 158	com/estrongs/android/pop/app/editor/ObservableScrollView:getHeight	()I
    //   339: aload_0
    //   340: getfield 23	com/estrongs/android/pop/app/editor/ac:b	Ljava/lang/StringBuilder;
    //   343: invokevirtual 135	java/lang/StringBuilder:toString	()Ljava/lang/String;
    //   346: aload_0
    //   347: getfield 18	com/estrongs/android/pop/app/editor/ac:a	Lcom/estrongs/android/pop/app/editor/PopNoteEditor;
    //   350: invokestatic 95	com/estrongs/android/pop/app/editor/PopNoteEditor:m	(Lcom/estrongs/android/pop/app/editor/PopNoteEditor;)Ljava/lang/String;
    //   353: iload 5
    //   355: invokestatic 161	com/estrongs/android/pop/app/editor/PopNoteEditor:a	(Lcom/estrongs/android/pop/app/editor/PopNoteEditor;Lcom/estrongs/android/pop/app/editor/ReaderTextView;ILjava/lang/String;Ljava/lang/String;I)I
    //   358: invokespecial 164	com/estrongs/android/pop/app/editor/ae:<init>	(Lcom/estrongs/android/pop/app/editor/PopNoteEditor;Ljava/lang/String;II)V
    //   361: astore 13
    //   363: aload_0
    //   364: getfield 18	com/estrongs/android/pop/app/editor/ac:a	Lcom/estrongs/android/pop/app/editor/PopNoteEditor;
    //   367: invokestatic 168	com/estrongs/android/pop/app/editor/PopNoteEditor:A	(Lcom/estrongs/android/pop/app/editor/PopNoteEditor;)Landroid/os/Handler;
    //   370: iconst_0
    //   371: invokevirtual 174	android/os/Handler:obtainMessage	(I)Landroid/os/Message;
    //   374: astore 14
    //   376: aload 14
    //   378: aload 13
    //   380: putfield 180	android/os/Message:obj	Ljava/lang/Object;
    //   383: aload_0
    //   384: getfield 18	com/estrongs/android/pop/app/editor/ac:a	Lcom/estrongs/android/pop/app/editor/PopNoteEditor;
    //   387: invokestatic 168	com/estrongs/android/pop/app/editor/PopNoteEditor:A	(Lcom/estrongs/android/pop/app/editor/PopNoteEditor;)Landroid/os/Handler;
    //   390: aload 14
    //   392: invokevirtual 184	android/os/Handler:sendMessage	(Landroid/os/Message;)Z
    //   395: pop
    //   396: aload_0
    //   397: getfield 18	com/estrongs/android/pop/app/editor/ac:a	Lcom/estrongs/android/pop/app/editor/PopNoteEditor;
    //   400: invokestatic 187	com/estrongs/android/pop/app/editor/PopNoteEditor:B	(Lcom/estrongs/android/pop/app/editor/PopNoteEditor;)V
    //   403: aload 12
    //   405: monitorexit
    //   406: return
    //   407: astore 13
    //   409: aload 13
    //   411: invokevirtual 190	java/lang/Exception:printStackTrace	()V
    //   414: goto -346 -> 68
    //   417: astore 13
    //   419: aload_0
    //   420: getfield 18	com/estrongs/android/pop/app/editor/ac:a	Lcom/estrongs/android/pop/app/editor/PopNoteEditor;
    //   423: ldc -65
    //   425: invokestatic 196	com/estrongs/android/pop/utils/a:a	(Landroid/app/Activity;I)V
    //   428: aload_0
    //   429: getfield 18	com/estrongs/android/pop/app/editor/ac:a	Lcom/estrongs/android/pop/app/editor/PopNoteEditor;
    //   432: invokestatic 187	com/estrongs/android/pop/app/editor/PopNoteEditor:B	(Lcom/estrongs/android/pop/app/editor/PopNoteEditor;)V
    //   435: goto -32 -> 403
    //   438: astore 13
    //   440: aload 12
    //   442: monitorexit
    //   443: aload 13
    //   445: athrow
    //   446: astore 14
    //   448: aload 14
    //   450: invokevirtual 190	java/lang/Exception:printStackTrace	()V
    //   453: aload_0
    //   454: getfield 18	com/estrongs/android/pop/app/editor/ac:a	Lcom/estrongs/android/pop/app/editor/PopNoteEditor;
    //   457: invokestatic 76	com/estrongs/android/pop/app/editor/PopNoteEditor:y	(Lcom/estrongs/android/pop/app/editor/PopNoteEditor;)Lcom/estrongs/android/pop/app/editor/b;
    //   460: invokevirtual 81	com/estrongs/android/pop/app/editor/b:close	()V
    //   463: dload_3
    //   464: dstore_1
    //   465: goto -269 -> 196
    //   468: astore 14
    //   470: aload 14
    //   472: invokevirtual 197	java/io/IOException:printStackTrace	()V
    //   475: dload_3
    //   476: dstore_1
    //   477: goto -281 -> 196
    //   480: astore 13
    //   482: aload_0
    //   483: getfield 18	com/estrongs/android/pop/app/editor/ac:a	Lcom/estrongs/android/pop/app/editor/PopNoteEditor;
    //   486: invokestatic 187	com/estrongs/android/pop/app/editor/PopNoteEditor:B	(Lcom/estrongs/android/pop/app/editor/PopNoteEditor;)V
    //   489: aload 13
    //   491: athrow
    //   492: aload_0
    //   493: getfield 18	com/estrongs/android/pop/app/editor/ac:a	Lcom/estrongs/android/pop/app/editor/PopNoteEditor;
    //   496: invokestatic 76	com/estrongs/android/pop/app/editor/PopNoteEditor:y	(Lcom/estrongs/android/pop/app/editor/PopNoteEditor;)Lcom/estrongs/android/pop/app/editor/b;
    //   499: invokevirtual 200	com/estrongs/android/pop/app/editor/b:b	()J
    //   502: lstore 10
    //   504: aload_0
    //   505: getfield 18	com/estrongs/android/pop/app/editor/ac:a	Lcom/estrongs/android/pop/app/editor/PopNoteEditor;
    //   508: invokestatic 203	com/estrongs/android/pop/app/editor/PopNoteEditor:D	(Lcom/estrongs/android/pop/app/editor/PopNoteEditor;)I
    //   511: pop
    //   512: iload 5
    //   514: aload 13
    //   516: arraylength
    //   517: if_icmpne +22 -> 539
    //   520: aload_0
    //   521: getfield 18	com/estrongs/android/pop/app/editor/ac:a	Lcom/estrongs/android/pop/app/editor/PopNoteEditor;
    //   524: invokestatic 113	com/estrongs/android/pop/app/editor/PopNoteEditor:x	(Lcom/estrongs/android/pop/app/editor/PopNoteEditor;)Lcom/estrongs/android/pop/app/editor/af;
    //   527: aload_0
    //   528: getfield 18	com/estrongs/android/pop/app/editor/ac:a	Lcom/estrongs/android/pop/app/editor/PopNoteEditor;
    //   531: invokestatic 143	com/estrongs/android/pop/app/editor/PopNoteEditor:w	(Lcom/estrongs/android/pop/app/editor/PopNoteEditor;)I
    //   534: lload 10
    //   536: invokevirtual 206	com/estrongs/android/pop/app/editor/af:a	(IJ)V
    //   539: lload 10
    //   541: lload 8
    //   543: lcmp
    //   544: iflt +41 -> 585
    //   547: aload_0
    //   548: getfield 23	com/estrongs/android/pop/app/editor/ac:b	Ljava/lang/StringBuilder;
    //   551: aload 13
    //   553: iconst_0
    //   554: iload 5
    //   556: invokevirtual 209	java/lang/StringBuilder:append	([CII)Ljava/lang/StringBuilder;
    //   559: pop
    //   560: aload_0
    //   561: getfield 23	com/estrongs/android/pop/app/editor/ac:b	Ljava/lang/StringBuilder;
    //   564: invokevirtual 39	java/lang/StringBuilder:length	()I
    //   567: sipush 12288
    //   570: if_icmple +15 -> 585
    //   573: aload_0
    //   574: getfield 23	com/estrongs/android/pop/app/editor/ac:b	Ljava/lang/StringBuilder;
    //   577: iconst_0
    //   578: sipush 4096
    //   581: invokevirtual 43	java/lang/StringBuilder:delete	(II)Ljava/lang/StringBuilder;
    //   584: pop
    //   585: lload 10
    //   587: l2d
    //   588: aload_0
    //   589: getfield 18	com/estrongs/android/pop/app/editor/ac:a	Lcom/estrongs/android/pop/app/editor/PopNoteEditor;
    //   592: invokestatic 105	com/estrongs/android/pop/app/editor/PopNoteEditor:E	(Lcom/estrongs/android/pop/app/editor/PopNoteEditor;)J
    //   595: l2d
    //   596: ddiv
    //   597: ldc2_w 144
    //   600: dmul
    //   601: dstore_3
    //   602: dload_3
    //   603: dstore_1
    //   604: dload_3
    //   605: aload_0
    //   606: getfield 25	com/estrongs/android/pop/app/editor/ac:c	I
    //   609: i2d
    //   610: dcmpl
    //   611: iflt -415 -> 196
    //   614: dload_3
    //   615: dstore_1
    //   616: goto +36 -> 652
    //   619: aload_0
    //   620: getfield 18	com/estrongs/android/pop/app/editor/ac:a	Lcom/estrongs/android/pop/app/editor/PopNoteEditor;
    //   623: invokestatic 33	com/estrongs/android/pop/app/editor/PopNoteEditor:u	(Lcom/estrongs/android/pop/app/editor/PopNoteEditor;)Ljava/lang/StringBuilder;
    //   626: aload 13
    //   628: iconst_0
    //   629: iload 7
    //   631: invokevirtual 209	java/lang/StringBuilder:append	([CII)Ljava/lang/StringBuilder;
    //   634: pop
    //   635: aload_0
    //   636: getfield 18	com/estrongs/android/pop/app/editor/ac:a	Lcom/estrongs/android/pop/app/editor/PopNoteEditor;
    //   639: invokestatic 203	com/estrongs/android/pop/app/editor/PopNoteEditor:D	(Lcom/estrongs/android/pop/app/editor/PopNoteEditor;)I
    //   642: pop
    //   643: iload 5
    //   645: iconst_1
    //   646: iadd
    //   647: istore 5
    //   649: goto -401 -> 248
    //   652: iload 5
    //   654: ifge -436 -> 218
    //   657: ldc2_w 144
    //   660: dstore_1
    //   661: goto -443 -> 218
    // Local variable table:
    //   start	length	slot	name	signature
    //   0	664	0	this	ac
    //   160	501	1	d1	double
    //   121	494	3	d2	double
    //   208	445	5	i	int
    //   243	11	6	j	int
    //   269	361	7	k	int
    //   143	399	8	l1	long
    //   502	84	10	l2	long
    //   7	434	12	localObject1	Object
    //   51	328	13	localObject2	Object
    //   407	3	13	localException1	Exception
    //   417	1	13	localException2	Exception
    //   438	6	13	localObject3	Object
    //   480	147	13	arrayOfChar	char[]
    //   157	234	14	localObject4	Object
    //   446	3	14	localException3	Exception
    //   468	3	14	localIOException	java.io.IOException
    // Exception table:
    //   from	to	target	type
    //   58	68	407	java/lang/Exception
    //   12	44	417	java/lang/Exception
    //   44	53	417	java/lang/Exception
    //   68	120	417	java/lang/Exception
    //   122	159	417	java/lang/Exception
    //   196	210	417	java/lang/Exception
    //   218	245	417	java/lang/Exception
    //   257	271	417	java/lang/Exception
    //   276	396	417	java/lang/Exception
    //   409	414	417	java/lang/Exception
    //   448	453	417	java/lang/Exception
    //   453	463	417	java/lang/Exception
    //   470	475	417	java/lang/Exception
    //   492	539	417	java/lang/Exception
    //   547	585	417	java/lang/Exception
    //   585	602	417	java/lang/Exception
    //   604	614	417	java/lang/Exception
    //   619	643	417	java/lang/Exception
    //   396	403	438	finally
    //   403	406	438	finally
    //   428	435	438	finally
    //   440	443	438	finally
    //   482	492	438	finally
    //   166	194	446	java/lang/Exception
    //   453	463	468	java/io/IOException
    //   12	44	480	finally
    //   44	53	480	finally
    //   58	68	480	finally
    //   68	120	480	finally
    //   122	159	480	finally
    //   166	194	480	finally
    //   196	210	480	finally
    //   218	245	480	finally
    //   257	271	480	finally
    //   276	396	480	finally
    //   409	414	480	finally
    //   419	428	480	finally
    //   448	453	480	finally
    //   453	463	480	finally
    //   470	475	480	finally
    //   492	539	480	finally
    //   547	585	480	finally
    //   585	602	480	finally
    //   604	614	480	finally
    //   619	643	480	finally
  }
}

/* Location:
 * Qualified Name:     com.estrongs.android.pop.app.editor.ac
 * Java Class Version: 6 (50.0)
 * JD-Core Version:    0.7.1
 */