package com.estrongs.android.b.a;

class g
  extends Thread
{
  g(f paramf) {}
  
  /* Error */
  public void run()
  {
    // Byte code:
    //   0: new 17	com/estrongs/android/b/a/n
    //   3: dup
    //   4: invokespecial 18	com/estrongs/android/b/a/n:<init>	()V
    //   7: astore_1
    //   8: aload_1
    //   9: invokevirtual 21	com/estrongs/android/b/a/n:b	()V
    //   12: aload_0
    //   13: monitorenter
    //   14: aload_0
    //   15: getfield 10	com/estrongs/android/b/a/g:a	Lcom/estrongs/android/b/a/f;
    //   18: aload_1
    //   19: getfield 24	com/estrongs/android/b/a/n:a	Lcom/estrongs/android/b/a/h;
    //   22: putfield 27	com/estrongs/android/b/a/f:a	Lcom/estrongs/android/b/a/h;
    //   25: aload_0
    //   26: getfield 10	com/estrongs/android/b/a/g:a	Lcom/estrongs/android/b/a/f;
    //   29: aload_1
    //   30: getfield 30	com/estrongs/android/b/a/n:b	Lcom/estrongs/android/b/a/k;
    //   33: putfield 31	com/estrongs/android/b/a/f:b	Lcom/estrongs/android/b/a/k;
    //   36: aload_0
    //   37: monitorexit
    //   38: aload_1
    //   39: invokestatic 34	com/estrongs/android/b/a/n:a	(Lcom/estrongs/android/b/a/n;)Z
    //   42: ifeq +33 -> 75
    //   45: aload_1
    //   46: invokevirtual 21	com/estrongs/android/b/a/n:b	()V
    //   49: aload_0
    //   50: monitorenter
    //   51: aload_0
    //   52: getfield 10	com/estrongs/android/b/a/g:a	Lcom/estrongs/android/b/a/f;
    //   55: aload_1
    //   56: getfield 24	com/estrongs/android/b/a/n:a	Lcom/estrongs/android/b/a/h;
    //   59: putfield 27	com/estrongs/android/b/a/f:a	Lcom/estrongs/android/b/a/h;
    //   62: aload_0
    //   63: getfield 10	com/estrongs/android/b/a/g:a	Lcom/estrongs/android/b/a/f;
    //   66: aload_1
    //   67: getfield 30	com/estrongs/android/b/a/n:b	Lcom/estrongs/android/b/a/k;
    //   70: putfield 31	com/estrongs/android/b/a/f:b	Lcom/estrongs/android/b/a/k;
    //   73: aload_0
    //   74: monitorexit
    //   75: return
    //   76: astore_1
    //   77: aload_0
    //   78: monitorexit
    //   79: aload_1
    //   80: athrow
    //   81: astore_1
    //   82: aload_0
    //   83: monitorexit
    //   84: aload_1
    //   85: athrow
    // Local variable table:
    //   start	length	slot	name	signature
    //   0	86	0	this	g
    //   7	60	1	localn	n
    //   76	4	1	localObject1	Object
    //   81	4	1	localObject2	Object
    // Exception table:
    //   from	to	target	type
    //   14	38	76	finally
    //   77	79	76	finally
    //   51	75	81	finally
    //   82	84	81	finally
  }
}

/* Location:
 * Qualified Name:     com.estrongs.android.b.a.g
 * Java Class Version: 6 (50.0)
 * JD-Core Version:    0.7.1
 */