package com.estrongs.android.util;

import android.content.Context;
import android.content.DialogInterface.OnClickListener;
import java.io.File;

class av
  implements DialogInterface.OnClickListener
{
  av(at paramat, String paramString, File paramFile, Context paramContext) {}
  
  /* Error */
  public void onClick(android.content.DialogInterface paramDialogInterface, int paramInt)
  {
    // Byte code:
    //   0: aload_1
    //   1: invokeinterface 43 1 0
    //   6: iconst_0
    //   7: istore 4
    //   9: iconst_0
    //   10: istore 5
    //   12: iconst_0
    //   13: istore 6
    //   15: iconst_0
    //   16: istore_3
    //   17: new 45	java/io/File
    //   20: dup
    //   21: new 47	java/lang/StringBuilder
    //   24: dup
    //   25: invokespecial 48	java/lang/StringBuilder:<init>	()V
    //   28: aload_0
    //   29: getfield 20	com/estrongs/android/util/av:a	Ljava/lang/String;
    //   32: invokevirtual 52	java/lang/StringBuilder:append	(Ljava/lang/String;)Ljava/lang/StringBuilder;
    //   35: ldc 54
    //   37: invokevirtual 52	java/lang/StringBuilder:append	(Ljava/lang/String;)Ljava/lang/StringBuilder;
    //   40: invokevirtual 58	java/lang/StringBuilder:toString	()Ljava/lang/String;
    //   43: invokespecial 61	java/io/File:<init>	(Ljava/lang/String;)V
    //   46: astore 7
    //   48: iload 6
    //   50: istore_2
    //   51: aload_0
    //   52: getfield 22	com/estrongs/android/util/av:b	Ljava/io/File;
    //   55: aload 7
    //   57: invokevirtual 65	java/io/File:renameTo	(Ljava/io/File;)Z
    //   60: pop
    //   61: iload 6
    //   63: istore_2
    //   64: new 67	java/util/HashMap
    //   67: dup
    //   68: iconst_2
    //   69: invokespecial 70	java/util/HashMap:<init>	(I)V
    //   72: astore_1
    //   73: iload 6
    //   75: istore_2
    //   76: aload_1
    //   77: ldc 72
    //   79: iconst_1
    //   80: invokestatic 78	java/lang/String:valueOf	(I)Ljava/lang/String;
    //   83: invokevirtual 82	java/util/HashMap:put	(Ljava/lang/Object;Ljava/lang/Object;)Ljava/lang/Object;
    //   86: pop
    //   87: iload 6
    //   89: istore_2
    //   90: new 84	com/estrongs/io/a/a/b
    //   93: dup
    //   94: aconst_null
    //   95: invokespecial 87	com/estrongs/io/a/a/b:<init>	(Lcom/estrongs/io/archive/d;)V
    //   98: astore 8
    //   100: iload 6
    //   102: istore_2
    //   103: aload 8
    //   105: iconst_1
    //   106: invokevirtual 90	com/estrongs/io/a/a/b:c	(Z)V
    //   109: iload 6
    //   111: istore_2
    //   112: new 92	com/estrongs/io/archive/i
    //   115: dup
    //   116: aload_0
    //   117: getfield 20	com/estrongs/android/util/av:a	Ljava/lang/String;
    //   120: aload 8
    //   122: aload_1
    //   123: invokespecial 95	com/estrongs/io/archive/i:<init>	(Ljava/lang/String;Lcom/estrongs/io/a/d;Ljava/util/Map;)V
    //   126: astore_1
    //   127: iload 6
    //   129: istore_2
    //   130: new 97	java/util/ArrayList
    //   133: dup
    //   134: invokespecial 98	java/util/ArrayList:<init>	()V
    //   137: astore 8
    //   139: iload 6
    //   141: istore_2
    //   142: aload 8
    //   144: invokestatic 102	com/estrongs/android/util/at:a	()Ljava/lang/String;
    //   147: invokevirtual 106	java/util/ArrayList:add	(Ljava/lang/Object;)Z
    //   150: pop
    //   151: iload 6
    //   153: istore_2
    //   154: aload_1
    //   155: aload 8
    //   157: invokevirtual 109	com/estrongs/io/archive/i:a	(Ljava/util/List;)V
    //   160: iload 6
    //   162: istore_2
    //   163: aload_0
    //   164: getfield 18	com/estrongs/android/util/av:d	Lcom/estrongs/android/util/at;
    //   167: invokestatic 112	com/estrongs/android/util/at:a	(Lcom/estrongs/android/util/at;)V
    //   170: iload 6
    //   172: istore_2
    //   173: new 45	java/io/File
    //   176: dup
    //   177: invokestatic 102	com/estrongs/android/util/at:a	()Ljava/lang/String;
    //   180: invokespecial 61	java/io/File:<init>	(Ljava/lang/String;)V
    //   183: invokevirtual 116	java/io/File:delete	()Z
    //   186: pop
    //   187: aload_0
    //   188: getfield 20	com/estrongs/android/util/av:a	Ljava/lang/String;
    //   191: astore_1
    //   192: aload_1
    //   193: invokestatic 121	com/estrongs/android/util/bd:b	(Ljava/lang/CharSequence;)Z
    //   196: ifeq +39 -> 235
    //   199: aload_1
    //   200: ldc 123
    //   202: invokevirtual 127	java/lang/String:endsWith	(Ljava/lang/String;)Z
    //   205: ifeq +61 -> 266
    //   208: new 47	java/lang/StringBuilder
    //   211: dup
    //   212: invokespecial 48	java/lang/StringBuilder:<init>	()V
    //   215: aload_1
    //   216: invokevirtual 52	java/lang/StringBuilder:append	(Ljava/lang/String;)Ljava/lang/StringBuilder;
    //   219: ldc -127
    //   221: invokevirtual 52	java/lang/StringBuilder:append	(Ljava/lang/String;)Ljava/lang/StringBuilder;
    //   224: invokevirtual 58	java/lang/StringBuilder:toString	()Ljava/lang/String;
    //   227: astore_1
    //   228: invokestatic 134	com/estrongs/fs/a/b:a	()Lcom/estrongs/fs/a/b;
    //   231: aload_1
    //   232: invokevirtual 136	com/estrongs/fs/a/b:a	(Ljava/lang/String;)V
    //   235: aload_0
    //   236: getfield 24	com/estrongs/android/util/av:c	Landroid/content/Context;
    //   239: invokestatic 141	com/estrongs/android/pop/ad:a	(Landroid/content/Context;)Lcom/estrongs/android/pop/ad;
    //   242: aload_0
    //   243: getfield 20	com/estrongs/android/util/av:a	Ljava/lang/String;
    //   246: invokevirtual 144	com/estrongs/android/pop/ad:J	(Ljava/lang/String;)V
    //   249: aload_0
    //   250: getfield 24	com/estrongs/android/util/av:c	Landroid/content/Context;
    //   253: ldc -111
    //   255: iconst_1
    //   256: invokestatic 150	com/estrongs/android/ui/view/ag:a	(Landroid/content/Context;II)V
    //   259: aload 7
    //   261: invokevirtual 116	java/io/File:delete	()Z
    //   264: pop
    //   265: return
    //   266: new 47	java/lang/StringBuilder
    //   269: dup
    //   270: invokespecial 48	java/lang/StringBuilder:<init>	()V
    //   273: aload_1
    //   274: invokevirtual 52	java/lang/StringBuilder:append	(Ljava/lang/String;)Ljava/lang/StringBuilder;
    //   277: ldc -104
    //   279: invokevirtual 52	java/lang/StringBuilder:append	(Ljava/lang/String;)Ljava/lang/StringBuilder;
    //   282: invokevirtual 58	java/lang/StringBuilder:toString	()Ljava/lang/String;
    //   285: astore_1
    //   286: goto -58 -> 228
    //   289: astore_1
    //   290: iload_3
    //   291: istore_2
    //   292: aload_1
    //   293: invokevirtual 155	java/io/IOException:printStackTrace	()V
    //   296: iload_3
    //   297: ifne +143 -> 440
    //   300: aload 7
    //   302: aload_0
    //   303: getfield 22	com/estrongs/android/util/av:b	Ljava/io/File;
    //   306: invokevirtual 65	java/io/File:renameTo	(Ljava/io/File;)Z
    //   309: pop
    //   310: aload_0
    //   311: getfield 24	com/estrongs/android/util/av:c	Landroid/content/Context;
    //   314: ldc -100
    //   316: iconst_1
    //   317: invokestatic 150	com/estrongs/android/ui/view/ag:a	(Landroid/content/Context;II)V
    //   320: return
    //   321: astore_1
    //   322: iload 4
    //   324: istore_3
    //   325: iload_3
    //   326: istore_2
    //   327: aload_1
    //   328: invokevirtual 157	com/estrongs/fs/FileSystemException:printStackTrace	()V
    //   331: iload_3
    //   332: ifne +108 -> 440
    //   335: aload 7
    //   337: aload_0
    //   338: getfield 22	com/estrongs/android/util/av:b	Ljava/io/File;
    //   341: invokevirtual 65	java/io/File:renameTo	(Ljava/io/File;)Z
    //   344: pop
    //   345: aload_0
    //   346: getfield 24	com/estrongs/android/util/av:c	Landroid/content/Context;
    //   349: ldc -100
    //   351: iconst_1
    //   352: invokestatic 150	com/estrongs/android/ui/view/ag:a	(Landroid/content/Context;II)V
    //   355: return
    //   356: astore_1
    //   357: iload 5
    //   359: istore_2
    //   360: iload_2
    //   361: ifne +79 -> 440
    //   364: aload 7
    //   366: aload_0
    //   367: getfield 22	com/estrongs/android/util/av:b	Ljava/io/File;
    //   370: invokevirtual 65	java/io/File:renameTo	(Ljava/io/File;)Z
    //   373: pop
    //   374: aload_0
    //   375: getfield 24	com/estrongs/android/util/av:c	Landroid/content/Context;
    //   378: ldc -100
    //   380: iconst_1
    //   381: invokestatic 150	com/estrongs/android/ui/view/ag:a	(Landroid/content/Context;II)V
    //   384: return
    //   385: astore_1
    //   386: iload_2
    //   387: ifne +23 -> 410
    //   390: aload 7
    //   392: aload_0
    //   393: getfield 22	com/estrongs/android/util/av:b	Ljava/io/File;
    //   396: invokevirtual 65	java/io/File:renameTo	(Ljava/io/File;)Z
    //   399: pop
    //   400: aload_0
    //   401: getfield 24	com/estrongs/android/util/av:c	Landroid/content/Context;
    //   404: ldc -100
    //   406: iconst_1
    //   407: invokestatic 150	com/estrongs/android/ui/view/ag:a	(Landroid/content/Context;II)V
    //   410: aload_1
    //   411: athrow
    //   412: astore_1
    //   413: iconst_1
    //   414: istore_2
    //   415: goto -29 -> 386
    //   418: astore_1
    //   419: iconst_1
    //   420: istore_2
    //   421: goto -61 -> 360
    //   424: astore_1
    //   425: iconst_1
    //   426: istore_3
    //   427: goto -102 -> 325
    //   430: astore_1
    //   431: iconst_1
    //   432: istore_3
    //   433: goto -143 -> 290
    //   436: astore_1
    //   437: goto -250 -> 187
    //   440: return
    // Local variable table:
    //   start	length	slot	name	signature
    //   0	441	0	this	av
    //   0	441	1	paramDialogInterface	android.content.DialogInterface
    //   0	441	2	paramInt	int
    //   16	417	3	i	int
    //   7	316	4	j	int
    //   10	348	5	k	int
    //   13	158	6	m	int
    //   46	345	7	localFile	File
    //   98	58	8	localObject	Object
    // Exception table:
    //   from	to	target	type
    //   51	61	289	java/io/IOException
    //   64	73	289	java/io/IOException
    //   76	87	289	java/io/IOException
    //   90	100	289	java/io/IOException
    //   103	109	289	java/io/IOException
    //   112	127	289	java/io/IOException
    //   130	139	289	java/io/IOException
    //   142	151	289	java/io/IOException
    //   154	160	289	java/io/IOException
    //   163	170	289	java/io/IOException
    //   173	187	289	java/io/IOException
    //   51	61	321	com/estrongs/fs/FileSystemException
    //   64	73	321	com/estrongs/fs/FileSystemException
    //   76	87	321	com/estrongs/fs/FileSystemException
    //   90	100	321	com/estrongs/fs/FileSystemException
    //   103	109	321	com/estrongs/fs/FileSystemException
    //   112	127	321	com/estrongs/fs/FileSystemException
    //   130	139	321	com/estrongs/fs/FileSystemException
    //   142	151	321	com/estrongs/fs/FileSystemException
    //   154	160	321	com/estrongs/fs/FileSystemException
    //   163	170	321	com/estrongs/fs/FileSystemException
    //   173	187	321	com/estrongs/fs/FileSystemException
    //   51	61	356	java/lang/NullPointerException
    //   64	73	356	java/lang/NullPointerException
    //   76	87	356	java/lang/NullPointerException
    //   90	100	356	java/lang/NullPointerException
    //   103	109	356	java/lang/NullPointerException
    //   112	127	356	java/lang/NullPointerException
    //   130	139	356	java/lang/NullPointerException
    //   142	151	356	java/lang/NullPointerException
    //   154	160	356	java/lang/NullPointerException
    //   163	170	356	java/lang/NullPointerException
    //   173	187	356	java/lang/NullPointerException
    //   51	61	385	finally
    //   64	73	385	finally
    //   76	87	385	finally
    //   90	100	385	finally
    //   103	109	385	finally
    //   112	127	385	finally
    //   130	139	385	finally
    //   142	151	385	finally
    //   154	160	385	finally
    //   163	170	385	finally
    //   173	187	385	finally
    //   292	296	385	finally
    //   327	331	385	finally
    //   187	228	412	finally
    //   228	235	412	finally
    //   235	265	412	finally
    //   266	286	412	finally
    //   187	228	418	java/lang/NullPointerException
    //   228	235	418	java/lang/NullPointerException
    //   235	265	418	java/lang/NullPointerException
    //   266	286	418	java/lang/NullPointerException
    //   187	228	424	com/estrongs/fs/FileSystemException
    //   228	235	424	com/estrongs/fs/FileSystemException
    //   235	265	424	com/estrongs/fs/FileSystemException
    //   266	286	424	com/estrongs/fs/FileSystemException
    //   187	228	430	java/io/IOException
    //   228	235	430	java/io/IOException
    //   235	265	430	java/io/IOException
    //   266	286	430	java/io/IOException
    //   163	170	436	java/lang/Exception
    //   173	187	436	java/lang/Exception
  }
}

/* Location:
 * Qualified Name:     com.estrongs.android.util.av
 * Java Class Version: 6 (50.0)
 * JD-Core Version:    0.7.1
 */