package com.flurry.sdk;

import android.graphics.Bitmap;
import android.widget.ImageView;
import java.lang.ref.WeakReference;

public class eb$a
  implements Runnable
{
  private String a;
  private WeakReference<ImageView> b;
  private Bitmap c;
  
  public eb$a(String paramString, ImageView paramImageView)
  {
    a = paramString;
    b = new WeakReference(paramImageView);
  }
  
  /* Error */
  public void run()
  {
    // Byte code:
    //   0: aconst_null
    //   1: astore_3
    //   2: aconst_null
    //   3: astore_2
    //   4: aload_0
    //   5: getfield 27	com/flurry/sdk/eb$a:b	Ljava/lang/ref/WeakReference;
    //   8: invokevirtual 38	java/lang/ref/WeakReference:get	()Ljava/lang/Object;
    //   11: checkcast 40	android/widget/ImageView
    //   14: astore 5
    //   16: aload 5
    //   18: ifnull +10 -> 28
    //   21: aload_0
    //   22: getfield 20	com/flurry/sdk/eb$a:a	Ljava/lang/String;
    //   25: ifnonnull +4 -> 29
    //   28: return
    //   29: aload_0
    //   30: getfield 20	com/flurry/sdk/eb$a:a	Ljava/lang/String;
    //   33: ldc 42
    //   35: invokevirtual 48	java/lang/String:startsWith	(Ljava/lang/String;)Z
    //   38: ifne +64 -> 102
    //   41: aload_0
    //   42: getfield 20	com/flurry/sdk/eb$a:a	Ljava/lang/String;
    //   45: ldc 50
    //   47: invokevirtual 48	java/lang/String:startsWith	(Ljava/lang/String;)Z
    //   50: ifne +52 -> 102
    //   53: new 52	java/io/File
    //   56: dup
    //   57: aload_0
    //   58: getfield 20	com/flurry/sdk/eb$a:a	Ljava/lang/String;
    //   61: invokespecial 55	java/io/File:<init>	(Ljava/lang/String;)V
    //   64: invokevirtual 59	java/io/File:exists	()Z
    //   67: ifeq -39 -> 28
    //   70: aload_0
    //   71: aload_0
    //   72: getfield 20	com/flurry/sdk/eb$a:a	Ljava/lang/String;
    //   75: invokestatic 65	android/graphics/BitmapFactory:decodeFile	(Ljava/lang/String;)Landroid/graphics/Bitmap;
    //   78: putfield 31	com/flurry/sdk/eb$a:c	Landroid/graphics/Bitmap;
    //   81: invokestatic 70	com/flurry/sdk/js:a	()Lcom/flurry/sdk/js;
    //   84: invokevirtual 74	com/flurry/sdk/js:f	()Landroid/os/Handler;
    //   87: new 76	com/flurry/sdk/eb$a$1
    //   90: dup
    //   91: aload_0
    //   92: aload 5
    //   94: invokespecial 79	com/flurry/sdk/eb$a$1:<init>	(Lcom/flurry/sdk/eb$a;Landroid/widget/ImageView;)V
    //   97: invokevirtual 85	android/os/Handler:post	(Ljava/lang/Runnable;)Z
    //   100: pop
    //   101: return
    //   102: new 87	java/net/URL
    //   105: dup
    //   106: aload_0
    //   107: getfield 20	com/flurry/sdk/eb$a:a	Ljava/lang/String;
    //   110: invokespecial 88	java/net/URL:<init>	(Ljava/lang/String;)V
    //   113: invokevirtual 92	java/net/URL:openConnection	()Ljava/net/URLConnection;
    //   116: checkcast 94	java/net/HttpURLConnection
    //   119: astore 4
    //   121: aload_3
    //   122: astore_2
    //   123: aload 4
    //   125: sipush 10000
    //   128: invokevirtual 98	java/net/HttpURLConnection:setConnectTimeout	(I)V
    //   131: aload_3
    //   132: astore_2
    //   133: aload 4
    //   135: sipush 30000
    //   138: invokevirtual 101	java/net/HttpURLConnection:setReadTimeout	(I)V
    //   141: aload_3
    //   142: astore_2
    //   143: aload 4
    //   145: iconst_1
    //   146: invokevirtual 105	java/net/HttpURLConnection:setInstanceFollowRedirects	(Z)V
    //   149: aload_3
    //   150: astore_2
    //   151: iconst_1
    //   152: invokestatic 108	java/net/HttpURLConnection:setFollowRedirects	(Z)V
    //   155: aload_3
    //   156: astore_2
    //   157: aload 4
    //   159: invokevirtual 112	java/net/HttpURLConnection:getInputStream	()Ljava/io/InputStream;
    //   162: astore_3
    //   163: aload_3
    //   164: astore_2
    //   165: aload 4
    //   167: invokevirtual 116	java/net/HttpURLConnection:getResponseCode	()I
    //   170: istore_1
    //   171: iload_1
    //   172: sipush 200
    //   175: if_icmpne +65 -> 240
    //   178: aload_3
    //   179: astore_2
    //   180: aload_0
    //   181: aload_3
    //   182: aconst_null
    //   183: aconst_null
    //   184: invokestatic 120	android/graphics/BitmapFactory:decodeStream	(Ljava/io/InputStream;Landroid/graphics/Rect;Landroid/graphics/BitmapFactory$Options;)Landroid/graphics/Bitmap;
    //   187: putfield 31	com/flurry/sdk/eb$a:c	Landroid/graphics/Bitmap;
    //   190: aload_3
    //   191: astore_2
    //   192: aload_0
    //   193: getfield 31	com/flurry/sdk/eb$a:c	Landroid/graphics/Bitmap;
    //   196: ifnull +25 -> 221
    //   199: aload_3
    //   200: astore_2
    //   201: invokestatic 70	com/flurry/sdk/js:a	()Lcom/flurry/sdk/js;
    //   204: invokevirtual 74	com/flurry/sdk/js:f	()Landroid/os/Handler;
    //   207: new 122	com/flurry/sdk/eb$a$2
    //   210: dup
    //   211: aload_0
    //   212: aload 5
    //   214: invokespecial 123	com/flurry/sdk/eb$a$2:<init>	(Lcom/flurry/sdk/eb$a;Landroid/widget/ImageView;)V
    //   217: invokevirtual 85	android/os/Handler:post	(Ljava/lang/Runnable;)Z
    //   220: pop
    //   221: aload_3
    //   222: ifnull +7 -> 229
    //   225: aload_3
    //   226: invokevirtual 128	java/io/InputStream:close	()V
    //   229: aload 4
    //   231: ifnull -203 -> 28
    //   234: aload 4
    //   236: invokevirtual 131	java/net/HttpURLConnection:disconnect	()V
    //   239: return
    //   240: iload_1
    //   241: sipush 301
    //   244: if_icmpne -23 -> 221
    //   247: aload_3
    //   248: astore_2
    //   249: invokestatic 70	com/flurry/sdk/js:a	()Lcom/flurry/sdk/js;
    //   252: invokevirtual 134	com/flurry/sdk/js:g	()Landroid/os/Handler;
    //   255: new 2	com/flurry/sdk/eb$a
    //   258: dup
    //   259: aload 4
    //   261: ldc -120
    //   263: invokevirtual 140	java/net/HttpURLConnection:getHeaderField	(Ljava/lang/String;)Ljava/lang/String;
    //   266: aload 5
    //   268: invokespecial 142	com/flurry/sdk/eb$a:<init>	(Ljava/lang/String;Landroid/widget/ImageView;)V
    //   271: invokevirtual 85	android/os/Handler:post	(Ljava/lang/Runnable;)Z
    //   274: pop
    //   275: goto -54 -> 221
    //   278: astore_2
    //   279: aload_3
    //   280: astore_2
    //   281: aload_2
    //   282: ifnull +7 -> 289
    //   285: aload_2
    //   286: invokevirtual 128	java/io/InputStream:close	()V
    //   289: aload 4
    //   291: ifnull -263 -> 28
    //   294: aload 4
    //   296: invokevirtual 131	java/net/HttpURLConnection:disconnect	()V
    //   299: return
    //   300: astore_3
    //   301: aconst_null
    //   302: astore 4
    //   304: aload_2
    //   305: ifnull +7 -> 312
    //   308: aload_2
    //   309: invokevirtual 128	java/io/InputStream:close	()V
    //   312: aload 4
    //   314: ifnull +8 -> 322
    //   317: aload 4
    //   319: invokevirtual 131	java/net/HttpURLConnection:disconnect	()V
    //   322: aload_3
    //   323: athrow
    //   324: astore_2
    //   325: goto -96 -> 229
    //   328: astore_2
    //   329: goto -40 -> 289
    //   332: astore_2
    //   333: goto -21 -> 312
    //   336: astore_3
    //   337: goto -33 -> 304
    //   340: astore_2
    //   341: aconst_null
    //   342: astore_2
    //   343: aconst_null
    //   344: astore 4
    //   346: goto -65 -> 281
    //   349: astore_2
    //   350: aconst_null
    //   351: astore_2
    //   352: goto -71 -> 281
    // Local variable table:
    //   start	length	slot	name	signature
    //   0	355	0	this	a
    //   170	75	1	i	int
    //   3	246	2	localInputStream1	java.io.InputStream
    //   278	1	2	localException1	Exception
    //   280	29	2	localInputStream2	java.io.InputStream
    //   324	1	2	localException2	Exception
    //   328	1	2	localException3	Exception
    //   332	1	2	localException4	Exception
    //   340	1	2	localException5	Exception
    //   342	1	2	localObject1	Object
    //   349	1	2	localException6	Exception
    //   351	1	2	localObject2	Object
    //   1	279	3	localInputStream3	java.io.InputStream
    //   300	23	3	localObject3	Object
    //   336	1	3	localObject4	Object
    //   119	226	4	localHttpURLConnection	java.net.HttpURLConnection
    //   14	253	5	localImageView	ImageView
    // Exception table:
    //   from	to	target	type
    //   165	171	278	java/lang/Exception
    //   180	190	278	java/lang/Exception
    //   192	199	278	java/lang/Exception
    //   201	221	278	java/lang/Exception
    //   249	275	278	java/lang/Exception
    //   102	121	300	finally
    //   225	229	324	java/lang/Exception
    //   285	289	328	java/lang/Exception
    //   308	312	332	java/lang/Exception
    //   123	131	336	finally
    //   133	141	336	finally
    //   143	149	336	finally
    //   151	155	336	finally
    //   157	163	336	finally
    //   165	171	336	finally
    //   180	190	336	finally
    //   192	199	336	finally
    //   201	221	336	finally
    //   249	275	336	finally
    //   102	121	340	java/lang/Exception
    //   123	131	349	java/lang/Exception
    //   133	141	349	java/lang/Exception
    //   143	149	349	java/lang/Exception
    //   151	155	349	java/lang/Exception
    //   157	163	349	java/lang/Exception
  }
}

/* Location:
 * Qualified Name:     com.flurry.sdk.eb.a
 * Java Class Version: 6 (50.0)
 * JD-Core Version:    0.7.1
 */