package com.flurry.sdk;

import android.graphics.Bitmap;
import android.graphics.BitmapFactory;
import android.util.Base64;
import java.io.ByteArrayInputStream;
import java.io.File;
import java.io.InputStream;

public class hc
{
  private static final String a = hc.class.getSimpleName();
  private static final int b = lr.b(25);
  private static final int c = lr.b(25);
  private static final int d = lr.b(50);
  private static final int e = lr.b(50);
  private static final int f = lr.b(25);
  private static final int g = lr.b(25);
  private boolean h;
  private Bitmap i;
  private Bitmap j;
  private Bitmap k;
  private Bitmap l;
  private Bitmap m;
  private Bitmap n;
  private Bitmap o;
  private Bitmap p;
  private Bitmap q;
  private Bitmap r;
  private Bitmap s;
  private Bitmap t;
  private Bitmap u;
  private Bitmap v;
  private Bitmap w;
  private Bitmap x;
  private Bitmap y;
  private Bitmap z;
  
  public static Bitmap a()
  {
    return Bitmap.createScaledBitmap(a("iVBORw0KGgoAAAANSUhEUgAAACAAAAAfCAYAAACGVs+MAAAAAXNSR0IArs4c6QAAASdJREFUSA3FV0sOAiEMde0hvIMHGdeeyAt4SFcmrk2M9pE0wzQw9APYpA6U9r0HM8H0cFjtRsPzOh02Asci0e8U+JI/yUeKADY43uQX8mQn+kUQAkaKYHLmeRDfkTyZXOx9Eip8VRIrNjxNuKZkhQgXnquoICaEEyomMdH6tB8viLeucIj2nXQlZ0VaUG0e45qeLfDWuomsllwjqcVrOKG4JHsRGpyv1943aFGsFDGVnBVdafDJdo4xYlPsrycgyad+A5KcP7havOvraJG01kNitODaPJMYK6g1f1eMF8xbtxETBQnVh4qzbbhwXEUZqRya8EzJkmlnrsJVJe2QtJZK+GiIkqE7QZcy+l8tF4FWcGPo09Cv8fW6Wew4gQg0wUVbKIqEqfYDRCrjHcTBVnEAAAAASUVORK5CYII="), f, g, true);
  }
  
  private static Bitmap a(InputStream paramInputStream, boolean paramBoolean)
  {
    if (paramInputStream == null) {
      return null;
    }
    paramInputStream = BitmapFactory.decodeStream(paramInputStream);
    if (paramInputStream != null) {
      if (!paramBoolean) {
        break label30;
      }
    }
    label30:
    for (int i1 = 320;; i1 = 160)
    {
      paramInputStream.setDensity(i1);
      return paramInputStream;
    }
  }
  
  private static Bitmap a(String paramString)
  {
    if (paramString == null) {}
    do
    {
      return null;
      paramString = Base64.decode(paramString, 0);
    } while (paramString == null);
    return a(new ByteArrayInputStream(paramString), false);
  }
  
  private da a(String paramString1, String paramString2)
  {
    paramString2 = i.a().l().b(paramString2);
    da localda = new da();
    a = paramString1;
    b = db.b;
    c = ("file://" + paramString2.getAbsolutePath());
    return localda;
  }
  
  private void a(InputStream paramInputStream, String paramString)
  {
    int i1 = -1;
    if (paramInputStream == null) {
      return;
    }
    if (y())
    {
      switch (paramString.hashCode())
      {
      }
      for (;;)
      {
        switch (i1)
        {
        default: 
          return;
        case 0: 
          i = a(paramInputStream, true);
          return;
          if (paramString.equals("android/closeX_retina.png"))
          {
            i1 = 0;
            continue;
            if (paramString.equals("android/pause_button_retina.png"))
            {
              i1 = 1;
              continue;
              if (paramString.equals("android/play_button_retina.png"))
              {
                i1 = 2;
                continue;
                if (paramString.equals("android/more_info_retina.png"))
                {
                  i1 = 3;
                  continue;
                  if (paramString.equals("android/collapse3x.png"))
                  {
                    i1 = 4;
                    continue;
                    if (paramString.equals("android/play_with_circle3x.png"))
                    {
                      i1 = 5;
                      continue;
                      if (paramString.equals("android/play_no_circle3x.png"))
                      {
                        i1 = 6;
                        continue;
                        if (paramString.equals("android/replay3x.png"))
                        {
                          i1 = 7;
                          continue;
                          if (paramString.equals("android/mute3x.png"))
                          {
                            i1 = 8;
                            continue;
                            if (paramString.equals("android/pause3x.png"))
                            {
                              i1 = 9;
                              continue;
                              if (paramString.equals("android/umute3x.png"))
                              {
                                i1 = 10;
                                continue;
                                if (paramString.equals("android/tumblr_logo.png"))
                                {
                                  i1 = 11;
                                  continue;
                                  if (paramString.equals("android/down_arrow.png"))
                                  {
                                    i1 = 12;
                                    continue;
                                    if (paramString.equals("android/down_arrow2x.png"))
                                    {
                                      i1 = 13;
                                      continue;
                                      if (paramString.equals("android/down_arrow3x.png"))
                                      {
                                        i1 = 14;
                                        continue;
                                        if (paramString.equals("android/up_arrow.png"))
                                        {
                                          i1 = 15;
                                          continue;
                                          if (paramString.equals("android/up_arrow2x.png"))
                                          {
                                            i1 = 16;
                                            continue;
                                            if (paramString.equals("android/up_arrow3x.png")) {
                                              i1 = 17;
                                            }
                                          }
                                        }
                                      }
                                    }
                                  }
                                }
                              }
                            }
                          }
                        }
                      }
                    }
                  }
                }
              }
            }
          }
          break;
        }
      }
      j = a(paramInputStream, true);
      return;
      k = a(paramInputStream, true);
      return;
      l = a(paramInputStream, true);
      return;
      o = a(paramInputStream, true);
      return;
      m = a(paramInputStream, true);
      return;
      p = a(paramInputStream, true);
      return;
      n = a(paramInputStream, true);
      return;
      r = a(paramInputStream, true);
      return;
      q = a(paramInputStream, true);
      return;
      s = a(paramInputStream, true);
      return;
      t = a(paramInputStream, true);
      return;
      u = a(paramInputStream, true);
      return;
      v = a(paramInputStream, true);
      return;
      w = a(paramInputStream, true);
      return;
      x = a(paramInputStream, true);
      return;
      y = a(paramInputStream, true);
      return;
      z = a(paramInputStream, true);
      return;
    }
    switch (paramString.hashCode())
    {
    }
    for (;;)
    {
      switch (i1)
      {
      default: 
        return;
      case 0: 
        i = a(paramInputStream, false);
        return;
        if (paramString.equals("android/closeX.png"))
        {
          i1 = 0;
          continue;
          if (paramString.equals("android/pause_button.png"))
          {
            i1 = 1;
            continue;
            if (paramString.equals("android/play_button.png"))
            {
              i1 = 2;
              continue;
              if (paramString.equals("android/more_info.png"))
              {
                i1 = 3;
                continue;
                if (paramString.equals("android/collapse.png"))
                {
                  i1 = 4;
                  continue;
                  if (paramString.equals("android/play_with_circle.png"))
                  {
                    i1 = 5;
                    continue;
                    if (paramString.equals("android/play_no_circle.png"))
                    {
                      i1 = 6;
                      continue;
                      if (paramString.equals("android/replay.png"))
                      {
                        i1 = 7;
                        continue;
                        if (paramString.equals("android/mute.png"))
                        {
                          i1 = 8;
                          continue;
                          if (paramString.equals("android/pause.png"))
                          {
                            i1 = 9;
                            continue;
                            if (paramString.equals("android/umute.png"))
                            {
                              i1 = 10;
                              continue;
                              if (paramString.equals("android/tumblr_logo.png"))
                              {
                                i1 = 11;
                                continue;
                                if (paramString.equals("android/down_arrow.png"))
                                {
                                  i1 = 12;
                                  continue;
                                  if (paramString.equals("android/down_arrow2x.png"))
                                  {
                                    i1 = 13;
                                    continue;
                                    if (paramString.equals("android/down_arrow3x.png"))
                                    {
                                      i1 = 14;
                                      continue;
                                      if (paramString.equals("android/up_arrow.png"))
                                      {
                                        i1 = 15;
                                        continue;
                                        if (paramString.equals("android/up_arrow2x.png"))
                                        {
                                          i1 = 16;
                                          continue;
                                          if (paramString.equals("android/up_arrow3x.png")) {
                                            i1 = 17;
                                          }
                                        }
                                      }
                                    }
                                  }
                                }
                              }
                            }
                          }
                        }
                      }
                    }
                  }
                }
              }
            }
          }
        }
        break;
      }
    }
    j = a(paramInputStream, false);
    return;
    k = a(paramInputStream, false);
    return;
    l = a(paramInputStream, false);
    return;
    o = a(paramInputStream, false);
    return;
    m = a(paramInputStream, true);
    return;
    p = a(paramInputStream, true);
    return;
    n = a(paramInputStream, false);
    return;
    r = a(paramInputStream, false);
    return;
    q = a(paramInputStream, false);
    return;
    s = a(paramInputStream, false);
    return;
    t = a(paramInputStream, false);
    return;
    u = a(paramInputStream, false);
    return;
    v = a(paramInputStream, false);
    return;
    w = a(paramInputStream, false);
    return;
    x = a(paramInputStream, false);
    return;
    y = a(paramInputStream, false);
    return;
    z = a(paramInputStream, false);
  }
  
  public static Bitmap b()
  {
    return Bitmap.createScaledBitmap(a("iVBORw0KGgoAAAANSUhEUgAAACIAAAAdCAYAAADPa766AAAAAXNSR0IArs4c6QAAAJhJREFUSA3tl1EKgDAMQ/ehBxK8/03EE4hH0EYIjMFAxlj2kUIoDArPrKs0pfbYonRvL+9TCYgrdIdkMIR4AgI6QktoaJQQcAVnQ8MQtNtO2Ak6wOyeoBMY1RhQnJiSYQUI/DcIochpDYBTDIEP/2IKR3IYeY8QZoqnaxg6UMu+JjtTc6B27p7564xkryEcr0m66eUw3dbNF6VbwqHE35rGAAAAAElFTkSuQmCC"), f, g, true);
  }
  
  public static Bitmap c()
  {
    return Bitmap.createScaledBitmap(a("iVBORw0KGgoAAAANSUhEUgAAACIAAAAdCAYAAADPa766AAAAAXNSR0IArs4c6QAAAKZJREFUSA3tl0sKgDAMBQX1DJ5D8P43EbduxCPoe2BKAt1UStpFAqEfMB3G0tJxqBcbSi3Is17J8kqEuJEXci3/vM4XE8rsyOfLpjC0QICAgQQTYcboUIMwo2SYbpgxOtSgezO8GlLIadii5f2UYFoA6DUPwMzUoie9+8YIYTwit2HTb/EA4Bo5CM65RkCI7jARJsSAtLEnxERX75ouXnpihjC/j+0XyA7Dch+5ivoAAAAASUVORK5CYII="), f, g, true);
  }
  
  public static Bitmap d()
  {
    return a("iVBORw0KGgoAAAANSUhEUgAAAFgAAAB0CAYAAAAB+/V5AAAAAXNSR0IArs4c6QAACx9JREFUeAHtXXtsFVUa78uWVtcHLChoaqkKcTFiIiqyLgmGZfGxPhKtxu4qa1CzEeMfkvpCYzYhm91kX9m14rpFg5BdYGN8JBJF44uHsImpWKSCLNRWRFoVHy193eLvp/c2c2bm3pk55zv3Tq/zJV9mzpnz/c73/e6Zb86cmU5LSyzI0aNHywC7CHozdAa0GloIeb20tPTKQnSc6bMisyO1BbnjgPUSdK4UpgHOZANbEVOONGlZAcA4kCsdlxaeKMEYvRPhxa+0PClSI+kUcRV4Kjfk6lnYb9XEWAy7szRtrZhJE3yhgJdLcGH6WAcHZ9B02MWKYNEUgeDO0SHGYfO5LrkOjFjtxo3gtlixI+CMGME4PWvhz/GGPr1naB87czGCEdlsgeiSEZyDxCtyHAt7aEvYhmOlncgsAumBZ8JlhkF34QK3wxDDz3yCX6Wr7gjKfa46kaIIwfCE0zPeZJjIiybGfrbDw8Ock8/xO+aq+xDlXa46kaJUDr5JwBtxggV8MoYwJhjp4UR48RtDT76B/SuGGLE0NyYYUd0BPc4wuqeQf3sNMWJpbkQwRm8VorrLMLKjsP+7IUZszY0IRlQPQ081jG4DRu9uQ4zYmmsTjNF7LqJqEojsDwIYsYXQIhjkcnrXAjWd5q3G6H0ztuwIOKZFMPr9F3SWYf+HYb/UECP25pEJxujlKX2LQGT3Y/R+KoATa4hIBIPcBxCNRN5dC5zHY82MkHOhciiIrUF/T0Al7ti2AWcRRi+nZ0UvgQSD3DPAwn+h5wmw8REwrga5/QJYfhClzsqysrLA+JztbexndQDE8u7sPug9UL7rYCofAODyfOZdEDxjZGSkGf0O53I+xNmUgv1CtNubC8fvmIdgEFuJho3Q5VCpFzfeAtY1cPBzbG2KJ+2gz9OEOuSypz7B6VRwO0C4cGO69OiMaTUKixHogLPyh7JfAWJvRLC3QedBlRxmSAIfvd8JYp8zxBnT5kwRT0M9qcIgKp6mnILdC3K/MsDRMV0Hoy90DF02fL/iSledXhEjeAgqIQMAaYGeredJfKwQwywfQi7U8ZAj1zQtDALjb9C/YsQe0HGimG0kUsMLIFbi7q4oeeatsmdqEzHSnHPMiFhF1zzSWkTRRZ+HgBKCLZMskYMtuxgP+M7OTj5/DHq4y3SrPLxNCA75+61Zs4bTT76ikEt4PdrgbJCkCCcbFvYTgi2Q6oRMCHayYWE/IdgCqU7IhGAnGxb2E4ItkOqETAh2smFhnwSbrqZZcKt4ICVuNOZh7ZRvR4ZZNOJjowew+jZkg0L40QDcSwSwpwlgfAdBgsMQk6u/STi4JFcD17E/oXzQVSdV5MNa/jlvbCTJwZZ/ioRgywQzRWyH8pl/oGze3lq74/3d1YEN0w2OO7am5NfXyzw7DNunqx0frX2IOqM0CIxUW1tbnws7VLECF5yfhmqJRhte3cwf44Kw7aurJV4ICtubt93AwMDmcePG/dF7JH81VlNEWWlhZ4AYeQV/nGWVYASYv6ES056sEpxKjcQ07Py5ZZXgoeGCn6H5YzJLT3YJHkoIjnSrXHlM+WBNTehZWkl5mdXfL8uYiVd1JIIv/dlFW+F+6GldvELN6Q3f+/0oZ4twBz1X9UgEh+tjTLbiIhT/IF1cknNYnFIVMCFY5UO8lBAsTqkKmBCs8iFeSggWp1QFTAhW+RAvJQSLU6oCJgSrfIiXEoLFKVUBE4JVPsRLCcHilKqACcEqH+KlhGBxSlXAhGCVD/FSQrA4pSpgsRGsPGXFOx+FfW8AXBcbwcqnDMrLy4P+rk0dbhZKUQmWeO3U5us+3U6OKioq6pzlQuxHfWSk/BWjpsN8D26/pm2Q2XuuBhP6+/uXDg4O8iuDWaWqqmqosrLS7xF4O7LMI1kNQxyISrDEc6tQLxqG8N2vCT++pAjImwtV6qIU8HbSkyC5I4qNs23UFCE1gp0+iO2niXhDDPB7IL41ry1RCeaHjkzlTFOAAPvlAcejHs4rwXuieufT/mKfOrEqjOKNAPuLGCC+Mos0Ua+LF3UE70dHfheDKP1fBIdtz0/vgUMcyZ4XQQIcZWx+/+7BaBQH9KkeBjnvQ01luopqpwQnz4WuhvZkcXgE9Z3QldDroCfQE2z3QJ3yjh0PfVDR62POnjX3f+sDba0KPpZCp0PnQn8JnQM9HcrPSHoE9cuhbjnL09BGBXptcPesUf6fDd+kMBEPR75bHpTCz4mDXidCU+7eNcoSn8vN6avJQcTT7orpXR28qBe5ElyleTvKK7Wp3GYKYNl+rQufozrytSMywelOV7o61yk2wuEaHcM82azz6ecGnzr5KhBTCe2GmspD8t7JISK4na4A23zQT0Id/7SNW49ojWCkCX6v8vcetOgVTQjglOhmebNwj+IZ8Pcn6J3LoPz0+iVpZQynQj2iRXAa5VFstRdB0hh0tDm9H8eNOw+XdHV13QFH50FJtHPUTkbZcwOlTTBGMd8K5zfeTeVajIpFpiA27BFjO3CVJdApU6YszNIX17nHu49pE0wgOPAfbP7tBtUo/wMkn69hlw8TJU3gw/vTmpqafpyl4ynues+QdjcIKoOY49GGc8S6oLYBxw/i+Gz8aB0B7fJ6GPHxDm63s9OOjo7H6urqlC/8pY/zrOYUdnQNxGgEExSE8DPi/AiG8jyMxyIKLxSvISDby5mR3EJ8e2DQ6jSqra39ubPs2K/CvvJAwZhggsMJ5qnLoKZPPKYCYxNIjlu6UP5bLuI9c9myZZPgq58oaUKEYPaCTrdhczn0M5YN5GTYbgbJdxtgiJjCBy4S/Q5gN7sBFyxY4DstQztlNmGcg90dw6F61L0A5TTGVF4CwN348T4wBYpqjzjOhs0/oZzrKtLX1/fy+PHjH8X3KEZzrdKgpGQryj2sExvBmQ5Axv+xPxvKfx9hKr8AQBuCbYYqp54pcDZ79DMV+gSO88LtIRekvl5fX9+cg1xCj45u8RFM9IzAURL0OPT0TJ3Bdhi2PDOItxE/pPIWjwEuF9g5h6Wvi6G8lpRDPdLT0/P0zJkznzlw4EDKc1CtGERxI3TEKsHsE84fi80S6FJotvkjDkUS5vlXoQyCj+r3gnD+AKEEPh2Dhlw/uDStc7CtgmaTj9evX//nhoaGPdka+NS/jbpu6wRnOkZQvC2+E0qyT8vUC22HgMM/6Gau5nLq11DOaKhMg7xwMsVMTiv756gNks927dq1cv78+VtCjFo3VicqWvNGcKZ3EM2AF0BvhV4N9X1sg/qCCf5FWltra+vzjY2N77S3t/N01xH+6C/nnWCnpyD7RyjPh3J6txAqPbIBGU7gy95Dhw69sWrVqm24Ff4knFVgq20FJdjtHoI8A3XMjbPS23Ow9SygoM5Y0Nf+3t7eHfv27WtfsWLFzubmZtM7UT+fumJFsJ+HIIJf/q+HknzORiZCJ6RSqUk4lSfi4laDBZhKbHnh4pb/wm0Y2ofjvWh3BC//dR8+fPgT5NFu5NSelpaWg5s2bepHe9vSG3uCczDAXM6bmak52hTyEGc1W8oL6YFh37yLOgTtg3JdgITHRY7Ake3QL8cywRkyuZr3KZSpIw4zkoPwg+T2Qr2POFg5RoUjmOliGrSiADFwzr0TyrNqVMZyDh4NwrXDix0vhnXQaqht4V3lPihHLtOWIsVIcCZAjmimDd69cTGfxEsI10B6oByp1O9SAba+UswEOwNmnHy0xTk1p328weHoDpOzB9COpz9zPQnliA1a7EGT7+WHQnAmXveWuZqLPLzYZ5RteJtL5W0yp1va8i0oVdWTfcH7WwAAAABJRU5ErkJggg==");
  }
  
  public static Bitmap e()
  {
    return Bitmap.createScaledBitmap(a("iVBORw0KGgoAAAANSUhEUgAAAB4AAAAuCAYAAAA/SqkPAAAAAXNSR0IArs4c6QAABFJJREFUWAm1l0toFFkUhu10J5MGiQOCDuhCycJFliLoRoMzUUlACTSR7jzahaizGCULFUdBAyoo6MIngoIxacGgdnxFkMwgKDgzIirqMIIiuNCFio+WPMa22+80uU1VV9W9tztYUNzH+c/56py6VXVryhTNkc/nqzTmSZkCAwu0r6/vDMfeSRECnH3BQEMAT9C2c26jvyPAv+LpsJ9nfX39IeZ/ddiWtra2ZgYHB+845ibV9WRMdvvI8jefqAcovfNifCT2Uy4wgXcC3RLkju0oF7YmyF7OfEiJe3t7N9Pfr8aaNoctkUwmz2k0RlMBnE6nf8xkMk/JaIbRA0EoFMqijQG/ZKP30xRKzcL5QLBlnO/9RKVzQCNoByj78lKb7bhYanHo7+9fkMvlhglcZxMA+Chnc2dn500bvVPjWlwdHR13MbZwjjhFQX0uMMp5hfWxKEgTNO8Ci6irq+t2OBxeSXcsyMk5D3gqWV9PpVLznfOmvqvUTjGPVgtlTzNX7ZwP6gN/h62RC38cpHHOezJWRu7btaqqqjgBv6o5XUvm07EPc8HzdDplCwSLAPgFwEm68uwaD+AzqdIfrPa5JrEWLM7AU2S+ngvIm4JN2GdxAX/yhMzW6Y1gcQZ+kmCbdIFKbHMk84GBgZ9K5ovDwMVVVDg6lHALF7DPMWXqPqmurm5MJBJvS4VWGSsnVqy8y3vU2KJtyGazN+SVXKotK2PlzMrdTynlo2J7/BWNRpva2to+K4eyMlZO3HP5dB5RY4t24djY2FXueVRpKwKLM2XfyEo/pQKZWtbGktHR0cGhoaEfRFtRqRWEYLIh7KNNqDmL9nJDQ0NsUmCBSPko4wvgMy2gStITUb1KWqBhyncaX2sot+dvXkgHK77HZBgaHx+Xe9xme9FA79bW1i7n8/vJd3trE4gt8HHga220E5p7dXV1TbFY7KOMKyo1b7CDQDfYQsn0Pt/4JtliKZ+yS81uYw/QbhXA1AJ9iL6pvb3dtZ8rK2My3U6Q300wZQf6KBKJ/MK7WjYJrsM6Y6DdQHe7vPWD/zAL1POBEDer5xjoBqDH9RyX9XlNTc3ieDz+yjXrGBhLzT2VHcgxh4+2S3lfspB+1kElgDZjoKsJlCJbq8cO7WvOxXxEnmmvTgcGuoog54EaqzIBeUOmjbwc/jVBxe6bMfdUfk0uA62xCsKvD9ClPDIPbPSi8axqPjaNzKdtoWgzQFeUA8XHDaa8iwBe4Sx+sEWkOUZ44bcA/Uej8TUVM5ZfEO7pdaBTfZXeSfnFWcVCuuU1mWcKYNkVsCm7BHSa2aWg+EKm8n88bKn3yArg5ubmcbJdx/m/R1EygeYr0DiZXisxlTUslpo91BCe8q+U1UTIYU8CvaDRWJmKYFEDv0jj+68EME+m64GmrCIbRC6waIGfBSJld/0rcf83AT1piGdt9oAn4KcAb1RR6G9lIR1W4+/e8lxv5tz1PUDfAOOinoaBSIPLAAAAAElFTkSuQmCC"), b, c, true);
  }
  
  public static Bitmap f()
  {
    return Bitmap.createScaledBitmap(a("iVBORw0KGgoAAAANSUhEUgAAAB4AAAAuCAYAAAA/SqkPAAAABGdBTUEAALGPC/xhBQAAACBjSFJNAAB6JgAAgIQAAPoAAACA6AAAdTAAAOpgAAA6mAAAF3CculE8AAABWWlUWHRYTUw6Y29tLmFkb2JlLnhtcAAAAAAAPHg6eG1wbWV0YSB4bWxuczp4PSJhZG9iZTpuczptZXRhLyIgeDp4bXB0az0iWE1QIENvcmUgNS40LjAiPgogICA8cmRmOlJERiB4bWxuczpyZGY9Imh0dHA6Ly93d3cudzMub3JnLzE5OTkvMDIvMjItcmRmLXN5bnRheC1ucyMiPgogICAgICA8cmRmOkRlc2NyaXB0aW9uIHJkZjphYm91dD0iIgogICAgICAgICAgICB4bWxuczp0aWZmPSJodHRwOi8vbnMuYWRvYmUuY29tL3RpZmYvMS4wLyI+CiAgICAgICAgIDx0aWZmOk9yaWVudGF0aW9uPjE8L3RpZmY6T3JpZW50YXRpb24+CiAgICAgIDwvcmRmOkRlc2NyaXB0aW9uPgogICA8L3JkZjpSREY+CjwveDp4bXBtZXRhPgpMwidZAAAEOUlEQVRYCbWXT0hUQRzHdd1yDdLEzP5AEURFBhVZXepUBJpRS7RCrlpol8oCozpUpIeELJIyKMSg9S9KJQpKWobSoS4du3esW6Hglvunz8+c5e3z7Xuz6zowO29mvr/fZ34z8+bNZmQsQwoEAo3kG3auM+06U+nr7Oy8GY1GH4ity+Wqr6qqemblJ61goqwH8lSBMjMzozxfrK6ufqnaVJk2cFdXVx2RtpPNPiMMoAp4r4JKaRYZ+7SfgVZGIpFODFxWRoBDtFcAf6v6lwwGeoYo+8lZyqlVCfwv7V7go9JvOUIrQ6s2oCeItM8JKrZoVpLbR0dHs6Xulp9UEhvpGNDX2K7QsSfi31lZWafKysr+iD6liIn0CLZDZI84cUpAZ4i2tLKy8qvSJr3GPT09B0Oh0AccrFZO7Eqgs+Qy3udJoy6piIHuDYfD73CgC53fUGaoDMB2JxpH2N3dvQvoBG0FxvZEz0QZYnrP1tTUjFhptCJmTbexkWR6C62cmNuAhoH6gco+sEyOYKZ3C04myBssPZgagSKN1gLtN3XFVW3BfX19G9lIAt0cZ2VfuQQ0YC+xOTL5yqwDOIWDnU5OVD/RNnAytaq6XWkZcW9v71qMZE2Tgd7RhcqAFr3HnEgFjFymd48INFMz03tbUzsviwOzkfLllQG6T9cJg2wl0gZdvdLFpnpwcHANG+l9ktAXqUAFPh/xwMBAXjAYFOgBNSKnkmtNwO/3XyBiuWUknVycSLlAx5KBQhnIzs6uTRUqo3SzprI+h6Sik4D99Hg8530+X1hHn0jjKi4uvk/ncCKBuZ2ZKWKGOihj+8Os0am7SkpK5goLC32Ix3UMRAP0HOe31cVO18X/i4DcCnJyck4zjXJSaSXgtZxusauslpFBFJsu1myWtSun74uh3+nxCpG3OIms+uMOEBHI+zw9Pf2RiLQPEcyaOLkaxV43xSJWBl6v95fb7T5O/Ztq0yjvyV8XDV1Msihi1cOhsp7dO0Xk21WbRnmVyNs0dIlvmaz5D06nozj5ruNINGzOJ6x5nY4+YcTKmCncStSfqG9SbQ5lhAFXc8HrsdM5gsWYKHYAl2kvsnOm+og8TK4A/ka1mUstsBgR+W6KSeBat0y0c0TuBW55y9QGC5zv9f6F73We1DVSkL8t5XzF5Foclxa9TnG9por8BSHiUqZxxtSVqOphoMPM1mGzICmwGPO6fAZ8kjxrdpagvor2ET6/cd/6pMHifOEviRe4/EVxTMxSLn8IxtiksXtcSmAhceWRy4MPeMiRjABtPnlcjmTRpwwWY6Z9CGd+HiNSd0poH8mRLLolgcUB8H6idrwG8Wo1on0oNpKWDBYnTPsr4Jfl2SrR18K+aDL2pQUsDnH8nOK60bk8A21jYLfM7WkDi2Om8jGguwZIBwO6Zqgv7yMHRjO5m82U1sC0Ru0E/Qd96KxVCBkW1wAAAABJRU5ErkJggg=="), d, e, true);
  }
  
  private boolean y()
  {
    return lr.e() >= 1.5F;
  }
  
  public boolean g()
  {
    return (i != null) && (j != null) && (k != null) && (l != null);
  }
  
  public Bitmap h()
  {
    return i;
  }
  
  public Bitmap i()
  {
    return k;
  }
  
  public Bitmap j()
  {
    return l;
  }
  
  public Bitmap k()
  {
    return m;
  }
  
  public Bitmap l()
  {
    return o;
  }
  
  public Bitmap m()
  {
    return p;
  }
  
  public Bitmap n()
  {
    return q;
  }
  
  public Bitmap o()
  {
    return t;
  }
  
  public Bitmap p()
  {
    return r;
  }
  
  public Bitmap q()
  {
    return s;
  }
  
  public da r()
  {
    return a("downArrowImage", "android/down_arrow.png");
  }
  
  public da s()
  {
    return a("downArrowImage", "android/down_arrow2x.png");
  }
  
  public da t()
  {
    return a("downArrowImage", "android/down_arrow3x.png");
  }
  
  public da u()
  {
    return a("upArrowImage", "android/up_arrow.png");
  }
  
  public da v()
  {
    return a("upArrowImage", "android/up_arrow2x.png");
  }
  
  public da w()
  {
    return a("upArrowImage", "android/up_arrow3x.png");
  }
  
  /* Error */
  public void x()
  {
    // Byte code:
    //   0: aconst_null
    //   1: astore_2
    //   2: aconst_null
    //   3: astore 4
    //   5: aconst_null
    //   6: astore 5
    //   8: aconst_null
    //   9: astore_3
    //   10: aload_0
    //   11: getfield 279	com/flurry/sdk/hc:h	Z
    //   14: ifeq +4 -> 18
    //   17: return
    //   18: invokestatic 107	com/flurry/sdk/i:a	()Lcom/flurry/sdk/i;
    //   21: invokevirtual 282	com/flurry/sdk/i:f	()Lcom/flurry/sdk/k;
    //   24: invokevirtual 287	com/flurry/sdk/k:b	()Ljava/io/File;
    //   27: astore 6
    //   29: aload 6
    //   31: ifnull +106 -> 137
    //   34: new 289	java/io/BufferedInputStream
    //   37: dup
    //   38: new 291	java/io/FileInputStream
    //   41: dup
    //   42: aload 6
    //   44: invokespecial 294	java/io/FileInputStream:<init>	(Ljava/io/File;)V
    //   47: invokespecial 297	java/io/BufferedInputStream:<init>	(Ljava/io/InputStream;)V
    //   50: astore_1
    //   51: aload_1
    //   52: astore 4
    //   54: new 299	java/util/zip/ZipInputStream
    //   57: dup
    //   58: new 289	java/io/BufferedInputStream
    //   61: dup
    //   62: aload_1
    //   63: invokespecial 297	java/io/BufferedInputStream:<init>	(Ljava/io/InputStream;)V
    //   66: invokespecial 300	java/util/zip/ZipInputStream:<init>	(Ljava/io/InputStream;)V
    //   69: astore_3
    //   70: aload_3
    //   71: invokevirtual 304	java/util/zip/ZipInputStream:getNextEntry	()Ljava/util/zip/ZipEntry;
    //   74: astore_2
    //   75: aload_2
    //   76: ifnull +626 -> 702
    //   79: aload_0
    //   80: aload_3
    //   81: aload_2
    //   82: invokevirtual 309	java/util/zip/ZipEntry:getName	()Ljava/lang/String;
    //   85: invokespecial 311	com/flurry/sdk/hc:a	(Ljava/io/InputStream;Ljava/lang/String;)V
    //   88: goto -18 -> 70
    //   91: astore_2
    //   92: aload_1
    //   93: astore_2
    //   94: aload_3
    //   95: astore_1
    //   96: iconst_3
    //   97: getstatic 44	com/flurry/sdk/hc:a	Ljava/lang/String;
    //   100: ldc_w 313
    //   103: invokestatic 318	com/flurry/sdk/kg:a	(ILjava/lang/String;Ljava/lang/String;)V
    //   106: aload_1
    //   107: invokestatic 323	com/flurry/sdk/lt:a	(Ljava/io/Closeable;)V
    //   110: aload_2
    //   111: invokestatic 323	com/flurry/sdk/lt:a	(Ljava/io/Closeable;)V
    //   114: aload_0
    //   115: invokevirtual 325	com/flurry/sdk/hc:g	()Z
    //   118: ifne +19 -> 137
    //   121: iconst_3
    //   122: getstatic 44	com/flurry/sdk/hc:a	Ljava/lang/String;
    //   125: ldc_w 327
    //   128: invokestatic 318	com/flurry/sdk/kg:a	(ILjava/lang/String;Ljava/lang/String;)V
    //   131: aload 6
    //   133: invokevirtual 330	java/io/File:delete	()Z
    //   136: pop
    //   137: aload_0
    //   138: getfield 156	com/flurry/sdk/hc:i	Landroid/graphics/Bitmap;
    //   141: ifnonnull +23 -> 164
    //   144: iconst_3
    //   145: getstatic 44	com/flurry/sdk/hc:a	Ljava/lang/String;
    //   148: ldc_w 332
    //   151: invokestatic 318	com/flurry/sdk/kg:a	(ILjava/lang/String;Ljava/lang/String;)V
    //   154: aload_0
    //   155: ldc_w 334
    //   158: invokestatic 71	com/flurry/sdk/hc:a	(Ljava/lang/String;)Landroid/graphics/Bitmap;
    //   161: putfield 156	com/flurry/sdk/hc:i	Landroid/graphics/Bitmap;
    //   164: aload_0
    //   165: getfield 198	com/flurry/sdk/hc:j	Landroid/graphics/Bitmap;
    //   168: ifnonnull +23 -> 191
    //   171: iconst_3
    //   172: getstatic 44	com/flurry/sdk/hc:a	Ljava/lang/String;
    //   175: ldc_w 336
    //   178: invokestatic 318	com/flurry/sdk/kg:a	(ILjava/lang/String;Ljava/lang/String;)V
    //   181: aload_0
    //   182: ldc_w 338
    //   185: invokestatic 71	com/flurry/sdk/hc:a	(Ljava/lang/String;)Landroid/graphics/Bitmap;
    //   188: putfield 198	com/flurry/sdk/hc:j	Landroid/graphics/Bitmap;
    //   191: aload_0
    //   192: getfield 200	com/flurry/sdk/hc:k	Landroid/graphics/Bitmap;
    //   195: ifnonnull +23 -> 218
    //   198: iconst_3
    //   199: getstatic 44	com/flurry/sdk/hc:a	Ljava/lang/String;
    //   202: ldc_w 340
    //   205: invokestatic 318	com/flurry/sdk/kg:a	(ILjava/lang/String;Ljava/lang/String;)V
    //   208: aload_0
    //   209: ldc_w 342
    //   212: invokestatic 71	com/flurry/sdk/hc:a	(Ljava/lang/String;)Landroid/graphics/Bitmap;
    //   215: putfield 200	com/flurry/sdk/hc:k	Landroid/graphics/Bitmap;
    //   218: aload_0
    //   219: getfield 202	com/flurry/sdk/hc:l	Landroid/graphics/Bitmap;
    //   222: ifnonnull +23 -> 245
    //   225: iconst_3
    //   226: getstatic 44	com/flurry/sdk/hc:a	Ljava/lang/String;
    //   229: ldc_w 344
    //   232: invokestatic 318	com/flurry/sdk/kg:a	(ILjava/lang/String;Ljava/lang/String;)V
    //   235: aload_0
    //   236: ldc_w 346
    //   239: invokestatic 71	com/flurry/sdk/hc:a	(Ljava/lang/String;)Landroid/graphics/Bitmap;
    //   242: putfield 202	com/flurry/sdk/hc:l	Landroid/graphics/Bitmap;
    //   245: aload_0
    //   246: getfield 206	com/flurry/sdk/hc:m	Landroid/graphics/Bitmap;
    //   249: ifnonnull +23 -> 272
    //   252: iconst_3
    //   253: getstatic 44	com/flurry/sdk/hc:a	Ljava/lang/String;
    //   256: ldc_w 348
    //   259: invokestatic 318	com/flurry/sdk/kg:a	(ILjava/lang/String;Ljava/lang/String;)V
    //   262: aload_0
    //   263: ldc_w 350
    //   266: invokestatic 71	com/flurry/sdk/hc:a	(Ljava/lang/String;)Landroid/graphics/Bitmap;
    //   269: putfield 206	com/flurry/sdk/hc:m	Landroid/graphics/Bitmap;
    //   272: aload_0
    //   273: getfield 210	com/flurry/sdk/hc:n	Landroid/graphics/Bitmap;
    //   276: ifnonnull +23 -> 299
    //   279: iconst_3
    //   280: getstatic 44	com/flurry/sdk/hc:a	Ljava/lang/String;
    //   283: ldc_w 352
    //   286: invokestatic 318	com/flurry/sdk/kg:a	(ILjava/lang/String;Ljava/lang/String;)V
    //   289: aload_0
    //   290: ldc_w 354
    //   293: invokestatic 71	com/flurry/sdk/hc:a	(Ljava/lang/String;)Landroid/graphics/Bitmap;
    //   296: putfield 210	com/flurry/sdk/hc:n	Landroid/graphics/Bitmap;
    //   299: aload_0
    //   300: getfield 204	com/flurry/sdk/hc:o	Landroid/graphics/Bitmap;
    //   303: ifnonnull +23 -> 326
    //   306: iconst_3
    //   307: getstatic 44	com/flurry/sdk/hc:a	Ljava/lang/String;
    //   310: ldc_w 356
    //   313: invokestatic 318	com/flurry/sdk/kg:a	(ILjava/lang/String;Ljava/lang/String;)V
    //   316: aload_0
    //   317: ldc_w 358
    //   320: invokestatic 71	com/flurry/sdk/hc:a	(Ljava/lang/String;)Landroid/graphics/Bitmap;
    //   323: putfield 204	com/flurry/sdk/hc:o	Landroid/graphics/Bitmap;
    //   326: aload_0
    //   327: getfield 208	com/flurry/sdk/hc:p	Landroid/graphics/Bitmap;
    //   330: ifnonnull +23 -> 353
    //   333: iconst_3
    //   334: getstatic 44	com/flurry/sdk/hc:a	Ljava/lang/String;
    //   337: ldc_w 360
    //   340: invokestatic 318	com/flurry/sdk/kg:a	(ILjava/lang/String;Ljava/lang/String;)V
    //   343: aload_0
    //   344: ldc_w 362
    //   347: invokestatic 71	com/flurry/sdk/hc:a	(Ljava/lang/String;)Landroid/graphics/Bitmap;
    //   350: putfield 208	com/flurry/sdk/hc:p	Landroid/graphics/Bitmap;
    //   353: aload_0
    //   354: getfield 214	com/flurry/sdk/hc:q	Landroid/graphics/Bitmap;
    //   357: ifnonnull +23 -> 380
    //   360: iconst_3
    //   361: getstatic 44	com/flurry/sdk/hc:a	Ljava/lang/String;
    //   364: ldc_w 364
    //   367: invokestatic 318	com/flurry/sdk/kg:a	(ILjava/lang/String;Ljava/lang/String;)V
    //   370: aload_0
    //   371: ldc_w 366
    //   374: invokestatic 71	com/flurry/sdk/hc:a	(Ljava/lang/String;)Landroid/graphics/Bitmap;
    //   377: putfield 214	com/flurry/sdk/hc:q	Landroid/graphics/Bitmap;
    //   380: aload_0
    //   381: getfield 212	com/flurry/sdk/hc:r	Landroid/graphics/Bitmap;
    //   384: ifnonnull +23 -> 407
    //   387: iconst_3
    //   388: getstatic 44	com/flurry/sdk/hc:a	Ljava/lang/String;
    //   391: ldc_w 368
    //   394: invokestatic 318	com/flurry/sdk/kg:a	(ILjava/lang/String;Ljava/lang/String;)V
    //   397: aload_0
    //   398: ldc_w 370
    //   401: invokestatic 71	com/flurry/sdk/hc:a	(Ljava/lang/String;)Landroid/graphics/Bitmap;
    //   404: putfield 212	com/flurry/sdk/hc:r	Landroid/graphics/Bitmap;
    //   407: aload_0
    //   408: getfield 216	com/flurry/sdk/hc:s	Landroid/graphics/Bitmap;
    //   411: ifnonnull +23 -> 434
    //   414: iconst_3
    //   415: getstatic 44	com/flurry/sdk/hc:a	Ljava/lang/String;
    //   418: ldc_w 372
    //   421: invokestatic 318	com/flurry/sdk/kg:a	(ILjava/lang/String;Ljava/lang/String;)V
    //   424: aload_0
    //   425: ldc_w 374
    //   428: invokestatic 71	com/flurry/sdk/hc:a	(Ljava/lang/String;)Landroid/graphics/Bitmap;
    //   431: putfield 216	com/flurry/sdk/hc:s	Landroid/graphics/Bitmap;
    //   434: aload_0
    //   435: getfield 218	com/flurry/sdk/hc:t	Landroid/graphics/Bitmap;
    //   438: ifnonnull +23 -> 461
    //   441: iconst_3
    //   442: getstatic 44	com/flurry/sdk/hc:a	Ljava/lang/String;
    //   445: ldc_w 376
    //   448: invokestatic 318	com/flurry/sdk/kg:a	(ILjava/lang/String;Ljava/lang/String;)V
    //   451: aload_0
    //   452: ldc_w 378
    //   455: invokestatic 71	com/flurry/sdk/hc:a	(Ljava/lang/String;)Landroid/graphics/Bitmap;
    //   458: putfield 218	com/flurry/sdk/hc:t	Landroid/graphics/Bitmap;
    //   461: aload_0
    //   462: getfield 220	com/flurry/sdk/hc:u	Landroid/graphics/Bitmap;
    //   465: ifnonnull +23 -> 488
    //   468: iconst_3
    //   469: getstatic 44	com/flurry/sdk/hc:a	Ljava/lang/String;
    //   472: ldc_w 380
    //   475: invokestatic 318	com/flurry/sdk/kg:a	(ILjava/lang/String;Ljava/lang/String;)V
    //   478: aload_0
    //   479: ldc_w 382
    //   482: invokestatic 71	com/flurry/sdk/hc:a	(Ljava/lang/String;)Landroid/graphics/Bitmap;
    //   485: putfield 220	com/flurry/sdk/hc:u	Landroid/graphics/Bitmap;
    //   488: aload_0
    //   489: getfield 222	com/flurry/sdk/hc:v	Landroid/graphics/Bitmap;
    //   492: ifnonnull +23 -> 515
    //   495: iconst_3
    //   496: getstatic 44	com/flurry/sdk/hc:a	Ljava/lang/String;
    //   499: ldc_w 384
    //   502: invokestatic 318	com/flurry/sdk/kg:a	(ILjava/lang/String;Ljava/lang/String;)V
    //   505: aload_0
    //   506: ldc_w 386
    //   509: invokestatic 71	com/flurry/sdk/hc:a	(Ljava/lang/String;)Landroid/graphics/Bitmap;
    //   512: putfield 222	com/flurry/sdk/hc:v	Landroid/graphics/Bitmap;
    //   515: aload_0
    //   516: getfield 224	com/flurry/sdk/hc:w	Landroid/graphics/Bitmap;
    //   519: ifnonnull +23 -> 542
    //   522: iconst_3
    //   523: getstatic 44	com/flurry/sdk/hc:a	Ljava/lang/String;
    //   526: ldc_w 388
    //   529: invokestatic 318	com/flurry/sdk/kg:a	(ILjava/lang/String;Ljava/lang/String;)V
    //   532: aload_0
    //   533: ldc_w 390
    //   536: invokestatic 71	com/flurry/sdk/hc:a	(Ljava/lang/String;)Landroid/graphics/Bitmap;
    //   539: putfield 224	com/flurry/sdk/hc:w	Landroid/graphics/Bitmap;
    //   542: aload_0
    //   543: getfield 226	com/flurry/sdk/hc:x	Landroid/graphics/Bitmap;
    //   546: ifnonnull +23 -> 569
    //   549: iconst_3
    //   550: getstatic 44	com/flurry/sdk/hc:a	Ljava/lang/String;
    //   553: ldc_w 392
    //   556: invokestatic 318	com/flurry/sdk/kg:a	(ILjava/lang/String;Ljava/lang/String;)V
    //   559: aload_0
    //   560: ldc_w 394
    //   563: invokestatic 71	com/flurry/sdk/hc:a	(Ljava/lang/String;)Landroid/graphics/Bitmap;
    //   566: putfield 226	com/flurry/sdk/hc:x	Landroid/graphics/Bitmap;
    //   569: aload_0
    //   570: getfield 228	com/flurry/sdk/hc:y	Landroid/graphics/Bitmap;
    //   573: ifnonnull +23 -> 596
    //   576: iconst_3
    //   577: getstatic 44	com/flurry/sdk/hc:a	Ljava/lang/String;
    //   580: ldc_w 396
    //   583: invokestatic 318	com/flurry/sdk/kg:a	(ILjava/lang/String;Ljava/lang/String;)V
    //   586: aload_0
    //   587: ldc_w 398
    //   590: invokestatic 71	com/flurry/sdk/hc:a	(Ljava/lang/String;)Landroid/graphics/Bitmap;
    //   593: putfield 228	com/flurry/sdk/hc:y	Landroid/graphics/Bitmap;
    //   596: aload_0
    //   597: getfield 230	com/flurry/sdk/hc:z	Landroid/graphics/Bitmap;
    //   600: ifnonnull +23 -> 623
    //   603: iconst_3
    //   604: getstatic 44	com/flurry/sdk/hc:a	Ljava/lang/String;
    //   607: ldc_w 400
    //   610: invokestatic 318	com/flurry/sdk/kg:a	(ILjava/lang/String;Ljava/lang/String;)V
    //   613: aload_0
    //   614: ldc_w 402
    //   617: invokestatic 71	com/flurry/sdk/hc:a	(Ljava/lang/String;)Landroid/graphics/Bitmap;
    //   620: putfield 230	com/flurry/sdk/hc:z	Landroid/graphics/Bitmap;
    //   623: invokestatic 107	com/flurry/sdk/i:a	()Lcom/flurry/sdk/i;
    //   626: invokevirtual 110	com/flurry/sdk/i:l	()Lcom/flurry/sdk/ab;
    //   629: astore_1
    //   630: aload_1
    //   631: aload_0
    //   632: getfield 220	com/flurry/sdk/hc:u	Landroid/graphics/Bitmap;
    //   635: ldc -70
    //   637: invokevirtual 405	com/flurry/sdk/ab:a	(Landroid/graphics/Bitmap;Ljava/lang/String;)Z
    //   640: pop
    //   641: aload_1
    //   642: aload_0
    //   643: getfield 222	com/flurry/sdk/hc:v	Landroid/graphics/Bitmap;
    //   646: ldc -68
    //   648: invokevirtual 405	com/flurry/sdk/ab:a	(Landroid/graphics/Bitmap;Ljava/lang/String;)Z
    //   651: pop
    //   652: aload_1
    //   653: aload_0
    //   654: getfield 224	com/flurry/sdk/hc:w	Landroid/graphics/Bitmap;
    //   657: ldc -66
    //   659: invokevirtual 405	com/flurry/sdk/ab:a	(Landroid/graphics/Bitmap;Ljava/lang/String;)Z
    //   662: pop
    //   663: aload_1
    //   664: aload_0
    //   665: getfield 226	com/flurry/sdk/hc:x	Landroid/graphics/Bitmap;
    //   668: ldc -64
    //   670: invokevirtual 405	com/flurry/sdk/ab:a	(Landroid/graphics/Bitmap;Ljava/lang/String;)Z
    //   673: pop
    //   674: aload_1
    //   675: aload_0
    //   676: getfield 228	com/flurry/sdk/hc:y	Landroid/graphics/Bitmap;
    //   679: ldc -62
    //   681: invokevirtual 405	com/flurry/sdk/ab:a	(Landroid/graphics/Bitmap;Ljava/lang/String;)Z
    //   684: pop
    //   685: aload_1
    //   686: aload_0
    //   687: getfield 230	com/flurry/sdk/hc:z	Landroid/graphics/Bitmap;
    //   690: ldc -60
    //   692: invokevirtual 405	com/flurry/sdk/ab:a	(Landroid/graphics/Bitmap;Ljava/lang/String;)Z
    //   695: pop
    //   696: aload_0
    //   697: iconst_1
    //   698: putfield 279	com/flurry/sdk/hc:h	Z
    //   701: return
    //   702: aload_3
    //   703: invokestatic 323	com/flurry/sdk/lt:a	(Ljava/io/Closeable;)V
    //   706: aload_1
    //   707: invokestatic 323	com/flurry/sdk/lt:a	(Ljava/io/Closeable;)V
    //   710: goto -596 -> 114
    //   713: astore_1
    //   714: aconst_null
    //   715: astore_1
    //   716: aload_2
    //   717: astore 5
    //   719: aload_1
    //   720: astore 4
    //   722: iconst_3
    //   723: getstatic 44	com/flurry/sdk/hc:a	Ljava/lang/String;
    //   726: ldc_w 407
    //   729: invokestatic 318	com/flurry/sdk/kg:a	(ILjava/lang/String;Ljava/lang/String;)V
    //   732: aload_2
    //   733: invokestatic 323	com/flurry/sdk/lt:a	(Ljava/io/Closeable;)V
    //   736: aload_1
    //   737: invokestatic 323	com/flurry/sdk/lt:a	(Ljava/io/Closeable;)V
    //   740: goto -626 -> 114
    //   743: astore_2
    //   744: aconst_null
    //   745: astore_1
    //   746: aload 4
    //   748: astore_3
    //   749: aload_3
    //   750: invokestatic 323	com/flurry/sdk/lt:a	(Ljava/io/Closeable;)V
    //   753: aload_1
    //   754: invokestatic 323	com/flurry/sdk/lt:a	(Ljava/io/Closeable;)V
    //   757: aload_2
    //   758: athrow
    //   759: astore_2
    //   760: aload 5
    //   762: astore_3
    //   763: aload 4
    //   765: astore_1
    //   766: goto -17 -> 749
    //   769: astore_2
    //   770: goto -21 -> 749
    //   773: astore_3
    //   774: aload_2
    //   775: astore 4
    //   777: aload_3
    //   778: astore_2
    //   779: aload_1
    //   780: astore_3
    //   781: aload 4
    //   783: astore_1
    //   784: goto -35 -> 749
    //   787: astore_3
    //   788: goto -72 -> 716
    //   791: astore_2
    //   792: aload_3
    //   793: astore_2
    //   794: goto -78 -> 716
    //   797: astore_1
    //   798: aconst_null
    //   799: astore_1
    //   800: aload_3
    //   801: astore_2
    //   802: goto -706 -> 96
    //   805: astore_2
    //   806: aconst_null
    //   807: astore_3
    //   808: aload_1
    //   809: astore_2
    //   810: aload_3
    //   811: astore_1
    //   812: goto -716 -> 96
    // Local variable table:
    //   start	length	slot	name	signature
    //   0	815	0	this	hc
    //   50	657	1	localObject1	Object
    //   713	1	1	localIOException1	java.io.IOException
    //   715	69	1	localObject2	Object
    //   797	1	1	localFileNotFoundException1	java.io.FileNotFoundException
    //   799	13	1	localObject3	Object
    //   1	81	2	localZipEntry	java.util.zip.ZipEntry
    //   91	1	2	localFileNotFoundException2	java.io.FileNotFoundException
    //   93	640	2	localObject4	Object
    //   743	15	2	localObject5	Object
    //   759	1	2	localObject6	Object
    //   769	6	2	localObject7	Object
    //   778	1	2	localObject8	Object
    //   791	1	2	localIOException2	java.io.IOException
    //   793	9	2	localObject9	Object
    //   805	1	2	localFileNotFoundException3	java.io.FileNotFoundException
    //   809	1	2	localObject10	Object
    //   9	754	3	localObject11	Object
    //   773	5	3	localObject12	Object
    //   780	1	3	localObject13	Object
    //   787	14	3	localIOException3	java.io.IOException
    //   807	4	3	localObject14	Object
    //   3	779	4	localObject15	Object
    //   6	755	5	localObject16	Object
    //   27	105	6	localFile	File
    // Exception table:
    //   from	to	target	type
    //   70	75	91	java/io/FileNotFoundException
    //   79	88	91	java/io/FileNotFoundException
    //   34	51	713	java/io/IOException
    //   34	51	743	finally
    //   54	70	759	finally
    //   722	732	759	finally
    //   70	75	769	finally
    //   79	88	769	finally
    //   96	106	773	finally
    //   54	70	787	java/io/IOException
    //   70	75	791	java/io/IOException
    //   79	88	791	java/io/IOException
    //   34	51	797	java/io/FileNotFoundException
    //   54	70	805	java/io/FileNotFoundException
  }
}

/* Location:
 * Qualified Name:     com.flurry.sdk.hc
 * Java Class Version: 6 (50.0)
 * JD-Core Version:    0.7.1
 */