package com.flurry.sdk;

public final class l
{
  private static final String a = l.class.getSimpleName();
  
  /* Error */
  public static java.util.List<be> a(java.io.File paramFile)
  {
    // Byte code:
    //   0: aconst_null
    //   1: astore_2
    //   2: aload_0
    //   3: ifnull +10 -> 13
    //   6: aload_0
    //   7: invokevirtual 29	java/io/File:exists	()Z
    //   10: ifne +7 -> 17
    //   13: invokestatic 35	java/util/Collections:emptyList	()Ljava/util/List;
    //   16: areturn
    //   17: new 37	com/flurry/sdk/be$b
    //   20: dup
    //   21: invokespecial 38	com/flurry/sdk/be$b:<init>	()V
    //   24: astore 4
    //   26: new 40	java/util/ArrayList
    //   29: dup
    //   30: invokespecial 41	java/util/ArrayList:<init>	()V
    //   33: astore 5
    //   35: new 43	java/io/FileInputStream
    //   38: dup
    //   39: aload_0
    //   40: invokespecial 46	java/io/FileInputStream:<init>	(Ljava/io/File;)V
    //   43: astore_3
    //   44: new 48	java/io/DataInputStream
    //   47: dup
    //   48: aload_3
    //   49: invokespecial 51	java/io/DataInputStream:<init>	(Ljava/io/InputStream;)V
    //   52: astore_0
    //   53: aload_0
    //   54: invokevirtual 55	java/io/DataInputStream:readShort	()S
    //   57: istore_1
    //   58: iconst_1
    //   59: iload_1
    //   60: if_icmpeq +14 -> 74
    //   63: aload_0
    //   64: invokestatic 60	com/flurry/sdk/lt:a	(Ljava/io/Closeable;)V
    //   67: aload_3
    //   68: invokestatic 60	com/flurry/sdk/lt:a	(Ljava/io/Closeable;)V
    //   71: aload 5
    //   73: areturn
    //   74: aload 5
    //   76: aload 4
    //   78: aload_0
    //   79: invokeinterface 66 2 0
    //   84: invokeinterface 72 2 0
    //   89: pop
    //   90: goto -37 -> 53
    //   93: astore 4
    //   95: aload_3
    //   96: astore_2
    //   97: aload 4
    //   99: astore_3
    //   100: iconst_3
    //   101: getstatic 16	com/flurry/sdk/l:a	Ljava/lang/String;
    //   104: ldc 74
    //   106: aload_3
    //   107: invokestatic 79	com/flurry/sdk/kg:a	(ILjava/lang/String;Ljava/lang/String;Ljava/lang/Throwable;)V
    //   110: aload_0
    //   111: invokestatic 60	com/flurry/sdk/lt:a	(Ljava/io/Closeable;)V
    //   114: aload_2
    //   115: invokestatic 60	com/flurry/sdk/lt:a	(Ljava/io/Closeable;)V
    //   118: aload 5
    //   120: areturn
    //   121: astore_2
    //   122: aconst_null
    //   123: astore_0
    //   124: aconst_null
    //   125: astore_3
    //   126: aload_0
    //   127: invokestatic 60	com/flurry/sdk/lt:a	(Ljava/io/Closeable;)V
    //   130: aload_3
    //   131: invokestatic 60	com/flurry/sdk/lt:a	(Ljava/io/Closeable;)V
    //   134: aload_2
    //   135: athrow
    //   136: astore_2
    //   137: aconst_null
    //   138: astore_0
    //   139: goto -13 -> 126
    //   142: astore_2
    //   143: goto -17 -> 126
    //   146: astore 4
    //   148: aload_2
    //   149: astore_3
    //   150: aload 4
    //   152: astore_2
    //   153: goto -27 -> 126
    //   156: astore_3
    //   157: aconst_null
    //   158: astore_0
    //   159: goto -59 -> 100
    //   162: astore 4
    //   164: aconst_null
    //   165: astore_0
    //   166: aload_3
    //   167: astore_2
    //   168: aload 4
    //   170: astore_3
    //   171: goto -71 -> 100
    // Local variable table:
    //   start	length	slot	name	signature
    //   0	174	0	paramFile	java.io.File
    //   57	4	1	i	int
    //   1	114	2	localObject1	Object
    //   121	14	2	localObject2	Object
    //   136	1	2	localObject3	Object
    //   142	7	2	localObject4	Object
    //   152	16	2	localObject5	Object
    //   43	107	3	localObject6	Object
    //   156	11	3	localException1	Exception
    //   170	1	3	localException2	Exception
    //   24	53	4	localb	be.b
    //   93	5	4	localException3	Exception
    //   146	5	4	localObject7	Object
    //   162	7	4	localException4	Exception
    //   33	86	5	localArrayList	java.util.ArrayList
    // Exception table:
    //   from	to	target	type
    //   53	58	93	java/lang/Exception
    //   74	90	93	java/lang/Exception
    //   35	44	121	finally
    //   44	53	136	finally
    //   53	58	142	finally
    //   74	90	142	finally
    //   100	110	146	finally
    //   35	44	156	java/lang/Exception
    //   44	53	162	java/lang/Exception
  }
  
  /* Error */
  public static java.util.List<ay> b(java.io.File paramFile)
  {
    // Byte code:
    //   0: aconst_null
    //   1: astore_2
    //   2: aload_0
    //   3: ifnull +10 -> 13
    //   6: aload_0
    //   7: invokevirtual 29	java/io/File:exists	()Z
    //   10: ifne +7 -> 17
    //   13: invokestatic 35	java/util/Collections:emptyList	()Ljava/util/List;
    //   16: areturn
    //   17: new 83	com/flurry/sdk/ay$a
    //   20: dup
    //   21: new 85	com/flurry/sdk/ax$a
    //   24: dup
    //   25: invokespecial 86	com/flurry/sdk/ax$a:<init>	()V
    //   28: invokespecial 89	com/flurry/sdk/ay$a:<init>	(Lcom/flurry/sdk/ax$a;)V
    //   31: astore 4
    //   33: new 40	java/util/ArrayList
    //   36: dup
    //   37: invokespecial 41	java/util/ArrayList:<init>	()V
    //   40: astore 5
    //   42: new 43	java/io/FileInputStream
    //   45: dup
    //   46: aload_0
    //   47: invokespecial 46	java/io/FileInputStream:<init>	(Ljava/io/File;)V
    //   50: astore_3
    //   51: new 48	java/io/DataInputStream
    //   54: dup
    //   55: aload_3
    //   56: invokespecial 51	java/io/DataInputStream:<init>	(Ljava/io/InputStream;)V
    //   59: astore_0
    //   60: ldc 90
    //   62: aload_0
    //   63: invokevirtual 94	java/io/DataInputStream:readUnsignedShort	()I
    //   66: if_icmpeq +57 -> 123
    //   69: new 96	java/io/IOException
    //   72: dup
    //   73: ldc 98
    //   75: invokespecial 101	java/io/IOException:<init>	(Ljava/lang/String;)V
    //   78: athrow
    //   79: astore 4
    //   81: aload_3
    //   82: astore_2
    //   83: aload 4
    //   85: astore_3
    //   86: iconst_3
    //   87: getstatic 16	com/flurry/sdk/l:a	Ljava/lang/String;
    //   90: ldc 103
    //   92: aload_3
    //   93: invokestatic 79	com/flurry/sdk/kg:a	(ILjava/lang/String;Ljava/lang/String;Ljava/lang/Throwable;)V
    //   96: aload_0
    //   97: invokestatic 60	com/flurry/sdk/lt:a	(Ljava/io/Closeable;)V
    //   100: aload_2
    //   101: invokestatic 60	com/flurry/sdk/lt:a	(Ljava/io/Closeable;)V
    //   104: aload 5
    //   106: areturn
    //   107: aload 5
    //   109: aload 4
    //   111: aload_0
    //   112: invokeinterface 66 2 0
    //   117: invokeinterface 72 2 0
    //   122: pop
    //   123: aload_0
    //   124: invokevirtual 55	java/io/DataInputStream:readShort	()S
    //   127: istore_1
    //   128: iconst_1
    //   129: iload_1
    //   130: if_icmpeq -23 -> 107
    //   133: aload_0
    //   134: invokestatic 60	com/flurry/sdk/lt:a	(Ljava/io/Closeable;)V
    //   137: aload_3
    //   138: invokestatic 60	com/flurry/sdk/lt:a	(Ljava/io/Closeable;)V
    //   141: aload 5
    //   143: areturn
    //   144: astore_2
    //   145: aconst_null
    //   146: astore_0
    //   147: aconst_null
    //   148: astore_3
    //   149: aload_0
    //   150: invokestatic 60	com/flurry/sdk/lt:a	(Ljava/io/Closeable;)V
    //   153: aload_3
    //   154: invokestatic 60	com/flurry/sdk/lt:a	(Ljava/io/Closeable;)V
    //   157: aload_2
    //   158: athrow
    //   159: astore_2
    //   160: aconst_null
    //   161: astore_0
    //   162: goto -13 -> 149
    //   165: astore_2
    //   166: goto -17 -> 149
    //   169: astore 4
    //   171: aload_2
    //   172: astore_3
    //   173: aload 4
    //   175: astore_2
    //   176: goto -27 -> 149
    //   179: astore_3
    //   180: aconst_null
    //   181: astore_0
    //   182: goto -96 -> 86
    //   185: astore 4
    //   187: aconst_null
    //   188: astore_0
    //   189: aload_3
    //   190: astore_2
    //   191: aload 4
    //   193: astore_3
    //   194: goto -108 -> 86
    // Local variable table:
    //   start	length	slot	name	signature
    //   0	197	0	paramFile	java.io.File
    //   127	4	1	i	int
    //   1	100	2	localObject1	Object
    //   144	14	2	localObject2	Object
    //   159	1	2	localObject3	Object
    //   165	7	2	localObject4	Object
    //   175	16	2	localObject5	Object
    //   50	123	3	localObject6	Object
    //   179	11	3	localException1	Exception
    //   193	1	3	localException2	Exception
    //   31	1	4	locala	ay.a
    //   79	31	4	localException3	Exception
    //   169	5	4	localObject7	Object
    //   185	7	4	localException4	Exception
    //   40	102	5	localArrayList	java.util.ArrayList
    // Exception table:
    //   from	to	target	type
    //   60	79	79	java/lang/Exception
    //   107	123	79	java/lang/Exception
    //   123	128	79	java/lang/Exception
    //   42	51	144	finally
    //   51	60	159	finally
    //   60	79	165	finally
    //   107	123	165	finally
    //   123	128	165	finally
    //   86	96	169	finally
    //   42	51	179	java/lang/Exception
    //   51	60	185	java/lang/Exception
  }
}

/* Location:
 * Qualified Name:     com.flurry.sdk.l
 * Java Class Version: 6 (50.0)
 * JD-Core Version:    0.7.1
 */