package com.estrongs.android.g;

import android.net.Uri;
import java.io.BufferedReader;
import java.io.ByteArrayInputStream;
import java.io.File;
import java.io.FileOutputStream;
import java.io.IOException;
import java.io.OutputStream;
import java.io.PrintStream;
import java.net.Socket;
import java.util.Properties;
import java.util.StringTokenizer;
import java.util.Vector;

class h
  implements Runnable
{
  private Socket b;
  
  public h(f paramf, Socket paramSocket)
  {
    b = paramSocket;
    paramf = new Thread(this);
    paramf.setDaemon(true);
    paramf.start();
  }
  
  private int a(byte[] paramArrayOfByte, int paramInt)
  {
    for (int i = paramInt;; i = paramInt + 1)
    {
      paramInt = i;
      if (i < paramArrayOfByte.length)
      {
        paramInt = i;
        if (paramArrayOfByte[i] == 13)
        {
          i += 1;
          paramInt = i;
          if (paramArrayOfByte[i] == 10)
          {
            i += 1;
            paramInt = i;
            if (paramArrayOfByte[i] == 13)
            {
              i += 1;
              paramInt = i;
              if (paramArrayOfByte[i] == 10) {
                paramInt = i;
              }
            }
          }
        }
      }
      else
      {
        return paramInt + 1;
      }
    }
  }
  
  private String a(String paramString)
  {
    try
    {
      paramString = Uri.decode(paramString);
      return paramString;
    }
    catch (Exception paramString)
    {
      a("400 Bad Request", "BAD REQUEST: Bad percent-encoding.");
    }
    return null;
  }
  
  private String a(byte[] paramArrayOfByte, int paramInt1, int paramInt2)
  {
    Object localObject = "";
    if (paramInt2 > 0) {
      localObject = System.getProperty("java.io.tmpdir");
    }
    try
    {
      localObject = File.createTempFile("NanoHTTPD", "", new File((String)localObject));
      FileOutputStream localFileOutputStream = new FileOutputStream((File)localObject);
      localFileOutputStream.write(paramArrayOfByte, paramInt1, paramInt2);
      localFileOutputStream.close();
      localObject = ((File)localObject).getAbsolutePath();
      return (String)localObject;
    }
    catch (Exception paramArrayOfByte)
    {
      System.err.println("Error: " + paramArrayOfByte.getMessage());
    }
    return "";
  }
  
  private void a(BufferedReader paramBufferedReader, Properties paramProperties1, Properties paramProperties2, Properties paramProperties3)
  {
    try
    {
      String str1 = paramBufferedReader.readLine();
      if (str1 == null) {
        return;
      }
      StringTokenizer localStringTokenizer = new StringTokenizer(str1);
      if (!localStringTokenizer.hasMoreTokens()) {
        a("400 Bad Request", "BAD REQUEST: Syntax error. Usage: GET /example/file.html");
      }
      String str2 = localStringTokenizer.nextToken();
      paramProperties1.put("method", str2);
      if (!localStringTokenizer.hasMoreTokens()) {
        a("400 Bad Request", "BAD REQUEST: Missing URI. Usage: GET /example/file.html");
      }
      int k = str1.indexOf(str2);
      int m = str2.length();
      int j = str1.indexOf("HTTP/1") - 1;
      int i = j;
      if (j < 0) {
        i = str1.indexOf("http/1") - 1;
      }
      if (i > 0)
      {
        str1 = str1.substring(m + k + 1, i);
        localStringTokenizer.nextToken();
        i = str1.indexOf('?');
        if (i < 0) {
          break label281;
        }
        a(str1.substring(i + 1), paramProperties2);
      }
      label281:
      for (paramProperties2 = a(str1.substring(0, i));; paramProperties2 = a(str1))
      {
        if (!localStringTokenizer.hasMoreTokens()) {
          break label291;
        }
        for (str1 = paramBufferedReader.readLine(); (str1 != null) && (str1.trim().length() > 0); str1 = paramBufferedReader.readLine())
        {
          i = str1.indexOf(':');
          if (i >= 0) {
            paramProperties3.put(str1.substring(0, i).trim().toLowerCase(), str1.substring(i + 1).trim());
          }
        }
        str1 = localStringTokenizer.nextToken();
        break;
      }
      label291:
      paramProperties1.put("uri", paramProperties2);
      return;
    }
    catch (IOException paramBufferedReader)
    {
      a("500 Internal Server Error", "SERVER INTERNAL ERROR: IOException: " + paramBufferedReader.getMessage());
    }
  }
  
  private void a(String paramString1, String paramString2)
  {
    a(paramString1, "text/plain", null, new ByteArrayInputStream(paramString2.getBytes()));
    throw new InterruptedException();
  }
  
  /* Error */
  private void a(String paramString1, String paramString2, Properties paramProperties, java.io.InputStream paramInputStream)
  {
    // Byte code:
    //   0: invokestatic 206	java/lang/Thread:currentThread	()Ljava/lang/Thread;
    //   3: invokevirtual 210	java/lang/Thread:getId	()J
    //   6: pop2
    //   7: iconst_0
    //   8: iconst_1
    //   9: invokestatic 215	com/estrongs/android/util/k:a	(ZZ)V
    //   12: aload_1
    //   13: ifnonnull +37 -> 50
    //   16: new 217	java/lang/Error
    //   19: dup
    //   20: ldc -37
    //   22: invokespecial 220	java/lang/Error:<init>	(Ljava/lang/String;)V
    //   25: athrow
    //   26: astore_1
    //   27: aload 4
    //   29: ifnull +8 -> 37
    //   32: aload 4
    //   34: invokevirtual 223	java/io/InputStream:close	()V
    //   37: aload_0
    //   38: getfield 19	com/estrongs/android/g/h:b	Ljava/net/Socket;
    //   41: invokevirtual 226	java/net/Socket:close	()V
    //   44: iconst_0
    //   45: iconst_1
    //   46: invokestatic 228	com/estrongs/android/util/k:b	(ZZ)V
    //   49: return
    //   50: aload_0
    //   51: getfield 19	com/estrongs/android/g/h:b	Ljava/net/Socket;
    //   54: invokevirtual 232	java/net/Socket:getOutputStream	()Ljava/io/OutputStream;
    //   57: astore 6
    //   59: new 234	java/io/PrintWriter
    //   62: dup
    //   63: aload 6
    //   65: invokespecial 237	java/io/PrintWriter:<init>	(Ljava/io/OutputStream;)V
    //   68: astore 7
    //   70: aload 7
    //   72: new 93	java/lang/StringBuilder
    //   75: dup
    //   76: invokespecial 94	java/lang/StringBuilder:<init>	()V
    //   79: ldc -17
    //   81: invokevirtual 100	java/lang/StringBuilder:append	(Ljava/lang/String;)Ljava/lang/StringBuilder;
    //   84: aload_1
    //   85: invokevirtual 100	java/lang/StringBuilder:append	(Ljava/lang/String;)Ljava/lang/StringBuilder;
    //   88: ldc -15
    //   90: invokevirtual 100	java/lang/StringBuilder:append	(Ljava/lang/String;)Ljava/lang/StringBuilder;
    //   93: invokevirtual 106	java/lang/StringBuilder:toString	()Ljava/lang/String;
    //   96: invokevirtual 244	java/io/PrintWriter:print	(Ljava/lang/String;)V
    //   99: aload_2
    //   100: ifnull +32 -> 132
    //   103: aload 7
    //   105: new 93	java/lang/StringBuilder
    //   108: dup
    //   109: invokespecial 94	java/lang/StringBuilder:<init>	()V
    //   112: ldc -10
    //   114: invokevirtual 100	java/lang/StringBuilder:append	(Ljava/lang/String;)Ljava/lang/StringBuilder;
    //   117: aload_2
    //   118: invokevirtual 100	java/lang/StringBuilder:append	(Ljava/lang/String;)Ljava/lang/StringBuilder;
    //   121: ldc -8
    //   123: invokevirtual 100	java/lang/StringBuilder:append	(Ljava/lang/String;)Ljava/lang/StringBuilder;
    //   126: invokevirtual 106	java/lang/StringBuilder:toString	()Ljava/lang/String;
    //   129: invokevirtual 244	java/io/PrintWriter:print	(Ljava/lang/String;)V
    //   132: aload_3
    //   133: ifnull +12 -> 145
    //   136: aload_3
    //   137: ldc -6
    //   139: invokevirtual 251	java/util/Properties:getProperty	(Ljava/lang/String;)Ljava/lang/String;
    //   142: ifnonnull +44 -> 186
    //   145: aload 7
    //   147: new 93	java/lang/StringBuilder
    //   150: dup
    //   151: invokespecial 94	java/lang/StringBuilder:<init>	()V
    //   154: ldc -3
    //   156: invokevirtual 100	java/lang/StringBuilder:append	(Ljava/lang/String;)Ljava/lang/StringBuilder;
    //   159: invokestatic 259	com/estrongs/android/g/f:j	()Ljava/text/SimpleDateFormat;
    //   162: new 261	java/util/Date
    //   165: dup
    //   166: invokespecial 262	java/util/Date:<init>	()V
    //   169: invokevirtual 268	java/text/SimpleDateFormat:format	(Ljava/util/Date;)Ljava/lang/String;
    //   172: invokevirtual 100	java/lang/StringBuilder:append	(Ljava/lang/String;)Ljava/lang/StringBuilder;
    //   175: ldc -8
    //   177: invokevirtual 100	java/lang/StringBuilder:append	(Ljava/lang/String;)Ljava/lang/StringBuilder;
    //   180: invokevirtual 106	java/lang/StringBuilder:toString	()Ljava/lang/String;
    //   183: invokevirtual 244	java/io/PrintWriter:print	(Ljava/lang/String;)V
    //   186: aload_3
    //   187: ifnull +80 -> 267
    //   190: aload_3
    //   191: invokevirtual 272	java/util/Properties:keys	()Ljava/util/Enumeration;
    //   194: astore_1
    //   195: aload_1
    //   196: invokeinterface 277 1 0
    //   201: ifeq +66 -> 267
    //   204: aload_1
    //   205: invokeinterface 281 1 0
    //   210: checkcast 143	java/lang/String
    //   213: astore_2
    //   214: aload_3
    //   215: aload_2
    //   216: invokevirtual 251	java/util/Properties:getProperty	(Ljava/lang/String;)Ljava/lang/String;
    //   219: astore 8
    //   221: aload 7
    //   223: new 93	java/lang/StringBuilder
    //   226: dup
    //   227: invokespecial 94	java/lang/StringBuilder:<init>	()V
    //   230: aload_2
    //   231: invokevirtual 100	java/lang/StringBuilder:append	(Ljava/lang/String;)Ljava/lang/StringBuilder;
    //   234: ldc_w 283
    //   237: invokevirtual 100	java/lang/StringBuilder:append	(Ljava/lang/String;)Ljava/lang/StringBuilder;
    //   240: aload 8
    //   242: invokevirtual 100	java/lang/StringBuilder:append	(Ljava/lang/String;)Ljava/lang/StringBuilder;
    //   245: ldc -8
    //   247: invokevirtual 100	java/lang/StringBuilder:append	(Ljava/lang/String;)Ljava/lang/StringBuilder;
    //   250: invokevirtual 106	java/lang/StringBuilder:toString	()Ljava/lang/String;
    //   253: invokevirtual 244	java/io/PrintWriter:print	(Ljava/lang/String;)V
    //   256: goto -61 -> 195
    //   259: astore_1
    //   260: iconst_0
    //   261: iconst_1
    //   262: invokestatic 228	com/estrongs/android/util/k:b	(ZZ)V
    //   265: aload_1
    //   266: athrow
    //   267: aload 7
    //   269: ldc -8
    //   271: invokevirtual 244	java/io/PrintWriter:print	(Ljava/lang/String;)V
    //   274: aload 7
    //   276: invokevirtual 286	java/io/PrintWriter:flush	()V
    //   279: aload 4
    //   281: ifnull +26 -> 307
    //   284: ldc_w 287
    //   287: newarray <illegal type>
    //   289: astore_1
    //   290: aload 4
    //   292: aload_1
    //   293: iconst_0
    //   294: ldc_w 287
    //   297: invokevirtual 291	java/io/InputStream:read	([BII)I
    //   300: istore 5
    //   302: iload 5
    //   304: ifgt +29 -> 333
    //   307: aload 6
    //   309: invokevirtual 292	java/io/OutputStream:flush	()V
    //   312: aload 6
    //   314: invokevirtual 83	java/io/OutputStream:close	()V
    //   317: aload 4
    //   319: ifnull +8 -> 327
    //   322: aload 4
    //   324: invokevirtual 223	java/io/InputStream:close	()V
    //   327: iconst_0
    //   328: iconst_1
    //   329: invokestatic 228	com/estrongs/android/util/k:b	(ZZ)V
    //   332: return
    //   333: aload 6
    //   335: aload_1
    //   336: iconst_0
    //   337: iload 5
    //   339: invokevirtual 80	java/io/OutputStream:write	([BII)V
    //   342: goto -52 -> 290
    //   345: astore_1
    //   346: goto -309 -> 37
    //   349: astore_1
    //   350: goto -306 -> 44
    // Local variable table:
    //   start	length	slot	name	signature
    //   0	353	0	this	h
    //   0	353	1	paramString1	String
    //   0	353	2	paramString2	String
    //   0	353	3	paramProperties	Properties
    //   0	353	4	paramInputStream	java.io.InputStream
    //   300	38	5	i	int
    //   57	277	6	localOutputStream	OutputStream
    //   68	207	7	localPrintWriter	java.io.PrintWriter
    //   219	22	8	str	String
    // Exception table:
    //   from	to	target	type
    //   7	12	26	java/io/IOException
    //   16	26	26	java/io/IOException
    //   50	99	26	java/io/IOException
    //   103	132	26	java/io/IOException
    //   136	145	26	java/io/IOException
    //   145	186	26	java/io/IOException
    //   190	195	26	java/io/IOException
    //   195	256	26	java/io/IOException
    //   267	279	26	java/io/IOException
    //   284	290	26	java/io/IOException
    //   290	302	26	java/io/IOException
    //   307	317	26	java/io/IOException
    //   322	327	26	java/io/IOException
    //   333	342	26	java/io/IOException
    //   7	12	259	finally
    //   16	26	259	finally
    //   32	37	259	finally
    //   37	44	259	finally
    //   50	99	259	finally
    //   103	132	259	finally
    //   136	145	259	finally
    //   145	186	259	finally
    //   190	195	259	finally
    //   195	256	259	finally
    //   267	279	259	finally
    //   284	290	259	finally
    //   290	302	259	finally
    //   307	317	259	finally
    //   322	327	259	finally
    //   333	342	259	finally
    //   32	37	345	java/lang/Exception
    //   37	44	349	java/lang/Throwable
  }
  
  private void a(String paramString, Properties paramProperties)
  {
    if (paramString == null) {}
    for (;;)
    {
      return;
      paramString = new StringTokenizer(paramString, "&");
      while (paramString.hasMoreTokens())
      {
        String str = paramString.nextToken();
        int i = str.indexOf('=');
        if (i >= 0) {
          paramProperties.put(a(str.substring(0, i)).trim(), a(str.substring(i + 1)));
        }
      }
    }
  }
  
  private void a(String paramString, byte[] paramArrayOfByte, BufferedReader paramBufferedReader, Properties paramProperties1, Properties paramProperties2)
  {
    label596:
    for (;;)
    {
      int[] arrayOfInt;
      int i;
      try
      {
        arrayOfInt = a(paramArrayOfByte, paramString.getBytes());
        i = 1;
        localObject2 = paramBufferedReader.readLine();
        if (localObject2 != null)
        {
          if (((String)localObject2).indexOf(paramString) == -1) {
            a("400 Bad Request", "BAD REQUEST: Content type is multipart/form-data but next chunk does not start with boundary. Usage: GET /example/file.html");
          }
          i += 1;
          localObject3 = new Properties();
          localObject1 = paramBufferedReader.readLine();
          if ((localObject1 != null) && (((String)localObject1).trim().length() > 0))
          {
            j = ((String)localObject1).indexOf(':');
            if (j != -1) {
              ((Properties)localObject3).put(((String)localObject1).substring(0, j).trim().toLowerCase(), ((String)localObject1).substring(j + 1).trim());
            }
            localObject1 = paramBufferedReader.readLine();
            continue;
          }
          localObject2 = localObject1;
          if (localObject1 == null) {
            break label596;
          }
          localObject2 = ((Properties)localObject3).getProperty("content-disposition");
          if (localObject2 == null) {
            a("400 Bad Request", "BAD REQUEST: Content type is multipart/form-data but no content-disposition info found. Usage: GET /example/file.html");
          }
          localObject4 = new StringTokenizer((String)localObject2, "; ");
          localObject2 = new Properties();
          if (((StringTokenizer)localObject4).hasMoreTokens())
          {
            str = ((StringTokenizer)localObject4).nextToken();
            j = str.indexOf('=');
            if (j == -1) {
              continue;
            }
            ((Properties)localObject2).put(str.substring(0, j).trim().toLowerCase(), str.substring(j + 1).trim());
            continue;
          }
        }
        else
        {
          return;
        }
      }
      catch (IOException paramString)
      {
        a("500 Internal Server Error", "SERVER INTERNAL ERROR: IOException: " + paramString.getMessage());
      }
      Object localObject4 = ((Properties)localObject2).getProperty("name");
      String str = ((String)localObject4).substring(1, ((String)localObject4).length() - 1);
      if (((Properties)localObject3).getProperty("content-type") == null)
      {
        localObject3 = "";
        localObject2 = localObject1;
        localObject1 = localObject3;
        for (;;)
        {
          localObject4 = localObject1;
          localObject3 = localObject2;
          if (localObject2 == null) {
            break;
          }
          localObject4 = localObject1;
          localObject3 = localObject2;
          if (((String)localObject2).indexOf(paramString) != -1) {
            break;
          }
          localObject3 = paramBufferedReader.readLine();
          localObject2 = localObject3;
          if (localObject3 != null)
          {
            j = ((String)localObject3).indexOf(paramString);
            if (j == -1)
            {
              localObject1 = (String)localObject1 + (String)localObject3;
              localObject2 = localObject3;
            }
            else
            {
              localObject1 = (String)localObject1 + ((String)localObject3).substring(0, j - 2);
              localObject2 = localObject3;
            }
          }
        }
      }
      if (i > arrayOfInt.length) {
        a("500 Internal Server Error", "Error processing request");
      }
      int j = a(paramArrayOfByte, arrayOfInt[(i - 2)]);
      paramProperties2.put(str, a(paramArrayOfByte, j, arrayOfInt[(i - 1)] - j - 4));
      Object localObject1 = ((Properties)localObject2).getProperty("filename");
      localObject1 = ((String)localObject1).substring(1, ((String)localObject1).length() - 1);
      do
      {
        localObject2 = paramBufferedReader.readLine();
        localObject4 = localObject1;
        localObject3 = localObject2;
        if (localObject2 == null) {
          break;
        }
      } while (((String)localObject2).indexOf(paramString) == -1);
      Object localObject3 = localObject2;
      localObject4 = localObject1;
      Object localObject2 = localObject3;
      paramProperties1.put(str, localObject4);
    }
  }
  
  public int[] a(byte[] paramArrayOfByte1, byte[] paramArrayOfByte2)
  {
    int i1 = 0;
    Vector localVector = new Vector();
    int i = 0;
    int k = -1;
    int j = 0;
    if (i < paramArrayOfByte1.length)
    {
      int n;
      if (paramArrayOfByte1[i] == paramArrayOfByte2[j])
      {
        int m = k;
        if (j == 0) {
          m = i;
        }
        int i2 = j + 1;
        n = i;
        k = m;
        j = i2;
        if (i2 == paramArrayOfByte2.length)
        {
          localVector.addElement(new Integer(m));
          k = -1;
          j = 0;
          n = i;
        }
      }
      for (;;)
      {
        i = n + 1;
        break;
        n = i - j;
        k = -1;
        j = 0;
      }
    }
    paramArrayOfByte1 = new int[localVector.size()];
    i = i1;
    while (i < paramArrayOfByte1.length)
    {
      paramArrayOfByte1[i] = ((Integer)localVector.elementAt(i)).intValue();
      i += 1;
    }
    return paramArrayOfByte1;
  }
  
  /* Error */
  public void run()
  {
    // Byte code:
    //   0: iconst_0
    //   1: istore 6
    //   3: iconst_0
    //   4: istore 7
    //   6: iconst_0
    //   7: istore 8
    //   9: iconst_0
    //   10: istore 5
    //   12: iload 5
    //   14: istore_3
    //   15: iload 6
    //   17: istore 4
    //   19: iload 8
    //   21: istore_2
    //   22: aload_0
    //   23: getfield 19	com/estrongs/android/g/h:b	Ljava/net/Socket;
    //   26: invokevirtual 350	java/net/Socket:getInputStream	()Ljava/io/InputStream;
    //   29: astore 18
    //   31: aload 18
    //   33: ifnonnull +4 -> 37
    //   36: return
    //   37: iload 5
    //   39: istore_3
    //   40: iload 6
    //   42: istore 4
    //   44: iload 8
    //   46: istore_2
    //   47: sipush 8192
    //   50: newarray <illegal type>
    //   52: astore 15
    //   54: iload 5
    //   56: istore_3
    //   57: iload 6
    //   59: istore 4
    //   61: iload 8
    //   63: istore_2
    //   64: aload 18
    //   66: aload 15
    //   68: iconst_0
    //   69: sipush 8192
    //   72: invokevirtual 291	java/io/InputStream:read	([BII)I
    //   75: istore 9
    //   77: iload 9
    //   79: ifle +1908 -> 1987
    //   82: iload 5
    //   84: istore_3
    //   85: iload 6
    //   87: istore 4
    //   89: iload 8
    //   91: istore_2
    //   92: new 116	java/io/BufferedReader
    //   95: dup
    //   96: new 352	java/io/InputStreamReader
    //   99: dup
    //   100: new 187	java/io/ByteArrayInputStream
    //   103: dup
    //   104: aload 15
    //   106: iconst_0
    //   107: iload 9
    //   109: invokespecial 354	java/io/ByteArrayInputStream:<init>	([BII)V
    //   112: invokespecial 357	java/io/InputStreamReader:<init>	(Ljava/io/InputStream;)V
    //   115: invokespecial 360	java/io/BufferedReader:<init>	(Ljava/io/Reader;)V
    //   118: astore 17
    //   120: iload 5
    //   122: istore_3
    //   123: iload 6
    //   125: istore 4
    //   127: iload 8
    //   129: istore_2
    //   130: new 135	java/util/Properties
    //   133: dup
    //   134: invokespecial 303	java/util/Properties:<init>	()V
    //   137: astore 16
    //   139: iload 5
    //   141: istore_3
    //   142: iload 6
    //   144: istore 4
    //   146: iload 8
    //   148: istore_2
    //   149: new 135	java/util/Properties
    //   152: dup
    //   153: invokespecial 303	java/util/Properties:<init>	()V
    //   156: astore 19
    //   158: iload 5
    //   160: istore_3
    //   161: iload 6
    //   163: istore 4
    //   165: iload 8
    //   167: istore_2
    //   168: new 135	java/util/Properties
    //   171: dup
    //   172: invokespecial 303	java/util/Properties:<init>	()V
    //   175: astore 20
    //   177: iload 5
    //   179: istore_3
    //   180: iload 6
    //   182: istore 4
    //   184: iload 8
    //   186: istore_2
    //   187: new 135	java/util/Properties
    //   190: dup
    //   191: invokespecial 303	java/util/Properties:<init>	()V
    //   194: astore 21
    //   196: iload 5
    //   198: istore_3
    //   199: iload 6
    //   201: istore 4
    //   203: iload 8
    //   205: istore_2
    //   206: aload_0
    //   207: aload 17
    //   209: aload 16
    //   211: aload 19
    //   213: aload 20
    //   215: invokespecial 362	com/estrongs/android/g/h:a	(Ljava/io/BufferedReader;Ljava/util/Properties;Ljava/util/Properties;Ljava/util/Properties;)V
    //   218: iload 5
    //   220: istore_3
    //   221: iload 6
    //   223: istore 4
    //   225: iload 8
    //   227: istore_2
    //   228: aload 16
    //   230: ldc -123
    //   232: invokevirtual 251	java/util/Properties:getProperty	(Ljava/lang/String;)Ljava/lang/String;
    //   235: astore 22
    //   237: iload 5
    //   239: istore_3
    //   240: iload 6
    //   242: istore 4
    //   244: iload 8
    //   246: istore_2
    //   247: aload 16
    //   249: ldc -78
    //   251: invokevirtual 251	java/util/Properties:getProperty	(Ljava/lang/String;)Ljava/lang/String;
    //   254: astore 16
    //   256: ldc2_w 363
    //   259: lstore 11
    //   261: iload 5
    //   263: istore_3
    //   264: iload 6
    //   266: istore 4
    //   268: iload 8
    //   270: istore_2
    //   271: aload 20
    //   273: ldc_w 366
    //   276: invokevirtual 251	java/util/Properties:getProperty	(Ljava/lang/String;)Ljava/lang/String;
    //   279: astore 17
    //   281: lload 11
    //   283: lstore 13
    //   285: aload 17
    //   287: ifnull +23 -> 310
    //   290: iload 5
    //   292: istore_3
    //   293: iload 6
    //   295: istore 4
    //   297: iload 8
    //   299: istore_2
    //   300: aload 17
    //   302: invokestatic 369	java/lang/Integer:parseInt	(Ljava/lang/String;)I
    //   305: istore_1
    //   306: iload_1
    //   307: i2l
    //   308: lstore 13
    //   310: iconst_0
    //   311: istore_2
    //   312: iload_2
    //   313: iload 9
    //   315: if_icmpge +1667 -> 1982
    //   318: iload_2
    //   319: istore_1
    //   320: aload 15
    //   322: iload_2
    //   323: baload
    //   324: bipush 13
    //   326: if_icmpne +327 -> 653
    //   329: iload_2
    //   330: iconst_1
    //   331: iadd
    //   332: istore_2
    //   333: iload_2
    //   334: istore_1
    //   335: aload 15
    //   337: iload_2
    //   338: baload
    //   339: bipush 10
    //   341: if_icmpne +312 -> 653
    //   344: iload_2
    //   345: iconst_1
    //   346: iadd
    //   347: istore_2
    //   348: iload_2
    //   349: istore_1
    //   350: aload 15
    //   352: iload_2
    //   353: baload
    //   354: bipush 13
    //   356: if_icmpne +297 -> 653
    //   359: iload_2
    //   360: iconst_1
    //   361: iadd
    //   362: istore_2
    //   363: iload_2
    //   364: istore_1
    //   365: aload 15
    //   367: iload_2
    //   368: baload
    //   369: bipush 10
    //   371: if_icmpne +282 -> 653
    //   374: iconst_1
    //   375: istore_1
    //   376: iload_2
    //   377: iconst_1
    //   378: iadd
    //   379: istore 10
    //   381: iload 5
    //   383: istore_3
    //   384: iload 6
    //   386: istore 4
    //   388: iload 8
    //   390: istore_2
    //   391: new 371	java/io/ByteArrayOutputStream
    //   394: dup
    //   395: invokespecial 372	java/io/ByteArrayOutputStream:<init>	()V
    //   398: astore 23
    //   400: iload 10
    //   402: iload 9
    //   404: if_icmpge +1584 -> 1988
    //   407: iload 5
    //   409: istore_3
    //   410: iload 6
    //   412: istore 4
    //   414: iload 8
    //   416: istore_2
    //   417: aload 23
    //   419: aload 15
    //   421: iload 10
    //   423: iload 9
    //   425: iload 10
    //   427: isub
    //   428: invokevirtual 373	java/io/ByteArrayOutputStream:write	([BII)V
    //   431: goto +1557 -> 1988
    //   434: iload 5
    //   436: istore_3
    //   437: iload 6
    //   439: istore 4
    //   441: iload 8
    //   443: istore_2
    //   444: sipush 512
    //   447: newarray <illegal type>
    //   449: astore 15
    //   451: iload 9
    //   453: istore_1
    //   454: iload_1
    //   455: iflt +228 -> 683
    //   458: lload 11
    //   460: lconst_0
    //   461: lcmp
    //   462: ifle +221 -> 683
    //   465: iload 5
    //   467: istore_3
    //   468: iload 6
    //   470: istore 4
    //   472: iload 8
    //   474: istore_2
    //   475: aload 18
    //   477: aload 15
    //   479: iconst_0
    //   480: sipush 512
    //   483: invokevirtual 291	java/io/InputStream:read	([BII)I
    //   486: istore 9
    //   488: lload 11
    //   490: iload 9
    //   492: i2l
    //   493: lsub
    //   494: lstore 13
    //   496: lload 13
    //   498: lstore 11
    //   500: iload 9
    //   502: istore_1
    //   503: iload 9
    //   505: ifle -51 -> 454
    //   508: iload 5
    //   510: istore_3
    //   511: iload 6
    //   513: istore 4
    //   515: iload 8
    //   517: istore_2
    //   518: aload 23
    //   520: aload 15
    //   522: iconst_0
    //   523: iload 9
    //   525: invokevirtual 373	java/io/ByteArrayOutputStream:write	([BII)V
    //   528: lload 13
    //   530: lstore 11
    //   532: iload 9
    //   534: istore_1
    //   535: goto -81 -> 454
    //   538: astore 15
    //   540: iload_3
    //   541: istore_2
    //   542: aload_0
    //   543: ldc -76
    //   545: new 93	java/lang/StringBuilder
    //   548: dup
    //   549: invokespecial 94	java/lang/StringBuilder:<init>	()V
    //   552: ldc -74
    //   554: invokevirtual 100	java/lang/StringBuilder:append	(Ljava/lang/String;)Ljava/lang/StringBuilder;
    //   557: aload 15
    //   559: invokevirtual 183	java/io/IOException:getMessage	()Ljava/lang/String;
    //   562: invokevirtual 100	java/lang/StringBuilder:append	(Ljava/lang/String;)Ljava/lang/StringBuilder;
    //   565: invokevirtual 106	java/lang/StringBuilder:toString	()Ljava/lang/String;
    //   568: invokespecial 48	com/estrongs/android/g/h:a	(Ljava/lang/String;Ljava/lang/String;)V
    //   571: iload_3
    //   572: ifeq +1415 -> 1987
    //   575: aload_0
    //   576: getfield 14	com/estrongs/android/g/h:a	Lcom/estrongs/android/g/f;
    //   579: invokestatic 377	com/estrongs/android/g/f:c	(Lcom/estrongs/android/g/f;)Ljava/lang/Object;
    //   582: astore 15
    //   584: aload 15
    //   586: monitorenter
    //   587: aload_0
    //   588: getfield 14	com/estrongs/android/g/h:a	Lcom/estrongs/android/g/f;
    //   591: invokestatic 381	com/estrongs/android/g/f:g	(Lcom/estrongs/android/g/f;)I
    //   594: pop
    //   595: aload_0
    //   596: getfield 14	com/estrongs/android/g/h:a	Lcom/estrongs/android/g/f;
    //   599: invokestatic 384	com/estrongs/android/g/f:h	(Lcom/estrongs/android/g/f;)I
    //   602: ifne +39 -> 641
    //   605: aload_0
    //   606: getfield 14	com/estrongs/android/g/h:a	Lcom/estrongs/android/g/f;
    //   609: new 386	com/estrongs/android/g/i
    //   612: dup
    //   613: aload_0
    //   614: invokespecial 389	com/estrongs/android/g/i:<init>	(Lcom/estrongs/android/g/h;)V
    //   617: invokestatic 392	com/estrongs/android/g/f:a	(Lcom/estrongs/android/g/f;Ljava/util/TimerTask;)Ljava/util/TimerTask;
    //   620: pop
    //   621: aload_0
    //   622: getfield 14	com/estrongs/android/g/h:a	Lcom/estrongs/android/g/f;
    //   625: invokestatic 396	com/estrongs/android/g/f:i	(Lcom/estrongs/android/g/f;)Ljava/util/Timer;
    //   628: aload_0
    //   629: getfield 14	com/estrongs/android/g/h:a	Lcom/estrongs/android/g/f;
    //   632: invokestatic 400	com/estrongs/android/g/f:f	(Lcom/estrongs/android/g/f;)Ljava/util/TimerTask;
    //   635: ldc2_w 401
    //   638: invokevirtual 408	java/util/Timer:schedule	(Ljava/util/TimerTask;J)V
    //   641: aload 15
    //   643: monitorexit
    //   644: return
    //   645: astore 16
    //   647: aload 15
    //   649: monitorexit
    //   650: aload 16
    //   652: athrow
    //   653: iload_1
    //   654: iconst_1
    //   655: iadd
    //   656: istore_2
    //   657: goto -345 -> 312
    //   660: iload_1
    //   661: ifeq +16 -> 677
    //   664: lload 13
    //   666: lstore 11
    //   668: lload 13
    //   670: ldc2_w 363
    //   673: lcmp
    //   674: ifne -240 -> 434
    //   677: lconst_0
    //   678: lstore 11
    //   680: goto -246 -> 434
    //   683: iload 5
    //   685: istore_3
    //   686: iload 6
    //   688: istore 4
    //   690: iload 8
    //   692: istore_2
    //   693: aload 23
    //   695: invokevirtual 411	java/io/ByteArrayOutputStream:toByteArray	()[B
    //   698: astore 17
    //   700: iload 5
    //   702: istore_3
    //   703: iload 6
    //   705: istore 4
    //   707: iload 8
    //   709: istore_2
    //   710: aload_0
    //   711: getfield 14	com/estrongs/android/g/h:a	Lcom/estrongs/android/g/f;
    //   714: aload 23
    //   716: invokevirtual 411	java/io/ByteArrayOutputStream:toByteArray	()[B
    //   719: invokestatic 414	com/estrongs/android/g/f:a	(Lcom/estrongs/android/g/f;[B)[B
    //   722: pop
    //   723: iload 5
    //   725: istore_3
    //   726: iload 6
    //   728: istore 4
    //   730: iload 8
    //   732: istore_2
    //   733: new 116	java/io/BufferedReader
    //   736: dup
    //   737: new 352	java/io/InputStreamReader
    //   740: dup
    //   741: new 187	java/io/ByteArrayInputStream
    //   744: dup
    //   745: aload 17
    //   747: invokespecial 194	java/io/ByteArrayInputStream:<init>	([B)V
    //   750: invokespecial 357	java/io/InputStreamReader:<init>	(Ljava/io/InputStream;)V
    //   753: invokespecial 360	java/io/BufferedReader:<init>	(Ljava/io/Reader;)V
    //   756: astore 23
    //   758: iload 5
    //   760: istore_3
    //   761: iload 6
    //   763: istore 4
    //   765: iload 8
    //   767: istore_2
    //   768: aload 22
    //   770: ldc_w 416
    //   773: invokevirtual 420	java/lang/String:equalsIgnoreCase	(Ljava/lang/String;)Z
    //   776: ifeq +238 -> 1014
    //   779: ldc 51
    //   781: astore 15
    //   783: iload 5
    //   785: istore_3
    //   786: iload 6
    //   788: istore 4
    //   790: iload 8
    //   792: istore_2
    //   793: new 121	java/util/StringTokenizer
    //   796: dup
    //   797: aload 20
    //   799: ldc_w 313
    //   802: invokevirtual 251	java/util/Properties:getProperty	(Ljava/lang/String;)Ljava/lang/String;
    //   805: ldc_w 309
    //   808: invokespecial 296	java/util/StringTokenizer:<init>	(Ljava/lang/String;Ljava/lang/String;)V
    //   811: astore 24
    //   813: iload 5
    //   815: istore_3
    //   816: iload 6
    //   818: istore 4
    //   820: iload 8
    //   822: istore_2
    //   823: aload 24
    //   825: invokevirtual 126	java/util/StringTokenizer:hasMoreTokens	()Z
    //   828: ifeq +20 -> 848
    //   831: iload 5
    //   833: istore_3
    //   834: iload 6
    //   836: istore 4
    //   838: iload 8
    //   840: istore_2
    //   841: aload 24
    //   843: invokevirtual 131	java/util/StringTokenizer:nextToken	()Ljava/lang/String;
    //   846: astore 15
    //   848: iload 5
    //   850: istore_3
    //   851: iload 6
    //   853: istore 4
    //   855: iload 8
    //   857: istore_2
    //   858: aload 15
    //   860: ldc_w 422
    //   863: invokevirtual 420	java/lang/String:equalsIgnoreCase	(Ljava/lang/String;)Z
    //   866: ifeq +538 -> 1404
    //   869: iload 5
    //   871: istore_3
    //   872: iload 6
    //   874: istore 4
    //   876: iload 8
    //   878: istore_2
    //   879: aload 24
    //   881: invokevirtual 126	java/util/StringTokenizer:hasMoreTokens	()Z
    //   884: ifne +22 -> 906
    //   887: iload 5
    //   889: istore_3
    //   890: iload 6
    //   892: istore 4
    //   894: iload 8
    //   896: istore_2
    //   897: aload_0
    //   898: ldc 43
    //   900: ldc_w 424
    //   903: invokespecial 48	com/estrongs/android/g/h:a	(Ljava/lang/String;Ljava/lang/String;)V
    //   906: iload 5
    //   908: istore_3
    //   909: iload 6
    //   911: istore 4
    //   913: iload 8
    //   915: istore_2
    //   916: new 121	java/util/StringTokenizer
    //   919: dup
    //   920: aload 24
    //   922: invokevirtual 131	java/util/StringTokenizer:nextToken	()Ljava/lang/String;
    //   925: ldc_w 426
    //   928: invokespecial 296	java/util/StringTokenizer:<init>	(Ljava/lang/String;Ljava/lang/String;)V
    //   931: astore 15
    //   933: iload 5
    //   935: istore_3
    //   936: iload 6
    //   938: istore 4
    //   940: iload 8
    //   942: istore_2
    //   943: aload 15
    //   945: invokevirtual 429	java/util/StringTokenizer:countTokens	()I
    //   948: iconst_2
    //   949: if_icmpeq +22 -> 971
    //   952: iload 5
    //   954: istore_3
    //   955: iload 6
    //   957: istore 4
    //   959: iload 8
    //   961: istore_2
    //   962: aload_0
    //   963: ldc 43
    //   965: ldc_w 431
    //   968: invokespecial 48	com/estrongs/android/g/h:a	(Ljava/lang/String;Ljava/lang/String;)V
    //   971: iload 5
    //   973: istore_3
    //   974: iload 6
    //   976: istore 4
    //   978: iload 8
    //   980: istore_2
    //   981: aload 15
    //   983: invokevirtual 131	java/util/StringTokenizer:nextToken	()Ljava/lang/String;
    //   986: pop
    //   987: iload 5
    //   989: istore_3
    //   990: iload 6
    //   992: istore 4
    //   994: iload 8
    //   996: istore_2
    //   997: aload_0
    //   998: aload 15
    //   1000: invokevirtual 131	java/util/StringTokenizer:nextToken	()Ljava/lang/String;
    //   1003: aload 17
    //   1005: aload 23
    //   1007: aload 19
    //   1009: aload 21
    //   1011: invokespecial 433	com/estrongs/android/g/h:a	(Ljava/lang/String;[BLjava/io/BufferedReader;Ljava/util/Properties;Ljava/util/Properties;)V
    //   1014: iload 5
    //   1016: istore_3
    //   1017: iload 6
    //   1019: istore 4
    //   1021: iload 8
    //   1023: istore_2
    //   1024: aload 16
    //   1026: invokestatic 438	com/estrongs/android/util/ap:bH	(Ljava/lang/String;)Ljava/lang/String;
    //   1029: astore 17
    //   1031: iload 5
    //   1033: istore_3
    //   1034: iload 6
    //   1036: istore 4
    //   1038: iload 8
    //   1040: istore_2
    //   1041: aload_0
    //   1042: getfield 14	com/estrongs/android/g/h:a	Lcom/estrongs/android/g/f;
    //   1045: invokestatic 377	com/estrongs/android/g/f:c	(Lcom/estrongs/android/g/f;)Ljava/lang/Object;
    //   1048: astore 24
    //   1050: iload 5
    //   1052: istore_3
    //   1053: iload 6
    //   1055: istore 4
    //   1057: iload 8
    //   1059: istore_2
    //   1060: aload 24
    //   1062: monitorenter
    //   1063: aload 17
    //   1065: ifnull +912 -> 1977
    //   1068: aload 17
    //   1070: invokestatic 443	com/estrongs/android/pop/netfs/utils/TypeUtils:isAudioFile	(Ljava/lang/String;)Z
    //   1073: ifne +11 -> 1084
    //   1076: aload 17
    //   1078: invokestatic 446	com/estrongs/android/pop/netfs/utils/TypeUtils:isVideoFile	(Ljava/lang/String;)Z
    //   1081: ifeq +896 -> 1977
    //   1084: invokestatic 451	com/estrongs/android/util/bk:q	()Z
    //   1087: ifne +890 -> 1977
    //   1090: aload_0
    //   1091: getfield 14	com/estrongs/android/g/h:a	Lcom/estrongs/android/g/f;
    //   1094: invokestatic 454	com/estrongs/android/g/f:d	(Lcom/estrongs/android/g/f;)I
    //   1097: pop
    //   1098: iconst_1
    //   1099: istore 4
    //   1101: iconst_1
    //   1102: istore_3
    //   1103: iload 4
    //   1105: istore_2
    //   1106: aload_0
    //   1107: getfield 14	com/estrongs/android/g/h:a	Lcom/estrongs/android/g/f;
    //   1110: invokestatic 458	com/estrongs/android/g/f:e	(Lcom/estrongs/android/g/f;)Lcom/estrongs/android/ui/notification/d;
    //   1113: ifnull +521 -> 1634
    //   1116: iload_3
    //   1117: istore_1
    //   1118: iload 4
    //   1120: istore_2
    //   1121: aload_0
    //   1122: getfield 14	com/estrongs/android/g/h:a	Lcom/estrongs/android/g/f;
    //   1125: invokestatic 400	com/estrongs/android/g/f:f	(Lcom/estrongs/android/g/f;)Ljava/util/TimerTask;
    //   1128: ifnull +31 -> 1159
    //   1131: iload 4
    //   1133: istore_2
    //   1134: aload_0
    //   1135: getfield 14	com/estrongs/android/g/h:a	Lcom/estrongs/android/g/f;
    //   1138: invokestatic 400	com/estrongs/android/g/f:f	(Lcom/estrongs/android/g/f;)Ljava/util/TimerTask;
    //   1141: invokevirtual 463	java/util/TimerTask:cancel	()Z
    //   1144: pop
    //   1145: iload 4
    //   1147: istore_2
    //   1148: aload_0
    //   1149: getfield 14	com/estrongs/android/g/h:a	Lcom/estrongs/android/g/f;
    //   1152: aconst_null
    //   1153: invokestatic 392	com/estrongs/android/g/f:a	(Lcom/estrongs/android/g/f;Ljava/util/TimerTask;)Ljava/util/TimerTask;
    //   1156: pop
    //   1157: iload_3
    //   1158: istore_1
    //   1159: iload_1
    //   1160: istore_2
    //   1161: aload 24
    //   1163: monitorexit
    //   1164: iload_1
    //   1165: istore_2
    //   1166: iload_1
    //   1167: istore_3
    //   1168: iload_1
    //   1169: istore 4
    //   1171: aload_0
    //   1172: getfield 19	com/estrongs/android/g/h:b	Ljava/net/Socket;
    //   1175: invokevirtual 467	java/net/Socket:getInetAddress	()Ljava/net/InetAddress;
    //   1178: invokevirtual 472	java/net/InetAddress:getHostAddress	()Ljava/lang/String;
    //   1181: astore 24
    //   1183: aload 17
    //   1185: ifnull +826 -> 2011
    //   1188: iload_1
    //   1189: istore_2
    //   1190: iload_1
    //   1191: istore_3
    //   1192: iload_1
    //   1193: istore 4
    //   1195: aload 17
    //   1197: invokestatic 475	com/estrongs/android/util/ap:I	(Ljava/lang/String;)I
    //   1200: ifne +498 -> 1698
    //   1203: goto +808 -> 2011
    //   1206: iload_1
    //   1207: istore_2
    //   1208: iload_1
    //   1209: istore_3
    //   1210: iload_1
    //   1211: istore 4
    //   1213: invokestatic 478	com/estrongs/android/util/bk:p	()Z
    //   1216: ifeq +18 -> 1234
    //   1219: iload_1
    //   1220: istore_2
    //   1221: iload_1
    //   1222: istore_3
    //   1223: iload_1
    //   1224: istore 4
    //   1226: aload 24
    //   1228: invokestatic 480	com/estrongs/android/g/f:e	(Ljava/lang/String;)Z
    //   1231: ifne +20 -> 1251
    //   1234: iload_1
    //   1235: istore_2
    //   1236: iload_1
    //   1237: istore_3
    //   1238: iload_1
    //   1239: istore 4
    //   1241: aload 24
    //   1243: aload 15
    //   1245: invokestatic 483	com/estrongs/android/g/f:a	(Ljava/lang/String;Ljava/lang/String;)Z
    //   1248: ifeq +444 -> 1692
    //   1251: iload_1
    //   1252: istore_2
    //   1253: iload_1
    //   1254: istore_3
    //   1255: iload_1
    //   1256: istore 4
    //   1258: aload_0
    //   1259: getfield 14	com/estrongs/android/g/h:a	Lcom/estrongs/android/g/f;
    //   1262: aload 16
    //   1264: aload 22
    //   1266: aload 20
    //   1268: aload 19
    //   1270: aload 21
    //   1272: invokevirtual 486	com/estrongs/android/g/f:a	(Ljava/lang/String;Ljava/lang/String;Ljava/util/Properties;Ljava/util/Properties;Ljava/util/Properties;)Lcom/estrongs/android/g/j;
    //   1275: astore 15
    //   1277: aload 15
    //   1279: ifnonnull +483 -> 1762
    //   1282: iload_1
    //   1283: istore_2
    //   1284: iload_1
    //   1285: istore_3
    //   1286: iload_1
    //   1287: istore 4
    //   1289: aload_0
    //   1290: ldc -76
    //   1292: ldc_w 488
    //   1295: invokespecial 48	com/estrongs/android/g/h:a	(Ljava/lang/String;Ljava/lang/String;)V
    //   1298: iload_1
    //   1299: istore_2
    //   1300: iload_1
    //   1301: istore_3
    //   1302: iload_1
    //   1303: istore 4
    //   1305: aload 23
    //   1307: invokevirtual 489	java/io/BufferedReader:close	()V
    //   1310: iload_1
    //   1311: istore_2
    //   1312: iload_1
    //   1313: istore_3
    //   1314: iload_1
    //   1315: istore 4
    //   1317: aload 18
    //   1319: invokevirtual 223	java/io/InputStream:close	()V
    //   1322: iload_1
    //   1323: ifeq +664 -> 1987
    //   1326: aload_0
    //   1327: getfield 14	com/estrongs/android/g/h:a	Lcom/estrongs/android/g/f;
    //   1330: invokestatic 377	com/estrongs/android/g/f:c	(Lcom/estrongs/android/g/f;)Ljava/lang/Object;
    //   1333: astore 15
    //   1335: aload 15
    //   1337: monitorenter
    //   1338: aload_0
    //   1339: getfield 14	com/estrongs/android/g/h:a	Lcom/estrongs/android/g/f;
    //   1342: invokestatic 381	com/estrongs/android/g/f:g	(Lcom/estrongs/android/g/f;)I
    //   1345: pop
    //   1346: aload_0
    //   1347: getfield 14	com/estrongs/android/g/h:a	Lcom/estrongs/android/g/f;
    //   1350: invokestatic 384	com/estrongs/android/g/f:h	(Lcom/estrongs/android/g/f;)I
    //   1353: ifne +39 -> 1392
    //   1356: aload_0
    //   1357: getfield 14	com/estrongs/android/g/h:a	Lcom/estrongs/android/g/f;
    //   1360: new 386	com/estrongs/android/g/i
    //   1363: dup
    //   1364: aload_0
    //   1365: invokespecial 389	com/estrongs/android/g/i:<init>	(Lcom/estrongs/android/g/h;)V
    //   1368: invokestatic 392	com/estrongs/android/g/f:a	(Lcom/estrongs/android/g/f;Ljava/util/TimerTask;)Ljava/util/TimerTask;
    //   1371: pop
    //   1372: aload_0
    //   1373: getfield 14	com/estrongs/android/g/h:a	Lcom/estrongs/android/g/f;
    //   1376: invokestatic 396	com/estrongs/android/g/f:i	(Lcom/estrongs/android/g/f;)Ljava/util/Timer;
    //   1379: aload_0
    //   1380: getfield 14	com/estrongs/android/g/h:a	Lcom/estrongs/android/g/f;
    //   1383: invokestatic 400	com/estrongs/android/g/f:f	(Lcom/estrongs/android/g/f;)Ljava/util/TimerTask;
    //   1386: ldc2_w 401
    //   1389: invokevirtual 408	java/util/Timer:schedule	(Ljava/util/TimerTask;J)V
    //   1392: aload 15
    //   1394: monitorexit
    //   1395: return
    //   1396: astore 16
    //   1398: aload 15
    //   1400: monitorexit
    //   1401: aload 16
    //   1403: athrow
    //   1404: ldc 51
    //   1406: astore 15
    //   1408: iload 5
    //   1410: istore_3
    //   1411: iload 6
    //   1413: istore 4
    //   1415: iload 8
    //   1417: istore_2
    //   1418: sipush 512
    //   1421: newarray <illegal type>
    //   1423: astore 17
    //   1425: iload 5
    //   1427: istore_3
    //   1428: iload 6
    //   1430: istore 4
    //   1432: iload 8
    //   1434: istore_2
    //   1435: aload 23
    //   1437: aload 17
    //   1439: invokevirtual 492	java/io/BufferedReader:read	([C)I
    //   1442: istore_1
    //   1443: iload_1
    //   1444: iflt +81 -> 1525
    //   1447: iload 5
    //   1449: istore_3
    //   1450: iload 6
    //   1452: istore 4
    //   1454: iload 8
    //   1456: istore_2
    //   1457: aload 15
    //   1459: ldc -8
    //   1461: invokevirtual 495	java/lang/String:endsWith	(Ljava/lang/String;)Z
    //   1464: ifne +61 -> 1525
    //   1467: iload 5
    //   1469: istore_3
    //   1470: iload 6
    //   1472: istore 4
    //   1474: iload 8
    //   1476: istore_2
    //   1477: new 93	java/lang/StringBuilder
    //   1480: dup
    //   1481: invokespecial 94	java/lang/StringBuilder:<init>	()V
    //   1484: aload 15
    //   1486: invokevirtual 100	java/lang/StringBuilder:append	(Ljava/lang/String;)Ljava/lang/StringBuilder;
    //   1489: aload 17
    //   1491: iconst_0
    //   1492: iload_1
    //   1493: invokestatic 499	java/lang/String:valueOf	([CII)Ljava/lang/String;
    //   1496: invokevirtual 100	java/lang/StringBuilder:append	(Ljava/lang/String;)Ljava/lang/StringBuilder;
    //   1499: invokevirtual 106	java/lang/StringBuilder:toString	()Ljava/lang/String;
    //   1502: astore 15
    //   1504: iload 5
    //   1506: istore_3
    //   1507: iload 6
    //   1509: istore 4
    //   1511: iload 8
    //   1513: istore_2
    //   1514: aload 23
    //   1516: aload 17
    //   1518: invokevirtual 492	java/io/BufferedReader:read	([C)I
    //   1521: istore_1
    //   1522: goto -79 -> 1443
    //   1525: iload 5
    //   1527: istore_3
    //   1528: iload 6
    //   1530: istore 4
    //   1532: iload 8
    //   1534: istore_2
    //   1535: aload_0
    //   1536: aload 15
    //   1538: invokevirtual 173	java/lang/String:trim	()Ljava/lang/String;
    //   1541: aload 19
    //   1543: invokespecial 168	com/estrongs/android/g/h:a	(Ljava/lang/String;Ljava/util/Properties;)V
    //   1546: goto -532 -> 1014
    //   1549: astore 15
    //   1551: iload 4
    //   1553: ifeq +434 -> 1987
    //   1556: aload_0
    //   1557: getfield 14	com/estrongs/android/g/h:a	Lcom/estrongs/android/g/f;
    //   1560: invokestatic 377	com/estrongs/android/g/f:c	(Lcom/estrongs/android/g/f;)Ljava/lang/Object;
    //   1563: astore 15
    //   1565: aload 15
    //   1567: monitorenter
    //   1568: aload_0
    //   1569: getfield 14	com/estrongs/android/g/h:a	Lcom/estrongs/android/g/f;
    //   1572: invokestatic 381	com/estrongs/android/g/f:g	(Lcom/estrongs/android/g/f;)I
    //   1575: pop
    //   1576: aload_0
    //   1577: getfield 14	com/estrongs/android/g/h:a	Lcom/estrongs/android/g/f;
    //   1580: invokestatic 384	com/estrongs/android/g/f:h	(Lcom/estrongs/android/g/f;)I
    //   1583: ifne +39 -> 1622
    //   1586: aload_0
    //   1587: getfield 14	com/estrongs/android/g/h:a	Lcom/estrongs/android/g/f;
    //   1590: new 386	com/estrongs/android/g/i
    //   1593: dup
    //   1594: aload_0
    //   1595: invokespecial 389	com/estrongs/android/g/i:<init>	(Lcom/estrongs/android/g/h;)V
    //   1598: invokestatic 392	com/estrongs/android/g/f:a	(Lcom/estrongs/android/g/f;Ljava/util/TimerTask;)Ljava/util/TimerTask;
    //   1601: pop
    //   1602: aload_0
    //   1603: getfield 14	com/estrongs/android/g/h:a	Lcom/estrongs/android/g/f;
    //   1606: invokestatic 396	com/estrongs/android/g/f:i	(Lcom/estrongs/android/g/f;)Ljava/util/Timer;
    //   1609: aload_0
    //   1610: getfield 14	com/estrongs/android/g/h:a	Lcom/estrongs/android/g/f;
    //   1613: invokestatic 400	com/estrongs/android/g/f:f	(Lcom/estrongs/android/g/f;)Ljava/util/TimerTask;
    //   1616: ldc2_w 401
    //   1619: invokevirtual 408	java/util/Timer:schedule	(Ljava/util/TimerTask;J)V
    //   1622: aload 15
    //   1624: monitorexit
    //   1625: return
    //   1626: astore 16
    //   1628: aload 15
    //   1630: monitorexit
    //   1631: aload 16
    //   1633: athrow
    //   1634: iload 4
    //   1636: istore_2
    //   1637: aload_0
    //   1638: getfield 14	com/estrongs/android/g/h:a	Lcom/estrongs/android/g/f;
    //   1641: new 501	com/estrongs/android/ui/notification/d
    //   1644: dup
    //   1645: invokestatic 506	com/estrongs/android/pop/FexApplication:a	()Lcom/estrongs/android/pop/FexApplication;
    //   1648: invokespecial 509	com/estrongs/android/ui/notification/d:<init>	(Landroid/content/Context;)V
    //   1651: invokestatic 512	com/estrongs/android/g/f:a	(Lcom/estrongs/android/g/f;Lcom/estrongs/android/ui/notification/d;)Lcom/estrongs/android/ui/notification/d;
    //   1654: pop
    //   1655: iload_3
    //   1656: istore_1
    //   1657: goto -498 -> 1159
    //   1660: iload_1
    //   1661: istore_2
    //   1662: aload 24
    //   1664: monitorexit
    //   1665: iload_1
    //   1666: istore_2
    //   1667: iload_1
    //   1668: istore_3
    //   1669: iload_1
    //   1670: istore 4
    //   1672: aload 15
    //   1674: athrow
    //   1675: astore 15
    //   1677: iload_1
    //   1678: istore_3
    //   1679: iload_1
    //   1680: istore 4
    //   1682: iload_1
    //   1683: istore_2
    //   1684: aload 15
    //   1686: invokevirtual 515	java/lang/Exception:printStackTrace	()V
    //   1689: goto -525 -> 1164
    //   1692: aconst_null
    //   1693: astore 15
    //   1695: goto -418 -> 1277
    //   1698: iload_1
    //   1699: istore_2
    //   1700: iload_1
    //   1701: istore_3
    //   1702: iload_1
    //   1703: istore 4
    //   1705: ldc_w 517
    //   1708: aload 24
    //   1710: invokevirtual 521	java/lang/String:equals	(Ljava/lang/Object;)Z
    //   1713: ifne +20 -> 1733
    //   1716: iload_1
    //   1717: istore_2
    //   1718: iload_1
    //   1719: istore_3
    //   1720: iload_1
    //   1721: istore 4
    //   1723: aload 24
    //   1725: aload 17
    //   1727: invokestatic 483	com/estrongs/android/g/f:a	(Ljava/lang/String;Ljava/lang/String;)Z
    //   1730: ifeq +300 -> 2030
    //   1733: iload_1
    //   1734: istore_2
    //   1735: iload_1
    //   1736: istore_3
    //   1737: iload_1
    //   1738: istore 4
    //   1740: aload_0
    //   1741: getfield 14	com/estrongs/android/g/h:a	Lcom/estrongs/android/g/f;
    //   1744: aload 16
    //   1746: aload 22
    //   1748: aload 20
    //   1750: aload 19
    //   1752: aload 21
    //   1754: invokevirtual 486	com/estrongs/android/g/f:a	(Ljava/lang/String;Ljava/lang/String;Ljava/util/Properties;Ljava/util/Properties;Ljava/util/Properties;)Lcom/estrongs/android/g/j;
    //   1757: astore 15
    //   1759: goto -482 -> 1277
    //   1762: iload_1
    //   1763: istore_2
    //   1764: iload_1
    //   1765: istore_3
    //   1766: iload_1
    //   1767: istore 4
    //   1769: aload_0
    //   1770: aload 15
    //   1772: getfield 526	com/estrongs/android/g/j:a	Ljava/lang/String;
    //   1775: aload 15
    //   1777: getfield 528	com/estrongs/android/g/j:b	Ljava/lang/String;
    //   1780: aload 15
    //   1782: getfield 531	com/estrongs/android/g/j:d	Ljava/util/Properties;
    //   1785: aload 15
    //   1787: getfield 534	com/estrongs/android/g/j:c	Ljava/io/InputStream;
    //   1790: invokespecial 197	com/estrongs/android/g/h:a	(Ljava/lang/String;Ljava/lang/String;Ljava/util/Properties;Ljava/io/InputStream;)V
    //   1793: goto -495 -> 1298
    //   1796: astore 15
    //   1798: iload_2
    //   1799: istore_3
    //   1800: goto -1260 -> 540
    //   1803: astore 16
    //   1805: aload 16
    //   1807: invokevirtual 515	java/lang/Exception:printStackTrace	()V
    //   1810: goto -418 -> 1392
    //   1813: astore 16
    //   1815: aload 16
    //   1817: invokevirtual 515	java/lang/Exception:printStackTrace	()V
    //   1820: goto -1179 -> 641
    //   1823: astore 16
    //   1825: aload 16
    //   1827: invokevirtual 515	java/lang/Exception:printStackTrace	()V
    //   1830: goto -208 -> 1622
    //   1833: astore 15
    //   1835: iload_2
    //   1836: ifeq +72 -> 1908
    //   1839: aload_0
    //   1840: getfield 14	com/estrongs/android/g/h:a	Lcom/estrongs/android/g/f;
    //   1843: invokestatic 377	com/estrongs/android/g/f:c	(Lcom/estrongs/android/g/f;)Ljava/lang/Object;
    //   1846: astore 16
    //   1848: aload 16
    //   1850: monitorenter
    //   1851: aload_0
    //   1852: getfield 14	com/estrongs/android/g/h:a	Lcom/estrongs/android/g/f;
    //   1855: invokestatic 381	com/estrongs/android/g/f:g	(Lcom/estrongs/android/g/f;)I
    //   1858: pop
    //   1859: aload_0
    //   1860: getfield 14	com/estrongs/android/g/h:a	Lcom/estrongs/android/g/f;
    //   1863: invokestatic 384	com/estrongs/android/g/f:h	(Lcom/estrongs/android/g/f;)I
    //   1866: ifne +39 -> 1905
    //   1869: aload_0
    //   1870: getfield 14	com/estrongs/android/g/h:a	Lcom/estrongs/android/g/f;
    //   1873: new 386	com/estrongs/android/g/i
    //   1876: dup
    //   1877: aload_0
    //   1878: invokespecial 389	com/estrongs/android/g/i:<init>	(Lcom/estrongs/android/g/h;)V
    //   1881: invokestatic 392	com/estrongs/android/g/f:a	(Lcom/estrongs/android/g/f;Ljava/util/TimerTask;)Ljava/util/TimerTask;
    //   1884: pop
    //   1885: aload_0
    //   1886: getfield 14	com/estrongs/android/g/h:a	Lcom/estrongs/android/g/f;
    //   1889: invokestatic 396	com/estrongs/android/g/f:i	(Lcom/estrongs/android/g/f;)Ljava/util/Timer;
    //   1892: aload_0
    //   1893: getfield 14	com/estrongs/android/g/h:a	Lcom/estrongs/android/g/f;
    //   1896: invokestatic 400	com/estrongs/android/g/f:f	(Lcom/estrongs/android/g/f;)Ljava/util/TimerTask;
    //   1899: ldc2_w 401
    //   1902: invokevirtual 408	java/util/Timer:schedule	(Ljava/util/TimerTask;J)V
    //   1905: aload 16
    //   1907: monitorexit
    //   1908: aload 15
    //   1910: athrow
    //   1911: astore 17
    //   1913: aload 17
    //   1915: invokevirtual 515	java/lang/Exception:printStackTrace	()V
    //   1918: goto -13 -> 1905
    //   1921: astore 15
    //   1923: aload 16
    //   1925: monitorexit
    //   1926: aload 15
    //   1928: athrow
    //   1929: astore 17
    //   1931: lload 11
    //   1933: lstore 13
    //   1935: goto -1625 -> 310
    //   1938: astore 15
    //   1940: iload_3
    //   1941: istore_2
    //   1942: goto -107 -> 1835
    //   1945: astore 15
    //   1947: goto -396 -> 1551
    //   1950: astore 15
    //   1952: goto -1381 -> 571
    //   1955: astore 15
    //   1957: iload 7
    //   1959: istore_1
    //   1960: goto -283 -> 1677
    //   1963: astore 15
    //   1965: iconst_0
    //   1966: istore_1
    //   1967: goto -307 -> 1660
    //   1970: aload 17
    //   1972: astore 15
    //   1974: goto -768 -> 1206
    //   1977: iconst_0
    //   1978: istore_1
    //   1979: goto -820 -> 1159
    //   1982: iconst_0
    //   1983: istore_1
    //   1984: goto -1608 -> 376
    //   1987: return
    //   1988: iload 10
    //   1990: iload 9
    //   1992: if_icmpge -1332 -> 660
    //   1995: lload 13
    //   1997: iload 9
    //   1999: iload 10
    //   2001: isub
    //   2002: iconst_1
    //   2003: iadd
    //   2004: i2l
    //   2005: lsub
    //   2006: lstore 11
    //   2008: goto -1574 -> 434
    //   2011: aload 17
    //   2013: ifnonnull -43 -> 1970
    //   2016: aload 16
    //   2018: astore 15
    //   2020: goto -814 -> 1206
    //   2023: astore 15
    //   2025: iload_2
    //   2026: istore_1
    //   2027: goto -367 -> 1660
    //   2030: aconst_null
    //   2031: astore 15
    //   2033: goto -756 -> 1277
    // Local variable table:
    //   start	length	slot	name	signature
    //   0	2036	0	this	h
    //   305	1722	1	i	int
    //   21	2005	2	j	int
    //   14	1927	3	k	int
    //   17	1751	4	m	int
    //   10	1516	5	n	int
    //   1	1528	6	i1	int
    //   4	1954	7	i2	int
    //   7	1526	8	i3	int
    //   75	1927	9	i4	int
    //   379	1623	10	i5	int
    //   259	1748	11	l1	long
    //   283	1713	13	l2	long
    //   52	469	15	arrayOfByte	byte[]
    //   538	20	15	localIOException1	IOException
    //   1549	1	15	localInterruptedException1	InterruptedException
    //   1675	10	15	localException1	Exception
    //   1693	93	15	localj	j
    //   1796	1	15	localIOException2	IOException
    //   1833	76	15	localObject3	Object
    //   1921	6	15	localObject4	Object
    //   1938	1	15	localObject5	Object
    //   1945	1	15	localInterruptedException2	InterruptedException
    //   1950	1	15	localThrowable	Throwable
    //   1955	1	15	localException2	Exception
    //   1963	1	15	localObject6	Object
    //   1972	47	15	localObject7	Object
    //   2023	1	15	localObject8	Object
    //   2031	1	15	localObject9	Object
    //   137	118	16	localObject10	Object
    //   645	618	16	str1	String
    //   1396	6	16	localObject11	Object
    //   1626	119	16	str2	String
    //   1803	3	16	localException3	Exception
    //   1813	3	16	localException4	Exception
    //   1823	3	16	localException5	Exception
    //   118	1608	17	localObject13	Object
    //   1911	3	17	localException6	Exception
    //   1929	83	17	localNumberFormatException	NumberFormatException
    //   29	1289	18	localInputStream	java.io.InputStream
    //   156	1595	19	localProperties1	Properties
    //   175	1574	20	localProperties2	Properties
    //   194	1559	21	localProperties3	Properties
    //   235	1512	22	str3	String
    //   398	1117	23	localObject14	Object
    //   811	913	24	localObject15	Object
    // Exception table:
    //   from	to	target	type
    //   22	31	538	java/io/IOException
    //   47	54	538	java/io/IOException
    //   64	77	538	java/io/IOException
    //   92	120	538	java/io/IOException
    //   130	139	538	java/io/IOException
    //   149	158	538	java/io/IOException
    //   168	177	538	java/io/IOException
    //   187	196	538	java/io/IOException
    //   206	218	538	java/io/IOException
    //   228	237	538	java/io/IOException
    //   247	256	538	java/io/IOException
    //   271	281	538	java/io/IOException
    //   300	306	538	java/io/IOException
    //   391	400	538	java/io/IOException
    //   417	431	538	java/io/IOException
    //   444	451	538	java/io/IOException
    //   475	488	538	java/io/IOException
    //   518	528	538	java/io/IOException
    //   693	700	538	java/io/IOException
    //   710	723	538	java/io/IOException
    //   733	758	538	java/io/IOException
    //   768	779	538	java/io/IOException
    //   793	813	538	java/io/IOException
    //   823	831	538	java/io/IOException
    //   841	848	538	java/io/IOException
    //   858	869	538	java/io/IOException
    //   879	887	538	java/io/IOException
    //   897	906	538	java/io/IOException
    //   916	933	538	java/io/IOException
    //   943	952	538	java/io/IOException
    //   962	971	538	java/io/IOException
    //   981	987	538	java/io/IOException
    //   997	1014	538	java/io/IOException
    //   1024	1031	538	java/io/IOException
    //   1041	1050	538	java/io/IOException
    //   1060	1063	538	java/io/IOException
    //   1418	1425	538	java/io/IOException
    //   1435	1443	538	java/io/IOException
    //   1457	1467	538	java/io/IOException
    //   1477	1504	538	java/io/IOException
    //   1514	1522	538	java/io/IOException
    //   1535	1546	538	java/io/IOException
    //   1684	1689	538	java/io/IOException
    //   587	641	645	finally
    //   641	644	645	finally
    //   647	650	645	finally
    //   1815	1820	645	finally
    //   1338	1392	1396	finally
    //   1392	1395	1396	finally
    //   1398	1401	1396	finally
    //   1805	1810	1396	finally
    //   22	31	1549	java/lang/InterruptedException
    //   47	54	1549	java/lang/InterruptedException
    //   64	77	1549	java/lang/InterruptedException
    //   92	120	1549	java/lang/InterruptedException
    //   130	139	1549	java/lang/InterruptedException
    //   149	158	1549	java/lang/InterruptedException
    //   168	177	1549	java/lang/InterruptedException
    //   187	196	1549	java/lang/InterruptedException
    //   206	218	1549	java/lang/InterruptedException
    //   228	237	1549	java/lang/InterruptedException
    //   247	256	1549	java/lang/InterruptedException
    //   271	281	1549	java/lang/InterruptedException
    //   300	306	1549	java/lang/InterruptedException
    //   391	400	1549	java/lang/InterruptedException
    //   417	431	1549	java/lang/InterruptedException
    //   444	451	1549	java/lang/InterruptedException
    //   475	488	1549	java/lang/InterruptedException
    //   518	528	1549	java/lang/InterruptedException
    //   693	700	1549	java/lang/InterruptedException
    //   710	723	1549	java/lang/InterruptedException
    //   733	758	1549	java/lang/InterruptedException
    //   768	779	1549	java/lang/InterruptedException
    //   793	813	1549	java/lang/InterruptedException
    //   823	831	1549	java/lang/InterruptedException
    //   841	848	1549	java/lang/InterruptedException
    //   858	869	1549	java/lang/InterruptedException
    //   879	887	1549	java/lang/InterruptedException
    //   897	906	1549	java/lang/InterruptedException
    //   916	933	1549	java/lang/InterruptedException
    //   943	952	1549	java/lang/InterruptedException
    //   962	971	1549	java/lang/InterruptedException
    //   981	987	1549	java/lang/InterruptedException
    //   997	1014	1549	java/lang/InterruptedException
    //   1024	1031	1549	java/lang/InterruptedException
    //   1041	1050	1549	java/lang/InterruptedException
    //   1060	1063	1549	java/lang/InterruptedException
    //   1418	1425	1549	java/lang/InterruptedException
    //   1435	1443	1549	java/lang/InterruptedException
    //   1457	1467	1549	java/lang/InterruptedException
    //   1477	1504	1549	java/lang/InterruptedException
    //   1514	1522	1549	java/lang/InterruptedException
    //   1535	1546	1549	java/lang/InterruptedException
    //   1684	1689	1549	java/lang/InterruptedException
    //   1568	1622	1626	finally
    //   1622	1625	1626	finally
    //   1628	1631	1626	finally
    //   1825	1830	1626	finally
    //   1672	1675	1675	java/lang/Exception
    //   1171	1183	1796	java/io/IOException
    //   1195	1203	1796	java/io/IOException
    //   1213	1219	1796	java/io/IOException
    //   1226	1234	1796	java/io/IOException
    //   1241	1251	1796	java/io/IOException
    //   1258	1277	1796	java/io/IOException
    //   1289	1298	1796	java/io/IOException
    //   1305	1310	1796	java/io/IOException
    //   1317	1322	1796	java/io/IOException
    //   1672	1675	1796	java/io/IOException
    //   1705	1716	1796	java/io/IOException
    //   1723	1733	1796	java/io/IOException
    //   1740	1759	1796	java/io/IOException
    //   1769	1793	1796	java/io/IOException
    //   1338	1392	1803	java/lang/Exception
    //   587	641	1813	java/lang/Exception
    //   1568	1622	1823	java/lang/Exception
    //   22	31	1833	finally
    //   47	54	1833	finally
    //   64	77	1833	finally
    //   92	120	1833	finally
    //   130	139	1833	finally
    //   149	158	1833	finally
    //   168	177	1833	finally
    //   187	196	1833	finally
    //   206	218	1833	finally
    //   228	237	1833	finally
    //   247	256	1833	finally
    //   271	281	1833	finally
    //   300	306	1833	finally
    //   391	400	1833	finally
    //   417	431	1833	finally
    //   444	451	1833	finally
    //   475	488	1833	finally
    //   518	528	1833	finally
    //   542	571	1833	finally
    //   693	700	1833	finally
    //   710	723	1833	finally
    //   733	758	1833	finally
    //   768	779	1833	finally
    //   793	813	1833	finally
    //   823	831	1833	finally
    //   841	848	1833	finally
    //   858	869	1833	finally
    //   879	887	1833	finally
    //   897	906	1833	finally
    //   916	933	1833	finally
    //   943	952	1833	finally
    //   962	971	1833	finally
    //   981	987	1833	finally
    //   997	1014	1833	finally
    //   1024	1031	1833	finally
    //   1041	1050	1833	finally
    //   1060	1063	1833	finally
    //   1418	1425	1833	finally
    //   1435	1443	1833	finally
    //   1457	1467	1833	finally
    //   1477	1504	1833	finally
    //   1514	1522	1833	finally
    //   1535	1546	1833	finally
    //   1684	1689	1833	finally
    //   1851	1905	1911	java/lang/Exception
    //   1851	1905	1921	finally
    //   1905	1908	1921	finally
    //   1913	1918	1921	finally
    //   1923	1926	1921	finally
    //   300	306	1929	java/lang/NumberFormatException
    //   1171	1183	1938	finally
    //   1195	1203	1938	finally
    //   1213	1219	1938	finally
    //   1226	1234	1938	finally
    //   1241	1251	1938	finally
    //   1258	1277	1938	finally
    //   1289	1298	1938	finally
    //   1305	1310	1938	finally
    //   1317	1322	1938	finally
    //   1672	1675	1938	finally
    //   1705	1716	1938	finally
    //   1723	1733	1938	finally
    //   1740	1759	1938	finally
    //   1769	1793	1938	finally
    //   1171	1183	1945	java/lang/InterruptedException
    //   1195	1203	1945	java/lang/InterruptedException
    //   1213	1219	1945	java/lang/InterruptedException
    //   1226	1234	1945	java/lang/InterruptedException
    //   1241	1251	1945	java/lang/InterruptedException
    //   1258	1277	1945	java/lang/InterruptedException
    //   1289	1298	1945	java/lang/InterruptedException
    //   1305	1310	1945	java/lang/InterruptedException
    //   1317	1322	1945	java/lang/InterruptedException
    //   1672	1675	1945	java/lang/InterruptedException
    //   1705	1716	1945	java/lang/InterruptedException
    //   1723	1733	1945	java/lang/InterruptedException
    //   1740	1759	1945	java/lang/InterruptedException
    //   1769	1793	1945	java/lang/InterruptedException
    //   542	571	1950	java/lang/Throwable
    //   1041	1050	1955	java/lang/Exception
    //   1060	1063	1955	java/lang/Exception
    //   1068	1084	1963	finally
    //   1084	1098	1963	finally
    //   1106	1116	2023	finally
    //   1121	1131	2023	finally
    //   1134	1145	2023	finally
    //   1148	1157	2023	finally
    //   1161	1164	2023	finally
    //   1637	1655	2023	finally
    //   1662	1665	2023	finally
  }
}

/* Location:
 * Qualified Name:     com.estrongs.android.g.h
 * Java Class Version: 6 (50.0)
 * JD-Core Version:    0.7.1
 */