package com.estrongs.fs.impl.pcs;

import com.estrongs.android.pop.netfs.utils.FastPipedInputStream;
import com.estrongs.android.pop.netfs.utils.UploadOutputStream;

class d
  extends Thread
{
  d(PcsFileSystem paramPcsFileSystem, long paramLong, FastPipedInputStream paramFastPipedInputStream, String paramString1, String paramString2, String paramString3, UploadOutputStream paramUploadOutputStream, boolean paramBoolean1, boolean paramBoolean2, String paramString4, String paramString5, String paramString6, String paramString7) {}
  
  /* Error */
  public void run()
  {
    // Byte code:
    //   0: aload_0
    //   1: getfield 29	com/estrongs/fs/impl/pcs/d:a	J
    //   4: lconst_0
    //   5: lcmp
    //   6: ifne +311 -> 317
    //   9: lconst_1
    //   10: lstore_2
    //   11: iconst_1
    //   12: istore 6
    //   14: new 60	java/util/ArrayList
    //   17: dup
    //   18: invokespecial 61	java/util/ArrayList:<init>	()V
    //   21: astore 9
    //   23: aload_0
    //   24: getfield 29	com/estrongs/fs/impl/pcs/d:a	J
    //   27: getstatic 66	com/estrongs/fs/impl/pcs/PcsFileSystem:a	I
    //   30: i2l
    //   31: lcmp
    //   32: ifle +302 -> 334
    //   35: aload_0
    //   36: getfield 31	com/estrongs/fs/impl/pcs/d:b	Lcom/estrongs/android/pop/netfs/utils/FastPipedInputStream;
    //   39: astore 8
    //   41: aload_0
    //   42: getfield 33	com/estrongs/fs/impl/pcs/d:c	Ljava/lang/String;
    //   45: astore 10
    //   47: aload_0
    //   48: getfield 29	com/estrongs/fs/impl/pcs/d:a	J
    //   51: lconst_0
    //   52: lcmp
    //   53: ifne +272 -> 325
    //   56: lconst_1
    //   57: lstore 4
    //   59: new 68	com/estrongs/android/pop/netfs/utils/LengthStreamBody
    //   62: dup
    //   63: aload 8
    //   65: aload 10
    //   67: lload 4
    //   69: getstatic 66	com/estrongs/fs/impl/pcs/PcsFileSystem:a	I
    //   72: i2l
    //   73: invokespecial 71	com/estrongs/android/pop/netfs/utils/LengthStreamBody:<init>	(Ljava/io/InputStream;Ljava/lang/String;JJ)V
    //   76: astore 8
    //   78: lload_2
    //   79: lconst_0
    //   80: lcmp
    //   81: ifle +611 -> 692
    //   84: invokestatic 74	com/estrongs/fs/impl/pcs/PcsFileSystem:a	()Lorg/apache/http/client/HttpClient;
    //   87: astore 10
    //   89: new 76	org/apache/http/client/methods/HttpPost
    //   92: dup
    //   93: aload_0
    //   94: getfield 35	com/estrongs/fs/impl/pcs/d:d	Ljava/lang/String;
    //   97: invokespecial 79	org/apache/http/client/methods/HttpPost:<init>	(Ljava/lang/String;)V
    //   100: astore 11
    //   102: aload_0
    //   103: getfield 37	com/estrongs/fs/impl/pcs/d:e	Ljava/lang/String;
    //   106: ldc 81
    //   108: invokevirtual 87	java/lang/String:startsWith	(Ljava/lang/String;)Z
    //   111: ifeq +39 -> 150
    //   114: aload 11
    //   116: ldc 89
    //   118: new 91	java/lang/StringBuilder
    //   121: dup
    //   122: invokespecial 92	java/lang/StringBuilder:<init>	()V
    //   125: ldc 94
    //   127: invokevirtual 98	java/lang/StringBuilder:append	(Ljava/lang/String;)Ljava/lang/StringBuilder;
    //   130: aload_0
    //   131: getfield 27	com/estrongs/fs/impl/pcs/d:m	Lcom/estrongs/fs/impl/pcs/PcsFileSystem;
    //   134: aload_0
    //   135: getfield 37	com/estrongs/fs/impl/pcs/d:e	Ljava/lang/String;
    //   138: invokestatic 101	com/estrongs/fs/impl/pcs/PcsFileSystem:a	(Lcom/estrongs/fs/impl/pcs/PcsFileSystem;Ljava/lang/String;)Ljava/lang/String;
    //   141: invokevirtual 98	java/lang/StringBuilder:append	(Ljava/lang/String;)Ljava/lang/StringBuilder;
    //   144: invokevirtual 105	java/lang/StringBuilder:toString	()Ljava/lang/String;
    //   147: invokevirtual 109	org/apache/http/client/methods/HttpPost:addHeader	(Ljava/lang/String;Ljava/lang/String;)V
    //   150: new 111	org/apache/http/entity/mime/MultipartEntity
    //   153: dup
    //   154: getstatic 117	org/apache/http/entity/mime/HttpMultipartMode:STRICT	Lorg/apache/http/entity/mime/HttpMultipartMode;
    //   157: aconst_null
    //   158: aconst_null
    //   159: invokespecial 120	org/apache/http/entity/mime/MultipartEntity:<init>	(Lorg/apache/http/entity/mime/HttpMultipartMode;Ljava/lang/String;Ljava/nio/charset/Charset;)V
    //   162: astore 12
    //   164: aload 12
    //   166: ldc 122
    //   168: aload 8
    //   170: invokevirtual 126	org/apache/http/entity/mime/MultipartEntity:addPart	(Ljava/lang/String;Lorg/apache/http/entity/mime/content/ContentBody;)V
    //   173: aload 11
    //   175: aload 12
    //   177: invokevirtual 130	org/apache/http/client/methods/HttpPost:setEntity	(Lorg/apache/http/HttpEntity;)V
    //   180: aload 10
    //   182: aload 11
    //   184: invokeinterface 136 2 0
    //   189: astore 10
    //   191: aload 10
    //   193: invokestatic 142	com/estrongs/android/pop/netfs/utils/HttpUtils:parseAsJSON	(Lorg/apache/http/HttpResponse;)Ljava/util/Map;
    //   196: astore 11
    //   198: aload_0
    //   199: getfield 27	com/estrongs/fs/impl/pcs/d:m	Lcom/estrongs/fs/impl/pcs/PcsFileSystem;
    //   202: aload 11
    //   204: ldc -112
    //   206: invokestatic 147	com/estrongs/fs/impl/pcs/PcsFileSystem:a	(Lcom/estrongs/fs/impl/pcs/PcsFileSystem;Ljava/util/Map;Ljava/lang/String;)Z
    //   209: istore 7
    //   211: iload 7
    //   213: ifne +252 -> 465
    //   216: iconst_0
    //   217: istore 6
    //   219: lload_2
    //   220: lconst_0
    //   221: lcmp
    //   222: ifle +6 -> 228
    //   225: iconst_0
    //   226: istore 6
    //   228: iload 6
    //   230: ifeq +459 -> 689
    //   233: aload_0
    //   234: getfield 27	com/estrongs/fs/impl/pcs/d:m	Lcom/estrongs/fs/impl/pcs/PcsFileSystem;
    //   237: aload_0
    //   238: getfield 33	com/estrongs/fs/impl/pcs/d:c	Ljava/lang/String;
    //   241: aload_0
    //   242: getfield 37	com/estrongs/fs/impl/pcs/d:e	Ljava/lang/String;
    //   245: aload_0
    //   246: getfield 29	com/estrongs/fs/impl/pcs/d:a	J
    //   249: aload 9
    //   251: invokestatic 150	com/estrongs/fs/impl/pcs/PcsFileSystem:a	(Lcom/estrongs/fs/impl/pcs/PcsFileSystem;Ljava/lang/String;Ljava/lang/String;JLjava/util/List;)Ljava/lang/String;
    //   254: astore 8
    //   256: aload 8
    //   258: ifnonnull +431 -> 689
    //   261: iconst_0
    //   262: istore 6
    //   264: iload 6
    //   266: istore 7
    //   268: aload_0
    //   269: getfield 39	com/estrongs/fs/impl/pcs/d:f	Lcom/estrongs/android/pop/netfs/utils/UploadOutputStream;
    //   272: iload 6
    //   274: invokevirtual 156	com/estrongs/android/pop/netfs/utils/UploadOutputStream:setResult	(Z)V
    //   277: aload_0
    //   278: getfield 41	com/estrongs/fs/impl/pcs/d:g	Z
    //   281: ifeq +35 -> 316
    //   284: aload_0
    //   285: getfield 43	com/estrongs/fs/impl/pcs/d:h	Z
    //   288: ifeq +28 -> 316
    //   291: iload 6
    //   293: ifeq +238 -> 531
    //   296: aload_0
    //   297: getfield 27	com/estrongs/fs/impl/pcs/d:m	Lcom/estrongs/fs/impl/pcs/PcsFileSystem;
    //   300: aload_0
    //   301: getfield 45	com/estrongs/fs/impl/pcs/d:i	Ljava/lang/String;
    //   304: aload_0
    //   305: getfield 47	com/estrongs/fs/impl/pcs/d:j	Ljava/lang/String;
    //   308: aload_0
    //   309: getfield 49	com/estrongs/fs/impl/pcs/d:k	Ljava/lang/String;
    //   312: invokevirtual 160	com/estrongs/fs/impl/pcs/PcsFileSystem:deleteFile	(Ljava/lang/String;Ljava/lang/String;Ljava/lang/String;)Z
    //   315: pop
    //   316: return
    //   317: aload_0
    //   318: getfield 29	com/estrongs/fs/impl/pcs/d:a	J
    //   321: lstore_2
    //   322: goto -311 -> 11
    //   325: aload_0
    //   326: getfield 29	com/estrongs/fs/impl/pcs/d:a	J
    //   329: lstore 4
    //   331: goto -272 -> 59
    //   334: aload_0
    //   335: getfield 31	com/estrongs/fs/impl/pcs/d:b	Lcom/estrongs/android/pop/netfs/utils/FastPipedInputStream;
    //   338: astore 8
    //   340: aload_0
    //   341: getfield 33	com/estrongs/fs/impl/pcs/d:c	Ljava/lang/String;
    //   344: astore 10
    //   346: aload_0
    //   347: getfield 29	com/estrongs/fs/impl/pcs/d:a	J
    //   350: lconst_0
    //   351: lcmp
    //   352: ifne +104 -> 456
    //   355: lconst_1
    //   356: lstore 4
    //   358: new 68	com/estrongs/android/pop/netfs/utils/LengthStreamBody
    //   361: dup
    //   362: aload 8
    //   364: aload 10
    //   366: lload 4
    //   368: invokespecial 163	com/estrongs/android/pop/netfs/utils/LengthStreamBody:<init>	(Ljava/io/InputStream;Ljava/lang/String;J)V
    //   371: astore 8
    //   373: goto -295 -> 78
    //   376: astore 8
    //   378: iconst_1
    //   379: istore 6
    //   381: iload 6
    //   383: istore 7
    //   385: aload 8
    //   387: invokevirtual 166	java/lang/Exception:printStackTrace	()V
    //   390: iload 6
    //   392: istore 7
    //   394: aload_0
    //   395: getfield 39	com/estrongs/fs/impl/pcs/d:f	Lcom/estrongs/android/pop/netfs/utils/UploadOutputStream;
    //   398: iconst_0
    //   399: invokevirtual 156	com/estrongs/android/pop/netfs/utils/UploadOutputStream:setResult	(Z)V
    //   402: iload 6
    //   404: istore 7
    //   406: aload_0
    //   407: getfield 31	com/estrongs/fs/impl/pcs/d:b	Lcom/estrongs/android/pop/netfs/utils/FastPipedInputStream;
    //   410: invokevirtual 171	com/estrongs/android/pop/netfs/utils/FastPipedInputStream:close	()V
    //   413: aload_0
    //   414: getfield 41	com/estrongs/fs/impl/pcs/d:g	Z
    //   417: ifeq -101 -> 316
    //   420: aload_0
    //   421: getfield 43	com/estrongs/fs/impl/pcs/d:h	Z
    //   424: ifeq -108 -> 316
    //   427: iload 6
    //   429: ifeq +130 -> 559
    //   432: aload_0
    //   433: getfield 27	com/estrongs/fs/impl/pcs/d:m	Lcom/estrongs/fs/impl/pcs/PcsFileSystem;
    //   436: aload_0
    //   437: getfield 45	com/estrongs/fs/impl/pcs/d:i	Ljava/lang/String;
    //   440: aload_0
    //   441: getfield 47	com/estrongs/fs/impl/pcs/d:j	Ljava/lang/String;
    //   444: aload_0
    //   445: getfield 49	com/estrongs/fs/impl/pcs/d:k	Ljava/lang/String;
    //   448: invokevirtual 160	com/estrongs/fs/impl/pcs/PcsFileSystem:deleteFile	(Ljava/lang/String;Ljava/lang/String;Ljava/lang/String;)Z
    //   451: pop
    //   452: return
    //   453: astore 8
    //   455: return
    //   456: aload_0
    //   457: getfield 29	com/estrongs/fs/impl/pcs/d:a	J
    //   460: lstore 4
    //   462: goto -104 -> 358
    //   465: aload 11
    //   467: ldc -83
    //   469: invokeinterface 179 2 0
    //   474: astore 11
    //   476: aload 11
    //   478: ifnonnull +9 -> 487
    //   481: iconst_0
    //   482: istore 6
    //   484: goto -265 -> 219
    //   487: aload 9
    //   489: aload 11
    //   491: checkcast 83	java/lang/String
    //   494: invokevirtual 183	java/util/ArrayList:add	(Ljava/lang/Object;)Z
    //   497: pop
    //   498: aload 10
    //   500: invokeinterface 189 1 0
    //   505: astore 10
    //   507: aload 10
    //   509: ifnull +10 -> 519
    //   512: aload 10
    //   514: invokeinterface 194 1 0
    //   519: getstatic 66	com/estrongs/fs/impl/pcs/PcsFileSystem:a	I
    //   522: istore_1
    //   523: lload_2
    //   524: iload_1
    //   525: i2l
    //   526: lsub
    //   527: lstore_2
    //   528: goto -450 -> 78
    //   531: aload_0
    //   532: getfield 27	com/estrongs/fs/impl/pcs/d:m	Lcom/estrongs/fs/impl/pcs/PcsFileSystem;
    //   535: aload_0
    //   536: getfield 45	com/estrongs/fs/impl/pcs/d:i	Ljava/lang/String;
    //   539: aload_0
    //   540: getfield 47	com/estrongs/fs/impl/pcs/d:j	Ljava/lang/String;
    //   543: aload_0
    //   544: getfield 49	com/estrongs/fs/impl/pcs/d:k	Ljava/lang/String;
    //   547: aload_0
    //   548: getfield 51	com/estrongs/fs/impl/pcs/d:l	Ljava/lang/String;
    //   551: invokevirtual 198	com/estrongs/fs/impl/pcs/PcsFileSystem:renameFile	(Ljava/lang/String;Ljava/lang/String;Ljava/lang/String;Ljava/lang/String;)Z
    //   554: pop
    //   555: return
    //   556: astore 8
    //   558: return
    //   559: aload_0
    //   560: getfield 27	com/estrongs/fs/impl/pcs/d:m	Lcom/estrongs/fs/impl/pcs/PcsFileSystem;
    //   563: aload_0
    //   564: getfield 45	com/estrongs/fs/impl/pcs/d:i	Ljava/lang/String;
    //   567: aload_0
    //   568: getfield 47	com/estrongs/fs/impl/pcs/d:j	Ljava/lang/String;
    //   571: aload_0
    //   572: getfield 49	com/estrongs/fs/impl/pcs/d:k	Ljava/lang/String;
    //   575: aload_0
    //   576: getfield 51	com/estrongs/fs/impl/pcs/d:l	Ljava/lang/String;
    //   579: invokevirtual 198	com/estrongs/fs/impl/pcs/PcsFileSystem:renameFile	(Ljava/lang/String;Ljava/lang/String;Ljava/lang/String;Ljava/lang/String;)Z
    //   582: pop
    //   583: return
    //   584: astore 8
    //   586: aload_0
    //   587: getfield 41	com/estrongs/fs/impl/pcs/d:g	Z
    //   590: ifeq +35 -> 625
    //   593: aload_0
    //   594: getfield 43	com/estrongs/fs/impl/pcs/d:h	Z
    //   597: ifeq +28 -> 625
    //   600: iload 6
    //   602: ifeq +26 -> 628
    //   605: aload_0
    //   606: getfield 27	com/estrongs/fs/impl/pcs/d:m	Lcom/estrongs/fs/impl/pcs/PcsFileSystem;
    //   609: aload_0
    //   610: getfield 45	com/estrongs/fs/impl/pcs/d:i	Ljava/lang/String;
    //   613: aload_0
    //   614: getfield 47	com/estrongs/fs/impl/pcs/d:j	Ljava/lang/String;
    //   617: aload_0
    //   618: getfield 49	com/estrongs/fs/impl/pcs/d:k	Ljava/lang/String;
    //   621: invokevirtual 160	com/estrongs/fs/impl/pcs/PcsFileSystem:deleteFile	(Ljava/lang/String;Ljava/lang/String;Ljava/lang/String;)Z
    //   624: pop
    //   625: aload 8
    //   627: athrow
    //   628: aload_0
    //   629: getfield 27	com/estrongs/fs/impl/pcs/d:m	Lcom/estrongs/fs/impl/pcs/PcsFileSystem;
    //   632: aload_0
    //   633: getfield 45	com/estrongs/fs/impl/pcs/d:i	Ljava/lang/String;
    //   636: aload_0
    //   637: getfield 47	com/estrongs/fs/impl/pcs/d:j	Ljava/lang/String;
    //   640: aload_0
    //   641: getfield 49	com/estrongs/fs/impl/pcs/d:k	Ljava/lang/String;
    //   644: aload_0
    //   645: getfield 51	com/estrongs/fs/impl/pcs/d:l	Ljava/lang/String;
    //   648: invokevirtual 198	com/estrongs/fs/impl/pcs/PcsFileSystem:renameFile	(Ljava/lang/String;Ljava/lang/String;Ljava/lang/String;Ljava/lang/String;)Z
    //   651: pop
    //   652: goto -27 -> 625
    //   655: astore 9
    //   657: goto -32 -> 625
    //   660: astore 8
    //   662: goto -76 -> 586
    //   665: astore 8
    //   667: iload 7
    //   669: istore 6
    //   671: goto -85 -> 586
    //   674: astore 8
    //   676: goto -263 -> 413
    //   679: astore 8
    //   681: goto -300 -> 381
    //   684: astore 8
    //   686: goto -305 -> 381
    //   689: goto -425 -> 264
    //   692: iconst_1
    //   693: istore 6
    //   695: goto -476 -> 219
    // Local variable table:
    //   start	length	slot	name	signature
    //   0	698	0	this	d
    //   522	3	1	n	int
    //   10	518	2	l1	long
    //   57	404	4	l2	long
    //   12	682	6	bool1	boolean
    //   209	459	7	bool2	boolean
    //   39	333	8	localObject1	Object
    //   376	10	8	localException1	Exception
    //   453	1	8	localException2	Exception
    //   556	1	8	localException3	Exception
    //   584	42	8	localObject2	Object
    //   660	1	8	localObject3	Object
    //   665	1	8	localObject4	Object
    //   674	1	8	localException4	Exception
    //   679	1	8	localException5	Exception
    //   684	1	8	localException6	Exception
    //   21	467	9	localArrayList	java.util.ArrayList
    //   655	1	9	localException7	Exception
    //   45	468	10	localObject5	Object
    //   100	390	11	localObject6	Object
    //   162	14	12	localMultipartEntity	org.apache.http.entity.mime.MultipartEntity
    // Exception table:
    //   from	to	target	type
    //   14	56	376	java/lang/Exception
    //   59	78	376	java/lang/Exception
    //   84	150	376	java/lang/Exception
    //   150	211	376	java/lang/Exception
    //   325	331	376	java/lang/Exception
    //   334	355	376	java/lang/Exception
    //   358	373	376	java/lang/Exception
    //   456	462	376	java/lang/Exception
    //   465	476	376	java/lang/Exception
    //   487	507	376	java/lang/Exception
    //   512	519	376	java/lang/Exception
    //   519	523	376	java/lang/Exception
    //   413	427	453	java/lang/Exception
    //   432	452	453	java/lang/Exception
    //   559	583	453	java/lang/Exception
    //   277	291	556	java/lang/Exception
    //   296	316	556	java/lang/Exception
    //   531	555	556	java/lang/Exception
    //   14	56	584	finally
    //   59	78	584	finally
    //   84	150	584	finally
    //   150	211	584	finally
    //   325	331	584	finally
    //   334	355	584	finally
    //   358	373	584	finally
    //   456	462	584	finally
    //   465	476	584	finally
    //   487	507	584	finally
    //   512	519	584	finally
    //   519	523	584	finally
    //   586	600	655	java/lang/Exception
    //   605	625	655	java/lang/Exception
    //   628	652	655	java/lang/Exception
    //   233	256	660	finally
    //   268	277	665	finally
    //   385	390	665	finally
    //   394	402	665	finally
    //   406	413	665	finally
    //   385	390	674	java/lang/Exception
    //   394	402	674	java/lang/Exception
    //   406	413	674	java/lang/Exception
    //   233	256	679	java/lang/Exception
    //   268	277	684	java/lang/Exception
  }
}

/* Location:
 * Qualified Name:     com.estrongs.fs.impl.pcs.d
 * Java Class Version: 6 (50.0)
 * JD-Core Version:    0.7.1
 */