package com.dianxinos.library.notify.network;

class q
  implements Runnable
{
  q(o paramo) {}
  
  /* Error */
  public void run()
  {
    // Byte code:
    //   0: aload_0
    //   1: getfield 12	com/dianxinos/library/notify/network/q:a	Lcom/dianxinos/library/notify/network/o;
    //   4: aload_0
    //   5: getfield 12	com/dianxinos/library/notify/network/q:a	Lcom/dianxinos/library/notify/network/o;
    //   8: invokestatic 24	com/dianxinos/library/notify/network/o:a	(Lcom/dianxinos/library/notify/network/o;)Ljava/io/File;
    //   11: iconst_1
    //   12: iconst_1
    //   13: aload_0
    //   14: getfield 12	com/dianxinos/library/notify/network/q:a	Lcom/dianxinos/library/notify/network/o;
    //   17: invokestatic 28	com/dianxinos/library/notify/network/o:b	(Lcom/dianxinos/library/notify/network/o;)Lcom/dianxinos/library/notify/network/l;
    //   20: invokeinterface 34 1 0
    //   25: invokestatic 39	com/dianxinos/library/notify/network/d:a	(Ljava/io/File;IIJ)Lcom/dianxinos/library/notify/network/d;
    //   28: invokestatic 42	com/dianxinos/library/notify/network/o:a	(Lcom/dianxinos/library/notify/network/o;Lcom/dianxinos/library/notify/network/d;)Lcom/dianxinos/library/notify/network/d;
    //   31: pop
    //   32: new 44	java/lang/StringBuilder
    //   35: dup
    //   36: invokespecial 45	java/lang/StringBuilder:<init>	()V
    //   39: ldc 47
    //   41: invokevirtual 51	java/lang/StringBuilder:append	(Ljava/lang/String;)Ljava/lang/StringBuilder;
    //   44: aload_0
    //   45: getfield 12	com/dianxinos/library/notify/network/q:a	Lcom/dianxinos/library/notify/network/o;
    //   48: invokestatic 24	com/dianxinos/library/notify/network/o:a	(Lcom/dianxinos/library/notify/network/o;)Ljava/io/File;
    //   51: invokevirtual 54	java/lang/StringBuilder:append	(Ljava/lang/Object;)Ljava/lang/StringBuilder;
    //   54: invokevirtual 58	java/lang/StringBuilder:toString	()Ljava/lang/String;
    //   57: invokestatic 63	com/dianxinos/library/dxbase/j:a	(Ljava/lang/String;)V
    //   60: aload_0
    //   61: getfield 12	com/dianxinos/library/notify/network/q:a	Lcom/dianxinos/library/notify/network/o;
    //   64: invokestatic 24	com/dianxinos/library/notify/network/o:a	(Lcom/dianxinos/library/notify/network/o;)Ljava/io/File;
    //   67: astore_1
    //   68: aload_1
    //   69: monitorenter
    //   70: aload_0
    //   71: getfield 12	com/dianxinos/library/notify/network/q:a	Lcom/dianxinos/library/notify/network/o;
    //   74: invokestatic 24	com/dianxinos/library/notify/network/o:a	(Lcom/dianxinos/library/notify/network/o;)Ljava/io/File;
    //   77: invokevirtual 66	java/lang/Object:notifyAll	()V
    //   80: aload_1
    //   81: monitorexit
    //   82: return
    //   83: astore_1
    //   84: new 44	java/lang/StringBuilder
    //   87: dup
    //   88: invokespecial 45	java/lang/StringBuilder:<init>	()V
    //   91: ldc 68
    //   93: invokevirtual 51	java/lang/StringBuilder:append	(Ljava/lang/String;)Ljava/lang/StringBuilder;
    //   96: aload_0
    //   97: getfield 12	com/dianxinos/library/notify/network/q:a	Lcom/dianxinos/library/notify/network/o;
    //   100: invokestatic 24	com/dianxinos/library/notify/network/o:a	(Lcom/dianxinos/library/notify/network/o;)Ljava/io/File;
    //   103: invokevirtual 54	java/lang/StringBuilder:append	(Ljava/lang/Object;)Ljava/lang/StringBuilder;
    //   106: invokevirtual 58	java/lang/StringBuilder:toString	()Ljava/lang/String;
    //   109: invokestatic 71	com/dianxinos/library/dxbase/j:c	(Ljava/lang/String;)V
    //   112: aload_0
    //   113: getfield 12	com/dianxinos/library/notify/network/q:a	Lcom/dianxinos/library/notify/network/o;
    //   116: aconst_null
    //   117: invokestatic 42	com/dianxinos/library/notify/network/o:a	(Lcom/dianxinos/library/notify/network/o;Lcom/dianxinos/library/notify/network/d;)Lcom/dianxinos/library/notify/network/d;
    //   120: pop
    //   121: goto -61 -> 60
    //   124: astore_2
    //   125: aload_1
    //   126: monitorexit
    //   127: aload_2
    //   128: athrow
    // Local variable table:
    //   start	length	slot	name	signature
    //   0	129	0	this	q
    //   83	43	1	localIOException	java.io.IOException
    //   124	4	2	localObject	Object
    // Exception table:
    //   from	to	target	type
    //   0	60	83	java/io/IOException
    //   70	82	124	finally
    //   125	127	124	finally
  }
}

/* Location:
 * Qualified Name:     com.dianxinos.library.notify.network.q
 * Java Class Version: 6 (50.0)
 * JD-Core Version:    0.7.1
 */