package com.estrongs.android.view;

import android.view.View;

public class bj
  implements cn
{
  int a = 0;
  
  protected bj(ak paramak) {}
  
  public View a()
  {
    return null;
  }
  
  public bl a(View paramView)
  {
    return new bl(paramView);
  }
  
  /* Error */
  public void a(ci paramci, int paramInt)
  {
    // Byte code:
    //   0: aload_0
    //   1: getfield 14	com/estrongs/android/view/bj:b	Lcom/estrongs/android/view/ak;
    //   4: iload_2
    //   5: invokevirtual 36	com/estrongs/android/view/ak:e	(I)Ljava/lang/Object;
    //   8: checkcast 38	com/estrongs/fs/h
    //   11: astore 5
    //   13: aload 5
    //   15: ifnonnull +4 -> 19
    //   18: return
    //   19: aload_0
    //   20: getfield 14	com/estrongs/android/view/bj:b	Lcom/estrongs/android/view/ak;
    //   23: getfield 42	com/estrongs/android/view/ak:q	Z
    //   26: ifeq +11 -> 37
    //   29: aload 5
    //   31: invokestatic 45	com/estrongs/android/view/ak:a	(Lcom/estrongs/fs/h;)Z
    //   34: ifne -16 -> 18
    //   37: aload_1
    //   38: checkcast 24	com/estrongs/android/view/bl
    //   41: astore 4
    //   43: aload 4
    //   45: getfield 48	com/estrongs/android/view/bl:a	Landroid/widget/TextView;
    //   48: aload 5
    //   50: invokeinterface 52 1 0
    //   55: invokevirtual 58	android/widget/TextView:setText	(Ljava/lang/CharSequence;)V
    //   58: aload 5
    //   60: invokeinterface 62 1 0
    //   65: invokevirtual 67	com/estrongs/fs/w:a	()Z
    //   68: ifeq +954 -> 1022
    //   71: aload 4
    //   73: getfield 69	com/estrongs/android/view/bl:e	Landroid/widget/TextView;
    //   76: aload_0
    //   77: getfield 14	com/estrongs/android/view/bj:b	Lcom/estrongs/android/view/ak;
    //   80: ldc 70
    //   82: invokevirtual 74	com/estrongs/android/view/ak:j	(I)Ljava/lang/String;
    //   85: invokevirtual 58	android/widget/TextView:setText	(Ljava/lang/CharSequence;)V
    //   88: aload 4
    //   90: getfield 77	com/estrongs/android/view/bl:b	Landroid/widget/ImageView;
    //   93: instanceof 79
    //   96: ifeq +21 -> 117
    //   99: aload 4
    //   101: getfield 77	com/estrongs/android/view/bl:b	Landroid/widget/ImageView;
    //   104: checkcast 79	com/estrongs/android/pop/esclasses/ESImageView
    //   107: astore_1
    //   108: aload_1
    //   109: aconst_null
    //   110: invokevirtual 83	com/estrongs/android/pop/esclasses/ESImageView:setTopCornerImage	(Landroid/graphics/drawable/Drawable;)V
    //   113: aload_1
    //   114: invokevirtual 86	com/estrongs/android/pop/esclasses/ESImageView:invalidate	()V
    //   117: aload_0
    //   118: getfield 14	com/estrongs/android/view/bj:b	Lcom/estrongs/android/view/ak;
    //   121: getfield 90	com/estrongs/android/view/ak:C	Ljava/lang/String;
    //   124: invokestatic 96	com/estrongs/android/util/ap:ac	(Ljava/lang/String;)Z
    //   127: ifeq +932 -> 1059
    //   130: aload 4
    //   132: getfield 99	com/estrongs/android/view/bl:f	Landroid/widget/TextView;
    //   135: aload_0
    //   136: getfield 14	com/estrongs/android/view/bj:b	Lcom/estrongs/android/view/ak;
    //   139: getfield 102	com/estrongs/android/view/ak:e	Ljava/text/SimpleDateFormat;
    //   142: aload 5
    //   144: invokeinterface 106 1 0
    //   149: invokestatic 112	java/lang/Long:valueOf	(J)Ljava/lang/Long;
    //   152: invokevirtual 118	java/text/SimpleDateFormat:format	(Ljava/lang/Object;)Ljava/lang/String;
    //   155: invokevirtual 58	android/widget/TextView:setText	(Ljava/lang/CharSequence;)V
    //   158: aload 4
    //   160: getfield 122	com/estrongs/android/view/bl:c	Landroid/view/View;
    //   163: iconst_0
    //   164: invokevirtual 128	android/view/View:setVisibility	(I)V
    //   167: aload 4
    //   169: getfield 130	com/estrongs/android/view/bl:j	Landroid/widget/ImageView;
    //   172: aload 5
    //   174: invokevirtual 136	android/widget/ImageView:setTag	(Ljava/lang/Object;)V
    //   177: aload 5
    //   179: invokestatic 142	com/estrongs/android/h/f:g	(Lcom/estrongs/fs/h;)I
    //   182: istore_3
    //   183: aload 5
    //   185: invokestatic 144	com/estrongs/android/h/f:b	(Lcom/estrongs/fs/h;)Z
    //   188: ifeq +905 -> 1093
    //   191: aload 5
    //   193: invokeinterface 147 1 0
    //   198: aload 4
    //   200: getfield 130	com/estrongs/android/view/bl:j	Landroid/widget/ImageView;
    //   203: aload 5
    //   205: iload_3
    //   206: iconst_1
    //   207: invokestatic 152	com/estrongs/android/h/a/e:b	(Ljava/lang/String;Landroid/widget/ImageView;Lcom/estrongs/fs/h;IZ)V
    //   210: invokestatic 156	com/estrongs/android/view/ak:u	()Ljava/util/Map;
    //   213: aload 5
    //   215: invokeinterface 147 1 0
    //   220: invokeinterface 162 2 0
    //   225: checkcast 164	com/estrongs/android/pop/app/compress/bb
    //   228: astore_1
    //   229: aload_1
    //   230: ifnull +52 -> 282
    //   233: aload_1
    //   234: aload_0
    //   235: getfield 14	com/estrongs/android/view/bj:b	Lcom/estrongs/android/view/ak;
    //   238: invokestatic 167	com/estrongs/android/view/ak:e	(Lcom/estrongs/android/view/ak;)Lcom/estrongs/android/pop/app/compress/br;
    //   241: invokevirtual 170	com/estrongs/android/pop/app/compress/bb:a	(Lcom/estrongs/android/pop/app/compress/br;)V
    //   244: aload_0
    //   245: getfield 14	com/estrongs/android/view/bj:b	Lcom/estrongs/android/view/ak;
    //   248: aload_1
    //   249: aload 4
    //   251: getfield 174	com/estrongs/android/view/bl:d	Landroid/widget/ProgressBar;
    //   254: aload 4
    //   256: getfield 99	com/estrongs/android/view/bl:f	Landroid/widget/TextView;
    //   259: aload 4
    //   261: getfield 69	com/estrongs/android/view/bl:e	Landroid/widget/TextView;
    //   264: aload 4
    //   266: getfield 176	com/estrongs/android/view/bl:g	Landroid/widget/TextView;
    //   269: aload 4
    //   271: getfield 77	com/estrongs/android/view/bl:b	Landroid/widget/ImageView;
    //   274: aload 4
    //   276: getfield 179	com/estrongs/android/view/bl:h	Landroid/widget/TextView;
    //   279: invokestatic 182	com/estrongs/android/view/ak:a	(Lcom/estrongs/android/view/ak;Lcom/estrongs/android/pop/app/compress/bb;Landroid/widget/ProgressBar;Landroid/widget/TextView;Landroid/widget/TextView;Landroid/widget/TextView;Landroid/widget/ImageView;Landroid/widget/TextView;)V
    //   282: invokestatic 186	com/estrongs/android/view/ak:w	()Ljava/util/LinkedList;
    //   285: invokevirtual 192	java/util/LinkedList:size	()I
    //   288: ifle +121 -> 409
    //   291: invokestatic 186	com/estrongs/android/view/ak:w	()Ljava/util/LinkedList;
    //   294: invokevirtual 196	java/util/LinkedList:getFirst	()Ljava/lang/Object;
    //   297: checkcast 198	com/estrongs/android/pop/app/compress/ba
    //   300: astore 6
    //   302: aload 6
    //   304: getfield 200	com/estrongs/android/pop/app/compress/ba:a	Ljava/lang/String;
    //   307: invokestatic 204	com/estrongs/android/util/ap:bV	(Ljava/lang/String;)Ljava/lang/String;
    //   310: aload 5
    //   312: invokeinterface 147 1 0
    //   317: invokevirtual 210	java/lang/String:equals	(Ljava/lang/Object;)Z
    //   320: ifeq +89 -> 409
    //   323: new 164	com/estrongs/android/pop/app/compress/bb
    //   326: dup
    //   327: aload_0
    //   328: getfield 14	com/estrongs/android/view/bj:b	Lcom/estrongs/android/view/ak;
    //   331: getfield 214	com/estrongs/android/view/ak:ag	Landroid/app/Activity;
    //   334: invokespecial 217	com/estrongs/android/pop/app/compress/bb:<init>	(Landroid/content/Context;)V
    //   337: astore 7
    //   339: aload 7
    //   341: aload_0
    //   342: getfield 14	com/estrongs/android/view/bj:b	Lcom/estrongs/android/view/ak;
    //   345: invokestatic 167	com/estrongs/android/view/ak:e	(Lcom/estrongs/android/view/ak;)Lcom/estrongs/android/pop/app/compress/br;
    //   348: invokevirtual 170	com/estrongs/android/pop/app/compress/bb:a	(Lcom/estrongs/android/pop/app/compress/br;)V
    //   351: aload_0
    //   352: getfield 14	com/estrongs/android/view/bj:b	Lcom/estrongs/android/view/ak;
    //   355: aload 7
    //   357: aload 4
    //   359: getfield 174	com/estrongs/android/view/bl:d	Landroid/widget/ProgressBar;
    //   362: aload 4
    //   364: getfield 99	com/estrongs/android/view/bl:f	Landroid/widget/TextView;
    //   367: aload 4
    //   369: getfield 69	com/estrongs/android/view/bl:e	Landroid/widget/TextView;
    //   372: aload 4
    //   374: getfield 176	com/estrongs/android/view/bl:g	Landroid/widget/TextView;
    //   377: aload 4
    //   379: getfield 77	com/estrongs/android/view/bl:b	Landroid/widget/ImageView;
    //   382: aload 4
    //   384: getfield 179	com/estrongs/android/view/bl:h	Landroid/widget/TextView;
    //   387: invokestatic 182	com/estrongs/android/view/ak:a	(Lcom/estrongs/android/view/ak;Lcom/estrongs/android/pop/app/compress/bb;Landroid/widget/ProgressBar;Landroid/widget/TextView;Landroid/widget/TextView;Landroid/widget/TextView;Landroid/widget/ImageView;Landroid/widget/TextView;)V
    //   390: aload 7
    //   392: aload 6
    //   394: invokevirtual 220	com/estrongs/android/pop/app/compress/bb:a	(Lcom/estrongs/android/pop/app/compress/ba;)V
    //   397: aload 7
    //   399: invokevirtual 222	com/estrongs/android/pop/app/compress/bb:b	()V
    //   402: invokestatic 186	com/estrongs/android/view/ak:w	()Ljava/util/LinkedList;
    //   405: invokevirtual 225	java/util/LinkedList:removeFirst	()Ljava/lang/Object;
    //   408: pop
    //   409: invokestatic 228	com/estrongs/android/view/ak:v	()Ljava/util/Map;
    //   412: aload 5
    //   414: invokeinterface 147 1 0
    //   419: invokeinterface 162 2 0
    //   424: checkcast 230	com/estrongs/android/pop/app/compress/ax
    //   427: astore 6
    //   429: aload 6
    //   431: ifnull +76 -> 507
    //   434: aload 6
    //   436: aload 4
    //   438: getfield 174	com/estrongs/android/view/bl:d	Landroid/widget/ProgressBar;
    //   441: invokevirtual 233	com/estrongs/android/pop/app/compress/ax:a	(Landroid/widget/ProgressBar;)V
    //   444: aload 6
    //   446: aload 4
    //   448: getfield 99	com/estrongs/android/view/bl:f	Landroid/widget/TextView;
    //   451: invokevirtual 236	com/estrongs/android/pop/app/compress/ax:b	(Landroid/widget/TextView;)V
    //   454: aload 6
    //   456: aload 4
    //   458: getfield 69	com/estrongs/android/view/bl:e	Landroid/widget/TextView;
    //   461: invokevirtual 238	com/estrongs/android/pop/app/compress/ax:c	(Landroid/widget/TextView;)V
    //   464: aload 6
    //   466: aload 4
    //   468: getfield 176	com/estrongs/android/view/bl:g	Landroid/widget/TextView;
    //   471: invokevirtual 240	com/estrongs/android/pop/app/compress/ax:d	(Landroid/widget/TextView;)V
    //   474: aload 6
    //   476: aload 4
    //   478: getfield 77	com/estrongs/android/view/bl:b	Landroid/widget/ImageView;
    //   481: invokevirtual 243	com/estrongs/android/pop/app/compress/ax:a	(Landroid/widget/ImageView;)V
    //   484: aload 6
    //   486: aload 4
    //   488: getfield 179	com/estrongs/android/view/bl:h	Landroid/widget/TextView;
    //   491: invokevirtual 245	com/estrongs/android/pop/app/compress/ax:a	(Landroid/widget/TextView;)V
    //   494: aload 6
    //   496: invokevirtual 247	com/estrongs/android/pop/app/compress/ax:b	()Z
    //   499: ifne +8 -> 507
    //   502: aload 6
    //   504: invokevirtual 249	com/estrongs/android/pop/app/compress/ax:c	()V
    //   507: aload_1
    //   508: ifnonnull +74 -> 582
    //   511: aload 6
    //   513: ifnonnull +69 -> 582
    //   516: aload 4
    //   518: getfield 174	com/estrongs/android/view/bl:d	Landroid/widget/ProgressBar;
    //   521: bipush 8
    //   523: invokevirtual 252	android/widget/ProgressBar:setVisibility	(I)V
    //   526: aload 4
    //   528: getfield 99	com/estrongs/android/view/bl:f	Landroid/widget/TextView;
    //   531: iconst_0
    //   532: invokevirtual 253	android/widget/TextView:setVisibility	(I)V
    //   535: aload 4
    //   537: getfield 69	com/estrongs/android/view/bl:e	Landroid/widget/TextView;
    //   540: iconst_0
    //   541: invokevirtual 253	android/widget/TextView:setVisibility	(I)V
    //   544: aload 4
    //   546: getfield 176	com/estrongs/android/view/bl:g	Landroid/widget/TextView;
    //   549: bipush 8
    //   551: invokevirtual 253	android/widget/TextView:setVisibility	(I)V
    //   554: aload 4
    //   556: getfield 77	com/estrongs/android/view/bl:b	Landroid/widget/ImageView;
    //   559: ldc -2
    //   561: invokevirtual 257	android/widget/ImageView:setImageResource	(I)V
    //   564: aload 4
    //   566: getfield 179	com/estrongs/android/view/bl:h	Landroid/widget/TextView;
    //   569: aload_0
    //   570: getfield 14	com/estrongs/android/view/bj:b	Lcom/estrongs/android/view/ak;
    //   573: ldc_w 258
    //   576: invokevirtual 74	com/estrongs/android/view/ak:j	(I)Ljava/lang/String;
    //   579: invokevirtual 58	android/widget/TextView:setText	(Ljava/lang/CharSequence;)V
    //   582: aload 5
    //   584: invokeinterface 147 1 0
    //   589: invokestatic 263	com/estrongs/android/pop/app/compress/a/d:a	(Ljava/lang/String;)Lcom/estrongs/android/pop/app/compress/a/e;
    //   592: astore 7
    //   594: aload 7
    //   596: ifnull +529 -> 1125
    //   599: aload 7
    //   601: getfield 267	com/estrongs/android/pop/app/compress/a/e:d	Z
    //   604: ifeq +521 -> 1125
    //   607: aload 7
    //   609: getfield 269	com/estrongs/android/pop/app/compress/a/e:c	Ljava/lang/String;
    //   612: ifnull +513 -> 1125
    //   615: new 271	java/io/File
    //   618: dup
    //   619: aload 7
    //   621: getfield 269	com/estrongs/android/pop/app/compress/a/e:c	Ljava/lang/String;
    //   624: invokespecial 274	java/io/File:<init>	(Ljava/lang/String;)V
    //   627: invokevirtual 277	java/io/File:exists	()Z
    //   630: ifeq +495 -> 1125
    //   633: aload 4
    //   635: getfield 77	com/estrongs/android/view/bl:b	Landroid/widget/ImageView;
    //   638: ldc_w 278
    //   641: invokevirtual 257	android/widget/ImageView:setImageResource	(I)V
    //   644: aload 4
    //   646: getfield 179	com/estrongs/android/view/bl:h	Landroid/widget/TextView;
    //   649: aload_0
    //   650: getfield 14	com/estrongs/android/view/bj:b	Lcom/estrongs/android/view/ak;
    //   653: ldc_w 279
    //   656: invokevirtual 74	com/estrongs/android/view/ak:j	(I)Ljava/lang/String;
    //   659: invokevirtual 58	android/widget/TextView:setText	(Ljava/lang/CharSequence;)V
    //   662: aload 4
    //   664: getfield 77	com/estrongs/android/view/bl:b	Landroid/widget/ImageView;
    //   667: instanceof 79
    //   670: ifeq +59 -> 729
    //   673: aload 4
    //   675: getfield 77	com/estrongs/android/view/bl:b	Landroid/widget/ImageView;
    //   678: checkcast 79	com/estrongs/android/pop/esclasses/ESImageView
    //   681: astore_1
    //   682: invokestatic 284	com/estrongs/android/pop/utils/aa:a	()Lcom/estrongs/android/pop/utils/aa;
    //   685: aload 5
    //   687: invokeinterface 147 1 0
    //   692: invokevirtual 286	com/estrongs/android/pop/utils/aa:b	(Ljava/lang/String;)Ljava/lang/String;
    //   695: ifnull +422 -> 1117
    //   698: aload_1
    //   699: invokevirtual 290	com/estrongs/android/pop/esclasses/ESImageView:getLeftCornorImage	()Landroid/graphics/drawable/Drawable;
    //   702: ifnonnull +415 -> 1117
    //   705: aload_1
    //   706: aload_0
    //   707: getfield 14	com/estrongs/android/view/bj:b	Lcom/estrongs/android/view/ak;
    //   710: getfield 214	com/estrongs/android/view/ak:ag	Landroid/app/Activity;
    //   713: invokevirtual 296	android/app/Activity:getResources	()Landroid/content/res/Resources;
    //   716: ldc_w 297
    //   719: invokevirtual 303	android/content/res/Resources:getDrawable	(I)Landroid/graphics/drawable/Drawable;
    //   722: invokevirtual 83	com/estrongs/android/pop/esclasses/ESImageView:setTopCornerImage	(Landroid/graphics/drawable/Drawable;)V
    //   725: aload_1
    //   726: invokevirtual 86	com/estrongs/android/pop/esclasses/ESImageView:invalidate	()V
    //   729: aload 4
    //   731: getfield 122	com/estrongs/android/view/bl:c	Landroid/view/View;
    //   734: new 305	com/estrongs/android/view/bk
    //   737: dup
    //   738: aload_0
    //   739: aload 5
    //   741: aload 4
    //   743: invokespecial 308	com/estrongs/android/view/bk:<init>	(Lcom/estrongs/android/view/bj;Lcom/estrongs/fs/h;Lcom/estrongs/android/view/bl;)V
    //   746: invokevirtual 312	android/view/View:setOnClickListener	(Landroid/view/View$OnClickListener;)V
    //   749: aload 4
    //   751: getfield 316	com/estrongs/android/view/bl:l	Landroid/widget/CheckBox;
    //   754: astore_1
    //   755: aload_0
    //   756: getfield 14	com/estrongs/android/view/bj:b	Lcom/estrongs/android/view/ak;
    //   759: getfield 42	com/estrongs/android/view/ak:q	Z
    //   762: ifeq +403 -> 1165
    //   765: iconst_0
    //   766: istore_3
    //   767: aload_1
    //   768: iload_3
    //   769: invokevirtual 319	android/widget/CheckBox:setVisibility	(I)V
    //   772: aload 4
    //   774: getfield 322	com/estrongs/android/view/bl:n	Landroid/widget/ImageView;
    //   777: ifnull +29 -> 806
    //   780: aload 4
    //   782: getfield 322	com/estrongs/android/view/bl:n	Landroid/widget/ImageView;
    //   785: astore 5
    //   787: aload_0
    //   788: getfield 14	com/estrongs/android/view/bj:b	Lcom/estrongs/android/view/ak;
    //   791: getfield 42	com/estrongs/android/view/ak:q	Z
    //   794: ifeq +377 -> 1171
    //   797: bipush 8
    //   799: istore_3
    //   800: aload 5
    //   802: iload_3
    //   803: invokevirtual 323	android/widget/ImageView:setVisibility	(I)V
    //   806: aload_0
    //   807: getfield 14	com/estrongs/android/view/bj:b	Lcom/estrongs/android/view/ak;
    //   810: getfield 42	com/estrongs/android/view/ak:q	Z
    //   813: ifeq +371 -> 1184
    //   816: aload_1
    //   817: iconst_0
    //   818: invokevirtual 319	android/widget/CheckBox:setVisibility	(I)V
    //   821: aload_0
    //   822: getfield 14	com/estrongs/android/view/bj:b	Lcom/estrongs/android/view/ak;
    //   825: iload_2
    //   826: invokevirtual 326	com/estrongs/android/view/ak:h	(I)Z
    //   829: ifeq +347 -> 1176
    //   832: aload_1
    //   833: iconst_1
    //   834: invokevirtual 330	android/widget/CheckBox:setChecked	(Z)V
    //   837: getstatic 334	com/estrongs/android/pop/z:v	Z
    //   840: ifne +171 -> 1011
    //   843: aload_0
    //   844: getfield 14	com/estrongs/android/view/bj:b	Lcom/estrongs/android/view/ak;
    //   847: getfield 42	com/estrongs/android/view/ak:q	Z
    //   850: ifeq +161 -> 1011
    //   853: new 336	android/graphics/Rect
    //   856: dup
    //   857: invokespecial 337	android/graphics/Rect:<init>	()V
    //   860: astore 5
    //   862: aload 4
    //   864: getfield 340	com/estrongs/android/view/bl:i	Landroid/view/View;
    //   867: aload 5
    //   869: invokevirtual 344	android/view/View:getHitRect	(Landroid/graphics/Rect;)V
    //   872: aload_0
    //   873: getfield 14	com/estrongs/android/view/bj:b	Lcom/estrongs/android/view/ak;
    //   876: iload_2
    //   877: invokevirtual 326	com/estrongs/android/view/ak:h	(I)Z
    //   880: ifeq +496 -> 1376
    //   883: iload_2
    //   884: ifne +309 -> 1193
    //   887: aload 5
    //   889: invokevirtual 347	android/graphics/Rect:isEmpty	()Z
    //   892: ifne +119 -> 1011
    //   895: aload_0
    //   896: getfield 14	com/estrongs/android/view/bj:b	Lcom/estrongs/android/view/ak;
    //   899: getfield 351	com/estrongs/android/view/ak:s	Ljava/util/Map;
    //   902: aload_0
    //   903: getfield 14	com/estrongs/android/view/bj:b	Lcom/estrongs/android/view/ak;
    //   906: iload_2
    //   907: invokevirtual 353	com/estrongs/android/view/ak:g	(I)Ljava/lang/String;
    //   910: invokeinterface 162 2 0
    //   915: checkcast 355	com/estrongs/android/ui/drag/j
    //   918: astore_1
    //   919: aload_1
    //   920: ifnonnull +491 -> 1411
    //   923: new 355	com/estrongs/android/ui/drag/j
    //   926: dup
    //   927: invokespecial 356	com/estrongs/android/ui/drag/j:<init>	()V
    //   930: astore_1
    //   931: aload_1
    //   932: iload_2
    //   933: invokevirtual 358	com/estrongs/android/ui/drag/j:a	(I)V
    //   936: aload_1
    //   937: aload 4
    //   939: getfield 340	com/estrongs/android/view/bl:i	Landroid/view/View;
    //   942: checkcast 360	com/estrongs/android/ui/drag/DragGrid
    //   945: invokevirtual 363	com/estrongs/android/ui/drag/j:a	(Lcom/estrongs/android/ui/drag/DragGrid;)V
    //   948: aload_0
    //   949: getfield 14	com/estrongs/android/view/bj:b	Lcom/estrongs/android/view/ak;
    //   952: getfield 351	com/estrongs/android/view/ak:s	Ljava/util/Map;
    //   955: aload_0
    //   956: getfield 14	com/estrongs/android/view/bj:b	Lcom/estrongs/android/view/ak;
    //   959: iload_2
    //   960: invokevirtual 353	com/estrongs/android/view/ak:g	(I)Ljava/lang/String;
    //   963: aload_1
    //   964: invokeinterface 367 3 0
    //   969: pop
    //   970: new 355	com/estrongs/android/ui/drag/j
    //   973: dup
    //   974: invokespecial 356	com/estrongs/android/ui/drag/j:<init>	()V
    //   977: astore 6
    //   979: aload 6
    //   981: iload_2
    //   982: invokevirtual 358	com/estrongs/android/ui/drag/j:a	(I)V
    //   985: aload 6
    //   987: aload 4
    //   989: getfield 340	com/estrongs/android/view/bl:i	Landroid/view/View;
    //   992: checkcast 360	com/estrongs/android/ui/drag/DragGrid
    //   995: invokevirtual 363	com/estrongs/android/ui/drag/j:a	(Lcom/estrongs/android/ui/drag/DragGrid;)V
    //   998: aload_1
    //   999: aload 5
    //   1001: aload 6
    //   1003: aload 4
    //   1005: getfield 340	com/estrongs/android/view/bl:i	Landroid/view/View;
    //   1008: invokevirtual 370	com/estrongs/android/ui/drag/j:a	(Landroid/graphics/Rect;Lcom/estrongs/android/ui/drag/j;Landroid/view/View;)V
    //   1011: aload_0
    //   1012: getfield 14	com/estrongs/android/view/bj:b	Lcom/estrongs/android/view/ak;
    //   1015: aload 4
    //   1017: iload_2
    //   1018: invokevirtual 372	com/estrongs/android/view/ak:b	(Lcom/estrongs/android/view/ci;I)V
    //   1021: return
    //   1022: aload 4
    //   1024: getfield 69	com/estrongs/android/view/bl:e	Landroid/widget/TextView;
    //   1027: aload 5
    //   1029: invokeinterface 375 1 0
    //   1034: invokestatic 380	com/estrongs/fs/util/j:c	(J)Ljava/lang/String;
    //   1037: invokevirtual 58	android/widget/TextView:setText	(Ljava/lang/CharSequence;)V
    //   1040: goto -952 -> 88
    //   1043: astore_1
    //   1044: aload_1
    //   1045: invokevirtual 383	java/lang/Exception:printStackTrace	()V
    //   1048: goto -931 -> 117
    //   1051: astore_1
    //   1052: aload_1
    //   1053: invokevirtual 383	java/lang/Exception:printStackTrace	()V
    //   1056: goto -898 -> 158
    //   1059: aload 4
    //   1061: getfield 99	com/estrongs/android/view/bl:f	Landroid/widget/TextView;
    //   1064: aload_0
    //   1065: getfield 14	com/estrongs/android/view/bj:b	Lcom/estrongs/android/view/ak;
    //   1068: getfield 214	com/estrongs/android/view/ak:ag	Landroid/app/Activity;
    //   1071: ldc_w 384
    //   1074: invokevirtual 387	android/app/Activity:getString	(I)Ljava/lang/String;
    //   1077: invokevirtual 58	android/widget/TextView:setText	(Ljava/lang/CharSequence;)V
    //   1080: aload 4
    //   1082: getfield 122	com/estrongs/android/view/bl:c	Landroid/view/View;
    //   1085: bipush 8
    //   1087: invokevirtual 128	android/view/View:setVisibility	(I)V
    //   1090: goto -923 -> 167
    //   1093: iload_3
    //   1094: aload 4
    //   1096: getfield 130	com/estrongs/android/view/bl:j	Landroid/widget/ImageView;
    //   1099: aload 5
    //   1101: invokestatic 390	com/estrongs/android/h/a/e:a	(ILandroid/widget/ImageView;Lcom/estrongs/fs/h;)V
    //   1104: goto -894 -> 210
    //   1107: astore 6
    //   1109: aload 6
    //   1111: invokevirtual 383	java/lang/Exception:printStackTrace	()V
    //   1114: goto -389 -> 725
    //   1117: aload_1
    //   1118: aconst_null
    //   1119: invokevirtual 83	com/estrongs/android/pop/esclasses/ESImageView:setTopCornerImage	(Landroid/graphics/drawable/Drawable;)V
    //   1122: goto -397 -> 725
    //   1125: aload 6
    //   1127: ifnonnull -398 -> 729
    //   1130: aload_1
    //   1131: ifnonnull -402 -> 729
    //   1134: aload 4
    //   1136: getfield 77	com/estrongs/android/view/bl:b	Landroid/widget/ImageView;
    //   1139: ldc -2
    //   1141: invokevirtual 257	android/widget/ImageView:setImageResource	(I)V
    //   1144: aload 4
    //   1146: getfield 179	com/estrongs/android/view/bl:h	Landroid/widget/TextView;
    //   1149: aload_0
    //   1150: getfield 14	com/estrongs/android/view/bj:b	Lcom/estrongs/android/view/ak;
    //   1153: ldc_w 258
    //   1156: invokevirtual 74	com/estrongs/android/view/ak:j	(I)Ljava/lang/String;
    //   1159: invokevirtual 58	android/widget/TextView:setText	(Ljava/lang/CharSequence;)V
    //   1162: goto -433 -> 729
    //   1165: bipush 8
    //   1167: istore_3
    //   1168: goto -401 -> 767
    //   1171: iconst_0
    //   1172: istore_3
    //   1173: goto -373 -> 800
    //   1176: aload_1
    //   1177: iconst_0
    //   1178: invokevirtual 330	android/widget/CheckBox:setChecked	(Z)V
    //   1181: goto -344 -> 837
    //   1184: aload_1
    //   1185: bipush 8
    //   1187: invokevirtual 319	android/widget/CheckBox:setVisibility	(I)V
    //   1190: goto -353 -> 837
    //   1193: aload_0
    //   1194: getfield 14	com/estrongs/android/view/bj:b	Lcom/estrongs/android/view/ak;
    //   1197: getfield 351	com/estrongs/android/view/ak:s	Ljava/util/Map;
    //   1200: aload_0
    //   1201: getfield 14	com/estrongs/android/view/bj:b	Lcom/estrongs/android/view/ak;
    //   1204: iload_2
    //   1205: invokevirtual 353	com/estrongs/android/view/ak:g	(I)Ljava/lang/String;
    //   1208: invokeinterface 162 2 0
    //   1213: checkcast 355	com/estrongs/android/ui/drag/j
    //   1216: astore_1
    //   1217: aload_1
    //   1218: ifnonnull +92 -> 1310
    //   1221: new 355	com/estrongs/android/ui/drag/j
    //   1224: dup
    //   1225: invokespecial 356	com/estrongs/android/ui/drag/j:<init>	()V
    //   1228: astore_1
    //   1229: aload_1
    //   1230: iload_2
    //   1231: invokevirtual 358	com/estrongs/android/ui/drag/j:a	(I)V
    //   1234: aload_1
    //   1235: aload 4
    //   1237: getfield 340	com/estrongs/android/view/bl:i	Landroid/view/View;
    //   1240: checkcast 360	com/estrongs/android/ui/drag/DragGrid
    //   1243: invokevirtual 363	com/estrongs/android/ui/drag/j:a	(Lcom/estrongs/android/ui/drag/DragGrid;)V
    //   1246: aload_1
    //   1247: invokevirtual 393	com/estrongs/android/ui/drag/j:b	()Lcom/estrongs/android/ui/drag/DragGrid;
    //   1250: invokevirtual 396	com/estrongs/android/ui/drag/DragGrid:getBackground	()Landroid/graphics/drawable/Drawable;
    //   1253: astore 5
    //   1255: aload_1
    //   1256: invokevirtual 393	com/estrongs/android/ui/drag/j:b	()Lcom/estrongs/android/ui/drag/DragGrid;
    //   1259: ldc_w 397
    //   1262: invokevirtual 400	com/estrongs/android/ui/drag/DragGrid:setBackgroundResource	(I)V
    //   1265: aload_1
    //   1266: aload_1
    //   1267: invokevirtual 393	com/estrongs/android/ui/drag/j:b	()Lcom/estrongs/android/ui/drag/DragGrid;
    //   1270: invokestatic 405	com/estrongs/android/ui/d/g:a	(Landroid/view/View;)Landroid/graphics/Bitmap;
    //   1273: invokevirtual 408	com/estrongs/android/ui/drag/j:a	(Landroid/graphics/Bitmap;)V
    //   1276: aload_1
    //   1277: invokevirtual 393	com/estrongs/android/ui/drag/j:b	()Lcom/estrongs/android/ui/drag/DragGrid;
    //   1280: aload 5
    //   1282: invokevirtual 411	com/estrongs/android/ui/drag/DragGrid:setBackgroundDrawable	(Landroid/graphics/drawable/Drawable;)V
    //   1285: aload_0
    //   1286: getfield 14	com/estrongs/android/view/bj:b	Lcom/estrongs/android/view/ak;
    //   1289: getfield 351	com/estrongs/android/view/ak:s	Ljava/util/Map;
    //   1292: aload_0
    //   1293: getfield 14	com/estrongs/android/view/bj:b	Lcom/estrongs/android/view/ak;
    //   1296: iload_2
    //   1297: invokevirtual 353	com/estrongs/android/view/ak:g	(I)Ljava/lang/String;
    //   1300: aload_1
    //   1301: invokeinterface 367 3 0
    //   1306: pop
    //   1307: goto -296 -> 1011
    //   1310: aload_1
    //   1311: iload_2
    //   1312: invokevirtual 358	com/estrongs/android/ui/drag/j:a	(I)V
    //   1315: aload_1
    //   1316: aload 4
    //   1318: getfield 340	com/estrongs/android/view/bl:i	Landroid/view/View;
    //   1321: checkcast 360	com/estrongs/android/ui/drag/DragGrid
    //   1324: invokevirtual 363	com/estrongs/android/ui/drag/j:a	(Lcom/estrongs/android/ui/drag/DragGrid;)V
    //   1327: aload_1
    //   1328: invokevirtual 414	com/estrongs/android/ui/drag/j:c	()Landroid/graphics/Bitmap;
    //   1331: ifnonnull -320 -> 1011
    //   1334: aload_1
    //   1335: invokevirtual 393	com/estrongs/android/ui/drag/j:b	()Lcom/estrongs/android/ui/drag/DragGrid;
    //   1338: invokevirtual 396	com/estrongs/android/ui/drag/DragGrid:getBackground	()Landroid/graphics/drawable/Drawable;
    //   1341: astore 5
    //   1343: aload_1
    //   1344: invokevirtual 393	com/estrongs/android/ui/drag/j:b	()Lcom/estrongs/android/ui/drag/DragGrid;
    //   1347: ldc_w 397
    //   1350: invokevirtual 400	com/estrongs/android/ui/drag/DragGrid:setBackgroundResource	(I)V
    //   1353: aload_1
    //   1354: aload_1
    //   1355: invokevirtual 393	com/estrongs/android/ui/drag/j:b	()Lcom/estrongs/android/ui/drag/DragGrid;
    //   1358: invokestatic 405	com/estrongs/android/ui/d/g:a	(Landroid/view/View;)Landroid/graphics/Bitmap;
    //   1361: invokevirtual 408	com/estrongs/android/ui/drag/j:a	(Landroid/graphics/Bitmap;)V
    //   1364: aload_1
    //   1365: invokevirtual 393	com/estrongs/android/ui/drag/j:b	()Lcom/estrongs/android/ui/drag/DragGrid;
    //   1368: aload 5
    //   1370: invokevirtual 411	com/estrongs/android/ui/drag/DragGrid:setBackgroundDrawable	(Landroid/graphics/drawable/Drawable;)V
    //   1373: goto -362 -> 1011
    //   1376: aload_0
    //   1377: getfield 14	com/estrongs/android/view/bj:b	Lcom/estrongs/android/view/ak;
    //   1380: getfield 351	com/estrongs/android/view/ak:s	Ljava/util/Map;
    //   1383: aload_0
    //   1384: getfield 14	com/estrongs/android/view/bj:b	Lcom/estrongs/android/view/ak;
    //   1387: iload_2
    //   1388: invokevirtual 36	com/estrongs/android/view/ak:e	(I)Ljava/lang/Object;
    //   1391: invokeinterface 417 2 0
    //   1396: checkcast 355	com/estrongs/android/ui/drag/j
    //   1399: astore_1
    //   1400: aload_1
    //   1401: ifnull -390 -> 1011
    //   1404: aload_1
    //   1405: invokevirtual 419	com/estrongs/android/ui/drag/j:e	()V
    //   1408: goto -397 -> 1011
    //   1411: goto -441 -> 970
    // Local variable table:
    //   start	length	slot	name	signature
    //   0	1414	0	this	bj
    //   0	1414	1	paramci	ci
    //   0	1414	2	paramInt	int
    //   182	991	3	i	int
    //   41	1276	4	localbl	bl
    //   11	1358	5	localObject1	Object
    //   300	702	6	localObject2	Object
    //   1107	19	6	localException	Exception
    //   337	283	7	localObject3	Object
    // Exception table:
    //   from	to	target	type
    //   99	117	1043	java/lang/Exception
    //   130	158	1051	java/lang/Exception
    //   705	725	1107	java/lang/Exception
  }
}

/* Location:
 * Qualified Name:     com.estrongs.android.view.bj
 * Java Class Version: 6 (50.0)
 * JD-Core Version:    0.7.1
 */