package com.estrongs.android.view;

import com.estrongs.a.a.p;

class di
  implements p
{
  di(cr paramcr, dp paramdp) {}
  
  /* Error */
  public void a(com.estrongs.a.a parama, int paramInt1, int paramInt2)
  {
    // Byte code:
    //   0: iconst_0
    //   1: istore 4
    //   3: aload_0
    //   4: getfield 14	com/estrongs/android/view/di:b	Lcom/estrongs/android/view/cr;
    //   7: getfield 29	com/estrongs/android/view/cr:W	Landroid/os/Handler;
    //   10: invokevirtual 35	android/os/Handler:getLooper	()Landroid/os/Looper;
    //   13: pop
    //   14: invokestatic 40	android/os/Looper:getMainLooper	()Landroid/os/Looper;
    //   17: invokevirtual 44	android/os/Looper:getThread	()Ljava/lang/Thread;
    //   20: astore 5
    //   22: invokestatic 49	java/lang/Thread:currentThread	()Ljava/lang/Thread;
    //   25: astore 6
    //   27: aload 5
    //   29: aload 6
    //   31: if_acmpne +6 -> 37
    //   34: iconst_1
    //   35: istore 4
    //   37: aload_1
    //   38: checkcast 51	com/estrongs/fs/b/al
    //   41: astore_1
    //   42: iload_2
    //   43: iconst_1
    //   44: if_icmpne +55 -> 99
    //   47: iload_3
    //   48: iconst_2
    //   49: if_icmpne +50 -> 99
    //   52: iload 4
    //   54: ifeq +11 -> 65
    //   57: aload_0
    //   58: getfield 14	com/estrongs/android/view/di:b	Lcom/estrongs/android/view/cr;
    //   61: invokestatic 54	com/estrongs/android/view/cr:b	(Lcom/estrongs/android/view/cr;)V
    //   64: return
    //   65: aload_0
    //   66: getfield 16	com/estrongs/android/view/di:a	Lcom/estrongs/android/view/dp;
    //   69: new 56	com/estrongs/android/view/dj
    //   72: dup
    //   73: aload_0
    //   74: invokespecial 59	com/estrongs/android/view/dj:<init>	(Lcom/estrongs/android/view/di;)V
    //   77: putfield 65	com/estrongs/android/view/dp:c	Ljava/lang/Runnable;
    //   80: aload_0
    //   81: getfield 14	com/estrongs/android/view/di:b	Lcom/estrongs/android/view/cr;
    //   84: getfield 29	com/estrongs/android/view/cr:W	Landroid/os/Handler;
    //   87: aload_0
    //   88: getfield 16	com/estrongs/android/view/di:a	Lcom/estrongs/android/view/dp;
    //   91: getfield 65	com/estrongs/android/view/dp:c	Ljava/lang/Runnable;
    //   94: invokevirtual 69	android/os/Handler:post	(Ljava/lang/Runnable;)Z
    //   97: pop
    //   98: return
    //   99: iload_3
    //   100: iconst_5
    //   101: if_icmpeq +8 -> 109
    //   104: iload_3
    //   105: iconst_4
    //   106: if_icmpne -42 -> 64
    //   109: aload_0
    //   110: getfield 14	com/estrongs/android/view/di:b	Lcom/estrongs/android/view/cr;
    //   113: iconst_0
    //   114: invokestatic 72	com/estrongs/android/view/cr:b	(Lcom/estrongs/android/view/cr;Z)Z
    //   117: pop
    //   118: aload_0
    //   119: getfield 14	com/estrongs/android/view/di:b	Lcom/estrongs/android/view/cr;
    //   122: getfield 76	com/estrongs/android/view/cr:C	Ljava/lang/String;
    //   125: astore 5
    //   127: aload_1
    //   128: getfield 79	com/estrongs/fs/b/al:b	Lcom/estrongs/fs/h;
    //   131: invokeinterface 85 1 0
    //   136: aload 5
    //   138: invokevirtual 91	java/lang/String:equals	(Ljava/lang/Object;)Z
    //   141: ifne +23 -> 164
    //   144: aload_0
    //   145: getfield 14	com/estrongs/android/view/di:b	Lcom/estrongs/android/view/cr;
    //   148: aconst_null
    //   149: invokestatic 94	com/estrongs/android/view/cr:a	(Lcom/estrongs/android/view/cr;Ljava/lang/String;)Ljava/lang/String;
    //   152: pop
    //   153: aload_0
    //   154: getfield 16	com/estrongs/android/view/di:a	Lcom/estrongs/android/view/dp;
    //   157: getfield 97	com/estrongs/android/view/dp:b	Landroid/os/ConditionVariable;
    //   160: invokevirtual 102	android/os/ConditionVariable:open	()V
    //   163: return
    //   164: iload 4
    //   166: ifeq +25 -> 191
    //   169: aload_0
    //   170: getfield 14	com/estrongs/android/view/di:b	Lcom/estrongs/android/view/cr;
    //   173: aload_1
    //   174: iload_3
    //   175: aload 5
    //   177: invokestatic 105	com/estrongs/android/view/cr:a	(Lcom/estrongs/android/view/cr;Lcom/estrongs/fs/b/al;ILjava/lang/String;)V
    //   180: aload_0
    //   181: getfield 16	com/estrongs/android/view/di:a	Lcom/estrongs/android/view/dp;
    //   184: getfield 97	com/estrongs/android/view/dp:b	Landroid/os/ConditionVariable;
    //   187: invokevirtual 102	android/os/ConditionVariable:open	()V
    //   190: return
    //   191: aload_0
    //   192: getfield 16	com/estrongs/android/view/di:a	Lcom/estrongs/android/view/dp;
    //   195: new 107	com/estrongs/android/view/dk
    //   198: dup
    //   199: aload_0
    //   200: aload_1
    //   201: iload_3
    //   202: aload 5
    //   204: invokespecial 110	com/estrongs/android/view/dk:<init>	(Lcom/estrongs/android/view/di;Lcom/estrongs/fs/b/al;ILjava/lang/String;)V
    //   207: putfield 113	com/estrongs/android/view/dp:d	Ljava/lang/Runnable;
    //   210: aload_0
    //   211: getfield 14	com/estrongs/android/view/di:b	Lcom/estrongs/android/view/cr;
    //   214: getfield 29	com/estrongs/android/view/cr:W	Landroid/os/Handler;
    //   217: aload_0
    //   218: getfield 16	com/estrongs/android/view/di:a	Lcom/estrongs/android/view/dp;
    //   221: getfield 113	com/estrongs/android/view/dp:d	Ljava/lang/Runnable;
    //   224: invokevirtual 69	android/os/Handler:post	(Ljava/lang/Runnable;)Z
    //   227: pop
    //   228: goto -48 -> 180
    //   231: astore_1
    //   232: aload_0
    //   233: getfield 16	com/estrongs/android/view/di:a	Lcom/estrongs/android/view/dp;
    //   236: getfield 97	com/estrongs/android/view/dp:b	Landroid/os/ConditionVariable;
    //   239: invokevirtual 102	android/os/ConditionVariable:open	()V
    //   242: aload_1
    //   243: athrow
    //   244: astore 5
    //   246: goto -209 -> 37
    // Local variable table:
    //   start	length	slot	name	signature
    //   0	249	0	this	di
    //   0	249	1	parama	com.estrongs.a.a
    //   0	249	2	paramInt1	int
    //   0	249	3	paramInt2	int
    //   1	164	4	i	int
    //   20	183	5	localObject	Object
    //   244	1	5	localException	Exception
    //   25	5	6	localThread	Thread
    // Exception table:
    //   from	to	target	type
    //   109	153	231	finally
    //   169	180	231	finally
    //   191	228	231	finally
    //   3	27	244	java/lang/Exception
  }
}

/* Location:
 * Qualified Name:     com.estrongs.android.view.di
 * Java Class Version: 6 (50.0)
 * JD-Core Version:    0.7.1
 */